Workbook

Sheet Guide
B1: How to use this file / วิธีใช้ไฟล์นี้
B3: Three tabs | C3: Dashboard = the overview. Register = where you type. Lists = the dropdown choices.
B4: แท็บ 3 อัน | C4: Dashboard คือภาพรวม, Register คือที่กรอกข้อมูล, Lists คือรายการตัวเลือก
B6: Step 1 | C6: Go to the Register tab. Each row is one licence, permit, tax, insurance policy or contract.
B7: Step 2 | C7: Fill in: Reference / Licence no., Issue date, Expiry date, Responsible person, Fee, and where the document is kept.
B9: Renew by | C9: The important split: OWNER or PROPERTY — who has to renew it. Pick from the dropdown. Owner rows are blue, Property rows are purple, and the Dashboard shows the two as two separate tables.
B10: Renew by = Owner | C10: The asset company (AMH … Co., Ltd.): the building and its inspections, the company registrations and taxes, asset insurance, the management agreement, lease and bank facilities.
B11: Renew by = Property | C11: The hotel operation: guest-facing licences (food, alcohol, pool), staff permits and health certificates, OTA agreements, and operating suppliers such as laundry, security, cleaning.
B12: ผู้ต่ออายุ | C12: Owner = เจ้าของอาคาร (บริษัท AMH) ดูแลตัวอาคาร ทะเบียนบริษัท ภาษี ประกันทรัพย์สิน สัญญาหลัก / Property = ฝ่ายโรงแรม ดูแลใบอนุญาตหน้างาน พนักงาน OTA และซัพพลายเออร์
B13: See one side only | C13: On the Register click the filter arrow on 'Renew by' and tick just Owner or just Property.
B14: Step 3 | C14: Leave the grey formula columns alone — Action by, Days left and Status fill themselves in.
B15: Step 4 | C15: Open the Dashboard tab to see what is expiring.
B17: The Dashboard | C17: Owner first, then Property. Each one is counted twice — once BY HOTEL and once BY DOCUMENT TYPE (licence, permit, certificate, tax, insurance, contract) — so a red number tells you which hotel and what kind of document.
... B34: Rebuild | C34: scripts/build_license_tracker.py rebuilds this file's structure. Rebuilding starts from empty rows, so keep your filled-in copy — do not overwrite it.

Sheet Dashboard
A1: Licence & Contract Dashboard — 4 properties
A2: Split by who renews it (OWNER / PROPERTY), then by hotel and by document type. All of it reads the Register tab. แยกตามผู้รับผิดชอบ แล้วแยกตามโรงแรมและประเภทเอกสาร
A4: As at | B4: =TODAY()
A6: OWNER — renewed by the asset company (AMH …) / เจ้าของอาคาร
A7: Hotel | B7: Expired | C7: Urgent (≤30 d) | D7: Due soon (≤90 d) | E7: OK | F7: No date | G7: Total
A8: SR9 | B8: =COUNTIFS(Register!$B$5:$B$404,"SR9",Register!$E$5:$E$404,"Owner",Register!$P$5:$P$404,"Expired") | C8: =COUNTIFS(Register!$B$5:$B$404,"SR9",Register!$E$5:$E$404,"Owner",Register!$P$5:$P$404,"Urgent") | D8: =COUNTIFS(Register!$B$5:$B$404,"SR9",Register!$E$5:$E$404,"Owner",Register!$P$5:$P$404,"Due soon") | E8: =COUNTIFS(Register!$B$5:$B$404,"SR9",Register!$E$5:$E$404,"Owner",Register!$P$5:$P$404,"OK") | F8: =COUNTIFS(Register!$B$5:$B$404,"SR9",Register!$E$5:$E$404,"Owner",Register!$P$5:$P$404,"No date") | G8: =COUNTIFS(Register!$B$5:$B$404,"SR9",Register!$E$5:$E$404,"Owner",Register!$F$5:$F$404,"?*") | I8: Somerset Rama 9 Bangkok
A9: AES | B9: =COUNTIFS(Register!$B$5:$B$404,"AES",Register!$E$5:$E$404,"Owner",Register!$P$5:$P$404,"Expired") | C9: =COUNTIFS(Register!$B$5:$B$404,"AES",Register!$E$5:$E$404,"Owner",Register!$P$5:$P$404,"Urgent") | D9: =COUNTIFS(Register!$B$5:$B$404,"AES",Register!$E$5:$E$404,"Owner",Register!$P$5:$P$404,"Due soon") | E9: =COUNTIFS(Register!$B$5:$B$404,"AES",Register!$E$5:$E$404,"Owner",Register!$P$5:$P$404,"OK") | F9: =COUNTIFS(Register!$B$5:$B$404,"AES",Register!$E$5:$E$404,"Owner",Register!$P$5:$P$404,"No date") | G9: =COUNTIFS(Register!$B$5:$B$404,"AES",Register!$E$5:$E$404,"Owner",Register!$F$5:$F$404,"?*") | I9: Ascott Embassy Sathorn Bangkok
A10: LYF | B10: =COUNTIFS(Register!$B$5:$B$404,"LYF",Register!$E$5:$E$404,"Owner",Register!$P$5:$P$404,"Expired") | C10: =COUNTIFS(Register!$B$5:$B$404,"LYF",Register!$E$5:$E$404,"Owner",Register!$P$5:$P$404,"Urgent") | D10: =COUNTIFS(Register!$B$5:$B$404,"LYF",Register!$E$5:$E$404,"Owner",Register!$P$5:$P$404,"Due soon") | E10: =COUNTIFS(Register!$B$5:$B$404,"LYF",Register!$E$5:$E$404,"Owner",Register!$P$5:$P$404,"OK") | F10: =COUNTIFS(Register!$B$5:$B$404,"LYF",Register!$E$5:$E$404,"Owner",Register!$P$5:$P$404,"No date") | G10: =COUNTIFS(Register!$B$5:$B$404,"LYF",Register!$E$5:$E$404,"Owner",Register!$F$5:$F$404,"?*") | I10: lyf Sukhumvit 8 Bangkok
A11: SP | B11: =COUNTIFS(Register!$B$5:$B$404,"SP",Register!$E$5:$E$404,"Owner",Register!$P$5:$P$404,"Expired") | C11: =COUNTIFS(Register!$B$5:$B$404,"SP",Register!$E$5:$E$404,"Owner",Register!$P$5:$P$404,"Urgent") | D11: =COUNTIFS(Register!$B$5:$B$404,"SP",Register!$E$5:$E$404,"Owner",Register!$P$5:$P$404,"Due soon") | E11: =COUNTIFS(Register!$B$5:$B$404,"SP",Register!$E$5:$E$404,"Owner",Register!$P$5:$P$404,"OK") | F11: =COUNTIFS(Register!$B$5:$B$404,"SP",Register!$E$5:$E$404,"Owner",Register!$P$5:$P$404,"No date") | G11: =COUNTIFS(Register!$B$5:$B$404,"SP",Register!$E$5:$E$404,"Owner",Register!$F$5:$F$404,"?*") | I11: Somerset Pattaya
A12: Subtotal | B12: =SUM(B8:B11) | C12: =SUM(C8:C11) | D12: =SUM(D8:D11) | E12: =SUM(E8:E11) | F12: =SUM(F8:F11) | G12: =SUM(G8:G11)
A14: Document type | B14: Expired | C14: Urgent (≤30 d) | D14: Due soon (≤90 d) | E14: OK | F14: No date | G14: Total
A15: Licence | B15: =COUNTIFS(Register!$D$5:$D$404,"Licence",Register!$E$5:$E$404,"Owner",Register!$P$5:$P$404,"Expired") | C15: =COUNTIFS(Register!$D$5:$D$404,"Licence",Register!$E$5:$E$404,"Owner",Register!$P$5:$P$404,"Urgent") | D15: =COUNTIFS(Register!$D$5:$D$404,"Licence",Register!$E$5:$E$404,"Owner",Register!$P$5:$P$404,"Due soon") | E15: =COUNTIFS(Register!$D$5:$D$404,"Licence",Register!$E$5:$E$404,"Owner",Register!$P$5:$P$404,"OK") | F15: =COUNTIFS(Register!$D$5:$D$404,"Licence",Register!$E$5:$E$404,"Owner",Register!$P$5:$P$404,"No date") | G15: =COUNTIFS(Register!$D$5:$D$404,"Licence",Register!$E$5:$E$404,"Owner",Register!$F$5:$F$404,"?*")
A16: Permit | B16: =COUNTIFS(Register!$D$5:$D$404,"Permit",Register!$E$5:$E$404,"Owner",Register!$P$5:$P$404,"Expired") | C16: =COUNTIFS(Register!$D$5:$D$404,"Permit",Register!$E$5:$E$404,"Owner",Register!$P$5:$P$404,"Urgent") | D16: =COUNTIFS(Register!$D$5:$D$404,"Permit",Register!$E$5:$E$404,"Owner",Register!$P$5:$P$404,"Due soon") | E16: =COUNTIFS(Register!$D$5:$D$404,"Permit",Register!$E$5:$E$404,"Owner",Register!$P$5:$P$404,"OK") | F16: =COUNTIFS(Register!$D$5:$D$404,"Permit",Register!$E$5:$E$404,"Owner",Register!$P$5:$P$404,"No date") | G16: =COUNTIFS(Register!$D$5:$D$404,"Permit",Register!$E$5:$E$404,"Owner",Register!$F$5:$F$404,"?*")
A17: Certificate | B17: =COUNTIFS(Register!$D$5:$D$404,"Certificate",Register!$E$5:$E$404,"Owner",Register!$P$5:$P$404,"Expired") | C17: =COUNTIFS(Register!$D$5:$D$404,"Certificate",Register!$E$5:$E$404,"Owner",Register!$P$5:$P$404,"Urgent") | D17: =COUNTIFS(Register!$D$5:$D$404,"Certificate",Register!$E$5:$E$404,"Owner",Register!$P$5:$P$404,"Due soon") | E17: =COUNTIFS(Register!$D$5:$D$404,"Certificate",Register!$E$5:$E$404,"Owner",Register!$P$5:$P$404,"OK") | F17: =COUNTIFS(Register!$D$5:$D$404,"Certificate",Register!$E$5:$E$404,"Owner",Register!$P$5:$P$404,"No date") | G17: =COUNTIFS(Register!$D$5:$D$404,"Certificate",Register!$E$5:$E$404,"Owner",Register!$F$5:$F$404,"?*")
A18: Tax / Registration | B18: =COUNTIFS(Register!$D$5:$D$404,"Tax / Registration",Register!$E$5:$E$404,"Owner",Register!$P$5:$P$404,"Expired") | C18: =COUNTIFS(Register!$D$5:$D$404,"Tax / Registration",Register!$E$5:$E$404,"Owner",Register!$P$5:$P$404,"Urgent") | D18: =COUNTIFS(Register!$D$5:$D$404,"Tax / Registration",Register!$E$5:$E$404,"Owner",Register!$P$5:$P$404,"Due soon") | E18: =COUNTIFS(Register!$D$5:$D$404,"Tax / Registration",Register!$E$5:$E$404,"Owner",Register!$P$5:$P$404,"OK") | F18: =COUNTIFS(Register!$D$5:$D$404,"Tax / Registration",Register!$E$5:$E$404,"Owner",Register!$P$5:$P$404,"No date") | G18: =COUNTIFS(Register!$D$5:$D$404,"Tax / Registration",Register!$E$5:$E$404,"Owner",Register!$F$5:$F$404,"?*")
A19: Insurance | B19: =COUNTIFS(Register!$D$5:$D$404,"Insurance",Register!$E$5:$E$404,"Owner",Register!$P$5:$P$404,"Expired") | C19: =COUNTIFS(Register!$D$5:$D$404,"Insurance",Register!$E$5:$E$404,"Owner",Register!$P$5:$P$404,"Urgent") | D19: =COUNTIFS(Register!$D$5:$D$404,"Insurance",Register!$E$5:$E$404,"Owner",Register!$P$5:$P$404,"Due soon") | E19: =COUNTIFS(Register!$D$5:$D$404,"Insurance",Register!$E$5:$E$404,"Owner",Register!$P$5:$P$404,"OK") | F19: =COUNTIFS(Register!$D$5:$D$404,"Insurance",Register!$E$5:$E$404,"Owner",Register!$P$5:$P$404,"No date") | G19: =COUNTIFS(Register!$D$5:$D$404,"Insurance",Register!$E$5:$E$404,"Owner",Register!$F$5:$F$404,"?*")
A20: Contract - Management | B20: =COUNTIFS(Register!$D$5:$D$404,"Contract - Management",Register!$E$5:$E$404,"Owner",Register!$P$5:$P$404,"Expired") | C20: =COUNTIFS(Register!$D$5:$D$404,"Contract - Management",Register!$E$5:$E$404,"Owner",Register!$P$5:$P$404,"Urgent") | D20: =COUNTIFS(Register!$D$5:$D$404,"Contract - Management",Register!$E$5:$E$404,"Owner",Register!$P$5:$P$404,"Due soon") | E20: =COUNTIFS(Register!$D$5:$D$404,"Contract - Management",Register!$E$5:$E$404,"Owner",Register!$P$5:$P$404,"OK") | F20: =COUNTIFS(Register!$D$5:$D$404,"Contract - Management",Register!$E$5:$E$404,"Owner",Register!$P$5:$P$404,"No date") | G20: =COUNTIFS(Register!$D$5:$D$404,"Contract - Management",Register!$E$5:$E$404,"Owner",Register!$F$5:$F$404,"?*")
A21: Contract - OTA | B21: =COUNTIFS(Register!$D$5:$D$404,"Contract - OTA",Register!$E$5:$E$404,"Owner",Register!$P$5:$P$404,"Expired") | C21: =COUNTIFS(Register!$D$5:$D$404,"Contract - OTA",Register!$E$5:$E$404,"Owner",Register!$P$5:$P$404,"Urgent") | D21: =COUNTIFS(Register!$D$5:$D$404,"Contract - OTA",Register!$E$5:$E$404,"Owner",Register!$P$5:$P$404,"Due soon") | E21: =COUNTIFS(Register!$D$5:$D$404,"Contract - OTA",Register!$E$5:$E$404,"Owner",Register!$P$5:$P$404,"OK") | F21: =COUNTIFS(Register!$D$5:$D$404,"Contract - OTA",Register!$E$5:$E$404,"Owner",Register!$P$5:$P$404,"No date") | G21: =COUNTIFS(Register!$D$5:$D$404,"Contract - OTA",Register!$E$5:$E$404,"Owner",Register!$F$5:$F$404,"?*")
A22: Contract - Service | B22: =COUNTIFS(Register!$D$5:$D$404,"Contract - Service",Register!$E$5:$E$404,"Owner",Register!$P$5:$P$404,"Expired") | C22: =COUNTIFS(Register!$D$5:$D$404,"Contract - Service",Register!$E$5:$E$404,"Owner",Register!$P$5:$P$404,"Urgent") | D22: =COUNTIFS(Register!$D$5:$D$404,"Contract - Service",Register!$E$5:$E$404,"Owner",Register!$P$5:$P$404,"Due soon") | E22: =COUNTIFS(Register!$D$5:$D$404,"Contract - Service",Register!$E$5:$E$404,"Owner",Register!$P$5:$P$404,"OK") | F22: =COUNTIFS(Register!$D$5:$D$404,"Contract - Service",Register!$E$5:$E$404,"Owner",Register!$P$5:$P$404,"No date") | G22: =COUNTIFS(Register!$D$5:$D$404,"Contract - Service",Register!$E$5:$E$404,"Owner",Register!$F$5:$F$404,"?*")
A23: Contract - Utility | B23: =COUNTIFS(Register!$D$5:$D$404,"Contract - Utility",Register!$E$5:$E$404,"Owner",Register!$P$5:$P$404,"Expired") | C23: =COUNTIFS(Register!$D$5:$D$404,"Contract - Utility",Register!$E$5:$E$404,"Owner",Register!$P$5:$P$404,"Urgent") | D23: =COUNTIFS(Register!$D$5:$D$404,"Contract - Utility",Register!$E$5:$E$404,"Owner",Register!$P$5:$P$404,"Due soon") | E23: =COUNTIFS(Register!$D$5:$D$404,"Contract - Utility",Register!$E$5:$E$404,"Owner",Register!$P$5:$P$404,"OK") | F23: =COUNTIFS(Register!$D$5:$D$404,"Contract - Utility",Register!$E$5:$E$404,"Owner",Register!$P$5:$P$404,"No date") | G23: =COUNTIFS(Register!$D$5:$D$404,"Contract - Utility",Register!$E$5:$E$404,"Owner",Register!$F$5:$F$404,"?*")
A24: Contract - Lease / Finance | B24: =COUNTIFS(Register!$D$5:$D$404,"Contract - Lease / Finance",Register!$E$5:$E$404,"Owner",Register!$P$5:$P$404,"Expired") | C24: =COUNTIFS(Register!$D$5:$D$404,"Contract - Lease / Finance",Register!$E$5:$E$404,"Owner",Register!$P$5:$P$404,"Urgent") | D24: =COUNTIFS(Register!$D$5:$D$404,"Contract - Lease / Finance",Register!$E$5:$E$404,"Owner",Register!$P$5:$P$404,"Due soon") | E24: =COUNTIFS(Register!$D$5:$D$404,"Contract - Lease / Finance",Register!$E$5:$E$404,"Owner",Register!$P$5:$P$404,"OK") | F24: =COUNTIFS(Register!$D$5:$D$404,"Contract - Lease / Finance",Register!$E$5:$E$404,"Owner",Register!$P$5:$P$404,"No date") | G24: =COUNTIFS(Register!$D$5:$D$404,"Contract - Lease / Finance",Register!$E$5:$E$404,"Owner",Register!$F$5:$F$404,"?*")
A25: Subtotal | B25: =SUM(B15:B24) | C25: =SUM(C15:C24) | D25: =SUM(D15:D24) | E25: =SUM(E15:E24) | F25: =SUM(F15:F24) | G25: =SUM(G15:G24) | I25: =IF(G25=G12,"✓ same total as by hotel","CHECK — does not match by hotel")
A27: PROPERTY — renewed by the hotel operation / ฝ่ายโรงแรม
A28: Hotel | B28: Expired | C28: Urgent (≤30 d) | D28: Due soon (≤90 d) | E28: OK | F28: No date | G28: Total
A29: SR9 | B29: =COUNTIFS(Register!$B$5:$B$404,"SR9",Register!$E$5:$E$404,"Property",Register!$P$5:$P$404,"Expired") | C29: =COUNTIFS(Register!$B$5:$B$404,"SR9",Register!$E$5:$E$404,"Property",Register!$P$5:$P$404,"Urgent") | D29: =COUNTIFS(Register!$B$5:$B$404,"SR9",Register!$E$5:$E$404,"Property",Register!$P$5:$P$404,"Due soon") | E29: =COUNTIFS(Register!$B$5:$B$404,"SR9",Register!$E$5:$E$404,"Property",Register!$P$5:$P$404,"OK") | F29: =COUNTIFS(Register!$B$5:$B$404,"SR9",Register!$E$5:$E$404,"Property",Register!$P$5:$P$404,"No date") | G29: =COUNTIFS(Register!$B$5:$B$404,"SR9",Register!$E$5:$E$404,"Property",Register!$F$5:$F$404,"?*") | I29: Somerset Rama 9 Bangkok
A30: AES | B30: =COUNTIFS(Register!$B$5:$B$404,"AES",Register!$E$5:$E$404,"Property",Register!$P$5:$P$404,"Expired") | C30: =COUNTIFS(Register!$B$5:$B$404,"AES",Register!$E$5:$E$404,"Property",Register!$P$5:$P$404,"Urgent") | D30: =COUNTIFS(Register!$B$5:$B$404,"AES",Register!$E$5:$E$404,"Property",Register!$P$5:$P$404,"Due soon") | E30: =COUNTIFS(Register!$B$5:$B$404,"AES",Register!$E$5:$E$404,"Property",Register!$P$5:$P$404,"OK") | F30: =COUNTIFS(Register!$B$5:$B$404,"AES",Register!$E$5:$E$404,"Property",Register!$P$5:$P$404,"No date") | G30: =COUNTIFS(Register!$B$5:$B$404,"AES",Register!$E$5:$E$404,"Property",Register!$F$5:$F$404,"?*") | I30: Ascott Embassy Sathorn Bangkok
A31: LYF | B31: =COUNTIFS(Register!$B$5:$B$404,"LYF",Register!$E$5:$E$404,"Property",Register!$P$5:$P$404,"Expired") | C31: =COUNTIFS(Register!$B$5:$B$404,"LYF",Register!$E$5:$E$404,"Property",Register!$P$5:$P$404,"Urgent") | D31: =COUNTIFS(Register!$B$5:$B$404,"LYF",Register!$E$5:$E$404,"Property",Register!$P$5:$P$404,"Due soon") | E31: =COUNTIFS(Register!$B$5:$B$404,"LYF",Register!$E$5:$E$404,"Property",Register!$P$5:$P$404,"OK") | F31: =COUNTIFS(Register!$B$5:$B$404,"LYF",Register!$E$5:$E$404,"Property",Register!$P$5:$P$404,"No date") | G31: =COUNTIFS(Register!$B$5:$B$404,"LYF",Register!$E$5:$E$404,"Property",Register!$F$5:$F$404,"?*") | I31: lyf Sukhumvit 8 Bangkok
A32: SP | B32: =COUNTIFS(Register!$B$5:$B$404,"SP",Register!$E$5:$E$404,"Property",Register!$P$5:$P$404,"Expired") | C32: =COUNTIFS(Register!$B$5:$B$404,"SP",Register!$E$5:$E$404,"Property",Register!$P$5:$P$404,"Urgent") | D32: =COUNTIFS(Register!$B$5:$B$404,"SP",Register!$E$5:$E$404,"Property",Register!$P$5:$P$404,"Due soon") | E32: =COUNTIFS(Register!$B$5:$B$404,"SP",Register!$E$5:$E$404,"Property",Register!$P$5:$P$404,"OK") | F32: =COUNTIFS(Register!$B$5:$B$404,"SP",Register!$E$5:$E$404,"Property",Register!$P$5:$P$404,"No date") | G32: =COUNTIFS(Register!$B$5:$B$404,"SP",Register!$E$5:$E$404,"Property",Register!$F$5:$F$404,"?*") | I32: Somerset Pattaya
A33: Subtotal | B33: =SUM(B29:B32) | C33: =SUM(C29:C32) | D33: =SUM(D29:D32) | E33: =SUM(E29:E32) | F33: =SUM(F29:F32) | G33: =SUM(G29:G32)
A35: Document type | B35: Expired | C35: Urgent (≤30 d) | D35: Due soon (≤90 d) | E35: OK | F35: No date | G35: Total
A36: Licence | B36: =COUNTIFS(Register!$D$5:$D$404,"Licence",Register!$E$5:$E$404,"Property",Register!$P$5:$P$404,"Expired") | C36: =COUNTIFS(Register!$D$5:$D$404,"Licence",Register!$E$5:$E$404,"Property",Register!$P$5:$P$404,"Urgent") | D36: =COUNTIFS(Register!$D$5:$D$404,"Licence",Register!$E$5:$E$404,"Property",Register!$P$5:$P$404,"Due soon") | E36: =COUNTIFS(Register!$D$5:$D$404,"Licence",Register!$E$5:$E$404,"Property",Register!$P$5:$P$404,"OK") | F36: =COUNTIFS(Register!$D$5:$D$404,"Licence",Register!$E$5:$E$404,"Property",Register!$P$5:$P$404,"No date") | G36: =COUNTIFS(Register!$D$5:$D$404,"Licence",Register!$E$5:$E$404,"Property",Register!$F$5:$F$404,"?*")
A37: Permit | B37: =COUNTIFS(Register!$D$5:$D$404,"Permit",Register!$E$5:$E$404,"Property",Register!$P$5:$P$404,"Expired") | C37: =COUNTIFS(Register!$D$5:$D$404,"Permit",Register!$E$5:$E$404,"Property",Register!$P$5:$P$404,"Urgent") | D37: =COUNTIFS(Register!$D$5:$D$404,"Permit",Register!$E$5:$E$404,"Property",Register!$P$5:$P$404,"Due soon") | E37: =COUNTIFS(Register!$D$5:$D$404,"Permit",Register!$E$5:$E$404,"Property",Register!$P$5:$P$404,"OK") | F37: =COUNTIFS(Register!$D$5:$D$404,"Permit",Register!$E$5:$E$404,"Property",Register!$P$5:$P$404,"No date") | G37: =COUNTIFS(Register!$D$5:$D$404,"Permit",Register!$E$5:$E$404,"Property",Register!$F$5:$F$404,"?*")
A38: Certificate | B38: =COUNTIFS(Register!$D$5:$D$404,"Certificate",Register!$E$5:$E$404,"Property",Register!$P$5:$P$404,"Expired") | C38: =COUNTIFS(Register!$D$5:$D$404,"Certificate",Register!$E$5:$E$404,"Property",Register!$P$5:$P$404,"Urgent") | D38: =COUNTIFS(Register!$D$5:$D$404,"Certificate",Register!$E$5:$E$404,"Property",Register!$P$5:$P$404,"Due soon") | E38: =COUNTIFS(Register!$D$5:$D$404,"Certificate",Register!$E$5:$E$404,"Property",Register!$P$5:$P$404,"OK") | F38: =COUNTIFS(Register!$D$5:$D$404,"Certificate",Register!$E$5:$E$404,"Property",Register!$P$5:$P$404,"No date") | G38: =COUNTIFS(Register!$D$5:$D$404,"Certificate",Register!$E$5:$E$404,"Property",Register!$F$5:$F$404,"?*")
A39: Tax / Registration | B39: =COUNTIFS(Register!$D$5:$D$404,"Tax / Registration",Register!$E$5:$E$404,"Property",Register!$P$5:$P$404,"Expired") | C39: =COUNTIFS(Register!$D$5:$D$404,"Tax / Registration",Register!$E$5:$E$404,"Property",Register!$P$5:$P$404,"Urgent") | D39: =COUNTIFS(Register!$D$5:$D$404,"Tax / Registration",Register!$E$5:$E$404,"Property",Register!$P$5:$P$404,"Due soon") | E39: =COUNTIFS(Register!$D$5:$D$404,"Tax / Registration",Register!$E$5:$E$404,"Property",Register!$P$5:$P$404,"OK") | F39: =COUNTIFS(Register!$D$5:$D$404,"Tax / Registration",Register!$E$5:$E$404,"Property",Register!$P$5:$P$404,"No date") | G39: =COUNTIFS(Register!$D$5:$D$404,"Tax / Registration",Register!$E$5:$E$404,"Property",Register!$F$5:$F$404,"?*")
A40: Insurance | B40: =COUNTIFS(Register!$D$5:$D$404,"Insurance",Register!$E$5:$E$404,"Property",Register!$P$5:$P$404,"Expired") | C40: =COUNTIFS(Register!$D$5:$D$404,"Insurance",Register!$E$5:$E$404,"Property",Register!$P$5:$P$404,"Urgent") | D40: =COUNTIFS(Register!$D$5:$D$404,"Insurance",Register!$E$5:$E$404,"Property",Register!$P$5:$P$404,"Due soon") | E40: =COUNTIFS(Register!$D$5:$D$404,"Insurance",Register!$E$5:$E$404,"Property",Register!$P$5:$P$404,"OK") | F40: =COUNTIFS(Register!$D$5:$D$404,"Insurance",Register!$E$5:$E$404,"Property",Register!$P$5:$P$404,"No date") | G40: =COUNTIFS(Register!$D$5:$D$404,"Insurance",Register!$E$5:$E$404,"Property",Register!$F$5:$F$404,"?*")
A41: Contract - Management | B41: =COUNTIFS(Register!$D$5:$D$404,"Contract - Management",Register!$E$5:$E$404,"Property",Register!$P$5:$P$404,"Expired") | C41: =COUNTIFS(Register!$D$5:$D$404,"Contract - Management",Register!$E$5:$E$404,"Property",Register!$P$5:$P$404,"Urgent") | D41: =COUNTIFS(Register!$D$5:$D$404,"Contract - Management",Register!$E$5:$E$404,"Property",Register!$P$5:$P$404,"Due soon") | E41: =COUNTIFS(Register!$D$5:$D$404,"Contract - Management",Register!$E$5:$E$404,"Property",Register!$P$5:$P$404,"OK") | F41: =COUNTIFS(Register!$D$5:$D$404,"Contract - Management",Register!$E$5:$E$404,"Property",Register!$P$5:$P$404,"No date") | G41: =COUNTIFS(Register!$D$5:$D$404,"Contract - Management",Register!$E$5:$E$404,"Property",Register!$F$5:$F$404,"?*")
A42: Contract - OTA | B42: =COUNTIFS(Register!$D$5:$D$404,"Contract - OTA",Register!$E$5:$E$404,"Property",Register!$P$5:$P$404,"Expired") | C42: =COUNTIFS(Register!$D$5:$D$404,"Contract - OTA",Register!$E$5:$E$404,"Property",Register!$P$5:$P$404,"Urgent") | D42: =COUNTIFS(Register!$D$5:$D$404,"Contract - OTA",Register!$E$5:$E$404,"Property",Register!$P$5:$P$404,"Due soon") | E42: =COUNTIFS(Register!$D$5:$D$404,"Contract - OTA",Register!$E$5:$E$404,"Property",Register!$P$5:$P$404,"OK") | F42: =COUNTIFS(Register!$D$5:$D$404,"Contract - OTA",Register!$E$5:$E$404,"Property",Register!$P$5:$P$404,"No date") | G42: =COUNTIFS(Register!$D$5:$D$404,"Contract - OTA",Register!$E$5:$E$404,"Property",Register!$F$5:$F$404,"?*")
A43: Contract - Service | B43: =COUNTIFS(Register!$D$5:$D$404,"Contract - Service",Register!$E$5:$E$404,"Property",Register!$P$5:$P$404,"Expired") | C43: =COUNTIFS(Register!$D$5:$D$404,"Contract - Service",Register!$E$5:$E$404,"Property",Register!$P$5:$P$404,"Urgent") | D43: =COUNTIFS(Register!$D$5:$D$404,"Contract - Service",Register!$E$5:$E$404,"Property",Register!$P$5:$P$404,"Due soon") | E43: =COUNTIFS(Register!$D$5:$D$404,"Contract - Service",Register!$E$5:$E$404,"Property",Register!$P$5:$P$404,"OK") | F43: =COUNTIFS(Register!$D$5:$D$404,"Contract - Service",Register!$E$5:$E$404,"Property",Register!$P$5:$P$404,"No date") | G43: =COUNTIFS(Register!$D$5:$D$404,"Contract - Service",Register!$E$5:$E$404,"Property",Register!$F$5:$F$404,"?*")
A44: Contract - Utility | B44: =COUNTIFS(Register!$D$5:$D$404,"Contract - Utility",Register!$E$5:$E$404,"Property",Register!$P$5:$P$404,"Expired") | C44: =COUNTIFS(Register!$D$5:$D$404,"Contract - Utility",Register!$E$5:$E$404,"Property",Register!$P$5:$P$404,"Urgent") | D44: =COUNTIFS(Register!$D$5:$D$404,"Contract - Utility",Register!$E$5:$E$404,"Property",Register!$P$5:$P$404,"Due soon") | E44: =COUNTIFS(Register!$D$5:$D$404,"Contract - Utility",Register!$E$5:$E$404,"Property",Register!$P$5:$P$404,"OK") | F44: =COUNTIFS(Register!$D$5:$D$404,"Contract - Utility",Register!$E$5:$E$404,"Property",Register!$P$5:$P$404,"No date") | G44: =COUNTIFS(Register!$D$5:$D$404,"Contract - Utility",Register!$E$5:$E$404,"Property",Register!$F$5:$F$404,"?*")
A45: Contract - Lease / Finance | B45: =COUNTIFS(Register!$D$5:$D$404,"Contract - Lease / Finance",Register!$E$5:$E$404,"Property",Register!$P$5:$P$404,"Expired") | C45: =COUNTIFS(Register!$D$5:$D$404,"Contract - Lease / Finance",Register!$E$5:$E$404,"Property",Register!$P$5:$P$404,"Urgent") | D45: =COUNTIFS(Register!$D$5:$D$404,"Contract - Lease / Finance",Register!$E$5:$E$404,"Property",Register!$P$5:$P$404,"Due soon") | E45: =COUNTIFS(Register!$D$5:$D$404,"Contract - Lease / Finance",Register!$E$5:$E$404,"Property",Register!$P$5:$P$404,"OK") | F45: =COUNTIFS(Register!$D$5:$D$404,"Contract - Lease / Finance",Register!$E$5:$E$404,"Property",Register!$P$5:$P$404,"No date") | G45: =COUNTIFS(Register!$D$5:$D$404,"Contract - Lease / Finance",Register!$E$5:$E$404,"Property",Register!$F$5:$F$404,"?*")
A46: Subtotal | B46: =SUM(B36:B45) | C46: =SUM(C36:C45) | D46: =SUM(D36:D45) | E46: =SUM(E36:E45) | F46: =SUM(F36:F45) | G46: =SUM(G36:G45) | I46: =IF(G46=G33,"✓ same total as by hotel","CHECK — does not match by hotel")
A48: NOT ASSIGNED — no Renew by chosen yet / ยังไม่ได้ระบุผู้รับผิดชอบ
A49: Hotel | B49: Expired | C49: Urgent (≤30 d) | D49: Due soon (≤90 d) | E49: OK | F49: No date | G49: Total
A50: SR9 | B50: =COUNTIFS(Register!$B$5:$B$404,"SR9",Register!$E$5:$E$404,"",Register!$P$5:$P$404,"Expired") | C50: =COUNTIFS(Register!$B$5:$B$404,"SR9",Register!$E$5:$E$404,"",Register!$P$5:$P$404,"Urgent") | D50: =COUNTIFS(Register!$B$5:$B$404,"SR9",Register!$E$5:$E$404,"",Register!$P$5:$P$404,"Due soon") | E50: =COUNTIFS(Register!$B$5:$B$404,"SR9",Register!$E$5:$E$404,"",Register!$P$5:$P$404,"OK") | F50: =COUNTIFS(Register!$B$5:$B$404,"SR9",Register!$E$5:$E$404,"",Register!$P$5:$P$404,"No date") | G50: =COUNTIFS(Register!$B$5:$B$404,"SR9",Register!$E$5:$E$404,"",Register!$F$5:$F$404,"?*") | I50: Somerset Rama 9 Bangkok
A51: AES | B51: =COUNTIFS(Register!$B$5:$B$404,"AES",Register!$E$5:$E$404,"",Register!$P$5:$P$404,"Expired") | C51: =COUNTIFS(Register!$B$5:$B$404,"AES",Register!$E$5:$E$404,"",Register!$P$5:$P$404,"Urgent") | D51: =COUNTIFS(Register!$B$5:$B$404,"AES",Register!$E$5:$E$404,"",Register!$P$5:$P$404,"Due soon") | E51: =COUNTIFS(Register!$B$5:$B$404,"AES",Register!$E$5:$E$404,"",Register!$P$5:$P$404,"OK") | F51: =COUNTIFS(Register!$B$5:$B$404,"AES",Register!$E$5:$E$404,"",Register!$P$5:$P$404,"No date") | G51: =COUNTIFS(Register!$B$5:$B$404,"AES",Register!$E$5:$E$404,"",Register!$F$5:$F$404,"?*") | I51: Ascott Embassy Sathorn Bangkok
A52: LYF | B52: =COUNTIFS(Register!$B$5:$B$404,"LYF",Register!$E$5:$E$404,"",Register!$P$5:$P$404,"Expired") | C52: =COUNTIFS(Register!$B$5:$B$404,"LYF",Register!$E$5:$E$404,"",Register!$P$5:$P$404,"Urgent") | D52: =COUNTIFS(Register!$B$5:$B$404,"LYF",Register!$E$5:$E$404,"",Register!$P$5:$P$404,"Due soon") | E52: =COUNTIFS(Register!$B$5:$B$404,"LYF",Register!$E$5:$E$404,"",Register!$P$5:$P$404,"OK") | F52: =COUNTIFS(Register!$B$5:$B$404,"LYF",Register!$E$5:$E$404,"",Register!$P$5:$P$404,"No date") | G52: =COUNTIFS(Register!$B$5:$B$404,"LYF",Register!$E$5:$E$404,"",Register!$F$5:$F$404,"?*") | I52: lyf Sukhumvit 8 Bangkok
A53: SP | B53: =COUNTIFS(Register!$B$5:$B$404,"SP",Register!$E$5:$E$404,"",Register!$P$5:$P$404,"Expired") | C53: =COUNTIFS(Register!$B$5:$B$404,"SP",Register!$E$5:$E$404,"",Register!$P$5:$P$404,"Urgent") | D53: =COUNTIFS(Register!$B$5:$B$404,"SP",Register!$E$5:$E$404,"",Register!$P$5:$P$404,"Due soon") | E53: =COUNTIFS(Register!$B$5:$B$404,"SP",Register!$E$5:$E$404,"",Register!$P$5:$P$404,"OK") | F53: =COUNTIFS(Register!$B$5:$B$404,"SP",Register!$E$5:$E$404,"",Register!$P$5:$P$404,"No date") | G53: =COUNTIFS(Register!$B$5:$B$404,"SP",Register!$E$5:$E$404,"",Register!$F$5:$F$404,"?*") | I53: Somerset Pattaya
A54: Subtotal | B54: =SUM(B50:B53) | C54: =SUM(C50:C53) | D54: =SUM(D50:D53) | E54: =SUM(E50:E53) | F54: =SUM(F50:F53) | G54: =SUM(G50:G53)
A56: ALL | B56: =B12+B33+B54 | C56: =C12+C33+C54 | D56: =D12+D33+D54 | E56: =E12+E33+E54 | F56: =F12+F33+F54 | G56: =G12+G33+G54 | I56: Owner + Property + Not assigned = every row in the Register
A58: Expiring next — soonest first, both responsibilities
A59: Hotel | B59: Renew by | C59: Document type | D59: Item | E59: Counterparty | F59: Expiry date | G59: Days left | H59: Status | I59: Responsible
A60: =IFERROR(INDEX(Register!$B$5:$B$404,MATCH(SMALL(Register!$V$5:$V$404,ROW()-59),Register!$V$5:$V$404,0)),"") | B60: =IFERROR(INDEX(Register!$E$5:$E$404,MATCH(SMALL(Register!$V$5:$V$404,ROW()-59),Register!$V$5:$V$404,0)),"") | C60: =IFERROR(INDEX(Register!$D$5:$D$404,MATCH(SMALL(Register!$V$5:$V$404,ROW()-59),Register!$V$5:$V$404,0)),"") | D60: =IFERROR(INDEX(Register!$F$5:$F$404,MATCH(SMALL(Register!$V$5:$V$404,ROW()-59),Register!$V$5:$V$404,0)),"") | E60: =IFERROR(INDEX(Register!$H$5:$H$404,MATCH(SMALL(Register!$V$5:$V$404,ROW()-59),Register!$V$5:$V$404,0)),"") | F60: =IFERROR(INDEX(Register!$K$5:$K$404,MATCH(SMALL(Register!$V$5:$V$404,ROW()-59),Register!$V$5:$V$404,0)),"") | G60: =IFERROR(INDEX(Register!$O$5:$O$404,MATCH(SMALL(Register!$V$5:$V$404,ROW()-59),Register!$V$5:$V$404,0)),"") | H60: =IFERROR(INDEX(Register!$P$5:$P$404,MATCH(SMALL(Register!$V$5:$V$404,ROW()-59),Register!$V$5:$V$404,0)),"") | I60: =IFERROR(INDEX(Register!$Q$5:$Q$404,MATCH(SMALL(Register!$V$5:$V$404,ROW()-59),Register!$V$5:$V$404,0)),"")
A61: =IFERROR(INDEX(Register!$B$5:$B$404,MATCH(SMALL(Register!$V$5:$V$404,ROW()-59),Register!$V$5:$V$404,0)),"") | B61: =IFERROR(INDEX(Register!$E$5:$E$404,MATCH(SMALL(Register!$V$5:$V$404,ROW()-59),Register!$V$5:$V$404,0)),"") | C61: =IFERROR(INDEX(Register!$D$5:$D$404,MATCH(SMALL(Register!$V$5:$V$404,ROW()-59),Register!$V$5:$V$404,0)),"") | D61: =IFERROR(INDEX(Register!$F$5:$F$404,MATCH(SMALL(Register!$V$5:$V$404,ROW()-59),Register!$V$5:$V$404,0)),"") | E61: =IFERROR(INDEX(Register!$H$5:$H$404,MATCH(SMALL(Register!$V$5:$V$404,ROW()-59),Register!$V$5:$V$404,0)),"") | F61: =IFERROR(INDEX(Register!$K$5:$K$404,MATCH(SMALL(Register!$V$5:$V$404,ROW()-59),Register!$V$5:$V$404,0)),"") | G61: =IFERROR(INDEX(Register!$O$5:$O$404,MATCH(SMALL(Register!$V$5:$V$404,ROW()-59),Register!$V$5:$V$404,0)),"") | H61: =IFERROR(INDEX(Register!$P$5:$P$404,MATCH(SMALL(Register!$V$5:$V$404,ROW()-59),Register!$V$5:$V$404,0)),"") | I61: =IFERROR(INDEX(Register!$Q$5:$Q$404,MATCH(SMALL(Register!$V$5:$V$404,ROW()-59),Register!$V$5:$V$404,0)),"")
A62: =IFERROR(INDEX(Register!$B$5:$B$404,MATCH(SMALL(Register!$V$5:$V$404,ROW()-59),Register!$V$5:$V$404,0)),"") | B62: =IFERROR(INDEX(Register!$E$5:$E$404,MATCH(SMALL(Register!$V$5:$V$404,ROW()-59),Register!$V$5:$V$404,0)),"") | C62: =IFERROR(INDEX(Register!$D$5:$D$404,MATCH(SMALL(Register!$V$5:$V$404,ROW()-59),Register!$V$5:$V$404,0)),"") | D62: =IFERROR(INDEX(Register!$F$5:$F$404,MATCH(SMALL(Register!$V$5:$V$404,ROW()-59),Register!$V$5:$V$404,0)),"") | E62: =IFERROR(INDEX(Register!$H$5:$H$404,MATCH(SMALL(Register!$V$5:$V$404,ROW()-59),Register!$V$5:$V$404,0)),"") | F62: =IFERROR(INDEX(Register!$K$5:$K$404,MATCH(SMALL(Register!$V$5:$V$404,ROW()-59),Register!$V$5:$V$404,0)),"") | G62: =IFERROR(INDEX(Register!$O$5:$O$404,MATCH(SMALL(Register!$V$5:$V$404,ROW()-59),Register!$V$5:$V$404,0)),"") | H62: =IFERROR(INDEX(Register!$P$5:$P$404,MATCH(SMALL(Register!$V$5:$V$404,ROW()-59),Register!$V$5:$V$404,0)),"") | I62: =IFERROR(INDEX(Register!$Q$5:$Q$404,MATCH(SMALL(Register!$V$5:$V$404,ROW()-59),Register!$V$5:$V$404,0)),"")
A63: =IFERROR(INDEX(Register!$B$5:$B$404,MATCH(SMALL(Register!$V$5:$V$404,ROW()-59),Register!$V$5:$V$404,0)),"") | B63: =IFERROR(INDEX(Register!$E$5:$E$404,MATCH(SMALL(Register!$V$5:$V$404,ROW()-59),Register!$V$5:$V$404,0)),"") | C63: =IFERROR(INDEX(Register!$D$5:$D$404,MATCH(SMALL(Register!$V$5:$V$404,ROW()-59),Register!$V$5:$V$404,0)),"") | D63: =IFERROR(INDEX(Register!$F$5:$F$404,MATCH(SMALL(Register!$V$5:$V$404,ROW()-59),Register!$V$5:$V$404,0)),"") | E63: =IFERROR(INDEX(Register!$H$5:$H$404,MATCH(SMALL(Register!$V$5:$V$404,ROW()-59),Register!$V$5:$V$404,0)),"") | F63: =IFERROR(INDEX(Register!$K$5:$K$404,MATCH(SMALL(Register!$V$5:$V$404,ROW()-59),Register!$V$5:$V$404,0)),"") | G63: =IFERROR(INDEX(Register!$O$5:$O$404,MATCH(SMALL(Register!$V$5:$V$404,ROW()-59),Register!$V$5:$V$404,0)),"") | H63: =IFERROR(INDEX(Register!$P$5:$P$404,MATCH(SMALL(Register!$V$5:$V$404,ROW()-59),Register!$V$5:$V$404,0)),"") | I63: =IFERROR(INDEX(Register!$Q$5:$Q$404,MATCH(SMALL(Register!$V$5:$V$404,ROW()-59),Register!$V$5:$V$404,0)),"")
A64: =IFERROR(INDEX(Register!$B$5:$B$404,MATCH(SMALL(Register!$V$5:$V$404,ROW()-59),Register!$V$5:$V$404,0)),"") | B64: =IFERROR(INDEX(Register!$E$5:$E$404,MATCH(SMALL(Register!$V$5:$V$404,ROW()-59),Register!$V$5:$V$404,0)),"") | C64: =IFERROR(INDEX(Register!$D$5:$D$404,MATCH(SMALL(Register!$V$5:$V$404,ROW()-59),Register!$V$5:$V$404,0)),"") | D64: =IFERROR(INDEX(Register!$F$5:$F$404,MATCH(SMALL(Register!$V$5:$V$404,ROW()-59),Register!$V$5:$V$404,0)),"") | E64: =IFERROR(INDEX(Register!$H$5:$H$404,MATCH(SMALL(Register!$V$5:$V$404,ROW()-59),Register!$V$5:$V$404,0)),"") | F64: =IFERROR(INDEX(Register!$K$5:$K$404,MATCH(SMALL(Register!$V$5:$V$404,ROW()-59),Register!$V$5:$V$404,0)),"") | G64: =IFERROR(INDEX(Register!$O$5:$O$404,MATCH(SMALL(Register!$V$5:$V$404,ROW()-59),Register!$V$5:$V$404,0)),"") | H64: =IFERROR(INDEX(Register!$P$5:$P$404,MATCH(SMALL(Register!$V$5:$V$404,ROW()-59),Register!$V$5:$V$404,0)),"") | I64: =IFERROR(INDEX(Register!$Q$5:$Q$404,MATCH(SMALL(Register!$V$5:$V$404,ROW()-59),Register!$V$5:$V$404,0)),"")
A65: =IFERROR(INDEX(Register!$B$5:$B$404,MATCH(SMALL(Register!$V$5:$V$404,ROW()-59),Register!$V$5:$V$404,0)),"") | B65: =IFERROR(INDEX(Register!$E$5:$E$404,MATCH(SMALL(Register!$V$5:$V$404,ROW()-59),Register!$V$5:$V$404,0)),"") | C65: =IFERROR(INDEX(Register!$D$5:$D$404,MATCH(SMALL(Register!$V$5:$V$404,ROW()-59),Register!$V$5:$V$404,0)),"") | D65: =IFERROR(INDEX(Register!$F$5:$F$404,MATCH(SMALL(Register!$V$5:$V$404,ROW()-59),Register!$V$5:$V$404,0)),"") | E65: =IFERROR(INDEX(Register!$H$5:$H$404,MATCH(SMALL(Register!$V$5:$V$404,ROW()-59),Register!$V$5:$V$404,0)),"") | F65: =IFERROR(INDEX(Register!$K$5:$K$404,MATCH(SMALL(Register!$V$5:$V$404,ROW()-59),Register!$V$5:$V$404,0)),"") | G65: =IFERROR(INDEX(Register!$O$5:$O$404,MATCH(SMALL(Register!$V$5:$V$404,ROW()-59),Register!$V$5:$V$404,0)),"") | H65: =IFERROR(INDEX(Register!$P$5:$P$404,MATCH(SMALL(Register!$V$5:$V$404,ROW()-59),Register!$V$5:$V$404,0)),"") | I65: =IFERROR(INDEX(Register!$Q$5:$Q$404,MATCH(SMALL(Register!$V$5:$V$404,ROW()-59),Register!$V$5:$V$404,0)),"")
A66: =IFERROR(INDEX(Register!$B$5:$B$404,MATCH(SMALL(Register!$V$5:$V$404,ROW()-59),Register!$V$5:$V$404,0)),"") | B66: =IFERROR(INDEX(Register!$E$5:$E$404,MATCH(SMALL(Register!$V$5:$V$404,ROW()-59),Register!$V$5:$V$404,0)),"") | C66: =IFERROR(INDEX(Register!$D$5:$D$404,MATCH(SMALL(Register!$V$5:$V$404,ROW()-59),Register!$V$5:$V$404,0)),"") | D66: =IFERROR(INDEX(Register!$F$5:$F$404,MATCH(SMALL(Register!$V$5:$V$404,ROW()-59),Register!$V$5:$V$404,0)),"") | E66: =IFERROR(INDEX(Register!$H$5:$H$404,MATCH(SMALL(Register!$V$5:$V$404,ROW()-59),Register!$V$5:$V$404,0)),"") | F66: =IFERROR(INDEX(Register!$K$5:$K$404,MATCH(SMALL(Register!$V$5:$V$404,ROW()-59),Register!$V$5:$V$404,0)),"") | G66: =IFERROR(INDEX(Register!$O$5:$O$404,MATCH(SMALL(Register!$V$5:$V$404,ROW()-59),Register!$V$5:$V$404,0)),"") | H66: =IFERROR(INDEX(Register!$P$5:$P$404,MATCH(SMALL(Register!$V$5:$V$404,ROW()-59),Register!$V$5:$V$404,0)),"") | I66: =IFERROR(INDEX(Register!$Q$5:$Q$404,MATCH(SMALL(Register!$V$5:$V$404,ROW()-59),Register!$V$5:$V$404,0)),"")
A67: =IFERROR(INDEX(Register!$B$5:$B$404,MATCH(SMALL(Register!$V$5:$V$404,ROW()-59),Register!$V$5:$V$404,0)),"") | B67: =IFERROR(INDEX(Register!$E$5:$E$404,MATCH(SMALL(Register!$V$5:$V$404,ROW()-59),Register!$V$5:$V$404,0)),"") | C67: =IFERROR(INDEX(Register!$D$5:$D$404,MATCH(SMALL(Register!$V$5:$V$404,ROW()-59),Register!$V$5:$V$404,0)),"") | D67: =IFERROR(INDEX(Register!$F$5:$F$404,MATCH(SMALL(Register!$V$5:$V$404,ROW()-59),Register!$V$5:$V$404,0)),"") | E67: =IFERROR(INDEX(Register!$H$5:$H$404,MATCH(SMALL(Register!$V$5:$V$404,ROW()-59),Register!$V$5:$V$404,0)),"") | F67: =IFERROR(INDEX(Register!$K$5:$K$404,MATCH(SMALL(Register!$V$5:$V$404,ROW()-59),Register!$V$5:$V$404,0)),"") | G67: =IFERROR(INDEX(Register!$O$5:$O$404,MATCH(SMALL(Register!$V$5:$V$404,ROW()-59),Register!$V$5:$V$404,0)),"") | H67: =IFERROR(INDEX(Register!$P$5:$P$404,MATCH(SMALL(Register!$V$5:$V$404,ROW()-59),Register!$V$5:$V$404,0)),"") | I67: =IFERROR(INDEX(Register!$Q$5:$Q$404,MATCH(SMALL(Register!$V$5:$V$404,ROW()-59),Register!$V$5:$V$404,0)),"")
A68: =IFERROR(INDEX(Register!$B$5:$B$404,MATCH(SMALL(Register!$V$5:$V$404,ROW()-59),Register!$V$5:$V$404,0)),"") | B68: =IFERROR(INDEX(Register!$E$5:$E$404,MATCH(SMALL(Register!$V$5:$V$404,ROW()-59),Register!$V$5:$V$404,0)),"") | C68: =IFERROR(INDEX(Register!$D$5:$D$404,MATCH(SMALL(Register!$V$5:$V$404,ROW()-59),Register!$V$5:$V$404,0)),"") | D68: =IFERROR(INDEX(Register!$F$5:$F$404,MATCH(SMALL(Register!$V$5:$V$404,ROW()-59),Register!$V$5:$V$404,0)),"") | E68: =IFERROR(INDEX(Register!$H$5:$H$404,MATCH(SMALL(Register!$V$5:$V$404,ROW()-59),Register!$V$5:$V$404,0)),"") | F68: =IFERROR(INDEX(Register!$K$5:$K$404,MATCH(SMALL(Register!$V$5:$V$404,ROW()-59),Register!$V$5:$V$404,0)),"") | G68: =IFERROR(INDEX(Register!$O$5:$O$404,MATCH(SMALL(Register!$V$5:$V$404,ROW()-59),Register!$V$5:$V$404,0)),"") | H68: =IFERROR(INDEX(Register!$P$5:$P$404,MATCH(SMALL(Register!$V$5:$V$404,ROW()-59),Register!$V$5:$V$404,0)),"") | I68: =IFERROR(INDEX(Register!$Q$5:$Q$404,MATCH(SMALL(Register!$V$5:$V$404,ROW()-59),Register!$V$5:$V$404,0)),"")
A69: =IFERROR(INDEX(Register!$B$5:$B$404,MATCH(SMALL(Register!$V$5:$V$404,ROW()-59),Register!$V$5:$V$404,0)),"") | B69: =IFERROR(INDEX(Register!$E$5:$E$404,MATCH(SMALL(Register!$V$5:$V$404,ROW()-59),Register!$V$5:$V$404,0)),"") | C69: =IFERROR(INDEX(Register!$D$5:$D$404,MATCH(SMALL(Register!$V$5:$V$404,ROW()-59),Register!$V$5:$V$404,0)),"") | D69: =IFERROR(INDEX(Register!$F$5:$F$404,MATCH(SMALL(Register!$V$5:$V$404,ROW()-59),Register!$V$5:$V$404,0)),"") | E69: =IFERROR(INDEX(Register!$H$5:$H$404,MATCH(SMALL(Register!$V$5:$V$404,ROW()-59),Register!$V$5:$V$404,0)),"") | F69: =IFERROR(INDEX(Register!$K$5:$K$404,MATCH(SMALL(Register!$V$5:$V$404,ROW()-59),Register!$V$5:$V$404,0)),"") | G69: =IFERROR(INDEX(Register!$O$5:$O$404,MATCH(SMALL(Register!$V$5:$V$404,ROW()-59),Register!$V$5:$V$404,0)),"") | H69: =IFERROR(INDEX(Register!$P$5:$P$404,MATCH(SMALL(Register!$V$5:$V$404,ROW()-59),Register!$V$5:$V$404,0)),"") | I69: =IFERROR(INDEX(Register!$Q$5:$Q$404,MATCH(SMALL(Register!$V$5:$V$404,ROW()-59),Register!$V$5:$V$404,0)),"")
A70: =IFERROR(INDEX(Register!$B$5:$B$404,MATCH(SMALL(Register!$V$5:$V$404,ROW()-59),Register!$V$5:$V$404,0)),"") | B70: =IFERROR(INDEX(Register!$E$5:$E$404,MATCH(SMALL(Register!$V$5:$V$404,ROW()-59),Register!$V$5:$V$404,0)),"") | C70: =IFERROR(INDEX(Register!$D$5:$D$404,MATCH(SMALL(Register!$V$5:$V$404,ROW()-59),Register!$V$5:$V$404,0)),"") | D70: =IFERROR(INDEX(Register!$F$5:$F$404,MATCH(SMALL(Register!$V$5:$V$404,ROW()-59),Register!$V$5:$V$404,0)),"") | E70: =IFERROR(INDEX(Register!$H$5:$H$404,MATCH(SMALL(Register!$V$5:$V$404,ROW()-59),Register!$V$5:$V$404,0)),"") | F70: =IFERROR(INDEX(Register!$K$5:$K$404,MATCH(SMALL(Register!$V$5:$V$404,ROW()-59),Register!$V$5:$V$404,0)),"") | G70: =IFERROR(INDEX(Register!$O$5:$O$404,MATCH(SMALL(Register!$V$5:$V$404,ROW()-59),Register!$V$5:$V$404,0)),"") | H70: =IFERROR(INDEX(Register!$P$5:$P$404,MATCH(SMALL(Register!$V$5:$V$404,ROW()-59),Register!$V$5:$V$404,0)),"") | I70: =IFERROR(INDEX(Register!$Q$5:$Q$404,MATCH(SMALL(Register!$V$5:$V$404,ROW()-59),Register!$V$5:$V$404,0)),"")
A71: =IFERROR(INDEX(Register!$B$5:$B$404,MATCH(SMALL(Register!$V$5:$V$404,ROW()-59),Register!$V$5:$V$404,0)),"") | B71: =IFERROR(INDEX(Register!$E$5:$E$404,MATCH(SMALL(Register!$V$5:$V$404,ROW()-59),Register!$V$5:$V$404,0)),"") | C71: =IFERROR(INDEX(Register!$D$5:$D$404,MATCH(SMALL(Register!$V$5:$V$404,ROW()-59),Register!$V$5:$V$404,0)),"") | D71: =IFERROR(INDEX(Register!$F$5:$F$404,MATCH(SMALL(Register!$V$5:$V$404,ROW()-59),Register!$V$5:$V$404,0)),"") | E71: =IFERROR(INDEX(Register!$H$5:$H$404,MATCH(SMALL(Register!$V$5:$V$404,ROW()-59),Register!$V$5:$V$404,0)),"") | F71: =IFERROR(INDEX(Register!$K$5:$K$404,MATCH(SMALL(Register!$V$5:$V$404,ROW()-59),Register!$V$5:$V$404,0)),"") | G71: =IFERROR(INDEX(Register!$O$5:$O$404,MATCH(SMALL(Register!$V$5:$V$404,ROW()-59),Register!$V$5:$V$404,0)),"") | H71: =IFERROR(INDEX(Register!$P$5:$P$404,MATCH(SMALL(Register!$V$5:$V$404,ROW()-59),Register!$V$5:$V$404,0)),"") | I71: =IFERROR(INDEX(Register!$Q$5:$Q$404,MATCH(SMALL(Register!$V$5:$V$404,ROW()-59),Register!$V$5:$V$404,0)),"")
... A89: =IFERROR(INDEX(Register!$B$5:$B$404,MATCH(SMALL(Register!$V$5:$V$404,ROW()-59),Register!$V$5:$V$404,0)),"") | B89: =IFERROR(INDEX(Register!$E$5:$E$404,MATCH(SMALL(Register!$V$5:$V$404,ROW()-59),Register!$V$5:$V$404,0)),"") | C89: =IFERROR(INDEX(Register!$D$5:$D$404,MATCH(SMALL(Register!$V$5:$V$404,ROW()-59),Register!$V$5:$V$404,0)),"") | D89: =IFERROR(INDEX(Register!$F$5:$F$404,MATCH(SMALL(Register!$V$5:$V$404,ROW()-59),Register!$V$5:$V$404,0)),"") | E89: =IFERROR(INDEX(Register!$H$5:$H$404,MATCH(SMALL(Register!$V$5:$V$404,ROW()-59),Register!$V$5:$V$404,0)),"") | F89: =IFERROR(INDEX(Register!$K$5:$K$404,MATCH(SMALL(Register!$V$5:$V$404,ROW()-59),Register!$V$5:$V$404,0)),"") | G89: =IFERROR(INDEX(Register!$O$5:$O$404,MATCH(SMALL(Register!$V$5:$V$404,ROW()-59),Register!$V$5:$V$404,0)),"") | H89: =IFERROR(INDEX(Register!$P$5:$P$404,MATCH(SMALL(Register!$V$5:$V$404,ROW()-59),Register!$V$5:$V$404,0)),"") | I89: =IFERROR(INDEX(Register!$Q$5:$Q$404,MATCH(SMALL(Register!$V$5:$V$404,ROW()-59),Register!$V$5:$V$404,0)),"")
A92: Who renews it / ใครต่ออายุ
A93: Owner | B93: the asset company (AMH …): building, entity, taxes, asset insurance, head agreements — เจ้าของอาคาร
A94: Property | B94: the hotel operation: guest-facing licences, staff, suppliers, OTAs — ฝ่ายโรงแรม
A96: Colours / สีบอกสถานะ
A97: Expired | B97: past the expiry date — เลยกำหนดแล้ว
A98: Urgent | B98: expires within 30 days — ครบกำหนดใน 30 วัน
A99: Due soon | B99: expires within 90 days — ครบกำหนดใน 90 วัน
A100: OK | B100: more than 90 days left — ยังมีเวลา
A101: No date | B101: expiry date not filled in yet — ยังไม่ได้ใส่วันหมดอายุ

Sheet Register
A1: Licence & Contract Register — Mitsui Thailand portfolio
A2: Type into the white columns only. Days left / Action by / Status calculate themselves. ใส่ข้อมูลเฉพาะช่องสีขาว ช่องสูตรจะคำนวณเอง
A4: No. | B4: Property | C4: Legal entity | D4: Category | E4: Renew by | F4: Item (EN) | G4: รายการ (TH) | H4: Authority / Counterparty | I4: Reference / Licence no. | J4: Issue date | K4: Expiry date | L4: Renewal cycle | M4: Notice (days) | N4: Action by | O4: Days left | P4: Status | Q4: Responsible | R4: Fee / Value (THB) | S4: Auto-renew | T4: Document location | U4: Notes | V4: SortKey
A5: =IF(F5="","",COUNTA($F$5:F5)) | B5: SR9 | C5: AMH Ratchada Co., Ltd. | D5: Licence | E5: Owner | F5: Hotel operating licence | G5: ใบอนุญาตประกอบธุรกิจโรงแรม | H5: Dept. of Provincial Administration / District Office | L5: Every 5 years | M5: 60 | N5: =IF(K5="","",K5-IF(M5="",0,M5)) | O5: =IF(K5="","",K5-TODAY()) | P5: =IF(F5="","",IF(K5="","No date",IF(O5<0,"Expired",IF(O5<=30,"Urgent",IF(O5<=90,"Due soon","OK"))))) | V5: =IF(F5="","",IF(K5="","",O5+ROW()/100000))
A6: =IF(F6="","",COUNTA($F$5:F6)) | B6: SR9 | C6: AMH Ratchada Co., Ltd. | D6: Permit | E6: Owner | F6: Building construction permit (อ.1) | G6: ใบอนุญาตก่อสร้างอาคาร (อ.1) | H6: Local authority (BMA / City Municipality) | L6: One-off | M6: 60 | N6: =IF(K6="","",K6-IF(M6="",0,M6)) | O6: =IF(K6="","",K6-TODAY()) | P6: =IF(F6="","",IF(K6="","No date",IF(O6<0,"Expired",IF(O6<=30,"Urgent",IF(O6<=90,"Due soon","OK"))))) | V6: =IF(F6="","",IF(K6="","",O6+ROW()/100000))
A7: =IF(F7="","",COUNTA($F$5:F7)) | B7: SR9 | C7: AMH Ratchada Co., Ltd. | D7: Certificate | E7: Owner | F7: Certificate of building use (อ.6) | G7: ใบรับรองการใช้อาคาร (อ.6) | H7: Local authority (BMA / City Municipality) | L7: One-off | M7: 60 | N7: =IF(K7="","",K7-IF(M7="",0,M7)) | O7: =IF(K7="","",K7-TODAY()) | P7: =IF(F7="","",IF(K7="","No date",IF(O7<0,"Expired",IF(O7<=30,"Urgent",IF(O7<=90,"Due soon","OK"))))) | V7: =IF(F7="","",IF(K7="","",O7+ROW()/100000))
A8: =IF(F8="","",COUNTA($F$5:F8)) | B8: SR9 | C8: AMH Ratchada Co., Ltd. | D8: Certificate | E8: Owner | F8: Annual building inspection report (ร.1) | G8: รายงานการตรวจสอบอาคารประจำปี (ร.1) | H8: Dept. of Public Works / local authority | L8: Annual | M8: 60 | N8: =IF(K8="","",K8-IF(M8="",0,M8)) | O8: =IF(K8="","",K8-TODAY()) | P8: =IF(F8="","",IF(K8="","No date",IF(O8<0,"Expired",IF(O8<=30,"Urgent",IF(O8<=90,"Due soon","OK"))))) | V8: =IF(F8="","",IF(K8="","",O8+ROW()/100000))
A9: =IF(F9="","",COUNTA($F$5:F9)) | B9: SR9 | C9: AMH Ratchada Co., Ltd. | D9: Certificate | E9: Owner | F9: Fire protection system inspection | G9: การตรวจสอบระบบป้องกันอัคคีภัย | H9: Licensed inspector | L9: Annual | M9: 60 | N9: =IF(K9="","",K9-IF(M9="",0,M9)) | O9: =IF(K9="","",K9-TODAY()) | P9: =IF(F9="","",IF(K9="","No date",IF(O9<0,"Expired",IF(O9<=30,"Urgent",IF(O9<=90,"Due soon","OK"))))) | V9: =IF(F9="","",IF(K9="","",O9+ROW()/100000))
A10: =IF(F10="","",COUNTA($F$5:F10)) | B10: SR9 | C10: AMH Ratchada Co., Ltd. | D10: Certificate | E10: Owner | F10: Lift / elevator inspection certificate | G10: ใบรับรองการตรวจสอบลิฟต์ | H10: Licensed engineer | L10: Annual | M10: 60 | N10: =IF(K10="","",K10-IF(M10="",0,M10)) | O10: =IF(K10="","",K10-TODAY()) | P10: =IF(F10="","",IF(K10="","No date",IF(O10<0,"Expired",IF(O10<=30,"Urgent",IF(O10<=90,"Due soon","OK"))))) | V10: =IF(F10="","",IF(K10="","",O10+ROW()/100000))
A11: =IF(F11="","",COUNTA($F$5:F11)) | B11: SR9 | C11: AMH Ratchada Co., Ltd. | D11: Certificate | E11: Owner | F11: Electrical system inspection | G11: การตรวจสอบระบบไฟฟ้า | H11: Licensed engineer | L11: Annual | M11: 60 | N11: =IF(K11="","",K11-IF(M11="",0,M11)) | O11: =IF(K11="","",K11-TODAY()) | P11: =IF(F11="","",IF(K11="","No date",IF(O11<0,"Expired",IF(O11<=30,"Urgent",IF(O11<=90,"Due soon","OK"))))) | V11: =IF(F11="","",IF(K11="","",O11+ROW()/100000))
A12: =IF(F12="","",COUNTA($F$5:F12)) | B12: SR9 | C12: AMH Ratchada Co., Ltd. | D12: Certificate | E12: Owner | F12: Generator / fuel storage permit | G12: ใบอนุญาตเครื่องกำเนิดไฟฟ้า / เก็บน้ำมันเชื้อเพลิง | H12: Dept. of Energy Business / local authority | L12: Annual | M12: 60 | N12: =IF(K12="","",K12-IF(M12="",0,M12)) | O12: =IF(K12="","",K12-TODAY()) | P12: =IF(F12="","",IF(K12="","No date",IF(O12<0,"Expired",IF(O12<=30,"Urgent",IF(O12<=90,"Due soon","OK"))))) | V12: =IF(F12="","",IF(K12="","",O12+ROW()/100000))
A13: =IF(F13="","",COUNTA($F$5:F13)) | B13: SR9 | C13: AMH Ratchada Co., Ltd. | D13: Certificate | E13: Owner | F13: Boiler / pressure vessel inspection | G13: การตรวจสอบหม้อไอน้ำ / ภาชนะรับแรงดัน | H13: Licensed engineer | L13: Annual | M13: 60 | N13: =IF(K13="","",K13-IF(M13="",0,M13)) | O13: =IF(K13="","",K13-TODAY()) | P13: =IF(F13="","",IF(K13="","No date",IF(O13<0,"Expired",IF(O13<=30,"Urgent",IF(O13<=90,"Due soon","OK"))))) | V13: =IF(F13="","",IF(K13="","",O13+ROW()/100000))
A14: =IF(F14="","",COUNTA($F$5:F14)) | B14: SR9 | C14: AMH Ratchada Co., Ltd. | D14: Certificate | E14: Owner | F14: EIA environmental monitoring report | G14: รายงานผลการปฏิบัติตามมาตรการ EIA | H14: Office of Natural Resources & Environmental Policy (ONEP) | L14: Other | M14: 60 | N14: =IF(K14="","",K14-IF(M14="",0,M14)) | O14: =IF(K14="","",K14-TODAY()) | P14: =IF(F14="","",IF(K14="","No date",IF(O14<0,"Expired",IF(O14<=30,"Urgent",IF(O14<=90,"Due soon","OK"))))) | V14: =IF(F14="","",IF(K14="","",O14+ROW()/100000))
A15: =IF(F15="","",COUNTA($F$5:F15)) | B15: SR9 | C15: AMH Ratchada Co., Ltd. | D15: Tax / Registration | E15: Owner | F15: Signage tax (billboard) | G15: ภาษีป้าย | H15: Local authority | L15: Annual | M15: 60 | N15: =IF(K15="","",K15-IF(M15="",0,M15)) | O15: =IF(K15="","",K15-TODAY()) | P15: =IF(F15="","",IF(K15="","No date",IF(O15<0,"Expired",IF(O15<=30,"Urgent",IF(O15<=90,"Due soon","OK"))))) | V15: =IF(F15="","",IF(K15="","",O15+ROW()/100000))
A16: =IF(F16="","",COUNTA($F$5:F16)) | B16: SR9 | C16: AMH Ratchada Co., Ltd. | D16: Tax / Registration | E16: Owner | F16: Land & building tax | G16: ภาษีที่ดินและสิ่งปลูกสร้าง | H16: Local authority | L16: Annual | M16: 60 | N16: =IF(K16="","",K16-IF(M16="",0,M16)) | O16: =IF(K16="","",K16-TODAY()) | P16: =IF(F16="","",IF(K16="","No date",IF(O16<0,"Expired",IF(O16<=30,"Urgent",IF(O16<=90,"Due soon","OK"))))) | V16: =IF(F16="","",IF(K16="","",O16+ROW()/100000))
... A24: =IF(F24="","",COUNTA($F$5:F24)) | B24: SR9 | C24: AMH Ratchada Co., Ltd. | D24: Contract - Management | E24: Owner | F24: Technical services / central fee agreement | G24: สัญญาค่าบริการส่วนกลาง | H24: Ascott International Management (Thailand) Ltd. | L24: Rolling / evergreen | M24: 60 | N24: =IF(K24="","",K24-IF(M24="",0,M24)) | O24: =IF(K24="","",K24-TODAY()) | P24: =IF(F24="","",IF(K24="","No date",IF(O24<0,"Expired",IF(O24<=30,"Urgent",IF(O24<=90,"Due soon","OK"))))) | V24: =IF(F24="","",IF(K24="","",O24+ROW()/100000))
A25: =IF(F25="","",COUNTA($F$5:F25)) | B25: SR9 | C25: AMH Ratchada Co., Ltd. | D25: Contract - Service | E25: Owner | F25: Lift maintenance | G25: สัญญาบำรุงรักษาลิฟต์ | L25: Annual | M25: 60 | N25: =IF(K25="","",K25-IF(M25="",0,M25)) | O25: =IF(K25="","",K25-TODAY()) | P25: =IF(F25="","",IF(K25="","No date",IF(O25<0,"Expired",IF(O25<=30,"Urgent",IF(O25<=90,"Due soon","OK"))))) | V25: =IF(F25="","",IF(K25="","",O25+ROW()/100000))
A26: =IF(F26="","",COUNTA($F$5:F26)) | B26: SR9 | C26: AMH Ratchada Co., Ltd. | D26: Contract - Service | E26: Owner | F26: HVAC / chiller maintenance | G26: สัญญาบำรุงรักษาระบบปรับอากาศ | L26: Annual | M26: 60 | N26: =IF(K26="","",K26-IF(M26="",0,M26)) | O26: =IF(K26="","",K26-TODAY()) | P26: =IF(F26="","",IF(K26="","No date",IF(O26<0,"Expired",IF(O26<=30,"Urgent",IF(O26<=90,"Due soon","OK"))))) | V26: =IF(F26="","",IF(K26="","",O26+ROW()/100000))
A27: =IF(F27="","",COUNTA($F$5:F27)) | B27: SR9 | C27: AMH Ratchada Co., Ltd. | D27: Contract - Service | E27: Owner | F27: Fire system maintenance | G27: สัญญาบำรุงรักษาระบบดับเพลิง | L27: Annual | M27: 60 | N27: =IF(K27="","",K27-IF(M27="",0,M27)) | O27: =IF(K27="","",K27-TODAY()) | P27: =IF(F27="","",IF(K27="","No date",IF(O27<0,"Expired",IF(O27<=30,"Urgent",IF(O27<=90,"Due soon","OK"))))) | V27: =IF(F27="","",IF(K27="","",O27+ROW()/100000))
A28: =IF(F28="","",COUNTA($F$5:F28)) | B28: SR9 | C28: AMH Ratchada Co., Ltd. | D28: Contract - Service | E28: Owner | F28: External audit & tax agent | G28: สัญญาผู้สอบบัญชีและที่ปรึกษาภาษี | L28: Annual | M28: 60 | N28: =IF(K28="","",K28-IF(M28="",0,M28)) | O28: =IF(K28="","",K28-TODAY()) | P28: =IF(F28="","",IF(K28="","No date",IF(O28<0,"Expired",IF(O28<=30,"Urgent",IF(O28<=90,"Due soon","OK"))))) | V28: =IF(F28="","",IF(K28="","",O28+ROW()/100000))
A29: =IF(F29="","",COUNTA($F$5:F29)) | B29: SR9 | C29: AMH Ratchada Co., Ltd. | D29: Contract - Utility | E29: Owner | F29: Electricity supply | G29: สัญญาไฟฟ้า | L29: Rolling / evergreen | M29: 60 | N29: =IF(K29="","",K29-IF(M29="",0,M29)) | O29: =IF(K29="","",K29-TODAY()) | P29: =IF(F29="","",IF(K29="","No date",IF(O29<0,"Expired",IF(O29<=30,"Urgent",IF(O29<=90,"Due soon","OK"))))) | V29: =IF(F29="","",IF(K29="","",O29+ROW()/100000))
A30: =IF(F30="","",COUNTA($F$5:F30)) | B30: SR9 | C30: AMH Ratchada Co., Ltd. | D30: Contract - Utility | E30: Owner | F30: Water supply | G30: สัญญาน้ำประปา | L30: Rolling / evergreen | M30: 60 | N30: =IF(K30="","",K30-IF(M30="",0,M30)) | O30: =IF(K30="","",K30-TODAY()) | P30: =IF(F30="","",IF(K30="","No date",IF(O30<0,"Expired",IF(O30<=30,"Urgent",IF(O30<=90,"Due soon","OK"))))) | V30: =IF(F30="","",IF(K30="","",O30+ROW()/100000))
A31: =IF(F31="","",COUNTA($F$5:F31)) | B31: SR9 | C31: AMH Ratchada Co., Ltd. | D31: Contract - Lease / Finance | E31: Owner | F31: Land / building lease | G31: สัญญาเช่าที่ดิน / อาคาร | L31: Other | M31: 60 | N31: =IF(K31="","",K31-IF(M31="",0,M31)) | O31: =IF(K31="","",K31-TODAY()) | P31: =IF(F31="","",IF(K31="","No date",IF(O31<0,"Expired",IF(O31<=30,"Urgent",IF(O31<=90,"Due soon","OK"))))) | V31: =IF(F31="","",IF(K31="","",O31+ROW()/100000))
A32: =IF(F32="","",COUNTA($F$5:F32)) | B32: SR9 | C32: AMH Ratchada Co., Ltd. | D32: Contract - Lease / Finance | E32: Owner | F32: Bank facility / loan agreement | G32: สัญญาสินเชื่อธนาคาร | L32: Other | M32: 60 | N32: =IF(K32="","",K32-IF(M32="",0,M32)) | O32: =IF(K32="","",K32-TODAY()) | P32: =IF(F32="","",IF(K32="","No date",IF(O32<0,"Expired",IF(O32<=30,"Urgent",IF(O32<=90,"Due soon","OK"))))) | V32: =IF(F32="","",IF(K32="","",O32+ROW()/100000))
A33: =IF(F33="","",COUNTA($F$5:F33)) | B33: SR9 | C33: AMH Ratchada Co., Ltd. | D33: Licence | E33: Property | F33: Hotel manager licence | G33: ใบอนุญาตผู้จัดการโรงแรม | H33: Dept. of Provincial Administration / District Office | L33: Every 5 years | M33: 60 | N33: =IF(K33="","",K33-IF(M33="",0,M33)) | O33: =IF(K33="","",K33-TODAY()) | P33: =IF(F33="","",IF(K33="","No date",IF(O33<0,"Expired",IF(O33<=30,"Urgent",IF(O33<=90,"Due soon","OK"))))) | V33: =IF(F33="","",IF(K33="","",O33+ROW()/100000))
A34: =IF(F34="","",COUNTA($F$5:F34)) | B34: SR9 | C34: AMH Ratchada Co., Ltd. | D34: Licence | E34: Property | F34: Food establishment licence | G34: ใบอนุญาตสถานที่จำหน่ายอาหาร/สะสมอาหาร | H34: Local authority (BMA / City Municipality) | L34: Annual | M34: 60 | N34: =IF(K34="","",K34-IF(M34="",0,M34)) | O34: =IF(K34="","",K34-TODAY()) | P34: =IF(F34="","",IF(K34="","No date",IF(O34<0,"Expired",IF(O34<=30,"Urgent",IF(O34<=90,"Due soon","OK"))))) | V34: =IF(F34="","",IF(K34="","",O34+ROW()/100000))
A35: =IF(F35="","",COUNTA($F$5:F35)) | B35: SR9 | C35: AMH Ratchada Co., Ltd. | D35: Licence | E35: Property | F35: Alcohol sale licence | G35: ใบอนุญาตขายสุรา | H35: Excise Department | L35: Annual | M35: 60 | N35: =IF(K35="","",K35-IF(M35="",0,M35)) | O35: =IF(K35="","",K35-TODAY()) | P35: =IF(F35="","",IF(K35="","No date",IF(O35<0,"Expired",IF(O35<=30,"Urgent",IF(O35<=90,"Due soon","OK"))))) | V35: =IF(F35="","",IF(K35="","",O35+ROW()/100000))
A36: =IF(F36="","",COUNTA($F$5:F36)) | B36: SR9 | C36: AMH Ratchada Co., Ltd. | D36: Licence | E36: Property | F36: Tobacco sale licence | G36: ใบอนุญาตขายยาสูบ | H36: Excise Department | L36: Annual | M36: 60 | N36: =IF(K36="","",K36-IF(M36="",0,M36)) | O36: =IF(K36="","",K36-TODAY()) | P36: =IF(F36="","",IF(K36="","No date",IF(O36<0,"Expired",IF(O36<=30,"Urgent",IF(O36<=90,"Due soon","OK"))))) | V36: =IF(F36="","",IF(K36="","",O36+ROW()/100000))
A37: =IF(F37="","",COUNTA($F$5:F37)) | B37: SR9 | C37: AMH Ratchada Co., Ltd. | D37: Licence | E37: Property | F37: Swimming pool / public place licence | G37: ใบอนุญาตสถานที่สาธารณะ (สระว่ายน้ำ) | H37: Local authority (BMA / City Municipality) | L37: Annual | M37: 60 | N37: =IF(K37="","",K37-IF(M37="",0,M37)) | O37: =IF(K37="","",K37-TODAY()) | P37: =IF(F37="","",IF(K37="","No date",IF(O37<0,"Expired",IF(O37<=30,"Urgent",IF(O37<=90,"Due soon","OK"))))) | V37: =IF(F37="","",IF(K37="","",O37+ROW()/100000))
A38: =IF(F38="","",COUNTA($F$5:F38)) | B38: SR9 | C38: AMH Ratchada Co., Ltd. | D38: Licence | E38: Property | F38: Radio / walkie-talkie frequency licence | G38: ใบอนุญาตวิทยุคมนาคม | H38: NBTC | L38: Annual | M38: 60 | N38: =IF(K38="","",K38-IF(M38="",0,M38)) | O38: =IF(K38="","",K38-TODAY()) | P38: =IF(F38="","",IF(K38="","No date",IF(O38<0,"Expired",IF(O38<=30,"Urgent",IF(O38<=90,"Due soon","OK"))))) | V38: =IF(F38="","",IF(K38="","",O38+ROW()/100000))
A39: =IF(F39="","",COUNTA($F$5:F39)) | B39: SR9 | C39: AMH Ratchada Co., Ltd. | D39: Licence | E39: Property | F39: Music / copyright public performance licence | G39: ใบอนุญาตเผยแพร่งานดนตรี (MCT / ลิขสิทธิ์) | H39: MCT / Phonorights / collecting societies | L39: Annual | M39: 60 | N39: =IF(K39="","",K39-IF(M39="",0,M39)) | O39: =IF(K39="","",K39-TODAY()) | P39: =IF(F39="","",IF(K39="","No date",IF(O39<0,"Expired",IF(O39<=30,"Urgent",IF(O39<=90,"Due soon","OK"))))) | V39: =IF(F39="","",IF(K39="","",O39+ROW()/100000))
A40: =IF(F40="","",COUNTA($F$5:F40)) | B40: SR9 | C40: AMH Ratchada Co., Ltd. | D40: Permit | E40: Property | F40: Waste / refuse disposal permit | G40: ใบอนุญาตกำจัดสิ่งปฏิกูลและมูลฝอย | H40: Local authority | L40: Annual | M40: 60 | N40: =IF(K40="","",K40-IF(M40="",0,M40)) | O40: =IF(K40="","",K40-TODAY()) | P40: =IF(F40="","",IF(K40="","No date",IF(O40<0,"Expired",IF(O40<=30,"Urgent",IF(O40<=90,"Due soon","OK"))))) | V40: =IF(F40="","",IF(K40="","",O40+ROW()/100000))
A41: =IF(F41="","",COUNTA($F$5:F41)) | B41: SR9 | C41: AMH Ratchada Co., Ltd. | D41: Permit | E41: Property | F41: Work permits / visas — foreign staff | G41: ใบอนุญาตทำงาน / วีซ่าพนักงานต่างชาติ | H41: Dept. of Employment / Immigration | L41: Annual | M41: 60 | N41: =IF(K41="","",K41-IF(M41="",0,M41)) | O41: =IF(K41="","",K41-TODAY()) | P41: =IF(F41="","",IF(K41="","No date",IF(O41<0,"Expired",IF(O41<=30,"Urgent",IF(O41<=90,"Due soon","OK"))))) | V41: =IF(F41="","",IF(K41="","",O41+ROW()/100000))
A42: =IF(F42="","",COUNTA($F$5:F42)) | B42: SR9 | C42: AMH Ratchada Co., Ltd. | D42: Certificate | E42: Property | F42: Swimming pool water quality test | G42: ผลตรวจคุณภาพน้ำสระว่ายน้ำ | H42: Accredited laboratory | L42: Other | M42: 60 | N42: =IF(K42="","",K42-IF(M42="",0,M42)) | O42: =IF(K42="","",K42-TODAY()) | P42: =IF(F42="","",IF(K42="","No date",IF(O42<0,"Expired",IF(O42<=30,"Urgent",IF(O42<=90,"Due soon","OK"))))) | V42: =IF(F42="","",IF(K42="","",O42+ROW()/100000))
A43: =IF(F43="","",COUNTA($F$5:F43)) | B43: SR9 | C43: AMH Ratchada Co., Ltd. | D43: Certificate | E43: Property | F43: Drinking / potable water quality test | G43: ผลตรวจคุณภาพน้ำดื่ม | H43: Accredited laboratory | L43: Annual | M43: 60 | N43: =IF(K43="","",K43-IF(M43="",0,M43)) | O43: =IF(K43="","",K43-TODAY()) | P43: =IF(F43="","",IF(K43="","No date",IF(O43<0,"Expired",IF(O43<=30,"Urgent",IF(O43<=90,"Due soon","OK"))))) | V43: =IF(F43="","",IF(K43="","",O43+ROW()/100000))
A44: =IF(F44="","",COUNTA($F$5:F44)) | B44: SR9 | C44: AMH Ratchada Co., Ltd. | D44: Certificate | E44: Property | F44: Wastewater treatment monitoring report | G44: รายงานผลการตรวจวัดคุณภาพน้ำทิ้ง | H44: Dept. of Pollution Control / local authority | L44: Other | M44: 60 | N44: =IF(K44="","",K44-IF(M44="",0,M44)) | O44: =IF(K44="","",K44-TODAY()) | P44: =IF(F44="","",IF(K44="","No date",IF(O44<0,"Expired",IF(O44<=30,"Urgent",IF(O44<=90,"Due soon","OK"))))) | V44: =IF(F44="","",IF(K44="","",O44+ROW()/100000))
... A52: =IF(F52="","",COUNTA($F$5:F52)) | B52: SR9 | C52: AMH Ratchada Co., Ltd. | D52: Contract - Service | E52: Property | F52: F&B outlet / catering operator | G52: สัญญาผู้ประกอบการอาหารและเครื่องดื่ม | H52: DK Wow Venture Co., Ltd. | L52: Annual | M52: 60 | N52: =IF(K52="","",K52-IF(M52="",0,M52)) | O52: =IF(K52="","",K52-TODAY()) | P52: =IF(F52="","",IF(K52="","No date",IF(O52<0,"Expired",IF(O52<=30,"Urgent",IF(O52<=90,"Due soon","OK"))))) | V52: =IF(F52="","",IF(K52="","",O52+ROW()/100000))
A53: =IF(F53="","",COUNTA($F$5:F53)) | B53: SR9 | C53: AMH Ratchada Co., Ltd. | D53: Contract - Service | E53: Property | F53: Security services | G53: สัญญาบริการรักษาความปลอดภัย | L53: Annual | M53: 60 | N53: =IF(K53="","",K53-IF(M53="",0,M53)) | O53: =IF(K53="","",K53-TODAY()) | P53: =IF(F53="","",IF(K53="","No date",IF(O53<0,"Expired",IF(O53<=30,"Urgent",IF(O53<=90,"Due soon","OK"))))) | V53: =IF(F53="","",IF(K53="","",O53+ROW()/100000))
A54: =IF(F54="","",COUNTA($F$5:F54)) | B54: SR9 | C54: AMH Ratchada Co., Ltd. | D54: Contract - Service | E54: Property | F54: Cleaning / housekeeping outsource | G54: สัญญาบริการทำความสะอาด | L54: Annual | M54: 60 | N54: =IF(K54="","",K54-IF(M54="",0,M54)) | O54: =IF(K54="","",K54-TODAY()) | P54: =IF(F54="","",IF(K54="","No date",IF(O54<0,"Expired",IF(O54<=30,"Urgent",IF(O54<=90,"Due soon","OK"))))) | V54: =IF(F54="","",IF(K54="","",O54+ROW()/100000))
A55: =IF(F55="","",COUNTA($F$5:F55)) | B55: SR9 | C55: AMH Ratchada Co., Ltd. | D55: Contract - Service | E55: Property | F55: Pest control | G55: สัญญากำจัดแมลง | L55: Annual | M55: 60 | N55: =IF(K55="","",K55-IF(M55="",0,M55)) | O55: =IF(K55="","",K55-TODAY()) | P55: =IF(F55="","",IF(K55="","No date",IF(O55<0,"Expired",IF(O55<=30,"Urgent",IF(O55<=90,"Due soon","OK"))))) | V55: =IF(F55="","",IF(K55="","",O55+ROW()/100000))
A56: =IF(F56="","",COUNTA($F$5:F56)) | B56: SR9 | C56: AMH Ratchada Co., Ltd. | D56: Contract - Service | E56: Property | F56: Landscaping / plant care | G56: สัญญาดูแลต้นไม้และภูมิทัศน์ | L56: Annual | M56: 60 | N56: =IF(K56="","",K56-IF(M56="",0,M56)) | O56: =IF(K56="","",K56-TODAY()) | P56: =IF(F56="","",IF(K56="","No date",IF(O56<0,"Expired",IF(O56<=30,"Urgent",IF(O56<=90,"Due soon","OK"))))) | V56: =IF(F56="","",IF(K56="","",O56+ROW()/100000))
A57: =IF(F57="","",COUNTA($F$5:F57)) | B57: SR9 | C57: AMH Ratchada Co., Ltd. | D57: Contract - Service | E57: Property | F57: Waste collection | G57: สัญญาเก็บขนขยะ | L57: Annual | M57: 60 | N57: =IF(K57="","",K57-IF(M57="",0,M57)) | O57: =IF(K57="","",K57-TODAY()) | P57: =IF(F57="","",IF(K57="","No date",IF(O57<0,"Expired",IF(O57<=30,"Urgent",IF(O57<=90,"Due soon","OK"))))) | V57: =IF(F57="","",IF(K57="","",O57+ROW()/100000))
A58: =IF(F58="","",COUNTA($F$5:F58)) | B58: SR9 | C58: AMH Ratchada Co., Ltd. | D58: Contract - Service | E58: Property | F58: PMS / property management system licence | G58: สัญญาระบบบริหารโรงแรม (PMS) | L58: Annual | M58: 60 | N58: =IF(K58="","",K58-IF(M58="",0,M58)) | O58: =IF(K58="","",K58-TODAY()) | P58: =IF(F58="","",IF(K58="","No date",IF(O58<0,"Expired",IF(O58<=30,"Urgent",IF(O58<=90,"Due soon","OK"))))) | V58: =IF(F58="","",IF(K58="","",O58+ROW()/100000))
A59: =IF(F59="","",COUNTA($F$5:F59)) | B59: SR9 | C59: AMH Ratchada Co., Ltd. | D59: Contract - Service | E59: Property | F59: Internet / IPTV / telephone | G59: สัญญาอินเทอร์เน็ต / IPTV / โทรศัพท์ | L59: Annual | M59: 60 | N59: =IF(K59="","",K59-IF(M59="",0,M59)) | O59: =IF(K59="","",K59-TODAY()) | P59: =IF(F59="","",IF(K59="","No date",IF(O59<0,"Expired",IF(O59<=30,"Urgent",IF(O59<=90,"Due soon","OK"))))) | V59: =IF(F59="","",IF(K59="","",O59+ROW()/100000))
A60: =IF(F60="","",COUNTA($F$5:F60)) | B60: AES | C60: AMH Sathorn Co., Ltd. | D60: Licence | E60: Owner | F60: Hotel operating licence | G60: ใบอนุญาตประกอบธุรกิจโรงแรม | H60: Dept. of Provincial Administration / District Office | L60: Every 5 years | M60: 60 | N60: =IF(K60="","",K60-IF(M60="",0,M60)) | O60: =IF(K60="","",K60-TODAY()) | P60: =IF(F60="","",IF(K60="","No date",IF(O60<0,"Expired",IF(O60<=30,"Urgent",IF(O60<=90,"Due soon","OK"))))) | V60: =IF(F60="","",IF(K60="","",O60+ROW()/100000))
A61: =IF(F61="","",COUNTA($F$5:F61)) | B61: AES | C61: AMH Sathorn Co., Ltd. | D61: Permit | E61: Owner | F61: Building construction permit (อ.1) | G61: ใบอนุญาตก่อสร้างอาคาร (อ.1) | H61: Local authority (BMA / City Municipality) | L61: One-off | M61: 60 | N61: =IF(K61="","",K61-IF(M61="",0,M61)) | O61: =IF(K61="","",K61-TODAY()) | P61: =IF(F61="","",IF(K61="","No date",IF(O61<0,"Expired",IF(O61<=30,"Urgent",IF(O61<=90,"Due soon","OK"))))) | V61: =IF(F61="","",IF(K61="","",O61+ROW()/100000))
A62: =IF(F62="","",COUNTA($F$5:F62)) | B62: AES | C62: AMH Sathorn Co., Ltd. | D62: Certificate | E62: Owner | F62: Certificate of building use (อ.6) | G62: ใบรับรองการใช้อาคาร (อ.6) | H62: Local authority (BMA / City Municipality) | L62: One-off | M62: 60 | N62: =IF(K62="","",K62-IF(M62="",0,M62)) | O62: =IF(K62="","",K62-TODAY()) | P62: =IF(F62="","",IF(K62="","No date",IF(O62<0,"Expired",IF(O62<=30,"Urgent",IF(O62<=90,"Due soon","OK"))))) | V62: =IF(F62="","",IF(K62="","",O62+ROW()/100000))
A63: =IF(F63="","",COUNTA($F$5:F63)) | B63: AES | C63: AMH Sathorn Co., Ltd. | D63: Certificate | E63: Owner | F63: Annual building inspection report (ร.1) | G63: รายงานการตรวจสอบอาคารประจำปี (ร.1) | H63: Dept. of Public Works / local authority | L63: Annual | M63: 60 | N63: =IF(K63="","",K63-IF(M63="",0,M63)) | O63: =IF(K63="","",K63-TODAY()) | P63: =IF(F63="","",IF(K63="","No date",IF(O63<0,"Expired",IF(O63<=30,"Urgent",IF(O63<=90,"Due soon","OK"))))) | V63: =IF(F63="","",IF(K63="","",O63+ROW()/100000))
A64: =IF(F64="","",COUNTA($F$5:F64)) | B64: AES | C64: AMH Sathorn Co., Ltd. | D64: Certificate | E64: Owner | F64: Fire protection system inspection | G64: การตรวจสอบระบบป้องกันอัคคีภัย | H64: Licensed inspector | L64: Annual | M64: 60 | N64: =IF(K64="","",K64-IF(M64="",0,M64)) | O64: =IF(K64="","",K64-TODAY()) | P64: =IF(F64="","",IF(K64="","No date",IF(O64<0,"Expired",IF(O64<=30,"Urgent",IF(O64<=90,"Due soon","OK"))))) | V64: =IF(F64="","",IF(K64="","",O64+ROW()/100000))
A65: =IF(F65="","",COUNTA($F$5:F65)) | B65: AES | C65: AMH Sathorn Co., Ltd. | D65: Certificate | E65: Owner | F65: Lift / elevator inspection certificate | G65: ใบรับรองการตรวจสอบลิฟต์ | H65: Licensed engineer | L65: Annual | M65: 60 | N65: =IF(K65="","",K65-IF(M65="",0,M65)) | O65: =IF(K65="","",K65-TODAY()) | P65: =IF(F65="","",IF(K65="","No date",IF(O65<0,"Expired",IF(O65<=30,"Urgent",IF(O65<=90,"Due soon","OK"))))) | V65: =IF(F65="","",IF(K65="","",O65+ROW()/100000))
A66: =IF(F66="","",COUNTA($F$5:F66)) | B66: AES | C66: AMH Sathorn Co., Ltd. | D66: Certificate | E66: Owner | F66: Electrical system inspection | G66: การตรวจสอบระบบไฟฟ้า | H66: Licensed engineer | L66: Annual | M66: 60 | N66: =IF(K66="","",K66-IF(M66="",0,M66)) | O66: =IF(K66="","",K66-TODAY()) | P66: =IF(F66="","",IF(K66="","No date",IF(O66<0,"Expired",IF(O66<=30,"Urgent",IF(O66<=90,"Due soon","OK"))))) | V66: =IF(F66="","",IF(K66="","",O66+ROW()/100000))
A67: =IF(F67="","",COUNTA($F$5:F67)) | B67: AES | C67: AMH Sathorn Co., Ltd. | D67: Certificate | E67: Owner | F67: Generator / fuel storage permit | G67: ใบอนุญาตเครื่องกำเนิดไฟฟ้า / เก็บน้ำมันเชื้อเพลิง | H67: Dept. of Energy Business / local authority | L67: Annual | M67: 60 | N67: =IF(K67="","",K67-IF(M67="",0,M67)) | O67: =IF(K67="","",K67-TODAY()) | P67: =IF(F67="","",IF(K67="","No date",IF(O67<0,"Expired",IF(O67<=30,"Urgent",IF(O67<=90,"Due soon","OK"))))) | V67: =IF(F67="","",IF(K67="","",O67+ROW()/100000))
A68: =IF(F68="","",COUNTA($F$5:F68)) | B68: AES | C68: AMH Sathorn Co., Ltd. | D68: Certificate | E68: Owner | F68: Boiler / pressure vessel inspection | G68: การตรวจสอบหม้อไอน้ำ / ภาชนะรับแรงดัน | H68: Licensed engineer | L68: Annual | M68: 60 | N68: =IF(K68="","",K68-IF(M68="",0,M68)) | O68: =IF(K68="","",K68-TODAY()) | P68: =IF(F68="","",IF(K68="","No date",IF(O68<0,"Expired",IF(O68<=30,"Urgent",IF(O68<=90,"Due soon","OK"))))) | V68: =IF(F68="","",IF(K68="","",O68+ROW()/100000))
A69: =IF(F69="","",COUNTA($F$5:F69)) | B69: AES | C69: AMH Sathorn Co., Ltd. | D69: Certificate | E69: Owner | F69: EIA environmental monitoring report | G69: รายงานผลการปฏิบัติตามมาตรการ EIA | H69: Office of Natural Resources & Environmental Policy (ONEP) | L69: Other | M69: 60 | N69: =IF(K69="","",K69-IF(M69="",0,M69)) | O69: =IF(K69="","",K69-TODAY()) | P69: =IF(F69="","",IF(K69="","No date",IF(O69<0,"Expired",IF(O69<=30,"Urgent",IF(O69<=90,"Due soon","OK"))))) | V69: =IF(F69="","",IF(K69="","",O69+ROW()/100000))
A70: =IF(F70="","",COUNTA($F$5:F70)) | B70: AES | C70: AMH Sathorn Co., Ltd. | D70: Tax / Registration | E70: Owner | F70: Signage tax (billboard) | G70: ภาษีป้าย | H70: Local authority | L70: Annual | M70: 60 | N70: =IF(K70="","",K70-IF(M70="",0,M70)) | O70: =IF(K70="","",K70-TODAY()) | P70: =IF(F70="","",IF(K70="","No date",IF(O70<0,"Expired",IF(O70<=30,"Urgent",IF(O70<=90,"Due soon","OK"))))) | V70: =IF(F70="","",IF(K70="","",O70+ROW()/100000))
A71: =IF(F71="","",COUNTA($F$5:F71)) | B71: AES | C71: AMH Sathorn Co., Ltd. | D71: Tax / Registration | E71: Owner | F71: Land & building tax | G71: ภาษีที่ดินและสิ่งปลูกสร้าง | H71: Local authority | L71: Annual | M71: 60 | N71: =IF(K71="","",K71-IF(M71="",0,M71)) | O71: =IF(K71="","",K71-TODAY()) | P71: =IF(F71="","",IF(K71="","No date",IF(O71<0,"Expired",IF(O71<=30,"Urgent",IF(O71<=90,"Due soon","OK"))))) | V71: =IF(F71="","",IF(K71="","",O71+ROW()/100000))
... A79: =IF(F79="","",COUNTA($F$5:F79)) | B79: AES | C79: AMH Sathorn Co., Ltd. | D79: Contract - Management | E79: Owner | F79: Technical services / central fee agreement | G79: สัญญาค่าบริการส่วนกลาง | H79: Ascott International Management (Thailand) Ltd. | L79: Rolling / evergreen | M79: 60 | N79: =IF(K79="","",K79-IF(M79="",0,M79)) | O79: =IF(K79="","",K79-TODAY()) | P79: =IF(F79="","",IF(K79="","No date",IF(O79<0,"Expired",IF(O79<=30,"Urgent",IF(O79<=90,"Due soon","OK"))))) | V79: =IF(F79="","",IF(K79="","",O79+ROW()/100000))
A80: =IF(F80="","",COUNTA($F$5:F80)) | B80: AES | C80: AMH Sathorn Co., Ltd. | D80: Contract - Service | E80: Owner | F80: Lift maintenance | G80: สัญญาบำรุงรักษาลิฟต์ | L80: Annual | M80: 60 | N80: =IF(K80="","",K80-IF(M80="",0,M80)) | O80: =IF(K80="","",K80-TODAY()) | P80: =IF(F80="","",IF(K80="","No date",IF(O80<0,"Expired",IF(O80<=30,"Urgent",IF(O80<=90,"Due soon","OK"))))) | V80: =IF(F80="","",IF(K80="","",O80+ROW()/100000))
A81: =IF(F81="","",COUNTA($F$5:F81)) | B81: AES | C81: AMH Sathorn Co., Ltd. | D81: Contract - Service | E81: Owner | F81: HVAC / chiller maintenance | G81: สัญญาบำรุงรักษาระบบปรับอากาศ | L81: Annual | M81: 60 | N81: =IF(K81="","",K81-IF(M81="",0,M81)) | O81: =IF(K81="","",K81-TODAY()) | P81: =IF(F81="","",IF(K81="","No date",IF(O81<0,"Expired",IF(O81<=30,"Urgent",IF(O81<=90,"Due soon","OK"))))) | V81: =IF(F81="","",IF(K81="","",O81+ROW()/100000))
A82: =IF(F82="","",COUNTA($F$5:F82)) | B82: AES | C82: AMH Sathorn Co., Ltd. | D82: Contract - Service | E82: Owner | F82: Fire system maintenance | G82: สัญญาบำรุงรักษาระบบดับเพลิง | L82: Annual | M82: 60 | N82: =IF(K82="","",K82-IF(M82="",0,M82)) | O82: =IF(K82="","",K82-TODAY()) | P82: =IF(F82="","",IF(K82="","No date",IF(O82<0,"Expired",IF(O82<=30,"Urgent",IF(O82<=90,"Due soon","OK"))))) | V82: =IF(F82="","",IF(K82="","",O82+ROW()/100000))
A83: =IF(F83="","",COUNTA($F$5:F83)) | B83: AES | C83: AMH Sathorn Co., Ltd. | D83: Contract - Service | E83: Owner | F83: External audit & tax agent | G83: สัญญาผู้สอบบัญชีและที่ปรึกษาภาษี | L83: Annual | M83: 60 | N83: =IF(K83="","",K83-IF(M83="",0,M83)) | O83: =IF(K83="","",K83-TODAY()) | P83: =IF(F83="","",IF(K83="","No date",IF(O83<0,"Expired",IF(O83<=30,"Urgent",IF(O83<=90,"Due soon","OK"))))) | V83: =IF(F83="","",IF(K83="","",O83+ROW()/100000))
A84: =IF(F84="","",COUNTA($F$5:F84)) | B84: AES | C84: AMH Sathorn Co., Ltd. | D84: Contract - Utility | E84: Owner | F84: Electricity supply | G84: สัญญาไฟฟ้า | L84: Rolling / evergreen | M84: 60 | N84: =IF(K84="","",K84-IF(M84="",0,M84)) | O84: =IF(K84="","",K84-TODAY()) | P84: =IF(F84="","",IF(K84="","No date",IF(O84<0,"Expired",IF(O84<=30,"Urgent",IF(O84<=90,"Due soon","OK"))))) | V84: =IF(F84="","",IF(K84="","",O84+ROW()/100000))
A85: =IF(F85="","",COUNTA($F$5:F85)) | B85: AES | C85: AMH Sathorn Co., Ltd. | D85: Contract - Utility | E85: Owner | F85: Water supply | G85: สัญญาน้ำประปา | L85: Rolling / evergreen | M85: 60 | N85: =IF(K85="","",K85-IF(M85="",0,M85)) | O85: =IF(K85="","",K85-TODAY()) | P85: =IF(F85="","",IF(K85="","No date",IF(O85<0,"Expired",IF(O85<=30,"Urgent",IF(O85<=90,"Due soon","OK"))))) | V85: =IF(F85="","",IF(K85="","",O85+ROW()/100000))
A86: =IF(F86="","",COUNTA($F$5:F86)) | B86: AES | C86: AMH Sathorn Co., Ltd. | D86: Contract - Lease / Finance | E86: Owner | F86: Land / building lease | G86: สัญญาเช่าที่ดิน / อาคาร | L86: Other | M86: 60 | N86: =IF(K86="","",K86-IF(M86="",0,M86)) | O86: =IF(K86="","",K86-TODAY()) | P86: =IF(F86="","",IF(K86="","No date",IF(O86<0,"Expired",IF(O86<=30,"Urgent",IF(O86<=90,"Due soon","OK"))))) | V86: =IF(F86="","",IF(K86="","",O86+ROW()/100000))
A87: =IF(F87="","",COUNTA($F$5:F87)) | B87: AES | C87: AMH Sathorn Co., Ltd. | D87: Contract - Lease / Finance | E87: Owner | F87: Bank facility / loan agreement | G87: สัญญาสินเชื่อธนาคาร | L87: Other | M87: 60 | N87: =IF(K87="","",K87-IF(M87="",0,M87)) | O87: =IF(K87="","",K87-TODAY()) | P87: =IF(F87="","",IF(K87="","No date",IF(O87<0,"Expired",IF(O87<=30,"Urgent",IF(O87<=90,"Due soon","OK"))))) | V87: =IF(F87="","",IF(K87="","",O87+ROW()/100000))
A88: =IF(F88="","",COUNTA($F$5:F88)) | B88: AES | C88: AMH Sathorn Co., Ltd. | D88: Licence | E88: Property | F88: Hotel manager licence | G88: ใบอนุญาตผู้จัดการโรงแรม | H88: Dept. of Provincial Administration / District Office | L88: Every 5 years | M88: 60 | N88: =IF(K88="","",K88-IF(M88="",0,M88)) | O88: =IF(K88="","",K88-TODAY()) | P88: =IF(F88="","",IF(K88="","No date",IF(O88<0,"Expired",IF(O88<=30,"Urgent",IF(O88<=90,"Due soon","OK"))))) | V88: =IF(F88="","",IF(K88="","",O88+ROW()/100000))
A89: =IF(F89="","",COUNTA($F$5:F89)) | B89: AES | C89: AMH Sathorn Co., Ltd. | D89: Licence | E89: Property | F89: Food establishment licence | G89: ใบอนุญาตสถานที่จำหน่ายอาหาร/สะสมอาหาร | H89: Local authority (BMA / City Municipality) | L89: Annual | M89: 60 | N89: =IF(K89="","",K89-IF(M89="",0,M89)) | O89: =IF(K89="","",K89-TODAY()) | P89: =IF(F89="","",IF(K89="","No date",IF(O89<0,"Expired",IF(O89<=30,"Urgent",IF(O89<=90,"Due soon","OK"))))) | V89: =IF(F89="","",IF(K89="","",O89+ROW()/100000))
A90: =IF(F90="","",COUNTA($F$5:F90)) | B90: AES | C90: AMH Sathorn Co., Ltd. | D90: Licence | E90: Property | F90: Alcohol sale licence | G90: ใบอนุญาตขายสุรา | H90: Excise Department | L90: Annual | M90: 60 | N90: =IF(K90="","",K90-IF(M90="",0,M90)) | O90: =IF(K90="","",K90-TODAY()) | P90: =IF(F90="","",IF(K90="","No date",IF(O90<0,"Expired",IF(O90<=30,"Urgent",IF(O90<=90,"Due soon","OK"))))) | V90: =IF(F90="","",IF(K90="","",O90+ROW()/100000))
A91: =IF(F91="","",COUNTA($F$5:F91)) | B91: AES | C91: AMH Sathorn Co., Ltd. | D91: Licence | E91: Property | F91: Tobacco sale licence | G91: ใบอนุญาตขายยาสูบ | H91: Excise Department | L91: Annual | M91: 60 | N91: =IF(K91="","",K91-IF(M91="",0,M91)) | O91: =IF(K91="","",K91-TODAY()) | P91: =IF(F91="","",IF(K91="","No date",IF(O91<0,"Expired",IF(O91<=30,"Urgent",IF(O91<=90,"Due soon","OK"))))) | V91: =IF(F91="","",IF(K91="","",O91+ROW()/100000))
A92: =IF(F92="","",COUNTA($F$5:F92)) | B92: AES | C92: AMH Sathorn Co., Ltd. | D92: Licence | E92: Property | F92: Swimming pool / public place licence | G92: ใบอนุญาตสถานที่สาธารณะ (สระว่ายน้ำ) | H92: Local authority (BMA / City Municipality) | L92: Annual | M92: 60 | N92: =IF(K92="","",K92-IF(M92="",0,M92)) | O92: =IF(K92="","",K92-TODAY()) | P92: =IF(F92="","",IF(K92="","No date",IF(O92<0,"Expired",IF(O92<=30,"Urgent",IF(O92<=90,"Due soon","OK"))))) | V92: =IF(F92="","",IF(K92="","",O92+ROW()/100000))
A93: =IF(F93="","",COUNTA($F$5:F93)) | B93: AES | C93: AMH Sathorn Co., Ltd. | D93: Licence | E93: Property | F93: Radio / walkie-talkie frequency licence | G93: ใบอนุญาตวิทยุคมนาคม | H93: NBTC | L93: Annual | M93: 60 | N93: =IF(K93="","",K93-IF(M93="",0,M93)) | O93: =IF(K93="","",K93-TODAY()) | P93: =IF(F93="","",IF(K93="","No date",IF(O93<0,"Expired",IF(O93<=30,"Urgent",IF(O93<=90,"Due soon","OK"))))) | V93: =IF(F93="","",IF(K93="","",O93+ROW()/100000))
A94: =IF(F94="","",COUNTA($F$5:F94)) | B94: AES | C94: AMH Sathorn Co., Ltd. | D94: Licence | E94: Property | F94: Music / copyright public performance licence | G94: ใบอนุญาตเผยแพร่งานดนตรี (MCT / ลิขสิทธิ์) | H94: MCT / Phonorights / collecting societies | L94: Annual | M94: 60 | N94: =IF(K94="","",K94-IF(M94="",0,M94)) | O94: =IF(K94="","",K94-TODAY()) | P94: =IF(F94="","",IF(K94="","No date",IF(O94<0,"Expired",IF(O94<=30,"Urgent",IF(O94<=90,"Due soon","OK"))))) | V94: =IF(F94="","",IF(K94="","",O94+ROW()/100000))
A95: =IF(F95="","",COUNTA($F$5:F95)) | B95: AES | C95: AMH Sathorn Co., Ltd. | D95: Permit | E95: Property | F95: Waste / refuse disposal permit | G95: ใบอนุญาตกำจัดสิ่งปฏิกูลและมูลฝอย | H95: Local authority | L95: Annual | M95: 60 | N95: =IF(K95="","",K95-IF(M95="",0,M95)) | O95: =IF(K95="","",K95-TODAY()) | P95: =IF(F95="","",IF(K95="","No date",IF(O95<0,"Expired",IF(O95<=30,"Urgent",IF(O95<=90,"Due soon","OK"))))) | V95: =IF(F95="","",IF(K95="","",O95+ROW()/100000))
A96: =IF(F96="","",COUNTA($F$5:F96)) | B96: AES | C96: AMH Sathorn Co., Ltd. | D96: Permit | E96: Property | F96: Work permits / visas — foreign staff | G96: ใบอนุญาตทำงาน / วีซ่าพนักงานต่างชาติ | H96: Dept. of Employment / Immigration | L96: Annual | M96: 60 | N96: =IF(K96="","",K96-IF(M96="",0,M96)) | O96: =IF(K96="","",K96-TODAY()) | P96: =IF(F96="","",IF(K96="","No date",IF(O96<0,"Expired",IF(O96<=30,"Urgent",IF(O96<=90,"Due soon","OK"))))) | V96: =IF(F96="","",IF(K96="","",O96+ROW()/100000))
A97: =IF(F97="","",COUNTA($F$5:F97)) | B97: AES | C97: AMH Sathorn Co., Ltd. | D97: Certificate | E97: Property | F97: Swimming pool water quality test | G97: ผลตรวจคุณภาพน้ำสระว่ายน้ำ | H97: Accredited laboratory | L97: Other | M97: 60 | N97: =IF(K97="","",K97-IF(M97="",0,M97)) | O97: =IF(K97="","",K97-TODAY()) | P97: =IF(F97="","",IF(K97="","No date",IF(O97<0,"Expired",IF(O97<=30,"Urgent",IF(O97<=90,"Due soon","OK"))))) | V97: =IF(F97="","",IF(K97="","",O97+ROW()/100000))
A98: =IF(F98="","",COUNTA($F$5:F98)) | B98: AES | C98: AMH Sathorn Co., Ltd. | D98: Certificate | E98: Property | F98: Drinking / potable water quality test | G98: ผลตรวจคุณภาพน้ำดื่ม | H98: Accredited laboratory | L98: Annual | M98: 60 | N98: =IF(K98="","",K98-IF(M98="",0,M98)) | O98: =IF(K98="","",K98-TODAY()) | P98: =IF(F98="","",IF(K98="","No date",IF(O98<0,"Expired",IF(O98<=30,"Urgent",IF(O98<=90,"Due soon","OK"))))) | V98: =IF(F98="","",IF(K98="","",O98+ROW()/100000))
A99: =IF(F99="","",COUNTA($F$5:F99)) | B99: AES | C99: AMH Sathorn Co., Ltd. | D99: Certificate | E99: Property | F99: Wastewater treatment monitoring report | G99: รายงานผลการตรวจวัดคุณภาพน้ำทิ้ง | H99: Dept. of Pollution Control / local authority | L99: Other | M99: 60 | N99: =IF(K99="","",K99-IF(M99="",0,M99)) | O99: =IF(K99="","",K99-TODAY()) | P99: =IF(F99="","",IF(K99="","No date",IF(O99<0,"Expired",IF(O99<=30,"Urgent",IF(O99<=90,"Due soon","OK"))))) | V99: =IF(F99="","",IF(K99="","",O99+ROW()/100000))
... A107: =IF(F107="","",COUNTA($F$5:F107)) | B107: AES | C107: AMH Sathorn Co., Ltd. | D107: Contract - Service | E107: Property | F107: F&B outlet / catering operator | G107: สัญญาผู้ประกอบการอาหารและเครื่องดื่ม | H107: DK Wow Venture Co., Ltd. | L107: Annual | M107: 60 | N107: =IF(K107="","",K107-IF(M107="",0,M107)) | O107: =IF(K107="","",K107-TODAY()) | P107: =IF(F107="","",IF(K107="","No date",IF(O107<0,"Expired",IF(O107<=30,"Urgent",IF(O107<=90,"Due soon","OK"))))) | V107: =IF(F107="","",IF(K107="","",O107+ROW()/100000))
A108: =IF(F108="","",COUNTA($F$5:F108)) | B108: AES | C108: AMH Sathorn Co., Ltd. | D108: Contract - Service | E108: Property | F108: Security services | G108: สัญญาบริการรักษาความปลอดภัย | L108: Annual | M108: 60 | N108: =IF(K108="","",K108-IF(M108="",0,M108)) | O108: =IF(K108="","",K108-TODAY()) | P108: =IF(F108="","",IF(K108="","No date",IF(O108<0,"Expired",IF(O108<=30,"Urgent",IF(O108<=90,"Due soon","OK"))))) | V108: =IF(F108="","",IF(K108="","",O108+ROW()/100000))
A109: =IF(F109="","",COUNTA($F$5:F109)) | B109: AES | C109: AMH Sathorn Co., Ltd. | D109: Contract - Service | E109: Property | F109: Cleaning / housekeeping outsource | G109: สัญญาบริการทำความสะอาด | L109: Annual | M109: 60 | N109: =IF(K109="","",K109-IF(M109="",0,M109)) | O109: =IF(K109="","",K109-TODAY()) | P109: =IF(F109="","",IF(K109="","No date",IF(O109<0,"Expired",IF(O109<=30,"Urgent",IF(O109<=90,"Due soon","OK"))))) | V109: =IF(F109="","",IF(K109="","",O109+ROW()/100000))
A110: =IF(F110="","",COUNTA($F$5:F110)) | B110: AES | C110: AMH Sathorn Co., Ltd. | D110: Contract - Service | E110: Property | F110: Pest control | G110: สัญญากำจัดแมลง | L110: Annual | M110: 60 | N110: =IF(K110="","",K110-IF(M110="",0,M110)) | O110: =IF(K110="","",K110-TODAY()) | P110: =IF(F110="","",IF(K110="","No date",IF(O110<0,"Expired",IF(O110<=30,"Urgent",IF(O110<=90,"Due soon","OK"))))) | V110: =IF(F110="","",IF(K110="","",O110+ROW()/100000))
A111: =IF(F111="","",COUNTA($F$5:F111)) | B111: AES | C111: AMH Sathorn Co., Ltd. | D111: Contract - Service | E111: Property | F111: Landscaping / plant care | G111: สัญญาดูแลต้นไม้และภูมิทัศน์ | L111: Annual | M111: 60 | N111: =IF(K111="","",K111-IF(M111="",0,M111)) | O111: =IF(K111="","",K111-TODAY()) | P111: =IF(F111="","",IF(K111="","No date",IF(O111<0,"Expired",IF(O111<=30,"Urgent",IF(O111<=90,"Due soon","OK"))))) | V111: =IF(F111="","",IF(K111="","",O111+ROW()/100000))
A112: =IF(F112="","",COUNTA($F$5:F112)) | B112: AES | C112: AMH Sathorn Co., Ltd. | D112: Contract - Service | E112: Property | F112: Waste collection | G112: สัญญาเก็บขนขยะ | L112: Annual | M112: 60 | N112: =IF(K112="","",K112-IF(M112="",0,M112)) | O112: =IF(K112="","",K112-TODAY()) | P112: =IF(F112="","",IF(K112="","No date",IF(O112<0,"Expired",IF(O112<=30,"Urgent",IF(O112<=90,"Due soon","OK"))))) | V112: =IF(F112="","",IF(K112="","",O112+ROW()/100000))
A113: =IF(F113="","",COUNTA($F$5:F113)) | B113: AES | C113: AMH Sathorn Co., Ltd. | D113: Contract - Service | E113: Property | F113: PMS / property management system licence | G113: สัญญาระบบบริหารโรงแรม (PMS) | L113: Annual | M113: 60 | N113: =IF(K113="","",K113-IF(M113="",0,M113)) | O113: =IF(K113="","",K113-TODAY()) | P113: =IF(F113="","",IF(K113="","No date",IF(O113<0,"Expired",IF(O113<=30,"Urgent",IF(O113<=90,"Due soon","OK"))))) | V113: =IF(F113="","",IF(K113="","",O113+ROW()/100000))
A114: =IF(F114="","",COUNTA($F$5:F114)) | B114: AES | C114: AMH Sathorn Co., Ltd. | D114: Contract - Service | E114: Property | F114: Internet / IPTV / telephone | G114: สัญญาอินเทอร์เน็ต / IPTV / โทรศัพท์ | L114: Annual | M114: 60 | N114: =IF(K114="","",K114-IF(M114="",0,M114)) | O114: =IF(K114="","",K114-TODAY()) | P114: =IF(F114="","",IF(K114="","No date",IF(O114<0,"Expired",IF(O114<=30,"Urgent",IF(O114<=90,"Due soon","OK"))))) | V114: =IF(F114="","",IF(K114="","",O114+ROW()/100000))
A115: =IF(F115="","",COUNTA($F$5:F115)) | B115: LYF | C115: AMH Sukhumvit 8 Co., Ltd. | D115: Licence | E115: Owner | F115: Hotel operating licence | G115: ใบอนุญาตประกอบธุรกิจโรงแรม | H115: Dept. of Provincial Administration / District Office | L115: Every 5 years | M115: 60 | N115: =IF(K115="","",K115-IF(M115="",0,M115)) | O115: =IF(K115="","",K115-TODAY()) | P115: =IF(F115="","",IF(K115="","No date",IF(O115<0,"Expired",IF(O115<=30,"Urgent",IF(O115<=90,"Due soon","OK"))))) | V115: =IF(F115="","",IF(K115="","",O115+ROW()/100000))
A116: =IF(F116="","",COUNTA($F$5:F116)) | B116: LYF | C116: AMH Sukhumvit 8 Co., Ltd. | D116: Permit | E116: Owner | F116: Building construction permit (อ.1) | G116: ใบอนุญาตก่อสร้างอาคาร (อ.1) | H116: Local authority (BMA / City Municipality) | L116: One-off | M116: 60 | N116: =IF(K116="","",K116-IF(M116="",0,M116)) | O116: =IF(K116="","",K116-TODAY()) | P116: =IF(F116="","",IF(K116="","No date",IF(O116<0,"Expired",IF(O116<=30,"Urgent",IF(O116<=90,"Due soon","OK"))))) | V116: =IF(F116="","",IF(K116="","",O116+ROW()/100000))
A117: =IF(F117="","",COUNTA($F$5:F117)) | B117: LYF | C117: AMH Sukhumvit 8 Co., Ltd. | D117: Certificate | E117: Owner | F117: Certificate of building use (อ.6) | G117: ใบรับรองการใช้อาคาร (อ.6) | H117: Local authority (BMA / City Municipality) | L117: One-off | M117: 60 | N117: =IF(K117="","",K117-IF(M117="",0,M117)) | O117: =IF(K117="","",K117-TODAY()) | P117: =IF(F117="","",IF(K117="","No date",IF(O117<0,"Expired",IF(O117<=30,"Urgent",IF(O117<=90,"Due soon","OK"))))) | V117: =IF(F117="","",IF(K117="","",O117+ROW()/100000))
A118: =IF(F118="","",COUNTA($F$5:F118)) | B118: LYF | C118: AMH Sukhumvit 8 Co., Ltd. | D118: Certificate | E118: Owner | F118: Annual building inspection report (ร.1) | G118: รายงานการตรวจสอบอาคารประจำปี (ร.1) | H118: Dept. of Public Works / local authority | L118: Annual | M118: 60 | N118: =IF(K118="","",K118-IF(M118="",0,M118)) | O118: =IF(K118="","",K118-TODAY()) | P118: =IF(F118="","",IF(K118="","No date",IF(O118<0,"Expired",IF(O118<=30,"Urgent",IF(O118<=90,"Due soon","OK"))))) | V118: =IF(F118="","",IF(K118="","",O118+ROW()/100000))
A119: =IF(F119="","",COUNTA($F$5:F119)) | B119: LYF | C119: AMH Sukhumvit 8 Co., Ltd. | D119: Certificate | E119: Owner | F119: Fire protection system inspection | G119: การตรวจสอบระบบป้องกันอัคคีภัย | H119: Licensed inspector | L119: Annual | M119: 60 | N119: =IF(K119="","",K119-IF(M119="",0,M119)) | O119: =IF(K119="","",K119-TODAY()) | P119: =IF(F119="","",IF(K119="","No date",IF(O119<0,"Expired",IF(O119<=30,"Urgent",IF(O119<=90,"Due soon","OK"))))) | V119: =IF(F119="","",IF(K119="","",O119+ROW()/100000))
A120: =IF(F120="","",COUNTA($F$5:F120)) | B120: LYF | C120: AMH Sukhumvit 8 Co., Ltd. | D120: Certificate | E120: Owner | F120: Lift / elevator inspection certificate | G120: ใบรับรองการตรวจสอบลิฟต์ | H120: Licensed engineer | L120: Annual | M120: 60 | N120: =IF(K120="","",K120-IF(M120="",0,M120)) | O120: =IF(K120="","",K120-TODAY()) | P120: =IF(F120="","",IF(K120="","No date",IF(O120<0,"Expired",IF(O120<=30,"Urgent",IF(O120<=90,"Due soon","OK"))))) | V120: =IF(F120="","",IF(K120="","",O120+ROW()/100000))
A121: =IF(F121="","",COUNTA($F$5:F121)) | B121: LYF | C121: AMH Sukhumvit 8 Co., Ltd. | D121: Certificate | E121: Owner | F121: Electrical system inspection | G121: การตรวจสอบระบบไฟฟ้า | H121: Licensed engineer | L121: Annual | M121: 60 | N121: =IF(K121="","",K121-IF(M121="",0,M121)) | O121: =IF(K121="","",K121-TODAY()) | P121: =IF(F121="","",IF(K121="","No date",IF(O121<0,"Expired",IF(O121<=30,"Urgent",IF(O121<=90,"Due soon","OK"))))) | V121: =IF(F121="","",IF(K121="","",O121+ROW()/100000))
A122: =IF(F122="","",COUNTA($F$5:F122)) | B122: LYF | C122: AMH Sukhumvit 8 Co., Ltd. | D122: Certificate | E122: Owner | F122: Generator / fuel storage permit | G122: ใบอนุญาตเครื่องกำเนิดไฟฟ้า / เก็บน้ำมันเชื้อเพลิง | H122: Dept. of Energy Business / local authority | L122: Annual | M122: 60 | N122: =IF(K122="","",K122-IF(M122="",0,M122)) | O122: =IF(K122="","",K122-TODAY()) | P122: =IF(F122="","",IF(K122="","No date",IF(O122<0,"Expired",IF(O122<=30,"Urgent",IF(O122<=90,"Due soon","OK"))))) | V122: =IF(F122="","",IF(K122="","",O122+ROW()/100000))
A123: =IF(F123="","",COUNTA($F$5:F123)) | B123: LYF | C123: AMH Sukhumvit 8 Co., Ltd. | D123: Certificate | E123: Owner | F123: Boiler / pressure vessel inspection | G123: การตรวจสอบหม้อไอน้ำ / ภาชนะรับแรงดัน | H123: Licensed engineer | L123: Annual | M123: 60 | N123: =IF(K123="","",K123-IF(M123="",0,M123)) | O123: =IF(K123="","",K123-TODAY()) | P123: =IF(F123="","",IF(K123="","No date",IF(O123<0,"Expired",IF(O123<=30,"Urgent",IF(O123<=90,"Due soon","OK"))))) | V123: =IF(F123="","",IF(K123="","",O123+ROW()/100000))
A124: =IF(F124="","",COUNTA($F$5:F124)) | B124: LYF | C124: AMH Sukhumvit 8 Co., Ltd. | D124: Certificate | E124: Owner | F124: EIA environmental monitoring report | G124: รายงานผลการปฏิบัติตามมาตรการ EIA | H124: Office of Natural Resources & Environmental Policy (ONEP) | L124: Other | M124: 60 | N124: =IF(K124="","",K124-IF(M124="",0,M124)) | O124: =IF(K124="","",K124-TODAY()) | P124: =IF(F124="","",IF(K124="","No date",IF(O124<0,"Expired",IF(O124<=30,"Urgent",IF(O124<=90,"Due soon","OK"))))) | V124: =IF(F124="","",IF(K124="","",O124+ROW()/100000))
A125: =IF(F125="","",COUNTA($F$5:F125)) | B125: LYF | C125: AMH Sukhumvit 8 Co., Ltd. | D125: Tax / Registration | E125: Owner | F125: Signage tax (billboard) | G125: ภาษีป้าย | H125: Local authority | L125: Annual | M125: 60 | N125: =IF(K125="","",K125-IF(M125="",0,M125)) | O125: =IF(K125="","",K125-TODAY()) | P125: =IF(F125="","",IF(K125="","No date",IF(O125<0,"Expired",IF(O125<=30,"Urgent",IF(O125<=90,"Due soon","OK"))))) | V125: =IF(F125="","",IF(K125="","",O125+ROW()/100000))
A126: =IF(F126="","",COUNTA($F$5:F126)) | B126: LYF | C126: AMH Sukhumvit 8 Co., Ltd. | D126: Tax / Registration | E126: Owner | F126: Land & building tax | G126: ภาษีที่ดินและสิ่งปลูกสร้าง | H126: Local authority | L126: Annual | M126: 60 | N126: =IF(K126="","",K126-IF(M126="",0,M126)) | O126: =IF(K126="","",K126-TODAY()) | P126: =IF(F126="","",IF(K126="","No date",IF(O126<0,"Expired",IF(O126<=30,"Urgent",IF(O126<=90,"Due soon","OK"))))) | V126: =IF(F126="","",IF(K126="","",O126+ROW()/100000))
... A134: =IF(F134="","",COUNTA($F$5:F134)) | B134: LYF | C134: AMH Sukhumvit 8 Co., Ltd. | D134: Contract - Management | E134: Owner | F134: Technical services / central fee agreement | G134: สัญญาค่าบริการส่วนกลาง | H134: Ascott International Management (Thailand) Ltd. | L134: Rolling / evergreen | M134: 60 | N134: =IF(K134="","",K134-IF(M134="",0,M134)) | O134: =IF(K134="","",K134-TODAY()) | P134: =IF(F134="","",IF(K134="","No date",IF(O134<0,"Expired",IF(O134<=30,"Urgent",IF(O134<=90,"Due soon","OK"))))) | V134: =IF(F134="","",IF(K134="","",O134+ROW()/100000))
A135: =IF(F135="","",COUNTA($F$5:F135)) | B135: LYF | C135: AMH Sukhumvit 8 Co., Ltd. | D135: Contract - Service | E135: Owner | F135: Lift maintenance | G135: สัญญาบำรุงรักษาลิฟต์ | L135: Annual | M135: 60 | N135: =IF(K135="","",K135-IF(M135="",0,M135)) | O135: =IF(K135="","",K135-TODAY()) | P135: =IF(F135="","",IF(K135="","No date",IF(O135<0,"Expired",IF(O135<=30,"Urgent",IF(O135<=90,"Due soon","OK"))))) | V135: =IF(F135="","",IF(K135="","",O135+ROW()/100000))
A136: =IF(F136="","",COUNTA($F$5:F136)) | B136: LYF | C136: AMH Sukhumvit 8 Co., Ltd. | D136: Contract - Service | E136: Owner | F136: HVAC / chiller maintenance | G136: สัญญาบำรุงรักษาระบบปรับอากาศ | L136: Annual | M136: 60 | N136: =IF(K136="","",K136-IF(M136="",0,M136)) | O136: =IF(K136="","",K136-TODAY()) | P136: =IF(F136="","",IF(K136="","No date",IF(O136<0,"Expired",IF(O136<=30,"Urgent",IF(O136<=90,"Due soon","OK"))))) | V136: =IF(F136="","",IF(K136="","",O136+ROW()/100000))
...

Sheet Lists
A1: Dropdown lists — used by the Register. Edit here to change the choices.
A3: Property | C3: Category | E3: Renewal cycle | G3: Auto-renew | I3: Status (reference) | K3: Property | L3: Full name | M3: Legal entity | O3: Renew by
A4: SR9 | C4: Licence | E4: Annual | G4: Yes | I4: Expired | K4: SR9 | L4: Somerset Rama 9 Bangkok | M4: AMH Ratchada Co., Ltd. | O4: Owner
A5: AES | C5: Permit | E5: Every 2 years | G5: No | I5: Urgent | K5: AES | L5: Ascott Embassy Sathorn Bangkok | M5: AMH Sathorn Co., Ltd. | O5: Property
A6: LYF | C6: Certificate | E6: Every 3 years | I6: Due soon | K6: LYF | L6: lyf Sukhumvit 8 Bangkok | M6: AMH Sukhumvit 8 Co., Ltd.
A7: SP | C7: Tax / Registration | E7: Every 5 years | I7: OK | K7: SP | L7: Somerset Pattaya | M7: AMH Pattaya Co., Ltd.
C8: Insurance | E8: One-off | I8: No date
C9: Contract - Management | E9: Rolling / evergreen
C10: Contract - OTA | E10: Monthly
C11: Contract - Service | E11: Other
C12: Contract - Utility
C13: Contract - Lease / Finance
