Workbook
Name \: OFFSET(Full_Print,0,0,[1]!Last_Row)
Name \: OFFSET(Full_Print,0,0,[1]!Last_Row)
Name \: OFFSET(Full_Print,0,0,[1]!Last_Row)
Name \: OFFSET(Full_Print,0,0,[1]!Last_Row)
Name \0: '[2]C-1'!$R$2
Name \200: #REF!
Name \a: '[3]ลูกหนี้(เก่า)'!#REF!
Name \b: '[3]ลูกหนี้(เก่า)'!#REF!
Name \c: '[3]ลูกหนี้(เก่า)'!#REF!
Name \d: #REF!
Name \e: #REF!
Name \f: #REF!
Name \g: #REF!
Name \h: #REF!
Name \i: #REF!
Name \j: #REF!
Name \k: #REF!
Name \l: #REF!
Name \m: #REF!
Name \n: #N/A
Name \o: #REF!
Name \p: #N/A
Name \q: #N/A
Name \r: [4]FSALES!#REF!
Name \s: #REF!
Name \t: '[5]ELEC45-01'!#REF!
Name \u: '[3]ลูกหนี้(เก่า)'!#REF!
Name \v: #REF!
Name \w: #N/A
Name \x: #REF!
Name \y: #REF!
Name \z: #REF!
Name _.._Specification_name__KAL2: #REF!
Name _??: '[7]????-??'!#REF!
Name _???: '[8]????-??'!#REF!
Name _?????: '[9]?????'!$C$6:$C$34
Name __??: '[10]????-??'!#REF!
Name __???: '[8]????-??'!#REF!
Name __?????: '[11]?????'!$C$6:$C$34
Name ___??: '[10]????-??'!#REF!
Name ___???: '[8]????-??'!#REF!
Name ___?????: '[11]?????'!$C$6:$C$34
Name ____??: '[12]????-??'!#REF!
Name ____???: '[8]????-??'!#REF!
Name ____?????: '[13]?????'!$C$6:$C$34
Name ___________________dkk1: #REF!
Name ___________________dkk2: #REF!
Name ___________________exp10: #REF!
Name ___________________exp11: #REF!
Name ___________________exp12: #REF!
Name ___________________EXP22: #REF!
Name ___________________exp5: #REF!
Name ___________________exp7: #REF!
Name ___________________exp8: #REF!
Name ___________________exp9: #REF!
Name ___________________lit1: #REF!
Name ___________________lit2: #REF!
Name ___________________SCB1: '[14]SCB 1 - Current'!$F$10
Name ___________________SCB2: '[14]SCB 2 - Current'!$F$11
Name ___________________Us1: #REF!

Sheet result FY25
C3: YTD performance
C4: Unit: kTHB
C5: SR9 | D5: Compare with MF Projection | I5: ATB | J5: Compare with MF Projection | O5: AES | P5: Compare with MF Projection | U5: lyf | V5: Compare with MF Projection | AA5: SP | AB5: Compare with MF Projection | AG5: Portfolio | AH5: Compare with MF Projection
D6: Ascott BP | E6: MF Projection | F6: Actual | G6: % change | J6: Ascott BP | K6: MF Projection | L6: Actual | M6: % change | P6: Ascott BP | Q6: MF Projection | R6: Actual | S6: % change | V6: Ascott BP | W6: MF Projection | X6: Actual | Y6: % change | AB6: Ascott BP | AC6: MF Projection | AD6: Actual | AE6: % change | AH6: Ascott BP | AI6: MF Projection | AJ6: Actual | AK6: % change
C7: OCC | D7: =(D37*31+E37*28+F37*31+G37*30+H37*31+I37*30+J37*31+K37*31+L37*30+M37*31+N37*30+O37*31)/365 -> 0.84442569 | E7: =(D41*31+E41*28+F41*31+G41*30+H41*31+I41*30+J41*31+K41*31+L41*30+M41*31+N41*30+O41*31)/(31+28+31+30+31+30+31+31+30+31+30+31) -> 0.75293443 | F7: =(D45*31+E45*28+F45*31+G45*30+H45*31+I45*30+J45*31+K45*31+L45*30+M45*31+N45*30+O45*31)/(31+28+31+30+31+30+31+31+30+31+30+31) -> 0.78250269 | G7: 0.039270704 | H7: =F7=P45 -> TRUE | I7: OCC | J7: 0.79402509 | K7: 0.69966099 | L7: 0.72463502 | M7: 0.035694472 | N7: =L7=P67 -> TRUE | O7: OCC | P7: 0.81647945 | Q7: 0.67088875 | R7: =(D89*31+E89*28+F89*31+G89*30+H89*31+I89*30+J89*31+K89*31+L89*30+M89*31+N89*30+O89*31)/(31+28+31+30+31+30+31+31+30+31+30+31) -> 0.70592068 | S7: 0.052217198 | T7: =R7=P89 -> TRUE | U7: OCC | V7: 0.78157674 | W7: 0.78725156 | X7: =(D111*31+E111*28+F111*31+G111*30+H111*31+I111*30+J111*31+K111*31+L111*30+M111*31+N111*30+O111*31)/(31+28+31+30+31+30+31+31+30+31+30+31) -> 0.82739085 | Y7: 0.050986612 | AA7: OCC | AB7: =(D125*31+E125*28+F125*31+G125*30+H125*31+I125*30+J125*31+K125*31+L125*30+M125*31+N125*30+O125*31)/(31+28+31+30+31+30+31+31+30+31+30+31) -> 0.7874091 | AC7: =(D129*31+E129*28+F129*31+G129*30+H129*31+I129*30+J129*31+K129*31+L129*30+M129*31+N129*30)/(31+28+31+30+31+30+31+31+30+31+30+31) -> 0.62414675 | AD7: =(D133*31+E133*28+F133*31+G133*30+H133*31+I133*30+J133*31+K133*31+L133*30+M133*31+N133*30+O133*31)/(31+28+31+30+31+30+31+31+30+31+30+31) -> 0.7187079 | AE7: =(AD7-AC7)/AC7 -> 0.15150468 | AG7: OCC | AH7: 0.8087677 | AI7: 0.70248041 | AJ7: =(F7*$E$33+L7*$E$55+R7*$E$77+X7*$E$99+AD7*$E$121)/SUM($E$33,$E$55,$E$77,$E$99,$E$121) -> 0.74487611 | AK7: 0.060351439
C8: ADR | D8: 3185.053 | E8: =(D42*31+E42*28+F42*31+G42*30+H42*31+I42*30+J42*31+K42*31+L42*30+M42*31+N42*30+O42*31)/(31+28+31+30+31+30+31+31+30+31+30+31) -> 2838.0497 | F8: =(D48*31+E48*28+F48*31+G48*30+H48*31+I48*30+J48*31+K48*31+L48*30+M48*31+N48*30+O48*31)/365 -> 2929.1183 | G8: 0.029879645 | H8: =F8=P48 -> TRUE | I8: ADR | J8: 4119.8256 | K8: 3484.3586 | L8: 3534.0011 | M8: 0.014247232 | N8: =L8=P70 -> TRUE | O8: ADR | P8: 4067.2988 | Q8: 3152.293 | R8: =(D92*31+E92*28+F92*31+G92*30+H92*31+I92*30+J92*31+K92*31+L92*30+M92*31+N92*30+O92*31)/(31+28+31+30+31+30+31+31+30+31+30+31) -> 3597.8954 | S8: 0.1413582 | T8: =R8=P92 -> TRUE | U8: ADR | V8: 1674.411 | W8: 1398.228 | X8: =(D114*31+E114*28+F114*31+G114*30+H114*31+I114*30+J114*31+K114*31+L114*30+M114*31+N114*30+O114*31)/(31+28+31+30+31+30+31+31+30+31+30+31) -> 1377.6142 | Y8: -0.014742813 | AA8: ADR | AB8: =(D126*31+E126*28+F126*31+G126*30+H126*31+I126*30+J126*31+K126*31+L126*30+M126*31)/(31+28+31+30+31+30+31+31+30+31+30+31) -> 3421.7709 | AC8: =(D130*31+E130*28+F130*31+G130*30+H130*31+I130*30+J130*31+K130*31+L130*30+M130*31)/(31+28+31+30+31+30+31+31+30+31+30+31) -> 3011.0882 | AD8: =(D136*31+E136*28+F136*31+G136*30+H136*31+I136*30+J136*31+K136*31+L136*30+M136*31+N136*30+O136*31)/(31+28+31+30+31+30+31+31+30+31+30+31) -> 3813.0355 | AE8: =(AD8-AC8)/AC8 -> 0.26633139 | AG8: ADR | AH8: 3490.4516 | AI8: 2916.4422 | AJ8: =(F8*F7*$E$33+L8*L7*$E$55+R8*R7*$E$77+X8*X7*$E$99+AD8*AD7*$E$121)/SUM(F7*$E$33,L7*$E$55,R7*$E$77,X7*$E$99,AD7*$E$121) -> 3179.5438 | AK8: 0.089657766
C9: RevPar | D9: =D8*D7 -> 2689.5406 | E9: =E8*E7 -> 2136.8653 | F9: =F8*F7 -> 2292.0429 | G9: 0.070323744 | I9: RevPar | J9: =J8*J7 -> 3271.2449 | K9: =K8*K7 -> 2437.8698 | L9: =L8*L7 -> 2560.8609 | M9: 0.050450252 | O9: RevPar | P9: =P8*P7 -> 3320.8659 | Q9: =Q8*Q7 -> 2114.8379 | R9: =R7*R8 -> 2539.8288 | S9: 0.20095673 | U9: RevPar | V9: =V7*V8 -> 1308.6807 | W9: =W7*W8 -> 1100.7572 | X9: =X7*X8 -> 1139.8253 | Y9: 0.035492113 | AA9: RevPar | AB9: =AB7*AB8 -> 2694.3336 | AC9: =AC7*AC8 -> 1879.3609 | AD9: =AD7*AD8 -> 2740.4587 | AE9: =(AD9-AC9)/AC9 -> 0.45818652 | AG9: RevPar | AH9: =AH7*AH8 -> 2822.9645 | AI9: =AI7*AI8 -> 2048.7435 | AJ9: =AJ7*AJ8 -> 2368.3662 | AK9: 0.15542018
C10: GOP Margin | D10: 0.58766999 | E10: 0.5741623 | F10: 0.57305356 | G10: -0.001931055 | I10: GOP Margin | J10: 0.58157673 | K10: 0.55172634 | L10: 0.55279341 | M10: 0.0019340494 | O10: GOP Margin | P10: 0.56835325 | Q10: 0.51270909 | R10: =R14/R12 -> 0.52329728 | S10: 0.020651471 | U10: GOP Margin | V10: 0.49173705 | W10: 0.47894649 | X10: =X14/X12 -> 0.49149722 | Y10: 0.026204857 | AA10: GOP Margin | AB10: =AB14/AB12 -> 0.57713849 | AC10: =AC14/AC12 -> 0.54830574 | AD10: =AD14/AD12 -> 0.55590946 | AE10: =(AD10-AC10)/AC10 -> 0.013867669 | AG10: GOP Margin | AH10: 0.57425666 | AI10: 0.5438053 | AJ10: =AJ14/AJ12 -> 0.54623705 | AK10: 0.0081316714
C12: Revenue | D12: 4.8923854e+08 | E12: 3.7349996e+08 | F12: 3.9452489e+08 | G12: 0.056291667 | I12: Revenue | J12: 5.6060193e+08 | K12: 4.1766098e+08 | L12: 4.4152883e+08 | M12: 0.05714648 | O12: Revenue | P12: 4.9719146e+08 | Q12: 3.5215685e+08 | R12: 3.8133572e+08 | S12: 0.082857612 | U12: Revenue | V12: 89376876 | W12: 79910226 | X12: 86351160 | Y12: 0.080602124 | AA12: Revenue | AB12: 3.9989037e+08 | AC12: 3.0865798e+08 | AD12: 3.3777501e+08 | AE12: 0.094334287 | AG12: Revenue | AH12: 2.0362992e+09 | AI12: 1.531886e+09 | AJ12: 1.3037406e+09 | AK12: -0.14893104
C13: OPEX | D13: -2.0171482e+08 | E13: -1.5892375e+08 | F13: -1.68441e+08 | G13: 0.059885626 | I13: OPEX | J13: -2.3232876e+08 | K13: -1.8761864e+08 | L13: -1.974546e+08 | M13: 0.052425315 | O13: OPEX | P13: -2.1355353e+08 | Q13: -1.7202664e+08 | R13: -1.8178378e+08 | S13: 0.056718716 | U13: OPEX | V13: -44921854 | W13: -41774081 | X13: -43909805 | Y13: 0.051125591 | AA13: OPEX | AB13: -1.6909825e+08 | AC13: -1.3941904e+08 | AD13: -1.5000269e+08 | AE13: 0.075912503 | AG13: OPEX | AH13: -8.6161721e+08 | AI13: -6.9976215e+08 | AJ13: -5.9158918e+08 | AK13: -0.15458534
C14: GOP | D14: 2.8752372e+08 | E14: 2.1457621e+08 | F14: 2.2608389e+08 | G14: 0.053629836 | I14: GOP | J14: 3.2827317e+08 | K14: 2.3004234e+08 | L14: 2.4407423e+08 | M14: 0.060996981 | O14: GOP | P14: 2.8363792e+08 | Q14: 1.801302e+08 | R14: 1.9955195e+08 | S14: 0.10782059 | U14: GOP | V14: 44455022 | W14: 38136145 | X14: 42441355 | Y14: 0.11289052 | AA14: GOP | AB14: 2.3079213e+08 | AC14: 1.6923894e+08 | AD14: 1.8777232e+08 | AE14: 0.10951015 | AG14: GOP | AH14: 1.174682e+09 | AI14: 8.3212383e+08 | AJ14: 7.1215142e+08 | AK14: -0.14417615 | AN14: 30888702
C15: JV expense | D15: -1.2583485e+08 | E15: -1.11362e+08 | F15: -1.1400689e+08 | G15: 0.023750455 | I15: JV expense | J15: -1.6865831e+08 | K15: -1.6248844e+08 | L15: -1.7492324e+08 | M15: 0.076527288 | O15: JV expense | P15: -1.4342121e+08 | Q15: -1.2066449e+08 | R15: -1.2997337e+08 | S15: 0.077146818 | U15: JV expense | V15: -27040640 | W15: -26570816 | X15: -26396203 | Y15: -0.006571612 | AA15: JV expense | AB15: -83954326 | AC15: -70240913 | AD15: -79989511 | AE15: 0.13878803 | AG15: JV expense | AH15: -5.4890933e+08 | AI15: -4.9132665e+08 | AJ15: -4.4529971e+08 | AK15: -0.093678914 | AN15: 4413117.5
C16: EBIT | D16: 1.6168887e+08 | E16: 1.0321421e+08 | F16: 1.12077e+08 | G16: 0.085867912 | I16: EBIT | J16: 1.5961486e+08 | K16: 67553903 | L16: 69150992 | M16: 0.023641697 | O16: EBIT | P16: 1.4021671e+08 | Q16: 59465713 | R16: 69578577 | S16: 0.17006209 | U16: EBIT | V16: 17414383 | W16: 11565329 | X16: 16045152 | Y16: 0.38734932 | AA16: EBIT | AB16: 1.468378e+08 | AC16: 98998027 | AD16: 1.0778281e+08 | AE16: 0.088736963 | AG16: EBIT | AH16: 6.2577263e+08 | AI16: 3.4079718e+08 | AJ16: 2.6685172e+08 | AK16: -0.21697792 | AN16: 35301819
B20: Portfolio | D20: 2025 | P20: Avg | R20: Overall GOP / EBIT | T20: 2025 | AF20: Total
D21: Jan | E21: Feb | F21: Mar | G21: Apr | H21: May | I21: Jun | J21: Jul | K21: Aug | L21: Sep | M21: Oct | N21: Nov | O21: Dec | T21: Jan | U21: Feb | V21: Mar | W21: Apr | X21: May | Y21: Jun | Z21: Jul | AA21: Aug | AB21: Sep | AC21: Oct | AD21: Nov | AE21: Dec
B22: Key Available | D22: =E33+E55+E77+E99+E121 -> 1809 | E22: =D22 -> 1809 | F22: =E22 -> 1809 | G22: =F22 -> 1809 | H22: =G22 -> 1809 | I22: =H22 -> 1809 | J22: =I22 -> 1809 | K22: =J22 -> 1809 | L22: =K22 -> 1809 | ... O22: =N22 -> 1809 | R22: Ascott BP GOP | T22: =SUM(T40,T62,T84,T106,T128) -> 1.0590519e+08 | U22: =SUM(U40,U62,U84,U106,U128) -> 1.0396394e+08 | V22: =SUM(V40,V62,V84,V106,V128) -> 93340290 | W22: =SUM(W40,W62,W84,W106,W128) -> 97710543 | X22: =SUM(X40,X62,X84,X106,X128) -> 81498889 | Y22: =SUM(Y40,Y62,Y84,Y106,Y128) -> 90769038 | Z22: =SUM(Z40,Z62,Z84,Z106,Z128) -> 1.1280233e+08 | AA22: =SUM(AA40,AA62,AA84,AA106,AA128) -> 1.1093336e+08 | ... AD22: =SUM(AD40,AD62,AD84,AD106,AD128) -> 1.0682416e+08 | AE22: 1.1295487e+08 | AF22: =SUM(T22:AE22) -> 1.174682e+09
B23: Ascott BP OCC | D23: =(D37*$E$33+D59*$E$55+D81*$E$77+D103*$E$99+D125*$E$121)/SUM($E$33,$E$55,$E$77,$E$99,$E$121) -> 0.82723844 | E23: =(E37*$E$33+E59*$E$55+E81*$E$77+E103*$E$99+E125*$E$121)/SUM($E$33,$E$55,$E$77,$E$99,$E$121) -> 0.88017689 | F23: =(F37*$E$33+F59*$E$55+F81*$E$77+F103*$E$99+F125*$E$121)/SUM($E$33,$E$55,$E$77,$E$99,$E$121) -> 0.80247985 | G23: =(G37*$E$33+G59*$E$55+G81*$E$77+G103*$E$99+G125*$E$121)/SUM($E$33,$E$55,$E$77,$E$99,$E$121) -> 0.80520865 | H23: =(H37*$E$33+H59*$E$55+H81*$E$77+H103*$E$99+H125*$E$121)/SUM($E$33,$E$55,$E$77,$E$99,$E$121) -> 0.76246312 | I23: =(I37*$E$33+I59*$E$55+I81*$E$77+I103*$E$99+I125*$E$121)/SUM($E$33,$E$55,$E$77,$E$99,$E$121) -> 0.81128518 | J23: =(J37*$E$33+J59*$E$55+J81*$E$77+J103*$E$99+J125*$E$121)/SUM($E$33,$E$55,$E$77,$E$99,$E$121) -> 0.86124196 | K23: =(K37*$E$33+K59*$E$55+K81*$E$77+K103*$E$99+K125*$E$121)/SUM($E$33,$E$55,$E$77,$E$99,$E$121) -> 0.85387355 | ... O23: =(O37*$E$33+O59*$E$55+O81*$E$77+O103*$E$99+O125*$E$121)/SUM($E$33,$E$55,$E$77,$E$99,$E$121) -> 0.8179414 | P23: =(D23*31+E23*28+F23*31+G23*30+H23*31+I23*30+J23*31+K23*31+L23*30+M23*31+N23*30+O23*31)/365 -> 0.8087677 | R23: MF Projection GOP | T23: =SUM(T41,T63,T85,T107,T129) -> 1.0874488e+08 | U23: =SUM(U41,U63,U85,U107,U129) -> 84829796 | V23: =SUM(V41,V63,V85,V107,V129) -> 66251300 | W23: =SUM(W41,W63,W85,W107,W129) -> 65881450 | X23: =SUM(X41,X63,X85,X107,X129) -> 60665411 | Y23: =SUM(Y41,Y63,Y85,Y107,Y129) -> 54936996 | Z23: =SUM(Z41,Z63,Z85,Z107,Z129) -> 72160205 | AA23: =SUM(AA41,AA63,AA85,AA107,AA129) -> 69030886 | ... AD23: =SUM(AD41,AD63,AD85,AD107,AD129) -> 69749394 | AE23: 77246729 | AF23: =SUM(T23:AE23) -> 8.3212383e+08
B24: Ascott BP ADR | D24: =(D38*$E$33*D37+D60*$E$55*D59+$E$77*D81*D82+$E$99*D103*D104+$E$121*D125*D126)/SUM($E$33*D37,$E$55*D59,$E$77*D81,$E$99*D103,$E$121*D125) -> 3711.9142 | E24: =(E38*$E$33*E37+E60*$E$55*E59+$E$77*E81*E82+$E$99*E103*E104+$E$121*E125*E126)/SUM($E$33*E37,$E$55*E59,$E$77*E81,$E$99*E103,$E$121*E125) -> 3790.0322 | F24: =(F38*$E$33*F37+F60*$E$55*F59+$E$77*F81*F82+$E$99*F103*F104+$E$121*F125*F126)/SUM($E$33*F37,$E$55*F59,$E$77*F81,$E$99*F103,$E$121*F125) -> 3546.3943 | G24: =(G38*$E$33*G37+G60*$E$55*G59+$E$77*G81*G82+$E$99*G103*G104+$E$121*G125*G126)/SUM($E$33*G37,$E$55*G59,$E$77*G81,$E$99*G103,$E$121*G125) -> 3758.4343 | H24: =(H38*$E$33*H37+H60*$E$55*H59+$E$77*H81*H82+$E$99*H103*H104+$E$121*H125*H126)/SUM($E$33*H37,$E$55*H59,$E$77*H81,$E$99*H103,$E$121*H125) -> 3415.0058 | I24: =(I38*$E$33*I37+I60*$E$55*I59+$E$77*I81*I82+$E$99*I103*I104+$E$121*I125*I126)/SUM($E$33*I37,$E$55*I59,$E$77*I81,$E$99*I103,$E$121*I125) -> 3553.0857 | J24: =(J38*$E$33*J37+J60*$E$55*J59+$E$77*J81*J82+$E$99*J103*J104+$E$121*J125*J126)/SUM($E$33*J37,$E$55*J59,$E$77*J81,$E$99*J103,$E$121*J125) -> 3722.0201 | K24: =(K38*$E$33*K37+K60*$E$55*K59+$E$77*K81*K82+$E$99*K103*K104+$E$121*K125*K126)/SUM($E$33*K37,$E$55*K59,$E$77*K81,$E$99*K103,$E$121*K125) -> 3725.8559 | ... O24: =(O38*$E$33*O37+O60*$E$55*O59+$E$77*O81*O82+$E$99*O103*O104+$E$121*O125*O126)/SUM($E$33*O37,$E$55*O59,$E$77*O81,$E$99*O103,$E$121*O125) -> 3787.6355 | P24: =(D24*31+E24*28+F24*31+G24*30+H24*31+I24*30+J24*31+K24*31+L24*30+M24*31+N24*30+O24*31)/365 -> 3604.2108 | R24: GOP | T24: =SUM(T42,T64,T86,T108,T130) -> 1.0874488e+08 | U24: =SUM(U42,U64,U86,U108,U130) -> 84829796 | V24: =SUM(V42,V64,V86,V108,V130) -> 66251300 | W24: =SUM(W42,W64,W86,W108,W130) -> 65881450 | X24: =SUM(X42,X64,X86,X108,X130) -> 60665411 | Y24: =SUM(Y42,Y64,Y86,Y108,Y130) -> 54936996 | Z24: =SUM(Z42,Z64,Z86,Z108,Z130) -> 76597600 | AA24: =SUM(AA42,AA64,AA86,AA108,AA130) -> 80493575 | ... AD24: =SUM(AD42,AD64,AD86,AD108,AD130) -> 82074071 | AE24: 1.0183326e+08 | AF24: =SUM(T24:AE24) -> 8.9992375e+08
B25: Ascott BP RevPar | D25: =D23*D24 -> 3070.6381 | E25: =E23*E24 -> 3335.8988 | F25: =F23*F24 -> 2845.91 | G25: =G23*G24 -> 3026.3238 | H25: =H23*H24 -> 2603.816 | I25: =I23*I24 -> 2882.5658 | J25: =J23*J24 -> 3205.5599 | K25: =K23*K24 -> 3181.4098 | ... P25: =P23*P24 -> 2914.9692 | R25: Ascott BP EBIT | T25: =SUM(T46,T68,T90,T112,T134) -> 59515077 | U25: =SUM(U46,U68,U90,U112,U134) -> 57748940 | V25: =SUM(V46,V68,V90,V112,V134) -> 47934545 | W25: =SUM(W46,W68,W90,W112,W134) -> 51946946 | X25: =SUM(X46,X68,X90,X112,X134) -> 37095664 | Y25: =SUM(Y46,Y68,Y90,Y112,Y134) -> 45586850 | Z25: =SUM(Z46,Z68,Z90,Z112,Z134) -> 65855049 | AA25: =SUM(AA46,AA68,AA90,AA112,AA134) -> 64120553 | ... AD25: =SUM(AD46,AD68,AD90,AD112,AD134) -> 60373028 | AE25: 65985930 | AF25: =SUM(T25:AE25) -> 6.2577263e+08
B26: MF Projection OCC | D26: =(D41*$E$33+D63*$E$55+D85*$E$77+D107*$E$99+D129*$E$121)/SUM($E$33,$E$55,$E$77,$E$99,$E$121) -> 0.8406497 | E26: =(E41*$E$33+E63*$E$55+E85*$E$77+E107*$E$99+E129*$E$121)/SUM($E$33,$E$55,$E$77,$E$99,$E$121) -> 0.82892743 | F26: =(F41*$E$33+F63*$E$55+F85*$E$77+F107*$E$99+F129*$E$121)/SUM($E$33,$E$55,$E$77,$E$99,$E$121) -> 0.66754043 | G26: =(G41*$E$33+G63*$E$55+G85*$E$77+G107*$E$99+G129*$E$121)/SUM($E$33,$E$55,$E$77,$E$99,$E$121) -> 0.66679565 | H26: =(H41*$E$33+H63*$E$55+H85*$E$77+H107*$E$99+H129*$E$121)/SUM($E$33,$E$55,$E$77,$E$99,$E$121) -> 0.67854277 | I26: =(I41*$E$33+I63*$E$55+I85*$E$77+I107*$E$99+I129*$E$121)/SUM($E$33,$E$55,$E$77,$E$99,$E$121) -> 0.66412383 | J26: =(J41*$E$33+J63*$E$55+J85*$E$77+J107*$E$99+J129*$E$121)/SUM($E$33,$E$55,$E$77,$E$99,$E$121) -> 0.75306098 | K26: =(K41*$E$33+K63*$E$55+K85*$E$77+K107*$E$99+K129*$E$121)/SUM($E$33,$E$55,$E$77,$E$99,$E$121) -> 0.71584998 | ... O26: =(O41*$E$33+O63*$E$55+O85*$E$77+O107*$E$99+O129*$E$121)/SUM($E$33,$E$55,$E$77,$E$99,$E$121) -> 0.75880736 | P26: =(D26*31+E26*28+F26*31+G26*30+H26*31+I26*30+J26*31+K26*31+L26*30+M26*31+N26*30+O26*31)/365 -> 0.71185678 | R26: MF Projection EBIT | T26: =SUM(T47,T69,T91,T113,T135) -> 62961089 | U26: =SUM(U47,U69,U91,U113,U135) -> 42824009 | V26: =SUM(V47,V69,V91,V113,V135) -> 24042174 | W26: =SUM(W47,W69,W91,W113,W135) -> 25051019 | X26: =SUM(X47,X69,X91,X113,X135) -> 17197184 | Y26: =SUM(Y47,Y69,Y91,Y113,Y135) -> 12899417 | Z26: =SUM(Z47,Z69,Z91,Z113,Z135) -> 31592298 | AA26: =SUM(AA47,AA69,AA91,AA113,AA135) -> 37914927 | ... AD26: =SUM(AD47,AD69,AD91,AD113,AD135) -> 39297058 | AE26: 35301888 | AF26: =SUM(T26:AE26) -> 3.6598599e+08
B27: MF Projection ADR | D27: =(D42*$E$33*D41+D64*$E$55*D63+$E$77*D85*D86+$E$99*D107*D108+$E$121*D129*D130)/SUM($E$33*D41,$E$55*D63,$E$77*D85,$E$99*D107,$E$121*D129) -> 3666.2182 | E27: =(E42*$E$33*E41+E64*$E$55*E63+$E$77*E85*E86+$E$99*E107*E108+$E$121*E129*E130)/SUM($E$33*E41,$E$55*E63,$E$77*E85,$E$99*E107,$E$121*E129) -> 3450.2617 | F27: =(F42*$E$33*F41+F64*$E$55*F63+$E$77*F85*F86+$E$99*F107*F108+$E$121*F129*F130)/SUM($E$33*F41,$E$55*F63,$E$77*F85,$E$99*F107,$E$121*F129) -> 3170.9934 | G27: =(G42*$E$33*G41+G64*$E$55*G63+$E$77*G85*G86+$E$99*G107*G108+$E$121*G129*G130)/SUM($E$33*G41,$E$55*G63,$E$77*G85,$E$99*G107,$E$121*G129) -> 3286.9449 | H27: =(H42*$E$33*H41+H64*$E$55*H63+$E$77*H85*H86+$E$99*H107*H108+$E$121*H129*H130)/SUM($E$33*H41,$E$55*H63,$E$77*H85,$E$99*H107,$E$121*H129) -> 2996.1266 | I27: =(I42*$E$33*I41+I64*$E$55*I63+$E$77*I85*I86+$E$99*I107*I108+$E$121*I129*I130)/SUM($E$33*I41,$E$55*I63,$E$77*I85,$E$99*I107,$E$121*I129) -> 2972.6018 | J27: =(J42*$E$33*J41+J64*$E$55*J63+$E$77*J85*J86+$E$99*J107*J108+$E$121*J129*J130)/SUM($E$33*J41,$E$55*J63,$E$77*J85,$E$99*J107,$E$121*J129) -> 3037.6327 | K27: =(K42*$E$33*K41+K64*$E$55*K63+$E$77*K85*K86+$E$99*K107*K108+$E$121*K129*K130)/SUM($E$33*K41,$E$55*K63,$E$77*K85,$E$99*K107,$E$121*K129) -> 3056.6866 | ... O27: =(O42*$E$33*O41+O64*$E$55*O63+$E$77*O85*O86+$E$99*O107*O108+$E$121*O129*O130)/SUM($E$33*O41,$E$55*O63,$E$77*O85,$E$99*O107,$E$121*O129) -> 3198.0453 | P27: =(D27*31+E27*28+F27*31+G27*30+H27*31+I27*30+J27*31+K27*31+L27*30+M27*31+N27*30+O27*31)/365 -> 3082.6497 | R27: EBIT | T27: =SUM(T48,T70,T92,T114,T136) -> 62874148 | U27: =SUM(U48,U70,U92,U114,U136) -> 42910949 | V27: =SUM(V48,V70,V92,V114,V136) -> 24042174 | W27: =SUM(W48,W70,W92,W114,W136) -> 25051019 | X27: =SUM(X48,X70,X92,X114,X136) -> 17197184 | Y27: =SUM(Y48,Y70,Y92,Y114,Y136) -> 12899417 | Z27: =SUM(Z48,Z70,Z92,Z114,Z136) -> 31592298 | AA27: =SUM(AA48,AA70,AA92,AA114,AA136) -> 37914927 | ... AD27: =SUM(AD48,AD70,AD92,AD114,AD136) -> 39297054 | AE27: 42089386 | AF27: =SUM(T27:AE27) -> 3.7277348e+08
B28: MF Projection RevPar | D28: =D26*D27 -> 3082.0053 | E28: =E26*E27 -> 2860.0165 | F28: =F26*F27 -> 2116.7663 | G28: =G26*G27 -> 2191.7205 | H28: =H26*H27 -> 2033.0001 | I28: =I26*I27 -> 1974.1757 | J28: =J26*J27 -> 2287.5227 | K28: =K26*K27 -> 2188.129 | ... P28: =P26*P27 -> 2194.4051 | R28: NPAT | T28: =SUM(T49,T71,T93,T115,T137) -> 19641310 | U28: =SUM(U49,U71,U93,U115,U137) -> 8588744.3 | V28: =SUM(V49,V71,V93,V115,V137) -> -16454804 | W28: =SUM(W49,W71,W93,W115,W137) -> -7814373.3 | X28: =SUM(X49,X71,X93,X115,X137) -> -14927964 | Y28: =SUM(Y49,Y71,Y93,Y115,Y137) -> -19192407 | Z28: =SUM(Z49,Z71,Z93,Z115,Z137) -> -1995255.5 | AA28: =SUM(AA49,AA71,AA93,AA115,AA137) -> 4540295.5 | ... AD28: =SUM(AD49,AD71,AD93,AD115,AD137) -> 7270548.1 | AE28: 14995095 | AF28: =SUM(T28:AE28) -> -50926259
B29: OCC | D29: =(D45*$E$33+D67*$E$55+D89*$E$77+D111*$E$99+D133*$E$121)/SUM($E$33,$E$55,$E$77,$E$99,$E$121) -> 0.8406497 | E29: =(E45*$E$33+E67*$E$55+E89*$E$77+E111*$E$99+E133*$E$121)/SUM($E$33,$E$55,$E$77,$E$99,$E$121) -> 0.82892743 | F29: =(F45*$E$33+F67*$E$55+F89*$E$77+F111*$E$99+F133*$E$121)/SUM($E$33,$E$55,$E$77,$E$99,$E$121) -> 0.66754043 | G29: =(G45*$E$33+G67*$E$55+G89*$E$77+G111*$E$99+G133*$E$121)/SUM($E$33,$E$55,$E$77,$E$99,$E$121) -> 0.66679565 | H29: =(H45*$E$33+H67*$E$55+H89*$E$77+H111*$E$99+H133*$E$121)/SUM($E$33,$E$55,$E$77,$E$99,$E$121) -> 0.68033289 | I29: =(I45*$E$33+I67*$E$55+I89*$E$77+I111*$E$99+I133*$E$121)/SUM($E$33,$E$55,$E$77,$E$99,$E$121) -> 0.66412383 | J29: =(J45*$E$33+J67*$E$55+J89*$E$77+J111*$E$99+J133*$E$121)/SUM($E$33,$E$55,$E$77,$E$99,$E$121) -> 0.7703775 | K29: =(K45*$E$33+K67*$E$55+K89*$E$77+K111*$E$99+K133*$E$121)/SUM($E$33,$E$55,$E$77,$E$99,$E$121) -> 0.79462901 | ... O29: =(O45*$E$33+O67*$E$55+O89*$E$77+O111*$E$99+O133*$E$121)/SUM($E$33,$E$55,$E$77,$E$99,$E$121) -> 0.82031761 | P29: =(D29*31+E29*28+F29*31+G29*30+H29*31+I29*30+J29*31+K29*31+L29*30+M29*31+N29*30+O29*31)/365 -> 0.74487611
B30: ADR | D30: =(D48*$E$33*D45+D70*$E$55*D67+$E$77*D89*D92+$E$99*D111*D114+$E$121*D133*D136)/SUM($E$33*D45,$E$55*D67,$E$77*D89,$E$99*D111,$E$121*D133) -> 3666.2182 | E30: =(E48*$E$33*E45+E70*$E$55*E67+$E$77*E89*E92+$E$99*E111*E114+$E$121*E133*E136)/SUM($E$33*E45,$E$55*E67,$E$77*E89,$E$99*E111,$E$121*E133) -> 3450.2617 | F30: =(F48*$E$33*F45+F70*$E$55*F67+$E$77*F89*F92+$E$99*F111*F114+$E$121*F133*F136)/SUM($E$33*F45,$E$55*F67,$E$77*F89,$E$99*F111,$E$121*F133) -> 3170.9934 | G30: =(G48*$E$33*G45+G70*$E$55*G67+$E$77*G89*G92+$E$99*G111*G114+$E$121*G133*G136)/SUM($E$33*G45,$E$55*G67,$E$77*G89,$E$99*G111,$E$121*G133) -> 3286.9449 | H30: =(H48*$E$33*H45+H70*$E$55*H67+$E$77*H89*H92+$E$99*H111*H114+$E$121*H133*H136)/SUM($E$33*H45,$E$55*H67,$E$77*H89,$E$99*H111,$E$121*H133) -> 2990.0159 | I30: =(I48*$E$33*I45+I70*$E$55*I67+$E$77*I89*I92+$E$99*I111*I114+$E$121*I133*I136)/SUM($E$33*I45,$E$55*I67,$E$77*I89,$E$99*I111,$E$121*I133) -> 2972.6018 | J30: =(J48*$E$33*J45+J70*$E$55*J67+$E$77*J89*J92+$E$99*J111*J114+$E$121*J133*J136)/SUM($E$33*J45,$E$55*J67,$E$77*J89,$E$99*J111,$E$121*J133) -> 3119.1504 | K30: =(K48*$E$33*K45+K70*$E$55*K67+$E$77*K89*K92+$E$99*K111*K114+$E$121*K133*K136)/SUM($E$33*K45,$E$55*K67,$E$77*K89,$E$99*K111,$E$121*K133) -> 3132.2813 | ... O30: =(O48*$E$33*O45+O70*$E$55*O67+$E$77*O89*O92+$E$99*O111*O114+$E$121*O133*O136)/SUM($E$33*O45,$E$55*O67,$E$77*O89,$E$99*O111,$E$121*O133) -> 3434.9158 | P30: =(D30*31+E30*28+F30*31+G30*30+H30*31+I30*30+J30*31+K30*31+L30*30+M30*31+N30*30+O30*31)/365 -> 3180.1886
B31: RevPar | D31: =D29*D30 -> 3082.0053 | E31: =E29*E30 -> 2860.0165 | F31: =F29*F30 -> 2116.7663 | G31: =G29*G30 -> 2191.7205 | H31: =H29*H30 -> 2034.2061 | I31: =I29*I30 -> 1974.1757 | J31: =J29*J30 -> 2402.9233 | K31: =K29*K30 -> 2489.0016 | ... P31: =P29*P30 -> 2368.8465 | AB31: =AB24-AB23 -> -666567.94 | AC31: =AC24-AC23 -> 15655186 | AF31: =AF23-AF24 -> -67799912
AB32: =AB27-AB26 -> -3.385 | AC32: =AC27-AC26 -> -3.39 | AF32: =AF27-AF26 -> 6787487.4
E33: 445 | P33: SR9 | R33: kthb
B34: SR9 | D34: 2025 | P34: Avg | R34: SR9 | T34: 2025 | AF34: Total | AH34: =SUM(AF36,AF58,AF80,AF102,AF124) -> 1.6415156e+09
D35: Jan | E35: Feb | F35: Mar | G35: Apr | H35: May | I35: Jun | J35: Jul | K35: Aug | L35: Sep | M35: Oct | N35: Nov | O35: Dec | T35: Jan | U35: Feb | V35: Mar | W35: Apr | X35: May | Y35: Jun | Z35: Jul | AA35: Aug | AB35: Sep | AC35: Oct | AD35: Nov | AE35: Dec | AH35: =AF24 -> 8.9992375e+08 | AI35: =AH35/AH34 -> 0.54822734
B36: Ascott BP | R36: Total Revenue | T36: 40471407 | U36: 35097386 | V36: 31885906 | W36: 28944482 | X36: 29907879 | Y36: 28869836 | Z36: 36038410 | AA36: 33833375 | AB36: 25832653 | AC36: 28644008 | AD36: 35706457 | AE36: 39293092 | AF36: =SUM(T36:AE36) -> 3.9452489e+08 | AH36: =AF27 -> 3.7277348e+08 | AI36: =AH36/AH34 -> 0.22709104
B37: OCC | D37: 0.90004112 | E37: 0.89 | F37: 0.86005213 | G37: 0.85449438 | H37: 0.86995288 | I37: 0.83042487 | J37: 0.90661213 | K37: 0.90993618 | L37: 0.67715356 | M37: 0.71547662 | N37: 0.86067416 | O37: 0.85770207 | P37: =(D37*31+E37*28+F37*31+G37*30+H37*31+I37*30+J37*31+K37*31+L37*30+M37*31+N37*30+O37*31)/365 -> 0.84442569 | R37: Ascott BP OPEX | T37: -17324064 | U37: -16257642 | V37: -16841922 | W37: -16999978 | X37: -17369705 | Y37: -16719378 | Z37: -16600895 | AA37: -17143570 | AB37: -16116868 | AC37: -16436879 | AD37: -16837325 | AE37: -17066591 | AF37: =SUM(T37:AE37) -> -2.0171482e+08
B38: ADR | D38: 3359.8465 | E38: 3390 | F38: 3349.797 | G38: 3380 | H38: 3320 | I38: 3304.9999 | J38: 3350.195 | K38: 3380.237 | L38: 2668 | M38: 2731 | N38: 2879 | O38: 3111 | P38: =(D38*31+E38*28+F38*31+G38*30+H38*31+I38*30+J38*31+K38*31+L38*30+M38*31+N38*30+O38*31)/365 -> 3185.053 | R38: MF Projection OPEX | T38: -16229518 | U38: -14927114 | V38: -13795448 | W38: -12830962 | X38: -13004015 | Y38: -12975051 | Z38: -14326344 | AA38: -13446375 | AB38: -9533685.2 | AC38: -9848834.7 | AD38: -13148126 | AE38: -14858277 | AF38: =SUM(T38:AE38) -> -1.5892375e+08
B39: RevPar | D39: =D37*D38 -> 3024 | E39: =E37*E38 -> 3017.1 | F39: =F37*F38 -> 2881 | G39: =G37*G38 -> 2888.191 | H39: =H37*H38 -> 2888.2436 | I39: =I37*I38 -> 2744.5541 | J39: =J37*J38 -> 3037.3275 | K39: =K37*K38 -> 3075.7999 | L39: 1806.6457 | M39: 1953.9667 | N39: 2477.8809 | O39: 2668.3111 | P39: =P37*P38 -> 2689.5406 | R39: OPEX | T39: -16229518 | U39: -14927114 | V39: -13795448 | W39: -12830962 | X39: -13004015 | Y39: -12975051 | Z39: -15032009 | AA39: -14366759 | AB39: -12105413 | AC39: -13283033 | AD39: -14449194 | AE39: -15442482 | AF39: =SUM(T39:AE39) -> -1.68441e+08
B40: MF Projection | R40: Ascott BP GOP | T40: 26263980 | U40: 23040152 | V40: 24706189 | W40: 23303141 | X40: 24295956 | Y40: 21626484 | Z40: 27188599 | AA40: 27182567 | AB40: 20112140 | AC40: 21209590 | AD40: 24239585 | AE40: 24355335 | AF40: =SUM(T40:AE40) -> 2.8752372e+08
B41: OCC | D41: 0.84682856 | E41: 0.87736758 | F41: 0.75208409 | G41: 0.6705618 | H41: 0.74889453 | I41: 0.73625468 | J41: 0.80820216 | K41: 0.75612342 | L41: 0.64810579 | M41: 0.64810579 | N41: 0.75612342 | O41: 0.7921293 | P41: =(D41*31+E41*28+F41*31+G41*30+H41*31+I41*30+J41*31+K41*31+L41*30+M41*31+N41*30+O41*31)/365 -> 0.75293443 | R41: MF Projection GOP | T41: 24241888 | U41: 20170272 | V41: 18090458 | W41: 16113520 | X41: 16903865 | Y41: 15894785 | Z41: 19592430 | AA41: 18249123 | AB41: 13244214 | AC41: 13677767 | AD41: 18066955 | AE41: 20330928 | AF41: =SUM(T41:AE41) -> 2.1457621e+08
B42: ADR | D42: 3342.4448 | E42: 3059.3151 | F42: 2930.9572 | G42: 3005.1264 | H42: 2764.293 | I42: 2778.2919 | J42: 2805.5548 | K42: 2832.5313 | L42: 2373.931 | M42: 2373.931 | N42: 2832.5313 | O42: 2967.4137 | P42: =(D42*31+E42*28+F42*31+G42*30+H42*31+I42*30+J42*31+K42*31+L42*30+M42*31+N42*30+O42*31)/365 -> 2838.0497 | R42: GOP | T42: =T36+T39 -> 24241888 | U42: =U36+U39 -> 20170272 | V42: =V36+V39 -> 18090458 | W42: =W36+W39 -> 16113520 | X42: =X36+X39 -> 16903865 | Y42: =Y36+Y39 -> 15894785 | Z42: =Z36+Z39 -> 21006401 | AA42: =AA36+AA39 -> 19466616 | ... AD42: =AD36+AD39 -> 21257263 | AE42: 23850610 | AF42: =AF36+AF39 -> 2.2608389e+08 | AG42: fall below
B43: RevPar | D43: =D41*D42 -> 2830.4777 | E43: =E41*E42 -> 2684.1438 | F43: =F41*F42 -> 2204.3263 | G43: =G41*G42 -> 2015.123 | H43: =H41*H42 -> 2070.1639 | I43: =I41*I42 -> 2045.5304 | J43: =J41*J42 -> 2267.4554 | K43: =K41*K42 -> 2141.7432 | L43: 1538.5584 | M43: 1538.5584 | N43: 2141.7432 | O43: 2350.5753 | P43: =P41*P42 -> 2136.8653 | R43: Ascott BP % GOP | T43: 0.60255009 | U43: 0.58629632 | V43: 0.5946405 | W43: 0.57819696 | X43: 0.58311702 | Y43: 0.56398482 | Z43: 0.6208932 | AA43: 0.61324015 | AB43: 0.55513913 | AC43: 0.56338856 | AD43: 0.59010245 | AE43: 0.58798171 | AF43: =AVERAGE(T43:AE43) -> 0.58662758
B44: Actual Result | R44: MF Projection % GOP | T44: 0.59898803 | U44: 0.57469443 | V44: 0.56734967 | W44: 0.55670437 | X44: 0.56519771 | Y44: 0.55056719 | Z44: 0.56308392 | AA44: 0.56308392 | AB44: 0.56308392 | AC44: 0.56308392 | AD44: 0.56308392 | AE44: 0.56308392 | AF44: =AVERAGE(T44:AE44) -> 0.56600041
B45: OCC | D45: ='[275]LSSS FY25'!C5 -> 0.84682856 | E45: ='[275]LSSS FY25'!D5 -> 0.87736758 | F45: ='[275]LSSS FY25'!E5 -> 0.75208409 | G45: ='[275]LSSS FY25'!F5 -> 0.6705618 | H45: ='[275]LSSS FY25'!G5 -> 0.74889453 | I45: ='[275]LSSS FY25'!H5 -> 0.73625468 | J45: ='[275]LSSS FY25'!I5 -> 0.84835085 | K45: ='[275]LSSS FY25'!J5 -> 0.80188474 | ... N45: ='[275]LSSS FY25'!M5 -> 0.86067416 | O45: 0.85770207 | P45: =(D45*31+E45*28+F45*31+G45*30+H45*31+I45*30+J45*31+K45*31+L45*30+M45*31+N45*30+O45*31)/365 -> 0.78250269 | R45: % GOP Margin | T45: =T42/T36 -> 0.59898803 | U45: =U42/U36 -> 0.57469443 | V45: =V42/V36 -> 0.56734967 | W45: =W42/W36 -> 0.55670437 | X45: =X42/X36 -> 0.56519771 | Y45: =Y42/Y36 -> 0.55056719 | Z45: =Z42/Z36 -> 0.58288923 | AA45: =AA42/AA36 -> 0.57536724 | ... AD45: =AD42/AD36 -> 0.59533387 | AE45: 0.60699245 | AF45: =AF42/AF36 -> 0.57305356
C46: LS | D46: ='[275]LSSS FY25'!C29 -> 0.14628489 | E46: ='[275]LSSS FY25'!D29 -> 0.10064205 | F46: ='[275]LSSS FY25'!E29 -> 0.078144255 | G46: ='[275]LSSS FY25'!F29 -> 0.085992509 | H46: ='[275]LSSS FY25'!G29 -> 0.13040957 | I46: ='[275]LSSS FY25'!H29 -> 0.1447191 | J46: ='[275]LSSS FY25'!I29 -> 0.10945995 | K46: ='[275]LSSS FY25'!J29 -> 0.095614353 | ... N46: ='[275]LSSS FY25'!M29 -> 0.093782772 | O46: 0.08851033 | P46: =(D46*31+E46*28+F46*31+G46*30+H46*31+I46*30+J46*31+K46*31+L46*30+M46*31+N46*30+O46*31)/365 -> 0.10244113 | R46: Ascott BP EBIT | T46: 15585082 | U46: 12636032 | V46: 14158999 | W46: 12859024 | X46: 13767477 | Y46: 11324323 | Z46: 16458783 | AA46: 16441117 | AB46: 9941860.1 | AC46: 10948719 | AD46: 13733159 | AE46: 13834297 | AF46: =SUM(T46:AE46) -> 1.6168887e+08
C47: SS | D47: ='[275]LSSS FY25'!C30 -> 0.70054368 | E47: ='[275]LSSS FY25'!D30 -> 0.77672552 | F47: ='[275]LSSS FY25'!E30 -> 0.67393983 | G47: ='[275]LSSS FY25'!F30 -> 0.58456929 | H47: ='[275]LSSS FY25'!G30 -> 0.61848496 | I47: ='[275]LSSS FY25'!H30 -> 0.59153558 | J47: ='[275]LSSS FY25'!I30 -> 0.7388909 | K47: ='[275]LSSS FY25'!J30 -> 0.70627039 | ... N47: ='[275]LSSS FY25'!M30 -> 0.76689139 | O47: 0.76919174 | P47: =(D47*31+E47*28+F47*31+G47*30+H47*31+I47*30+J47*31+K47*31+L47*30+M47*31+N47*30+O47*31)/365 -> 0.68006157 | R47: MF Projection EBIT | T47: 14387269 | U47: 10733552 | V47: 8487749.3 | W47: 7010547.3 | X47: 7542400.9 | Y47: 6575140.7 | Z47: 11159359 | AA47: 10240837 | AB47: 5107382.7 | AC47: 6268677.1 | AD47: 11258555 | AE47: 10009789 | AF47: =SUM(T47:AE47) -> 1.0878126e+08
B48: ADR | D48: ='[275]LSSS FY25'!C6 -> 3342.4448 | E48: ='[275]LSSS FY25'!D6 -> 3059.3151 | F48: ='[275]LSSS FY25'!E6 -> 2930.9572 | G48: ='[275]LSSS FY25'!F6 -> 3005.1264 | H48: ='[275]LSSS FY25'!G6 -> 2764.293 | I48: ='[275]LSSS FY25'!H6 -> 2778.2919 | J48: ='[275]LSSS FY25'!I6 -> 2948.5968 | K48: ='[275]LSSS FY25'!J6 -> 2942 | L48: 2657.1916 | M48: ='[275]LSSS FY25'!L6 -> 2731 | N48: ='[275]LSSS FY25'!M6 -> 2879 | O48: 3111 | P48: =(D48*31+E48*28+F48*31+G48*30+H48*31+I48*30+J48*31+K48*31+L48*30+M48*31+N48*30+O48*31)/365 -> 2929.1183 | R48: EBIT | T48: 14387269 | U48: 10733552 | V48: 8487749.3 | W48: 7010547.3 | X48: 7542400.9 | Y48: 6575140.7 | Z48: 11159359 | AA48: 10240837 | AB48: 5107382.7 | AC48: 6268677.1 | AD48: 11258555 | AE48: 13305527 | AF48: =SUM(T48:AE48) -> 1.12077e+08 | AG48: << excl. interest revenue
C49: LS | D49: 2062 | E49: 2236 | F49: 2267.0372 | G49: 2239.8422 | H49: 2055.8062 | I49: 2079.1717 | J49: 2178 | K49: 2156.2004 | L49: 2165.3418 | M49: 2007.1695 | N49: 2127.6645 | O49: 2049 | P49: =(D49*31+E49*28+F49*31+G49*30+H49*31+I49*30+J49*31+K49*31+L49*30+M49*31+N49*30+O49*31)/365 -> 2134.2472 | R49: NPAT | T49: 2928858.1 | U49: 810051.21 | V49: -6263633.4 | W49: -2777065.1 | X49: -2643252 | Y49: -5147623.2 | Z49: 287300.57 | AA49: -379638.2 | AB49: -29252572 | AC49: -3625544 | AD49: 785696.52 | AE49: 2163124.4 | AF49: =SUM(T49:AE49) -> -43114297
C50: SS | D50: 3609.8618 | E50: 3166.0527 | F50: 3007.9397 | G50: 3117.7028 | H50: 2913.6798 | I50: 2949.3316 | J50: 3062.7356 | K50: 3048.2668 | L50: 2734.2458 | M50: 2817.3981 | N50: 3042.808 | O50: 3234 | P50: =(D50*31+E50*28+F50*31+G50*30+H50*31+I50*30+J50*31+K50*31+L50*30+M50*31+N50*30+O50*31)/365 -> 3058.856
B51: RevPar | D51: =D45*D48 -> 2830.4777 | E51: =E45*E48 -> 2684.1438 | F51: =F45*F48 -> 2204.3263 | G51: =G45*G48 -> 2015.123 | H51: =H45*H48 -> 2070.1639 | I51: =I45*I48 -> 2045.5304 | J51: =J45*J48 -> 2501.4446 | K51: =K45*K48 -> 2359.1449 | ... N51: =N45*N48 -> 2477.8809 | O51: 2668.3111 | P51: =P45*P48 -> 2292.0429
C52: LS | D52: =D46*D49 -> 301.63943 | E52: =E46*E49 -> 225.03563 | F52: =F46*F49 -> 177.15594 | G52: =G46*G49 -> 192.60965 | H52: =H46*H49 -> 268.09679 | I52: =I46*I49 -> 300.89586 | J52: =J46*J49 -> 238.40377 | K52: =K46*K49 -> 206.1637 | ... N52: =N46*N49 -> 199.53827 | O52: 181.35767 | P52: =P46*P49 -> 218.63469 | S52: =AVERAGE(J45:L45) -> 0.77579638
C53: SS | D53: =D47*D50 -> 2528.8659 | E53: =E47*E50 -> 2459.154 | F53: =F47*F50 -> 2027.1704 | G53: =G47*G50 -> 1822.5133 | H53: =H47*H50 -> 1802.0671 | I53: =I47*I50 -> 1744.6346 | J53: =J47*J50 -> 2263.0275 | K53: =K47*K50 -> 2152.9006 | ... N53: =N47*N50 -> 2333.5032 | O53: 2487.5661 | P53: =P47*P50 -> 2080.2104 | S53: =AVERAGE(J48:L48) -> 2849.2628
C54: compset dif | D54: =D51/[275]Compset!B100 -> 1.0015845 | E54: =E51/[275]Compset!C100 -> 0.9679846 | F54: =F51/[275]Compset!D100 -> 0.9250914 | G54: =G51/[275]Compset!E100 -> 0.94715657 | H54: =H51/[275]Compset!F100 -> 0.96600307 | I54: =I51/[275]Compset!G100 -> 0.9315947 | J54: =J51/[275]Compset!H100 -> 1.0414484 | K54: =K51/[275]Compset!I100 -> 0.92813065 | ... O54: =O51/[275]Compset!M100 -> 1.1024778 | S54: =AVERAGE(J51:L51) -> 2219.9721
E55: 451 | P55: ATB
B56: ATB | D56: 2025 | P56: Avg | R56: ATB | T56: 2025 | AF56: Total
D57: Jan | E57: Feb | F57: Mar | G57: Apr | H57: May | I57: Jun | J57: Jul | K57: Aug | L57: Sep | M57: Oct | N57: Nov | O57: Dec | T57: Jan | U57: Feb | V57: Mar | W57: Apr | X57: May | Y57: Jun | Z57: Jul | AA57: Aug | AB57: Sep | AC57: Oct | AD57: Nov | AE57: Dec
B58: Ascott BP | R58: Total Revenue | T58: 44816874 | U58: 39315011 | V58: 33467186 | W58: 33126952 | X58: 32359986 | Y58: 32758379 | Z58: 35983638 | AA58: 39311513 | AB58: 30656088 | AC58: 35395218 | AD58: 38378768 | AE58: 45959221 | AF58: =SUM(T58:AE58) -> 4.4152883e+08
B59: OCC | D59: 0.80499087 | E59: 0.92001901 | F59: 0.82601018 | G59: 0.80437644 | H59: 0.72152202 | I59: 0.81163891 | J59: 0.85709058 | K59: 0.83999714 | L59: 0.79279022 | M59: 0.66881005 | N59: 0.72591374 | O59: 0.766 | P59: =(D59*31+E59*28+F59*31+G59*30+H59*31+I59*30+J59*31+K59*31+L59*30+M59*31+N59*30+O59*31)/365 -> 0.79402509 | R59: Ascott BP OPEX | T59: -19343621 | U59: -19615171 | V59: -19966998 | W59: -19132674 | X59: -18431379 | Y59: -19532167 | Z59: -20148691 | AA59: -19857854 | AB59: -18146582 | AC59: -18219875 | AD59: -19741661 | AE59: -20192087 | AF59: =SUM(T59:AE59) -> -2.3232876e+08
B60: ADR | D60: 4211.7489 | E60: 4154.9141 | F60: 3930.9029 | G60: 4174.3065 | H60: 3980.9364 | I60: 4071.976 | J60: 4245.1874 | K60: 4153.0141 | L60: 3838.2041 | M60: 3843.3963 | N60: 4378.1206 | O60: 4458.057 | P60: =(D60*31+E60*28+F60*31+G60*30+H60*31+I60*30+J60*31+K60*31+L60*30+M60*31+N60*30+O60*31)/365 -> 4119.8256 | R60: MF Projection OPEX | T60: -16429094 | U60: -16721318 | V60: -15985045 | W60: -15144800 | X60: -14935701 | Y60: -16249932 | Z60: -17528795 | AA60: -16566862 | AB60: -11769455 | AC60: -11953287 | AD60: -16150881 | AE60: -18183469 | AF60: =SUM(T60:AE60) -> -1.8761864e+08
B61: RevPar | D61: =D59*D60 -> 3390.4194 | E61: =E59*E60 -> 3822.5999 | F61: =F59*F60 -> 3246.9658 | G61: =G59*G60 -> 3357.7138 | H61: =H59*H60 -> 2872.3333 | I61: =I59*I60 -> 3304.9742 | J61: =J59*J60 -> 3638.5101 | K61: =K59*K60 -> 3488.52 | L61: 3042.8907 | M61: 2570.5021 | N61: 3178.1379 | O61: 3414.8717 | P61: =P59*P60 -> 3271.2449 | R61: OPEX | T61: -16429094 | U61: -16721318 | V61: -15985045 | W61: -15144800 | X61: -14935701 | Y61: -16249932 | Z61: -17153983 | AA61: -17176655 | AB61: -15502853 | AC61: -16966986 | AD61: -17233047 | AE61: -17955192 | AF61: =SUM(T61:AE61) -> -1.974546e+08
B62: MF Projection | R62: Ascott BP GOP | T62: 29008556 | U62: 29642266 | V62: 26435848 | W62: 27297452 | X62: 22716253 | Y62: 26252836 | Z62: 31859775 | AA62: 30060490 | AB62: 19250938 | AC62: 20603646 | AD62: 31725878 | AE62: 33419233 | AF62: =SUM(T62:AE62) -> 3.2827317e+08
B63: OCC | D63: 0.803 | E63: 0.80828318 | F63: 0.66211287 | G63: 0.62771619 | H63: 0.65252843 | I63: 0.67775314 | J63: 0.76558897 | K63: 0.71486522 | L63: 0.61274161 | M63: 0.61274161 | N63: 0.71486522 | O63: 0.74890642 | P63: =(D63*31+E63*28+F63*31+G63*30+H63*31+I63*30+J63*31+K63*31+L63*30+M63*31+N63*30+O63*31)/365 -> 0.69966099 | R63: MF Projection GOP | T63: 28387780 | U63: 22593693 | V63: 17482141 | W63: 17982152 | X63: 17424286 | Y63: 16508447 | Z63: 20647383 | AA63: 19590931 | AB63: 14376306 | AC63: 14230067 | AD63: 19314266 | AE63: 21504889 | AF63: =SUM(T63:AE63) -> 2.3004234e+08
B64: ADR | D64: 3904 | E64: 3768.8028 | F64: 3510.8796 | G64: 3763 | H64: 3463.2438 | I64: 3444.7295 | J64: 3462.3954 | K64: 3495.6877 | L64: 2929.7192 | M64: 2929.7192 | N64: 3495.6877 | O64: 3662.149 | P64: =(D64*31+E64*28+F64*31+G64*30+H64*31+I64*30+J64*31+K64*31+L64*30+M64*31+N64*30+O64*31)/365 -> 3484.3586 | R64: GOP | T64: =T58+T61 -> 28387780 | U64: =U58+U61 -> 22593693 | V64: =V58+V61 -> 17482141 | W64: =W58+W61 -> 17982152 | X64: =X58+X61 -> 17424286 | Y64: =Y58+Y61 -> 16508447 | Z64: =Z58+Z61 -> 18829655 | AA64: =AA58+AA61 -> 22134858 | ... AC64: =AC58+AC61 -> 18428232 | AD64: 21145720 | AE64: 28004029 | AF64: =SUM(T64:AE64) -> 2.4407423e+08
B65: RevPar | D65: =D63*D64 -> 3134.912 | E65: =E63*E64 -> 3046.2599 | F65: =F63*F64 -> 2324.5985 | G65: =G63*G64 -> 2362.096 | H65: =H63*H64 -> 2259.8651 | I65: =I63*I64 -> 2334.6762 | J65: =J63*J64 -> 2650.7718 | K65: =K63*K64 -> 2498.9455 | L65: 1795.1609 | M65: 1795.1609 | N65: 2498.9455 | O65: 2742.6069 | P65: =P63*P64 -> 2437.8698 | R65: Ascott BP % GOP | T65: 0.59994313 | U65: 0.60178255 | V65: 0.56970316 | W65: 0.58792544 | X65: 0.55206708 | Y65: 0.57339378 | Z65: 0.61258825 | AA65: 0.60219326 | AB65: 0.51476509 | AC65: 0.5307001 | AD65: 0.616425 | AE65: 0.6233615 | AF65: =AVERAGE(T65:AE65) -> 0.5820707
B66: Actual Result | R66: MF Projection % GOP | T66: 0.63341723 | U66: 0.57468363 | V66: 0.52236662 | W66: 0.54282544 | X66: 0.53845158 | Y66: 0.50394579 | Z66: 0.53454788 | AA66: 0.53454788 | AB66: 0.53454788 | AC66: 0.53454788 | AD66: 0.53454788 | AE66: 0.53454788 | AF66: =AVERAGE(T66:AE66) -> 0.54358146
B67: OCC | D67: ='[275]LSSS FY25'!C9 -> 0.803 | E67: ='[275]LSSS FY25'!D9 -> 0.80828318 | F67: ='[275]LSSS FY25'!E9 -> 0.66211287 | G67: ='[275]LSSS FY25'!F9 -> 0.62771619 | H67: ='[275]LSSS FY25'!G9 -> 0.65252843 | I67: ='[275]LSSS FY25'!H9 -> 0.67775314 | J67: ='[275]LSSS FY25'!I9 -> 0.72798798 | K67: ='[275]LSSS FY25'!J9 -> 0.79279022 | ... N67: ='[275]LSSS FY25'!M9 -> 0.766 | O67: 0.78571429 | P67: =(D67*31+E67*28+F67*31+G67*30+H67*31+I67*30+J67*31+K67*31+L67*30+M67*31+N67*30+O67*31)/365 -> 0.72463502 | R67: % GOP Margin | T67: =T64/T58 -> 0.63341723 | U67: =U64/U58 -> 0.57468363 | V67: =V64/V58 -> 0.52236662 | W67: =W64/W58 -> 0.54282544 | X67: =X64/X58 -> 0.53845158 | Y67: =Y64/Y58 -> 0.50394579 | Z67: =Z64/Z58 -> 0.52328381 | AA67: =AA64/AA58 -> 0.563063 | ... AD67: =AD64/AD58 -> 0.55097445 | AE67: 0.60932341 | AF67: =AF64/AF58 -> 0.55279341
C68: LS | D68: ='[275]LSSS FY25'!C34 -> 0.25 | E68: ='[275]LSSS FY25'!D34 -> 0.2216503 | F68: ='[275]LSSS FY25'!E34 -> 0.23109935 | G68: ='[275]LSSS FY25'!F34 -> 0.22010347 | H68: ='[275]LSSS FY25'!G34 -> 0.26886489 | I68: ='[275]LSSS FY25'!H34 -> 0.26622321 | J68: ='[275]LSSS FY25'!I34 -> 0.27637508 | K68: ='[275]LSSS FY25'!J34 -> 0.32514081 | ... O68: ='[275]LSSS FY25'!N34 -> 0 | P68: =(D68*31+E68*28+F68*31+G68*30+H68*31+I68*30+J68*31+K68*31+L68*30+M68*31+N68*30+O68*31)/365 -> 0.24731982 | R68: Ascott BP EBIT | T68: 14813422 | U68: 15390807 | V68: 12428728 | W68: 13246186 | X68: 9051287.7 | Y68: 12275616 | Z68: 17428659 | AA68: 15780814 | AB68: 5868950.5 | AC68: 7126209.3 | AD68: 17327898 | AE68: 18876287 | AF68: =SUM(T68:AE68) -> 1.5961486e+08
C69: SS | D69: ='[275]LSSS FY25'!C35 -> 0.553 | E69: ='[275]LSSS FY25'!D35 -> 0.58663288 | F69: ='[275]LSSS FY25'!E35 -> 0.43101352 | G69: ='[275]LSSS FY25'!F35 -> 0.40761271 | H69: ='[275]LSSS FY25'!G35 -> 0.38366354 | I69: ='[275]LSSS FY25'!H35 -> 0.41152993 | J69: ='[275]LSSS FY25'!I35 -> 0.4516129 | K69: ='[275]LSSS FY25'!J35 -> 0.46764941 | ... O69: ='[275]LSSS FY25'!N35 -> 0 | P69: =(D69*31+E69*28+F69*31+G69*30+H69*31+I69*30+J69*31+K69*31+L69*30+M69*31+N69*30+O69*31)/365 -> 0.41058331 | R69: MF Projection EBIT | T69: 14310137 | U69: 9194661 | V69: 4351856.4 | W69: 5432102.4 | X69: 2025598.3 | Y69: 2563764.8 | Z69: 3799037.7 | AA69: 8833772.7 | AB69: 2784586.6 | AC69: 5828257.3 | AD69: 8166180.1 | AE69: 3109387.2 | AF69: =SUM(T69:AE69) -> 70399341
B70: ADR | D70: ='[275]LSSS FY25'!C10 -> 3904 | E70: ='[275]LSSS FY25'!D10 -> 3768.8028 | F70: ='[275]LSSS FY25'!E10 -> 3510.8796 | G70: ='[275]LSSS FY25'!F10 -> 3763 | H70: ='[275]LSSS FY25'!G10 -> 3463.2438 | I70: ='[275]LSSS FY25'!H10 -> 3444.7295 | J70: ='[275]LSSS FY25'!I10 -> 3425.6718 | K70: ='[275]LSSS FY25'!J10 -> 3432.7446 | ... N70: ='[275]LSSS FY25'!M10 -> 3535 | O70: 3565.3739 | P70: =(D70*31+E70*28+F70*31+G70*30+H70*31+I70*30+J70*31+K70*31+L70*30+M70*31+N70*30+O70*31)/365 -> 3534.0011 | R70: EBIT | T70: 14310137 | U70: 9194661 | V70: 4351856.4 | W70: 5432102.4 | X70: 2025598.3 | Y70: 2563764.8 | Z70: 3799037.7 | AA70: 8833772.7 | AB70: 2784583.2 | AC70: 5828253.9 | AD70: 8166176.7 | AE70: 1861048 | AF70: =SUM(T70:AE70) -> 69150992
C71: LS | D71: 2434 | E71: 2540.855 | F71: 2390.5471 | G71: 2431.4258 | H71: 2386.8085 | I71: 2419 | J71: 2363.7198 | K71: 2373.8631 | L71: 2487.09 | M71: 2388.0539 | N71: 2482.9038 | P71: =(D71*31+E71*28+F71*31+G71*30+H71*31+I71*30+J71*31+K71*31+L71*30+M71*31+N71*30+O71*31)/365 -> 2219.7351 | R71: NPAT | T71: 2855051.1 | U71: 438267.84 | V71: -6798452.4 | W71: -3050085.4 | X71: -5800365 | Y71: -5168377.1 | Z71: -4330382.2 | AA71: 543369.61 | AB71: -3887046.4 | AC71: -1529400.8 | AD71: 518730.56 | AE71: -6704502.9 | AF71: =SUM(T71:AE71) -> -32913193
C72: SS | D72: 4568 | E72: 4232.7642 | F72: 4111.5756 | G72: 4482.0559 | H72: 4217.5914 | I72: 4108.1405 | J72: 4075.5582 | K72: 4138.401 | L72: 3975.3172 | M72: 3951.6231 | N72: 4219.7965 | P72: =(D72*31+E72*28+F72*31+G72*30+H72*31+I72*30+J72*31+K72*31+L72*30+M72*31+N72*30+O72*31)/365 -> 3832.9368
B73: RevPar | D73: =D67*D70 -> 3134.912 | E73: =E67*E70 -> 3046.2599 | F73: =F67*F70 -> 2324.5985 | G73: =G67*G70 -> 2362.096 | H73: =H67*H70 -> 2259.8651 | I73: =I67*I70 -> 2334.6762 | J73: =J67*J70 -> 2493.8479 | K73: =K67*K70 -> 2721.4463 | ... N73: =N67*N70 -> 2707.81 | O73: 2801.3652 | P73: =P67*P70 -> 2560.8609
C74: LS | D74: =D68*D71 -> 608.5 | E74: =E68*E71 -> 563.18128 | F74: =F68*F71 -> 552.45389 | G74: =G68*G71 -> 535.16526 | H74: =H68*H71 -> 641.72901 | I74: =I68*I71 -> 643.99394 | J74: =J68*J71 -> 653.27326 | K74: =K68*K71 -> 771.83977 | ... N74: =N68*N71 -> 739.18649 | P74: =P68*P71 -> 548.98447
C75: SS | D75: =D69*D72 -> 2526.104 | E75: =E69*E72 -> 2483.0787 | F75: =F69*F72 -> 1772.1446 | G75: =G69*G72 -> 1826.9429 | H75: =H69*H72 -> 1618.1361 | I75: =I69*I72 -> 1690.6228 | J75: =J69*J72 -> 1840.5747 | K75: =K69*K72 -> 1935.3208 | ... N75: =N69*N72 -> 1976.0865 | P75: =P69*P72 -> 1573.7399
C76: compset dif
E77: 393 | P77: AES | AA77: =-AA83/AA80 -> 0.46148823 | AB77: =-AB83/AB80 -> 0.58018689 | AC77: =-AC83/AC80 -> 0.48760717
B78: AES | D78: 2025 | P78: Avg | R78: AES | T78: 2025 | AF78: Total
D79: Jan | E79: Feb | F79: Mar | G79: Apr | H79: May | I79: Jun | J79: Jul | K79: Aug | L79: Sep | M79: Oct | N79: Nov | O79: Dec | T79: Jan | U79: Feb | V79: Mar | W79: Apr | X79: May | Y79: Jun | Z79: Jul | AA79: Aug | AB79: Sep | AC79: Oct | AD79: Nov | AE79: Dec
B80: Ascott BP | R80: Total Revenue | T80: 42691295 | U80: 34251573 | V80: 25843470 | W80: 29043751 | X80: 27716957 | Y80: 25848763 | Z80: 34667693 | AA80: 36380781 | AB80: 21232005 | AC80: 28366670 | AD80: 34822686 | AE80: 40470079 | AF80: =SUM(T80:AE80) -> 3.8133572e+08
B81: OCC | D81: 0.82 | E81: 0.83 | F81: 0.8 | G81: 0.824 | H81: 0.79 | I81: 0.82 | J81: 0.83 | K81: 0.835 | L81: 0.79 | M81: 0.8 | N81: 0.83 | O81: 0.83 | P81: =(D81*31+E81*28+F81*31+G81*30+H81*31+I81*30+J81*31+K81*31+L81*30+M81*31+N81*30+O81*31)/365 -> 0.81647945 | R81: Ascott BP OPEX | T81: -17848642 | U81: -17009575 | V81: -17646156 | W81: -17825550 | X81: -17751610 | Y81: -17823161 | Z81: -17738848 | AA81: -18307610 | AB81: -17430186 | AC81: -17901065 | AD81: -17951806 | AE81: -18319326 | AF81: =SUM(T81:AE81) -> -2.1355353e+08
B82: ADR | D82: 4243.1384 | E82: 4551.7612 | F82: 3897.1452 | G82: 4102.8769 | H82: 3484.9991 | I82: 3943.1384 | J82: 4286.701 | K82: 4334.8045 | L82: 3639.7617 | M82: 3801.0001 | N82: 4300 | O82: 4260 | P82: =(D82*31+E82*28+F82*31+G82*30+H82*31+I82*30+J82*31+K82*31+L82*30+M82*31+N82*30+O82*31)/365 -> 4067.2988 | R82: MF Projection OPEX | T82: -17308338 | U82: -15306277 | V82: -13172170 | W82: -15012238 | X82: -14635663 | Y82: -13544059 | Z82: -15511167 | AA82: -14943026 | AB82: -10617498 | AC82: -10838574 | AD82: -14716957 | AE82: -16420677 | AF82: =SUM(T82:AE82) -> -1.7202664e+08
B83: RevPar | D83: =D81*D82 -> 3479.3735 | E83: =E81*E82 -> 3777.9618 | F83: =F81*F82 -> 3117.7162 | G83: =G81*G82 -> 3380.7706 | H83: =H81*H82 -> 2753.1493 | I83: =I81*I82 -> 3233.3735 | J83: =J81*J82 -> 3557.9618 | K83: =K81*K82 -> 3619.5618 | L83: 2875.4117 | M83: 3040.8001 | N83: 3569 | O83: 3535.8 | P83: =P81*P82 -> 3320.8659 | R83: OPEX | T83: -17308338 | U83: -15306277 | V83: -13172170 | W83: -15012238 | X83: -14635663 | Y83: -13544059 | Z83: -15747989 | AA83: -16789302 | AB83: -12318531 | AC83: -13831792 | AD83: -16849409 | AE83: -17268007 | AF83: =SUM(T83:AE83) -> -1.8178378e+08
B84: MF Projection | R84: Ascott BP GOP | T84: 26223838 | U84: 26121499 | V84: 22048954 | W84: 23642961 | X84: 17441332 | Y84: 22003415 | Z84: 27271723 | AA84: 27508759 | AB84: 18065103 | AC84: 20876977 | AD84: 25862113 | AE84: 26571248 | AF84: =SUM(T84:AE84) -> 2.8363792e+08
B85: OCC | D85: 0.8132 | E85: 0.76372228 | F85: 0.57399655 | G85: 0.63850721 | H85: 0.66469671 | I85: 0.62315522 | J85: 0.72276235 | K85: 0.68348431 | L85: 0.58584369 | M85: 0.58584369 | N85: 0.68348431 | O85: 0.71603118 | P85: =(D85*31+E85*28+F85*31+G85*30+H85*31+I85*30+J85*31+K85*31+L85*30+M85*31+N85*30+O85*31)/365 -> 0.67088875 | R85: MF Projection GOP | T85: 25382957 | U85: 18945296 | V85: 12671300 | W85: 14031513 | X85: 13081294 | Y85: 12304704 | Z85: 15179012 | AA85: 14893427 | AB85: 11041402 | AC85: 11010928 | AD85: 15180886 | AE85: 16407483 | AF85: =SUM(T85:AE85) -> 1.801302e+08
B86: ADR | D86: 4191 | E86: 3937.8623 | F86: 3539 | G86: 3684.1803 | H86: 3298.76 | I86: 3365.5766 | J86: 3319.125 | K86: 3351.0397 | L86: 2808.4904 | M86: 2808.4904 | N86: 3351.0397 | O86: 3510.613 | P86: =(D86*31+E86*28+F86*31+G86*30+H86*31+I86*30+J86*31+K86*31+L86*30+M86*31+N86*30+O86*31)/365 -> 3427.6647 | R86: GOP | T86: =T80+T83 -> 25382957 | U86: =U80+U83 -> 18945296 | V86: =V80+V83 -> 12671300 | W86: =W80+W83 -> 14031513 | X86: =X80+X83 -> 13081294 | Y86: =Y80+Y83 -> 12304704 | Z86: =Z80+Z83 -> 18919704 | AA86: =AA80+AA83 -> 19591479 | ... AD86: =AD80+AD83 -> 17973277 | AE86: 23202072 | AF86: =SUM(T86:AE86) -> 1.9955195e+08 | AG86: fall below
B87: RevPar | D87: =D85*D86 -> 3408.1212 | E87: =E85*E86 -> 3007.4332 | F87: =F85*F86 -> 2031.3738 | G87: =G85*G86 -> 2352.3757 | H87: =H85*H86 -> 2192.6749 | I87: =I85*I86 -> 2097.2766 | J87: =J85*J86 -> 2398.9386 | K87: =K85*K86 -> 2290.383 | L87: 1645.3364 | M87: 1645.3364 | N87: 2290.383 | O87: 2513.7083 | P87: =P85*P86 -> 2299.5817 | R87: Ascott BP % GOP | T87: 0.59501617 | U87: 0.60563062 | V87: 0.55545768 | W87: 0.57014251 | X87: 0.49559175 | Y87: 0.5524807 | Z87: 0.60589596 | AA87: 0.60041335 | AB87: 0.50894369 | AC87: 0.5383711 | AD87: 0.59027162 | AE87: 0.59191152 | AF87: =AVERAGE(T87:AE87) -> 0.56751056
B88: Actual Result | R88: MF Projection % GOP | T88: 0.59456985 | U88: 0.55312193 | V88: 0.49030954 | W88: 0.48311641 | X88: 0.47195998 | Y88: 0.4760268 | Z88: 0.48179531 | AA88: 0.48179531 | AB88: 0.48179531 | AC88: 0.48179531 | AD88: 0.48179531 | AE88: 0.48179531 | AF88: =AVERAGE(T88:AE88) -> 0.49665636
B89: OCC | D89: ='[275]LSSS FY25'!C13 -> 0.8132 | E89: ='[275]LSSS FY25'!D13 -> 0.76372228 | F89: ='[275]LSSS FY25'!E13 -> 0.57399655 | G89: ='[275]LSSS FY25'!F13 -> 0.63850721 | H89: ='[275]LSSS FY25'!G13 -> 0.66469671 | I89: ='[275]LSSS FY25'!H13 -> 0.62315522 | J89: ='[275]LSSS FY25'!I13 -> 0.78437167 | K89: ='[275]LSSS FY25'!J13 -> 0.80333251 | ... N89: ='[275]LSSS FY25'!M13 -> 0.7989 | O89: 0.76 | P89: =(D89*31+E89*28+F89*31+G89*30+H89*31+I89*30+J89*31+K89*31+L89*30+M89*31+N89*30+O89*31)/365 -> 0.70592068 | R89: % GOP Margin | T89: =T86/T80 -> 0.59456985 | U89: =U86/U80 -> 0.55312193 | V89: =V86/V80 -> 0.49030954 | W89: =W86/W80 -> 0.48311641 | X89: =X86/X80 -> 0.47195998 | Y89: =Y86/Y80 -> 0.4760268 | Z89: =Z86/Z80 -> 0.54574453 | AA89: =AA86/AA80 -> 0.53851177 | ... AD89: =AD86/AD80 -> 0.51613701 | AE89: 0.57331422 | AF89: =AF86/AF80 -> 0.52329728
C90: LS | D90: ='[275]LSSS FY25'!C39 -> 0.152918 | E90: ='[275]LSSS FY25'!D39 -> 0.1308615 | F90: ='[275]LSSS FY25'!E39 -> 0.1261594 | G90: ='[275]LSSS FY25'!F39 -> 0.12239186 | H90: ='[275]LSSS FY25'!G39 -> 0.13724042 | I90: ='[275]LSSS FY25'!H39 -> 0.14792197 | J90: ='[275]LSSS FY25'!I39 -> 0.16243946 | K90: ='[275]LSSS FY25'!J39 -> 0.18271362 | ... N90: ='[275]LSSS FY25'!M39 -> 0.14881392 | O90: 0.17302799 | P90: =(D90*31+E90*28+F90*31+G90*30+H90*31+I90*30+J90*31+K90*31+L90*30+M90*31+N90*30+O90*31)/365 -> 0.1541951 | R90: Ascott BP EBIT | T90: 14065724 | U90: 13985799 | V90: 10226438 | W90: 11685561 | X90: 5984073.7 | Y90: 10179340 | Z90: 15029759 | AA90: 15232289 | AB90: 6553050.8 | AC90: 9150444.8 | AD90: 13738039 | AE90: 14386197 | AF90: =SUM(T90:AE90) -> 1.4021671e+08
C91: SS | D91: ='[275]LSSS FY25'!C40 -> 0.660282 | E91: ='[275]LSSS FY25'!D40 -> 0.63286078 | F91: ='[275]LSSS FY25'!E40 -> 0.44783715 | G91: ='[275]LSSS FY25'!F40 -> 0.51611535 | H91: ='[275]LSSS FY25'!G40 -> 0.52745629 | I91: ='[275]LSSS FY25'!H40 -> 0.47523325 | J91: ='[275]LSSS FY25'!I40 -> 0.6219322 | K91: ='[275]LSSS FY25'!J40 -> 0.6206189 | ... N91: ='[275]LSSS FY25'!M40 -> 0.65008608 | O91: 0.58697201 | P91: =(D91*31+E91*28+F91*31+G91*30+H91*31+I91*30+J91*31+K91*31+L91*30+M91*31+N91*30+O91*31)/365 -> 0.55172558 | R91: MF Projection EBIT | T91: 13559495 | U91: 8421304.2 | V91: 2019768 | W91: 3396036.2 | X91: 2443179.4 | Y91: 1748717.3 | Z91: 7756927.5 | AA91: 8674499 | AB91: -993272.96 | AC91: 3410463.8 | AD91: 7195199.7 | AE91: 9532724.1 | AF91: =SUM(T91:AE91) -> 67165041
B92: ADR | D92: ='[275]LSSS FY25'!C14 -> 4191 | E92: ='[275]LSSS FY25'!D14 -> 3937.8623 | F92: ='[275]LSSS FY25'!E14 -> 3539 | G92: ='[275]LSSS FY25'!F14 -> 3684.1803 | H92: ='[275]LSSS FY25'!G14 -> 3298.76 | I92: ='[275]LSSS FY25'!H14 -> 3365.5766 | J92: ='[275]LSSS FY25'!I14 -> 3484 | K92: ='[275]LSSS FY25'!J14 -> 3590.0136 | ... N92: ='[275]LSSS FY25'!M14 -> 3564 | O92: 4144 | P92: =(D92*31+E92*28+F92*31+G92*30+H92*31+I92*30+J92*31+K92*31+L92*30+M92*31+N92*30+O92*31)/365 -> 3597.8954 | R92: EBIT | T92: 13472555 | U92: 8508244.8 | V92: 2019768 | W92: 3396036.2 | X92: 2443179.4 | Y92: 1748717.3 | Z92: 7756927.5 | AA92: 8674499 | AB92: -993272.96 | AC92: 3410463.8 | AD92: 7195199.7 | AE92: 11946260 | AF92: =SUM(T92:AE92) -> 69578577
C93: LS | D93: 2458 | E93: 2618.2088 | F93: 2578.1711 | G93: 2569 | H93: 2487.6686 | I93: 2664.4 | J93: 2772.183 | K93: 2516.154 | L93: 2445.8893 | M93: 2389.4635 | N93: 2417.7284 | O93: 2467 | P93: =(D93*31+E93*28+F93*31+G93*30+H93*31+I93*30+J93*31+K93*31+L93*30+M93*31+N93*30+O93*31)/365 -> 2531.365 | R93: NPAT | T93: 3294249.9 | U93: 514337.61 | V93: -5295199.1 | W93: -3936052.5 | X93: -4948841.6 | Y93: -5020631.8 | Z93: 724442.33 | AA93: 1500923.8 | AB93: -5930021.7 | AC93: -2563845.7 | AD93: 623867.84 | AE93: 4157326.7 | AF93: =SUM(T93:AE93) -> -16879444
C94: SS | D94: 4593 | E94: 4210.7372 | F94: 3810.0368 | G94: 3948.7271 | H94: 3509.8103 | I94: 3583.8262 | J94: 3670.287 | K94: 3906.1638 | L94: 3512.298 | M94: 3443.6198 | N94: 3837.8036 | O94: 4638.0595 | P94: =(D94*31+E94*28+F94*31+G94*30+H94*31+I94*30+J94*31+K94*31+L94*30+M94*31+N94*30+O94*31)/365 -> 3887.892
B95: RevPar | D95: =D89*D92 -> 3408.1212 | E95: =E89*E92 -> 3007.4332 | F95: =F89*F92 -> 2031.3738 | G95: =G89*G92 -> 2352.3757 | H95: =H89*H92 -> 2192.6749 | I95: =I89*I92 -> 2097.2766 | J95: =J89*J92 -> 2732.7509 | K95: =K89*K92 -> 2883.9747 | ... N95: =N89*N92 -> 2847.2796 | O95: 3149.44 | P95: =P89*P92 -> 2539.8288
C96: LS | D96: =D90*D93 -> 375.87245 | E96: =E90*E93 -> 342.62275 | F96: =F90*F93 -> 325.26052 | G96: =G90*G93 -> 314.42468 | H96: =H90*H93 -> 341.40867 | I96: =I90*I93 -> 394.12328 | J96: =J90*J93 -> 450.31192 | K96: =K90*K93 -> 459.7356 | ... N96: =N90*N93 -> 359.79165 | O96: 426.86005 | P96: =P90*P93 -> 390.32408
C97: SS | D97: =D91*D94 -> 3032.6752 | E97: =E91*E94 -> 2664.8104 | F97: =F91*F94 -> 1706.276 | G97: =G91*G94 -> 2037.9987 | H97: =H91*H94 -> 1851.2715 | I97: =I91*I94 -> 1703.1534 | J97: =J91*J94 -> 2282.6697 | K97: =K91*K94 -> 2424.2391 | ... N97: =N91*N94 -> 2494.9027 | O97: 2722.4111 | P97: =P91*P94 -> 2145.0495
C98: compset dif | D98: =D95/[275]Compset!B166 -> 1.0387257 | E98: =E95/[275]Compset!C166 -> 0.97155947 | F98: =F95/[275]Compset!D166 -> 0.82907125 | G98: =G95/[275]Compset!E166 -> 1.2936443 | H98: =H95/[275]Compset!F166 -> 1.2829563 | I98: =I95/[275]Compset!G166 -> 1.1810586 | J98: =J95/[275]Compset!H166 -> 1.1918369 | K98: =K95/[275]Compset!I166 -> 1.2587618 | ... O98: =O95/[275]Compset!M166 -> 1.0924655
E99: 196 | P99: LYF8
B100: Lyf | D100: 2025 | P100: Avg | R100: Lyf | T100: 2025 | AF100: Total
D101: Jan | E101: Feb | F101: Mar | G101: Apr | H101: May | I101: Jun | J101: Jul | K101: Aug | L101: Sep | M101: Oct | N101: Nov | O101: Dec | T101: Jan | U101: Feb | V101: Mar | W101: Apr | X101: May | Y101: Jun | Z101: Jul | AA101: Aug | AB101: Sep | AC101: Oct | AD101: Nov | AE101: Dec
B102: Ascott BP | R102: Total Revenue | T102: 10057547 | U102: 8360412.3 | V102: 6748527.7 | W102: 6301518.4 | X102: 5674281.4 | Y102: 5270669.7 | Z102: 5699950.6 | AA102: 6542485.8 | AB102: 6165394.4 | AC102: 6668491 | AD102: 8769680.6 | AE102: 10092201 | AF102: =SUM(T102:AE102) -> 86351160
B103: OCC | D103: 0.75707702 | E103: 0.85641399 | F103: 0.67478604 | G103: 0.71428571 | H103: 0.67100066 | I103: 0.81632653 | J103: 0.8558262 | K103: 0.8722844 | L103: 0.78231293 | M103: 0.70770244 | N103: 0.86513605 | O103: 0.81468071 | P103: =(D103*31+E103*28+F103*31+G103*30+H103*31+I103*30+J103*31+K103*31+L103*30+M103*31+N103*30+O103*31)/365 -> 0.78157674 | R103: Ascott BP OPEX | T103: -3668186.2 | U103: -3718038 | V103: -3485839.4 | W103: -3561616.4 | X103: -3354546.9 | Y103: -3738315 | Z103: -3866614.1 | AA103: -3938439.4 | AB103: -3650015.5 | AC103: -3555366.1 | AD103: -4201212.7 | AE103: -4183664.7 | AF103: =SUM(T103:AE103) -> -44921854
B104: ADR | D104: 1600 | E104: 1650 | F104: 1550 | G104: 1500 | H104: 1300 | I104: 1450 | J104: 1450 | K104: 1550 | L104: 1380 | M104: 1380 | N104: 1730 | O104: 1800 | P104: =(D104*31+E104*28+F104*31+G104*30+H104*31+I104*30+J104*31+K104*31+L104*30+M104*31+N104*30+O104*31)/365 -> 1527.4795 | R104: MF Projection OPEX | T104: -4304087.4 | U104: -4066449.8 | V104: -3154037.9 | W104: -3542348.3 | X104: -3328025.7 | Y104: -3180360.6 | Z104: -3110457.1 | AA104: -3110457.1 | AB104: -3010119.8 | AC104: -3110457.1 | AD104: -3681795.4 | AE104: -4175484.4 | AF104: =SUM(T104:AE104) -> -41774081
B105: RevPar | D105: =D103*D104 -> 1211.3232 | E105: =E103*E104 -> 1413.0831 | F105: =F103*F104 -> 1045.9184 | G105: =G103*G104 -> 1071.4286 | H105: =H103*H104 -> 872.30086 | I105: =I103*I104 -> 1183.6735 | J105: =J103*J104 -> 1240.948 | K105: =K103*K104 -> 1352.0408 | ... P105: =P103*P104 -> 1193.8424 | R105: OPEX | T105: =-4304087.38 -> -4304087.4 | U105: -4066449.8 | V105: -3154037.9 | W105: -3542348.3 | X105: -3328025.7 | Y105: -3180360.6 | Z105: -3023107.9 | AA105: -3455938 | AB105: -3774574.8 | AC105: -3358245.4 | AD105: -4189774.1 | AE105: -4532855.3 | AF105: =SUM(T105:AE105) -> -43909805
B106: MF Projection | R106: Ascott BP GOP | T106: 3988652.1 | U106: 4339011.3 | V106: 3139943.7 | W106: 3014377.7 | X106: 2215137.6 | Y106: 3528945.4 | Z106: 4001490.5 | AA106: 4609876.2 | AB106: 2994822.8 | AC106: 2659839 | AD106: 4921513.4 | AE106: 5041412.3 | AF106: =SUM(T106:AE106) -> 44455022
...

Sheet result FY26
C3: YTD performance | F3: Jun
C4: Unit: kTHB
C5: SR9 | D5: Compare with MF Projection | I5: AES | J5: Compare with MF Projection | O5: lyf | P5: Compare with MF Projection | U5: SP | V5: Compare with MF Projection | AA5: Portfolio | AB5: Compare with MF Projection
D6: Ascott BP | E6: MF Projection | F6: Actual | G6: % change | J6: Ascott BP | K6: MF Projection | L6: Actual | M6: % change | P6: Ascott BP | Q6: MF Projection | R6: Actual | S6: % change | V6: Ascott BP | W6: MF Projection | X6: Actual | Y6: % change | AB6: Ascott BP | AC6: MF Projection | AD6: Actual | AE6: % change
C7: OCC | D7: {=SUMPRODUCT(D37:_xlfn.XLOOKUP($F$3,$D$21:$O$21,D37:O37),$D$19:_xlfn.XLOOKUP($F$3,$D$21:$O$21,$D$19:$O$19)/SUM($D$19:_xlfn.XLOOKUP($F$3,$D$21:$O$21,$D$19:$O$19)))} -> 0.80100999 | E7: {=SUMPRODUCT(D41:_xlfn.XLOOKUP($F$3,$D$21:$O$21,D41:O41),$D$19:_xlfn.XLOOKUP($F$3,$D$21:$O$21,$D$19:$O$19)/SUM($D$19:_xlfn.XLOOKUP($F$3,$D$21:$O$21,$D$19:$O$19)))} -> 0.80100999 | F7: {=SUMPRODUCT(D45:_xlfn.XLOOKUP($F$3,$D$21:$O$21,D45:O45),$D$19:_xlfn.XLOOKUP($F$3,$D$21:$O$21,$D$19:$O$19)/SUM($D$19:_xlfn.XLOOKUP($F$3,$D$21:$O$21,$D$19:$O$19)))} -> 0.80800795 | G7: =(F7-E7)/E7 -> 0.0087364097 | I7: OCC | J7: {=SUMPRODUCT(D60:_xlfn.XLOOKUP($F$3,$D$21:$O$21,D60:O60),$D$19:_xlfn.XLOOKUP($F$3,$D$21:$O$21,$D$19:$O$19)/SUM($D$19:_xlfn.XLOOKUP($F$3,$D$21:$O$21,$D$19:$O$19)))} -> 0.71707182 | K7: {=SUMPRODUCT(D64:_xlfn.XLOOKUP($F$3,$D$21:$O$21,D64:O64),$D$19:_xlfn.XLOOKUP($F$3,$D$21:$O$21,$D$19:$O$19)/SUM($D$19:_xlfn.XLOOKUP($F$3,$D$21:$O$21,$D$19:$O$19)))} -> 0.71601085 | L7: {=SUMPRODUCT(D68:_xlfn.XLOOKUP($F$3,$D$21:$O$21,D68:O68),$D$19:_xlfn.XLOOKUP($F$3,$D$21:$O$21,$D$19:$O$19)/SUM($D$19:_xlfn.XLOOKUP($F$3,$D$21:$O$21,$D$19:$O$19)))} -> 0.70444098 | M7: =(L7-K7)/K7 -> -0.0161588 | O7: OCC | P7: {=SUMPRODUCT(D83:_xlfn.XLOOKUP($F$3,$D$21:$O$21,D83:O83),$D$19:_xlfn.XLOOKUP($F$3,$D$21:$O$21,$D$19:$O$19)/SUM($D$19:_xlfn.XLOOKUP($F$3,$D$21:$O$21,$D$19:$O$19)))} -> 0.82641786 | Q7: {=SUMPRODUCT(D87:_xlfn.XLOOKUP($F$3,$D$21:$O$21,D87:O87),$D$19:_xlfn.XLOOKUP($F$3,$D$21:$O$21,$D$19:$O$19)/SUM($D$19:_xlfn.XLOOKUP($F$3,$D$21:$O$21,$D$19:$O$19)))} -> 0.82641786 | R7: {=SUMPRODUCT(D91:_xlfn.XLOOKUP($F$3,$D$21:$O$21,D91:O91),$D$19:_xlfn.XLOOKUP($F$3,$D$21:$O$21,$D$19:$O$19)/SUM($D$19:_xlfn.XLOOKUP($F$3,$D$21:$O$21,$D$19:$O$19)))} -> 0.78083775 | S7: =(R7-Q7)/Q7 -> -0.05515383 | U7: OCC | V7: {=SUMPRODUCT(D106:_xlfn.XLOOKUP($F$3,$D$21:$O$21,D106:O106),$D$19:_xlfn.XLOOKUP($F$3,$D$21:$O$21,$D$19:$O$19)/SUM($D$19:_xlfn.XLOOKUP($F$3,$D$21:$O$21,$D$19:$O$19)))} -> 0.74839779 | W7: {=SUMPRODUCT(D110:_xlfn.XLOOKUP($F$3,$D$21:$O$21,D110:O110),$D$19:_xlfn.XLOOKUP($F$3,$D$21:$O$21,$D$19:$O$19)/SUM($D$19:_xlfn.XLOOKUP($F$3,$D$21:$O$21,$D$19:$O$19)))} -> 0.73635837 | X7: {=SUMPRODUCT(D114:_xlfn.XLOOKUP($F$3,$D$21:$O$21,D114:O114),$D$19:_xlfn.XLOOKUP($F$3,$D$21:$O$21,$D$19:$O$19)/SUM($D$19:_xlfn.XLOOKUP($F$3,$D$21:$O$21,$D$19:$O$19)))} -> 0.73789305 | Y7: =(X7-W7)/W7 -> 0.0020841535 | AA7: OCC | AB7: {=SUMPRODUCT(D23:_xlfn.XLOOKUP($F$3,$D$21:$O$21,D23:O23),$D$19:_xlfn.XLOOKUP($F$3,$D$21:$O$21,$D$19:$O$19)/SUM($D$19:_xlfn.XLOOKUP($F$3,$D$21:$O$21,$D$19:$O$19)))} -> 0.76783318 | AC7: {=SUMPRODUCT(D26:_xlfn.XLOOKUP($F$3,$D$21:$O$21,D26:O26),$D$19:_xlfn.XLOOKUP($F$3,$D$21:$O$21,$D$19:$O$19)/SUM($D$19:_xlfn.XLOOKUP($F$3,$D$21:$O$21,$D$19:$O$19)))} -> 0.7646537 | AD7: {=SUMPRODUCT(D29:_xlfn.XLOOKUP($F$3,$D$21:$O$21,D29:O29),$D$19:_xlfn.XLOOKUP($F$3,$D$21:$O$21,$D$19:$O$19)/SUM($D$19:_xlfn.XLOOKUP($F$3,$D$21:$O$21,$D$19:$O$19)))} -> 0.75738615 | AE7: =(AD7-AC7)/AC7 -> -0.0095043718
C8: ADR | D8: {=SUMPRODUCT(D38:_xlfn.XLOOKUP($F$3,$D$21:$O$21,D38:O38),$D$19:_xlfn.XLOOKUP($F$3,$D$21:$O$21,$D$19:$O$19)/SUM($D$19:_xlfn.XLOOKUP($F$3,$D$21:$O$21,$D$19:$O$19)))} -> 2948.5504 | E8: {=SUMPRODUCT(D42:_xlfn.XLOOKUP($F$3,$D$21:$O$21,D42:O42),$D$19:_xlfn.XLOOKUP($F$3,$D$21:$O$21,$D$19:$O$19)/SUM($D$19:_xlfn.XLOOKUP($F$3,$D$21:$O$21,$D$19:$O$19)))} -> 2948.5504 | F8: {=SUMPRODUCT(D48:_xlfn.XLOOKUP($F$3,$D$21:$O$21,D48:O48),$D$19:_xlfn.XLOOKUP($F$3,$D$21:$O$21,$D$19:$O$19)/SUM($D$19:_xlfn.XLOOKUP($F$3,$D$21:$O$21,$D$19:$O$19)))} -> 2709.3088 | G8: =(F8-E8)/E8 -> -0.081138699 | I8: ADR | J8: {=SUMPRODUCT(D61:_xlfn.XLOOKUP($F$3,$D$21:$O$21,D61:O61),$D$19:_xlfn.XLOOKUP($F$3,$D$21:$O$21,$D$19:$O$19)/SUM($D$19:_xlfn.XLOOKUP($F$3,$D$21:$O$21,$D$19:$O$19)))} -> 3633.0588 | K8: {=SUMPRODUCT(D65:_xlfn.XLOOKUP($F$3,$D$21:$O$21,D65:O65),$D$19:_xlfn.XLOOKUP($F$3,$D$21:$O$21,$D$19:$O$19)/SUM($D$19:_xlfn.XLOOKUP($F$3,$D$21:$O$21,$D$19:$O$19)))} -> 3633.0588 | L8: {=SUMPRODUCT(D71:_xlfn.XLOOKUP($F$3,$D$21:$O$21,D71:O71),$D$19:_xlfn.XLOOKUP($F$3,$D$21:$O$21,$D$19:$O$19)/SUM($D$19:_xlfn.XLOOKUP($F$3,$D$21:$O$21,$D$19:$O$19)))} -> 3302.9306 | M8: =(L8-K8)/K8 -> -0.09086782 | O8: ADR | P8: {=SUMPRODUCT(D84:_xlfn.XLOOKUP($F$3,$D$21:$O$21,D84:O84),$D$19:_xlfn.XLOOKUP($F$3,$D$21:$O$21,$D$19:$O$19)/SUM($D$19:_xlfn.XLOOKUP($F$3,$D$21:$O$21,$D$19:$O$19)))} -> 1498.8101 | Q8: {=SUMPRODUCT(D88:_xlfn.XLOOKUP($F$3,$D$21:$O$21,D88:O88),$D$19:_xlfn.XLOOKUP($F$3,$D$21:$O$21,$D$19:$O$19)/SUM($D$19:_xlfn.XLOOKUP($F$3,$D$21:$O$21,$D$19:$O$19)))} -> 1476.6602 | R8: {=SUMPRODUCT(D94:_xlfn.XLOOKUP($F$3,$D$21:$O$21,D94:O94),$D$19:_xlfn.XLOOKUP($F$3,$D$21:$O$21,$D$19:$O$19)/SUM($D$19:_xlfn.XLOOKUP($F$3,$D$21:$O$21,$D$19:$O$19)))} -> 1360.3017 | S8: =(R8-Q8)/Q8 -> -0.078798408 | U8: ADR | V8: {=SUMPRODUCT(D107:_xlfn.XLOOKUP($F$3,$D$21:$O$21,D107:O107),$D$19:_xlfn.XLOOKUP($F$3,$D$21:$O$21,$D$19:$O$19)/SUM($D$19:_xlfn.XLOOKUP($F$3,$D$21:$O$21,$D$19:$O$19)))} -> 3859.9481 | W8: {=SUMPRODUCT(D111:_xlfn.XLOOKUP($F$3,$D$21:$O$21,D111:O111),$D$19:_xlfn.XLOOKUP($F$3,$D$21:$O$21,$D$19:$O$19)/SUM($D$19:_xlfn.XLOOKUP($F$3,$D$21:$O$21,$D$19:$O$19)))} -> 3856.0269 | X8: {=SUMPRODUCT(D117:_xlfn.XLOOKUP($F$3,$D$21:$O$21,D117:O117),$D$19:_xlfn.XLOOKUP($F$3,$D$21:$O$21,$D$19:$O$19)/SUM($D$19:_xlfn.XLOOKUP($F$3,$D$21:$O$21,$D$19:$O$19)))} -> 3512.1778 | Y8: =(X8-W8)/W8 -> -0.089171863 | AA8: ADR | AB8: {=SUMPRODUCT(D24:_xlfn.XLOOKUP($F$3,$D$21:$O$21,D24:O24),$D$19:_xlfn.XLOOKUP($F$3,$D$21:$O$21,$D$19:$O$19)/SUM($D$19:_xlfn.XLOOKUP($F$3,$D$21:$O$21,$D$19:$O$19)))} -> 3120.5896 | AC8: {=SUMPRODUCT(D27:_xlfn.XLOOKUP($F$3,$D$21:$O$21,D27:O27),$D$19:_xlfn.XLOOKUP($F$3,$D$21:$O$21,$D$19:$O$19)/SUM($D$19:_xlfn.XLOOKUP($F$3,$D$21:$O$21,$D$19:$O$19)))} -> 3113.4673 | AD8: {=SUMPRODUCT(D30:_xlfn.XLOOKUP($F$3,$D$21:$O$21,D30:O30),$D$19:_xlfn.XLOOKUP($F$3,$D$21:$O$21,$D$19:$O$19)/SUM($D$19:_xlfn.XLOOKUP($F$3,$D$21:$O$21,$D$19:$O$19)))} -> 2855.2308 | AE8: =(AD8-AC8)/AC8 -> -0.082941755 | AF8: YTD still lower than BG
C9: RevPar | D9: =D7*D8 -> 2361.8183 | E9: =E7*E8 -> 2361.8183 | F9: =F7*F8 -> 2189.143 | G9: =(F9-E9)/E9 -> -0.07311115 | I9: RevPar | J9: =J7*J8 -> 2605.1641 | K9: =K7*K8 -> 2601.3095 | L9: =L7*L8 -> 2326.7197 | M9: =(L9-K9)/K9 -> -0.1055583 | O9: RevPar | P9: =P7*P8 -> 1238.6434 | Q9: =Q7*Q8 -> 1220.3383 | R9: =R7*R8 -> 1062.1749 | S9: =(R9-Q9)/Q9 -> -0.1296062 | U9: RevPar | V9: =V7*V8 -> 2888.7766 | W9: =W7*W8 -> 2839.4177 | X9: =X7*X8 -> 2591.6116 | Y9: =(X9-W9)/W9 -> -0.087273557 | AA9: RevPar | AB9: =AB7*AB8 -> 2396.0922 | AC9: =AC7*AC8 -> 2380.7243 | AD9: =AD7*AD8 -> 2162.5123 | AE9: =(AD9-AC9)/AC9 -> -0.091657817
C10: GOP Margin | D10: =D14/D12 -> 0.57735728 | E10: =E14/E12 -> 0.56853481 | F10: =F14/F12 -> 0.57068731 | G10: =(F10-E10)/E10 -> 0.0037860519 | I10: GOP Margin | J10: =J14/J12 -> 0.52528254 | K10: =K14/K12 -> 0.5135675 | L10: =L14/L12 -> 0.5333681 | M10: =(L10-K10)/K10 -> 0.03855502 | O10: GOP Margin | P10: =P14/P12 -> 0.48843871 | Q10: =Q14/Q12 -> 0.48087657 | R10: =R14/R12 -> 0.45882112 | S10: =(R10-Q10)/Q10 -> -0.045865095 | U10: GOP Margin | V10: =V14/V12 -> 0.55534309 | W10: =W14/W12 -> 0.54979811 | X10: =X14/X12 -> 0.55324024 | Y10: =(X10-W10)/W10 -> 0.0062607202 | AA10: GOP Margin | AB10: =AB14/AB12 -> 0.54843882 | AC10: =AC14/AC12 -> 0.53988971 | AD10: =AD14/AD12 -> 0.54652062 | AE10: =(AD10-AC10)/AC10 -> 0.012281982
C12: Revenue | D12: =D14-D13 -> 2.1396618e+08 | E12: =E14-E13 -> 2.1396618e+08 | F12: =SUM(T36:AE36) -> 1.9627854e+08 | G12: =(F12-E12)/E12 -> -0.08266559 | I12: Revenue | J12: =J14-J13 -> 2.0401754e+08 | K12: =K14-K13 -> 2.0401754e+08 | L12: =SUM(T59:AE59) -> 1.7923401e+08 | M12: =(L12-K12)/K12 -> -0.12147746 | O12: Revenue | P12: =P14-P13 -> 45752307 | Q12: =Q14-Q13 -> 43602725 | R12: =SUM(T82:AE82) -> 39959053 | S12: =(R12-Q12)/Q12 -> -0.083565231 | U12: Revenue | V12: =V14-V13 -> 1.8566169e+08 | W12: =W14-W13 -> 1.8310152e+08 | X12: =SUM(T105:AE105) -> 1.6643298e+08 | Y12: =(X12-W12)/W12 -> -0.091034434 | AA12: Revenue | AB12: =SUM(D12,J12,P12,V12) -> 6.4939772e+08 | AC12: =SUM(E12,,K12,Q12,W12) -> 6.4468797e+08 | AD12: =SUM(F12,L12,R12,X12) -> 5.8190458e+08 | AE12: =(AD12-AC12)/AC12 -> -0.0973857 | AH12: =AF36+AF59+AF82+AF105 -> 5.8190458e+08
C13: OPEX | D13: =SUM(OFFSET($T37, 0, 0, 1, MATCH($F$3, $T$35:$AE$35, 0))) -> -90431249 | E13: =SUM(OFFSET($T38, 0, 0, 1, MATCH($F$3, $T$35:$AE$35, 0))) -> -92318958 | F13: =SUM(T39:AE39) -> -84264867 | G13: =(F13-E13)/E13 -> -0.087242007 | I13: OPEX | J13: =SUM(OFFSET($T60, 0, 0, 1, MATCH($F$3, $T$58:$AE$58, 0))) -> -96850691 | K13: =SUM(OFFSET($T61, 0, 0, 1, MATCH($F$3, $T$58:$AE$58, 0))) -> -99240765 | L13: =SUM(T62:AE62) -> -83636307 | M13: =(L13-K13)/K13 -> -0.15723839 | O13: OPEX | P13: =SUM(OFFSET($T83, 0, 0, 1, MATCH($F$3, $T$81:$AE$81, 0))) -> -23405109 | Q13: =SUM(OFFSET($T84, 0, 0, 1, MATCH($F$3, $T$81:$AE$81, 0))) -> -22635196 | R13: =SUM(T85:AE85) -> -21624996 | S13: =(R13-Q13)/Q13 -> -0.044629633 | U13: OPEX | V13: =SUM(OFFSET($T106, 0, 0, 1, MATCH($F$3, $T$104:$AE$104, 0))) -> -82555754 | W13: =SUM(OFFSET($T107, 0, 0, 1, MATCH($F$3, $T$104:$AE$104, 0))) -> -82432651 | X13: =SUM(T108:AE108) -> -74355557 | Y13: =(X13-W13)/W13 -> -0.097984159 | AA13: OPEX | AB13: =SUM(D13,J13,P13,V13) -> -2.932428e+08 | AC13: =SUM(E13,,K13,Q13,W13) -> -2.9662757e+08 | AD13: =SUM(F13,L13,R13,X13) -> -2.6388173e+08 | AE13: =(AD13-AC13)/AC13 -> -0.1103938 | AH13: =AF39+AF62+AF85+AF108 -> -2.6388173e+08
C14: GOP | D14: =SUM(OFFSET($T40, 0, 0, 1, MATCH($F$3, $T$35:$AE$35, 0))) -> 1.2353493e+08 | E14: =SUM(OFFSET($T41, 0, 0, 1, MATCH($F$3, $T$35:$AE$35, 0))) -> 1.2164722e+08 | F14: =F12+F13 -> 1.1201367e+08 | G14: =(F14-E14)/E14 -> -0.079192514 | I14: GOP | J14: =SUM(OFFSET($T63, 0, 0, 1, MATCH($F$3, $T$58:$AE$58, 0))) -> 1.0716685e+08 | K14: =SUM(OFFSET($T64, 0, 0, 1, MATCH($F$3, $T$58:$AE$58, 0))) -> 1.0477678e+08 | L14: =L12+L13 -> 95597704 | M14: =(L14-K14)/K14 -> -0.087606007 | O14: GOP | P14: =SUM(OFFSET($T86, 0, 0, 1, MATCH($F$3, $T$81:$AE$81, 0))) -> 22347198 | Q14: =SUM(OFFSET($T87, 0, 0, 1, MATCH($F$3, $T$81:$AE$81, 0))) -> 20967529 | R14: =R12+R13 -> 18334057 | S14: =(R14-Q14)/Q14 -> -0.1255976 | U14: GOP | V14: =SUM(OFFSET($T109, 0, 0, 1, MATCH($F$3, $T$104:$AE$104, 0))) -> 1.0310594e+08 | W14: =SUM(OFFSET($T110, 0, 0, 1, MATCH($F$3, $T$104:$AE$104, 0))) -> 1.0066887e+08 | X14: =X12+X13 -> 92077420 | Y14: =(X14-W14)/W14 -> -0.085343655 | AA14: GOP | AB14: =SUM(D14,J14,P14,V14) -> 3.5615492e+08 | AC14: =SUM(E14,,K14,Q14,W14) -> 3.480604e+08 | AD14: =SUM(F14,L14,R14,X14) -> 3.1802285e+08 | AE14: =(AD14-AC14)/AC14 -> -0.086299807
C15: JV expense | D15: =D16-D14 -> -44116320 | E15: =E16-E14 -> -61905238 | F15: =F16-F14 -> -59010430 | G15: =(F15-E15)/E15 -> -0.046761921 | I15: JV expense | J15: =J16-J14 -> -53265404 | K15: =K16-K14 -> -69690642 | L15: =L16-L14 -> -62082625 | M15: =(L15-K15)/K15 -> -0.10916843 | O15: JV expense | P15: =P16-P14 -> -15350520 | Q15: =Q16-Q14 -> -13970851 | R15: =R16-R14 -> -13788209 | S15: =(R15-Q15)/Q15 -> -0.013073059 | U15: JV expense | V15: =V16-V14 -> -10519785 | W15: =W16-W14 -> -41567488 | X15: =X16-X14 -> -39893137 | Y15: =(X15-W15)/W15 -> -0.040280323 | AA15: JV expense | AB15: =SUM(D15,J15,P15,V15) -> -1.2325203e+08 | AC15: =SUM(E15,K15,Q15,W15) -> -1.8713422e+08 | AD15: =SUM(F15,L15,R15,X15) -> -1.747744e+08 | AE15: =(AD15-AC15)/AC15 -> -0.066047884
C16: EBIT | D16: =SUM(OFFSET($T46, 0, 0, 1, MATCH($F$3, $T$35:$AE$35, 0))) -> 79418611 | E16: =SUM(OFFSET($T47, 0, 0, 1, MATCH($F$3, $T$35:$AE$35, 0))) -> 59741984 | F16: =SUM(T48:AE48) -> 53003242 | G16: =(F16-E16)/E16 -> -0.11279742 | I16: EBIT | J16: =SUM(OFFSET($T69, 0, 0, 1, MATCH($F$3, $T$58:$AE$58, 0))) -> 53901450 | K16: =SUM(OFFSET($T70, 0, 0, 1, MATCH($F$3, $T$58:$AE$58, 0))) -> 35086137 | L16: =SUM(T71:AE71) -> 33515079 | M16: =(L16-K16)/K16 -> -0.044777162 | O16: EBIT | P16: =SUM(OFFSET($T93, 0, 0, 1, MATCH($F$3, $T$81:$AE$81, 0))) -> 6996677.8 | Q16: =SUM(OFFSET($T93, 0, 0, 1, MATCH($F$3, $T$81:$AE$81, 0))) -> 6996677.8 | R16: =SUM(T94:AE94) -> 4545848.3 | S16: =(R16-Q16)/Q16 -> -0.35028474 | U16: EBIT | V16: =SUM(OFFSET($T115, 0, 0, 1, MATCH($F$3, $T$104:$AE$104, 0))) -> 92586154 | W16: =SUM(OFFSET($T116, 0, 0, 1, MATCH($F$3, $T$104:$AE$104, 0))) -> 59101381 | X16: =SUM(T117:AE117) -> 52184283 | Y16: =(X16-W16)/W16 -> -0.11703783 | AA16: EBIT | AB16: =SUM(D16,J16,P16,V16) -> 2.3290289e+08 | AC16: =SUM(E16,K16,Q16,W16) -> 1.6092618e+08 | AD16: =SUM(F16,L16,R16,X16) -> 1.4324845e+08 | AE16: =(AD16-AC16)/AC16 -> -0.10984991
D19: 31 | E19: 28 | F19: 31 | G19: 30 | H19: 31 | I19: 30 | J19: 31 | K19: 31 | L19: 30 | M19: 31 | N19: 30 | O19: 31 | P19: =SUM(D19:O19) -> 365
B20: Portfolio | D20: 2026 | P20: Avg | R20: Overall GOP / EBIT | T20: 2026 | AF20: Total
D21: Jan | E21: Feb | F21: Mar | G21: Apr | H21: May | I21: Jun | J21: Jul | K21: Aug | L21: Sep | M21: Oct | N21: Nov | O21: Dec | T21: Jan | U21: Feb | V21: Mar | W21: Apr | X21: May | Y21: Jun | Z21: Jul | AA21: Aug | AB21: Sep | AC21: Oct | AD21: Nov | AE21: Dec
B22: Key Available | D22: =E33+E56+E79+E102 -> 1358 | E22: =D22 -> 1358 | F22: =E22 -> 1358 | G22: =F22 -> 1358 | H22: =G22 -> 1358 | I22: =H22 -> 1358 | J22: =I22 -> 1358 | K22: =J22 -> 1358 | L22: =K22 -> 1358 | ... O22: =N22 -> 1358 | R22: Total Revenue | T22: =SUM(T36,T59,T82,T105) -> 1.1844209e+08 | U22: =SUM(U36,U59,U82,U105) -> 1.1670003e+08 | V22: =SUM(V36,V59,V82,V105) -> 99275487 | W22: =SUM(W36,W59,W82,W105) -> 88366637 | X22: =SUM(X36,X59,X82,X105) -> 80532065 | Y22: =SUM(Y36,Y59,Y82,Y105) -> 78588277 | AF22: =SUM(T22:AE22) -> 5.8190458e+08
B23: Ascott BP OCC | D23: =(D37*$E$33+D60*$E$56+D83*$E$79+D106*$E$102)/SUM($E$33,$E$56,$E$79,$E$102) -> 0.83438097 | E23: =(E37*$E$33+E60*$E$56+E83*$E$79+E106*$E$102)/SUM($E$33,$E$56,$E$79,$E$102) -> 0.87066274 | F23: =(F37*$E$33 +F60*$E$56+F83*$E$79+F106*$E$102)/SUM($E$33,$E$56,$E$79,$E$102) -> 0.71845978 | G23: =(G37*$E$33 +G60*$E$56+G83*$E$79+G106*$E$102)/SUM($E$33,$E$56,$E$79,$E$102) -> 0.75059156 | H23: =(H37*$E$33 +H60*$E$56+H83*$E$79+H106*$E$102)/SUM($E$33,$E$56,$E$79,$E$102) -> 0.72668749 | I23: =(I37*$E$33 +I60*$E$56+I83*$E$79+I106*$E$102)/SUM($E$33,$E$56,$E$79,$E$102) -> 0.71387089 | J23: =(J37*$E$33 +J60*$E$56+J83*$E$79+J106*$E$102)/SUM($E$33,$E$56,$E$79,$E$102) -> 0.79627702 | K23: =(K37*$E$33 +K60*$E$56+K83*$E$79+K106*$E$102)/SUM($E$33,$E$56,$E$79,$E$102) -> 0.80044325 | L23: =(L37*$E$33 +L60*$E$56+L83*$E$79+L106*$E$102)/SUM($E$33,$E$56,$E$79,$E$102) -> 0.72295042 | M23: =(M37*$E$33 +M60*$E$56+M83*$E$79+M106*$E$102)/SUM($E$33,$E$56,$E$79,$E$102) -> 0.77718205 | ... O23: =(O37*$E$33 +O60*$E$56+O83*$E$79+O106*$E$102)/SUM($E$33,$E$56,$E$79,$E$102) -> 0.8495425 | P23: =SUMPRODUCT(D23:O23,$D$19:$O$19)/$P$19 -> 0.78366552 | R23: Ascott BP GOP | T23: =SUM(T40,T63,T86,T109) -> 78829987 | U23: =SUM(U40,U63,U86,U109) -> 71946283 | V23: =SUM(V40,V63,V86,V109) -> 54075826 | W23: =SUM(W40,W63,W86,W109) -> 56774030 | X23: =SUM(X40,X63,X86,X109) -> 49198564 | Y23: =SUM(Y40,Y63,Y86,Y109) -> 45330230 | Z23: =SUM(Z40,Z63,Z86,Z109) -> 64092156 | AA23: =SUM(AA40,AA63,AA86,AA109) -> 65576849 | ... AE23: =SUM(AE40,AE63,AE86,AE109) -> 82223512 | AF23: =SUM(T23:AE23) -> 7.5223514e+08
B24: Ascott BP ADR | D24: =(D38*$E$33*D37+$E$56*D60*D61+$E$79*D83*D84+$E$102*D106*D107)/SUM($E$33*D37,$E$56*D60,$E$79*D83,$E$102*D106) -> 3413.3662 | E24: =(E38*$E$33*E37+$E$56*E60*E61+$E$79*E83*E84+$E$102*E106*E107)/SUM($E$33*E37,$E$56*E60,$E$79*E83,$E$102*E106) -> 3382.6642 | F24: =(F38*$E$33*F37+$E$56*F60*F61+$E$79*F83*F84+$E$102*F106*F107)/SUM($E$33*F37,$E$56*F60,$E$79*F83,$E$102*F106) -> 3058.381 | G24: =(G38*$E$33*G37+$E$56*G60*G61+$E$79*G83*G84+$E$102*G106*G107)/SUM($E$33*G37,$E$56*G60,$E$79*G83,$E$102*G106) -> 3155.5803 | H24: =(H38*$E$33*H37+$E$56*H60*H61+$E$79*H83*H84+$E$102*H106*H107)/SUM($E$33*H37,$E$56*H60,$E$79*H83,$E$102*H106) -> 2873.2876 | I24: =(I38*$E$33*I37+$E$56*I60*I61+$E$79*I83*I84+$E$102*I106*I107)/SUM($E$33*I37,$E$56*I60,$E$79*I83,$E$102*I106) -> 2858.2878 | J24: =(J38*$E$33*J37+$E$56*J60*J61+$E$79*J83*J84+$E$102*J106*J107)/SUM($E$33*J37,$E$56*J60,$E$79*J83,$E$102*J106) -> 3100.3129 | K24: =(K38*$E$33*K37+$E$56*K60*K61+$E$79*K83*K84+$E$102*K106*K107)/SUM($E$33*K37,$E$56*K60,$E$79*K83,$E$102*K106) -> 3136.4953 | ... O24: =(O38*$E$33*O37+$E$56*O60*O61+$E$79*O83*O84+$E$102*O106*O107)/SUM($E$33*O37,$E$56*O60,$E$79*O83,$E$102*O106) -> 3435.8626 | P24: =SUMPRODUCT(D24:O24,$D$19:$O$19)/$P$19 -> 3147.9902 | R24: MF Projection GOP | T24: =SUM(T41,T64,T87,T110) -> 77659698 | U24: =SUM(U41,U64,U87,U110) -> 70852649 | V24: =SUM(V41,V64,V87,V110) -> 53059061 | W24: =SUM(W41,W64,W87,W110) -> 55017009 | X24: =SUM(X41,X64,X87,X110) -> 47617488 | Y24: =SUM(Y41,Y64,Y87,Y110) -> 43854493 | Z24: =SUM(Z41,Z64,Z87,Z110) -> 62331518 | AA24: =SUM(AA41,AA64,AA87,AA110) -> 63761097 | ... AE24: =SUM(AE41,AE64,AE87,AE110) -> 81065223 | AF24: =SUM(T24:AE24) -> 7.3571204e+08
B25: Ascott BP RevPar | D25: =D23*D24 -> 2848.0478 | E25: =E23*E24 -> 2945.1596 | F25: =F23*F24 -> 2197.3238 | G25: =G23*G24 -> 2368.552 | H25: =H23*H24 -> 2087.9821 | I25: =I23*I24 -> 2040.4484 | J25: =J23*J24 -> 2468.7079 | K25: =K23*K24 -> 2510.5865 | ... O25: =O23*O24 -> 2918.9112 | P25: =SUMPRODUCT(D25:O25,$D$19:$O$19)/$P$19 -> 2476.3448 | R25: GOP | T25: =SUM(T42,T65,T88,T111) -> 70392032 | U25: =SUM(U42,U65,U88,U111) -> 70154061 | V25: =SUM(V42,V65,V88,V111) -> 55119529 | W25: =SUM(W42,W65,W88,W111) -> 45624481 | X25: =SUM(X42,X65,X88,X111) -> 39377310 | Y25: =SUM(Y42,Y65,Y88,Y111) -> 37355440 | Z25: =SUM(Z42,Z65,Z88,Z111) -> 0 | AA25: =SUM(AA42,AA65,AA88,AA111) -> 0 | ... AE25: =SUM(AE42,AE65,AE88,AE111) -> 0 | AF25: =SUM(T25:AE25) -> 3.1802285e+08 | AH25: =AF42+AF65+AF88+AF111 -> 3.1802285e+08
B26: MF Projection OCC | D26: =(D41*$E$33 +D64*$E$56+D87*$E$79+D110*$E$102)/SUM($E$33,$E$56,$E$79,$E$102) -> 0.83245997 | E26: =(E41*$E$33+E64*$E$56+E87*$E$79+E110*$E$102)/SUM($E$33,$E$56,$E$79,$E$102) -> 0.86924574 | F26: =(F41*$E$33 +F64*$E$56+F87*$E$79+F110*$E$102)/SUM($E$33,$E$56,$E$79,$E$102) -> 0.71962682 | G26: =(G41*$E$33 +G64*$E$56+G87*$E$79+G110*$E$102)/SUM($E$33,$E$56,$E$79,$E$102) -> 0.74549583 | H26: =(H41*$E$33 +H64*$E$56+H87*$E$79+H110*$E$102)/SUM($E$33,$E$56,$E$79,$E$102) -> 0.72024562 | I26: =(I41*$E$33 +I64*$E$56+I87*$E$79+I110*$E$102)/SUM($E$33,$E$56,$E$79,$E$102) -> 0.70854197 | J26: =(J41*$E$33 +J64*$E$56+J87*$E$79+J110*$E$102)/SUM($E$33,$E$56,$E$79,$E$102) -> 0.78948881 | K26: =(K41*$E$33 +K64*$E$56+K87*$E$79+K110*$E$102)/SUM($E$33,$E$56,$E$79,$E$102) -> 0.79556986 | L26: =(L41*$E$33 +L64*$E$56+L87*$E$79+L110*$E$102)/SUM($E$33,$E$56,$E$79,$E$102) -> 0.71707167 | M26: =(M41*$E$33 +M64*$E$56+M87*$E$79+M110*$E$102)/SUM($E$33,$E$56,$E$79,$E$102) -> 0.77668535 | ... O26: =(O41*$E$33 +O64*$E$56+O87*$E$79+O110*$E$102)/SUM($E$33,$E$56,$E$79,$E$102) -> 0.85063067 | P26: =SUMPRODUCT(D26:O26,$D$19:$O$19)/$P$19 -> 0.78070581 | R26: Ascott BP EBIT | T26: =SUM(T46,,T69,T92,T115) -> 57537870 | U26: =SUM(U46,,U69,U92,U115) -> 51332229 | V26: =SUM(V46,,V69,V92,V115) -> 35073195 | W26: =SUM(W46,,W69,W92,W115) -> 37413950 | X26: =SUM(X46,,X69,X92,X115) -> 30716749 | Y26: =SUM(Y46,,Y69,Y92,Y115) -> 27129925 | Z26: =SUM(Z46,,Z69,Z92,Z115) -> 44385870 | AA26: =SUM(AA46,,AA69,AA92,AA115) -> 45590233 | ... AE26: =SUM(AE46,,AE69,AE92,AE115) -> 60670935 | AF26: =SUM(T26:AE26) -> 5.1508784e+08
B27: MF Projection ADR | D27: =(D42*$E$33*D41+$E$56*D64*D65+$E$79*D87*D88+$E$102*D110*D111)/SUM($E$33*D41,$E$56*D64,$E$79*D87,$E$102*D110) -> 3408.1318 | E27: =(E42*$E$33*E41+$E$56*E64*E65+$E$79*E87*E88+$E$102*E110*E111)/SUM($E$33*E41,$E$56*E64,$E$79*E87,$E$102*E110) -> 3377.196 | F27: =(F42*$E$33*F41+$E$56*F64*F65+$E$79*F87*F88+$E$102*F110*F111)/SUM($E$33*F41,$E$56*F64,$E$79*F87,$E$102*F110) -> 3056.3442 | G27: =(G42*$E$33*G41+$E$56*G64*G65+$E$79*G87*G88+$E$102*G110*G111)/SUM($E$33*G41,$E$56*G64,$E$79*G87,$E$102*G110) -> 3145.5632 | H27: =(H42*$E$33*H41+$E$56*H64*H65+$E$79*H87*H88+$E$102*H110*H111)/SUM($E$33*H41,$E$56*H64,$E$79*H87,$E$102*H110) -> 2862.1638 | I27: =(I42*$E$33*I41+$E$56*I64*I65+$E$79*I87*I88+$E$102*I110*I111)/SUM($E$33*I41,$E$56*I64,$E$79*I87,$E$102*I110) -> 2849.4452 | J27: =(J42*$E$33*J41+$E$56*J64*J65+$E$79*J87*J88+$E$102*J110*J111)/SUM($E$33*J41,$E$56*J64,$E$79*J87,$E$102*J110) -> 3089.5062 | K27: =(K42*$E$33*K41+$E$56*K64*K65+$E$79*K87*K88+$E$102*K110*K111)/SUM($E$33*K41,$E$56*K64,$E$79*K87,$E$102*K110) -> 3126.8681 | ... O27: =(O42*$E$33*O41+$E$56*O64*O65+$E$79*O87*O88+$E$102*O110*O111)/SUM($E$33*O41,$E$56*O64,$E$79*O87,$E$102*O110) -> 3433.0169 | P27: =SUMPRODUCT(D27:O27,$D$19:$O$19)/$P$19 -> 3141.2196 | R27: MF Projection EBIT | T27: =SUM(T47,T70,T93,T116) -> 44996152 | U27: =SUM(U47,U70,U93,U116) -> 38690161 | V27: =SUM(V47,V70,V93,V116) -> 22252719 | W27: =SUM(W47,W70,W93,W116) -> 24020516 | X27: =SUM(X47,,X70,X93,X116) -> 17224917 | Y27: =SUM(Y47,Y70,Y93,Y116) -> 13741714 | Z27: =SUM(Z47,,Z70,Z93,Z116) -> 30862861 | AA27: =SUM(AA47,,AA70,AA93,AA116) -> 32155929 | AB27: =SUM(AB47,,AB70,AB93,AB116) -> 16972068 | AC27: =SUM(AC47,,AC70,AC93,AC116) -> 29560676 | AD27: =SUM(AD47,,AD70,AD93,AD116) -> 39965937 | AE27: =SUM(AE47,,AE70,AE93,AE116) -> 48200653 | AF27: =SUM(T27:AE27) -> 3.586443e+08
B28: MF Projection RevPar | D28: =D26*D27 -> 2837.1333 | E28: =E26*E27 -> 2935.6132 | F28: =F26*F27 -> 2199.4272 | G28: =G26*G27 -> 2345.0042 | H28: =H26*H27 -> 2061.4609 | I28: =I26*I27 -> 2018.9515 | J28: =J26*J27 -> 2439.1306 | K28: =K26*K27 -> 2487.642 | ... O28: =O26*O27 -> 2920.2294 | P28: =SUMPRODUCT(D28:O28,$D$19:$O$19)/$P$19 -> 2462.1676 | R28: EBIT | T28: =SUM(T48,,T71,T94,T117) -> 39303688 | U28: =SUM(U48,,U71,U94,U117) -> 38665478 | V28: =SUM(V48,,V71,V94,V117) -> 25601072 | W28: =SUM(W48,W71,W94,W117) -> 17306245 | X28: =SUM(X48,X71,X94,X117) -> 10784995 | Y28: =SUM(Y48,Y71,Y94,Y117) -> 11586975 | Z28: =SUM(Z48,,Z71,Z94,Z117) -> 0 | AA28: =SUM(AA48,,AA71,AA94,AA117) -> 0 | AB28: =SUM(AB48,,AB71,AB94,AB117) -> 0 | AC28: =SUM(AC48,,AC71,AC94,AC117) -> 0 | AD28: =SUM(AD48,,AD71,AD94,AD117) -> 0 | AF28: =SUM(T28:AE28) -> 1.4324845e+08
B29: OCC | D29: =(D45*$E$33+D68*$E$56+D91*$E$79+D114*$E$102)/SUM($E$33,$E$56,$E$79,$E$102) -> 0.84680982 | E29: =(E45*$E$33+E68*$E$56+E91*$E$79+E114*$E$102)/SUM($E$33,$E$56,$E$79,$E$102) -> 0.90195666 | F29: =(F45*$E$33+F68*$E$56+F91*$E$79+F114*$E$102)/SUM($E$33,$E$56,$E$79,$E$102) -> 0.78072593 | G29: =(G45*$E$33+G68*$E$56+G91*$E$79+G114*$E$102)/SUM($E$33,$E$56,$E$79,$E$102) -> 0.67734413 | H29: =(H45*$E$33+H68*$E$56+H91*$E$79+H114*$E$102)/SUM($E$33,$E$56,$E$79,$E$102) -> 0.67288232 | I29: =(I45*$E$33+I68*$E$56+I91*$E$79+I114*$E$102)/SUM($E$33,$E$56,$E$79,$E$102) -> 0.67329406 | J29: =(J45*$E$33+J68*$E$56+J91*$E$79+J114*$E$102)/SUM($E$33,$E$56,$E$79,$E$102) -> 0 | K29: =(K45*$E$33+K68*$E$56+K91*$E$79+K114*$E$102)/SUM($E$33,$E$56,$E$79,$E$102) -> 0 | ... O29: =(O45*$E$33+O68*$E$56+O91*$E$79+O114*$E$102)/SUM($E$33,$E$56,$E$79,$E$102) -> 0 | P29: =(D29*31+E29*28+F29*31+G29*30+H29*31+I29*30+J29*31+K29*31+L29*30+M29*31+N29*30+O29*31)/365 -> 0.37558053 | R29: NPAT | T29: =SUM(T49,,T72,T95,T118) -> 11772077 | U29: =SUM(U49,,U72,U95,U118) -> 15370113 | V29: =SUM(V49,,V72,V95,V118) -> 1938903.3 | W29: =SUM(W49,W72,W95,W118) -> -3928433.6 | X29: =SUM(X49,,X72,X95,X118) -> -8451432.5 | Y29: =SUM(Y49,,Y72,Y95,Y118) -> -8768805.6 | Z29: =SUM(Z49,,Z72,Z95,Z118) -> 0 | AA29: =SUM(AA49,,AA72,AA95,AA118) -> 0 | AB29: =SUM(AB49,,AB72,AB95,AB118) -> 0 | AC29: =SUM(AC49,,AC72,AC95,AC118) -> 0 | AD29: =SUM(AD49,,AD72,AD95,AD118) -> 0 | AF29: =SUM(T29:AE29) -> 7932421.7
B30: ADR | D30: =(D48*$E$33*D45+D71*$E$56*D68+$E$79*D91*D94+$E$102*D114*D117)/SUM($E$33*D45,$E$56*D68,$E$79*D91,$E$102*D114) -> 3061.3411 | E30: =(E48*$E$33*E45+E71*$E$56*E68+$E$79*E91*E94+$E$102*E114*E117)/SUM($E$33*E45,$E$56*E68,$E$79*E91,$E$102*E114) -> 3145.9799 | F30: =(F48*$E$33*F45+F71*$E$56*F68+$E$79*F91*F94+$E$102*F114*F117)/SUM($E$33*F45,$E$56*F68,$E$79*F91,$E$102*F114) -> 2768.387 | G30: =(G48*$E$33*G45+G71*$E$56*G68+$E$79*G91*G94+$E$102*G114*G117)/SUM($E$33*G45,$E$56*G68,$E$79*G91,$E$102*G114) -> 2954.5516 | H30: =(H48*$E$33*H45+H71*$E$56*H68+$E$79*H91*H94+$E$102*H114*H117)/SUM($E$33*H45,$E$56*H68,$E$79*H91,$E$102*H114) -> 2603.8035 | I30: =(I48*$E$33*I45+I71*$E$56*I68+$E$79*I91*I94+$E$102*I114*I117)/SUM($E$33*I45,$E$56*I68,$E$79*I91,$E$102*I114) -> 2621.1105 | J30: =(J48*$E$33*J45+J71*$E$56*J68+$E$79*J91*J94+$E$102*J114*J117)/SUM($E$33*J45,$E$56*J68,$E$79*J91,$E$102*J114) -> #DIV/0! | K30: =(K48*$E$33*K45+K71*$E$56*K68+$E$79*K91*K94+$E$102*K114*K117)/SUM($E$33*K45,$E$56*K68,$E$79*K91,$E$102*K114) -> #DIV/0! | ... O30: =(O48*$E$33*O45+O71*$E$56*O68+$E$79*O91*O94+$E$102*O114*O117)/SUM($E$33*O45,$E$56*O68,$E$79*O91,$E$102*O114) -> #DIV/0! | P30: =(D30*31+E30*28+F30*31+G30*30+H30*31+I30*30+J30*31+K30*31+L30*30+M30*31+N30*30+O30*31)/365 -> #DIV/0!
B31: RevPar | D31: =D30*D29 -> 2592.3738 | E31: =E30*E29 -> 2837.5376 | F31: =F30*F29 -> 2161.3515 | G31: =G30*G29 -> 2001.2482 | H31: =H30*H29 -> 1752.0533 | I31: =I30*I29 -> 1764.7781 | J31: =J30*J29 -> #DIV/0! | K31: =K30*K29 -> #DIV/0! | ... O31: =O30*O29 -> #DIV/0! | P31: =P29*P30 -> #DIV/0!
E33: 445 | R33: kthb
B34: SR9 | D34: =$D$20 -> 2026 | P34: Avg | R34: SR9 | T34: =$T$20 -> 2026 | AF34: Total
D35: Jan | E35: Feb | F35: Mar | G35: Apr | H35: May | I35: Jun | J35: Jul | K35: Aug | L35: Sep | M35: Oct | N35: Nov | O35: Dec | T35: Jan | U35: Feb | V35: Mar | W35: Apr | X35: May | Y35: Jun | Z35: Jul | AA35: Aug | AB35: Sep | AC35: Oct | AD35: Nov | AE35: Dec
B36: Ascott BP | R36: Total Revenue | T36: 36981091 | U36: 36798669 | V36: 33026704 | W36: 31830716 | X36: 29125528 | Y36: 28515832 | AF36: =SUM(T36:AE36) -> 1.9627854e+08
B37: OCC | D37: 0.86682856 | E37: 0.89736758 | F37: 0.78208409 | G37: 0.7405618 | H37: 0.76889453 | I37: 0.75625468 | J37: 0.78172526 | K37: 0.78114534 | L37: 0.75531835 | M37: 0.82826386 | N37: 0.88472285 | O37: 0.88175788 | P37: =SUMPRODUCT(D37:O37,$D$19:$O$19)/$P$19 -> 0.80998276 | R37: Ascott BP OPEX | T37: -16102007 | U37: -15239925 | V37: -14991348 | W37: -14549704 | X37: -14823126 | Y37: -14725138 | Z37: -14489481 | AA37: -14909282 | AB37: -14592954 | AC37: -15669793 | AD37: -15866354 | AE37: -16319282 | AF37: =SUM(T37:AE37) -> -1.8227839e+08
B38: ADR | D38: 3317.7326 | E38: 3007.5041 | F38: 2910.1404 | G38: 2995.4479 | H38: 2715.1868 | I38: 2745.9736 | J38: 2818.788 | K38: 2826.5746 | L38: 2790.6075 | M38: 2866.9397 | N38: 2951.3856 | O38: 3008.2437 | P38: =SUMPRODUCT(D38:O38,$D$19:$O$19)/$P$19 -> 2912.5598 | R38: MF Projection OPEX | T38: -16395234 | U38: -15552638 | V38: -15311509 | W38: -14863558 | X38: -15140416 | Y38: -15055603 | Z38: -14831472 | AA38: -15230278 | AB38: -14920940 | AC38: -15984544 | AD38: -16174226 | AE38: -16620660 | AF38: =SUM(T38:AE38) -> -1.8608108e+08
B39: RevPar | D39: =D37*D38 -> 2875.9054 | E39: =E37*E38 -> 2698.8366 | F39: =F37*F38 -> 2275.9745 | G39: =G37*G38 -> 2218.3143 | H39: =H37*H38 -> 2087.6923 | I39: =I37*I38 -> 2076.6554 | J39: =J37*J38 -> 2203.5178 | K39: =K37*K38 -> 2207.9656 | ... O39: =O37*O38 -> 2652.5426 | P39: =SUMPRODUCT(D39:O39,$D$19:$O$19)/$P$19 -> 2364.4076 | R39: OPEX | T39: -14552035 | U39: -14296298 | V39: -14344313 | W39: -14055717 | X39: -13969285 | Y39: -13047220 | AF39: =SUM(T39:AE39) -> -84264867
B40: MF Projection | R40: Ascott BP GOP | T40: 28209612 | U40: 22596705 | V40: 20224083 | W40: 18115263 | X40: 17743371 | Y40: 16645896 | Z40: 20355990 | AA40: 19906821 | AB40: 17405107 | AC40: 21642539 | AD40: 23884688 | AE40: 25396436 | AF40: =SUM(T40:AE40) -> 2.5212651e+08
B41: OCC | D41: 0.86682856 | E41: 0.89736758 | F41: 0.78208409 | G41: 0.7405618 | H41: 0.76889453 | I41: 0.75625468 | J41: 0.78172526 | K41: 0.78114534 | L41: 0.75531835 | M41: 0.82826386 | N41: 0.88472285 | O41: 0.88175788 | P41: =SUMPRODUCT(D41:O41,$D$19:$O$19)/$P$19 -> 0.80998276 | R41: MF Projection GOP | T41: ='[275]YTD compare'!P10 -> 27916385 | U41: 22283993 | V41: 19903922 | W41: 17801409 | X41: 17426081 | Y41: 16315431 | Z41: 20014000 | AA41: 19585825 | AB41: 17077121 | AC41: 21327788 | AD41: 23576816 | AE41: 25095059 | AF41: =SUM(T41:AE41) -> 2.4832383e+08
B42: ADR | D42: 3317.7326 | E42: 3007.5041 | F42: 2910.1404 | G42: 2995.4479 | H42: 2715.1868 | I42: 2745.9736 | J42: 2818.788 | K42: 2826.5746 | L42: 2790.6075 | M42: 2866.9397 | N42: 2951.3856 | O42: 3008.2437 | P42: =SUMPRODUCT(D42:O42,$D$19:$O$19)/$P$19 -> 2912.5598 | R42: GOP | T42: =T36+T39 -> 22429057 | U42: =U36+U39 -> 22502371 | V42: =V36+V39 -> 18682391 | W42: =W36+W39 -> 17774999 | X42: =X36+X39 -> 15156242 | Y42: =Y36+Y39 -> 15468612 | AF42: =AF36+AF39 -> 1.1201367e+08
B43: RevPar | D43: =D41*D42 -> 2875.9054 | E43: =E41*E42 -> 2698.8366 | F43: =F41*F42 -> 2275.9745 | G43: =G41*G42 -> 2218.3143 | H43: =H41*H42 -> 2087.6923 | I43: =I41*I42 -> 2076.6554 | J43: =J41*J42 -> 2203.5178 | K43: =K41*K42 -> 2207.9656 | ... O43: =O41*O42 -> 2652.5426 | P43: =SUMPRODUCT(D43:O43,$D$19:$O$19)/$P$19 -> 2364.4076 | R43: Ascott BP % GOP | T43: 0.63661885 | U43: 0.5972177 | V43: 0.57429605 | W43: 0.55457772 | X43: 0.54483512 | Y43: 0.53061356 | Z43: 0.58417893 | AA43: 0.57177052 | AB43: 0.54394256 | AC43: 0.58003715 | AD43: 0.60085691 | AE43: 0.60879777 | AF43: =AVERAGE(T43:AE43) -> 0.5773119
B44: Actual Result | R44: MF Projection % GOP | T44: 0.63 | U44: 0.59 | V44: 0.57 | W44: 0.54 | X44: 0.54 | Y44: 0.52 | Z44: 0.57 | AA44: 0.56 | AB44: 0.53 | AC44: 0.57 | AD44: 0.59 | AE44: 0.6 | AF44: =AVERAGE(T44:AE44) -> 0.5675
B45: OCC | D45: 0.87024284 | E45: ='[275]LSSS FY26'!D5 -> 0.90489567 | F45: ='[275]LSSS FY26'!E5 -> 0.79956506 | G45: ='[275]LSSS FY26'!F5 -> 0.76479401 | H45: ='[275]LSSS FY26'!G5 -> 0.74969192 | I45: ='[275]LSSS FY26'!H5 -> 0.76546816 | P45: =(D45*31+E45*28+F45*31+G45*30+H45*31+I45*30+J45*31+K45*31+L45*30+M45*31+N45*30+O45*31)/365 -> 0.40068339 | R45: % GOP Margin | T45: =T42/T36 -> 0.60650067 | U45: =U42/U36 -> 0.61149958 | V45: =V42/V36 -> 0.56567532 | W45: =W42/W36 -> 0.55842285 | X45: =X42/X36 -> 0.52037658 | Y45: =Y42/Y36 -> 0.54245698 | Z45: =Z42/Z36 -> #DIV/0! | AA45: =AA42/AA36 -> #DIV/0! | ... AF45: =AF42/AF36 -> 0.57068731
C46: LS | D46: ='[275]LSSS FY26'!C25 -> 0.1731062 | E46: ='[275]LSSS FY26'!D25 -> 0.10457464 | F46: ='[275]LSSS FY26'!E25 -> 0.095904313 | G46: ='[275]LSSS FY26'!F25 -> 0.10764045 | H46: ='[275]LSSS FY26'!G25 -> 0.1403407 | I46: ='[275]LSSS FY26'!H25 -> 0.16539326 | P46: =(D46*31+E46*28+F46*31+G46*30+H46*31+I45*30+J46*31+K46*31+L46*30+M46*31+N46*30+O46*31)/365 -> 0.11455133 | R46: Ascott BP EBIT | T46: 20104566 | U46: 15060403 | V46: 12865717 | W46: 10920042 | X46: 10747221 | Y46: 9720662 | Z46: 12999399 | AA46: 12573353 | AB46: 10435334 | AC46: 14165807 | AD46: 16120753 | AE46: 17504880 | AF46: =SUM(T46:AE46) -> 1.6321814e+08
C47: SS | D47: ='[275]LSSS FY26'!C26 -> 0.70395071 | E47: ='[275]LSSS FY26'!D26 -> 0.80032103 | F47: ='[275]LSSS FY26'!E26 -> 0.70366075 | G47: ='[275]LSSS FY26'!F26 -> 0.65715356 | H47: ='[275]LSSS FY26'!G26 -> 0.60935121 | I47: ='[275]LSSS FY26'!H26 -> 0.60007491 | P47: =(D47*31+E47*28+F47*31+G47*30+H47*31+I47*30+J47*31+K47*31+L47*30+M47*31+N47*30+O47*31)/365 -> 0.33603201 | R47: MF Projection EBIT | T47: 17046778 | U47: 11829988 | V47: 9614700.7 | W47: 7651465.5 | X47: 7314690.2 | Y47: 6284360.9 | Z47: 9776792 | AA47: 9360385.5 | AB47: 7007812.2 | AC47: 10958098 | AD47: 13072050 | AE47: 14470548 | AF47: =SUM(T47:AE47) -> 1.2438767e+08
B48: ADR | D48: 2779.1543 | E48: ='[275]LSSS FY26'!D6 -> 2966.1889 | F48: ='[275]LSSS FY26'!E6 -> 2700.893 | G48: ='[275]LSSS FY26'!F6 -> 2820.6903 | H48: ='[275]LSSS FY26'!G6 -> 2519.2705 | I48: ='[275]LSSS FY26'!H6 -> 2491.0682 | P48: =(D48*31+E48*28+F48*31+G48*30+H48*31+I48*30+J48*31+K48*31+L48*30+M48*31+N48*30+O48*31)/365 -> 1343.5203 | R48: EBIT | T48: 12467117 | U48: 12218882 | V48: 8778766.1 | W48: 8009317.5 | X48: 5620949.1 | Y48: 5908210.7 | AF48: =SUM(T48:AE48) -> 53003242 | AG48: << excl. interest revenue
C49: LS | D49: 2098.0189 | E49: 2071.3547 | G49: 2014.7591 | H49: 2008.3815 | I49: 2008.3815 | P49: =(D49*31+E49*28+F49*31+G49*30+H49*31+I49*30+J49*31+K49*31+L49*30+M49*31+N49*30+O49*31)/365 -> 838.3303 | R49: NPAT | T49: 1535418.8 | U49: 2091933.7 | V49: -1301086.9 | W49: -1672053.1 | X49: -3791097.2 | Y49: -3241503.1 | AF49: =SUM(T49:AE49) -> -6378387.8
C50: SS | D50: 2884.7362 | E50: 3083.1131 | G50: 2952.7002 | H50: 2636.9342 | I50: 2636.9342 | P50: =(D50*31+E50*28+F50*31+G50*30+H50*31+I50*30+J50*31+K50*31+L50*30+M50*31+N50*30+O50*31)/365 -> 1164.8986
B51: RevPar | D51: =D48*D45 -> 2418.5391 | E51: =E48*E45 -> 2684.0914 | F51: =F48*F45 -> 2159.5397 | G51: =G48*G45 -> 2157.247 | H51: =H48*H45 -> 1888.6767 | I51: =I48*I45 -> 1906.8334 | P51: =P45*P48 -> 538.32626 | R51: 2025 | S51: Revenue | T51: ='[275]result FY25'!T36 -> 40471407 | U51: ='[275]result FY25'!U36 -> 35097386 | V51: ='[275]result FY25'!V36 -> 31885906 | W51: ='[275]result FY25'!W36 -> 28944482 | X51: ='[275]result FY25'!X36 -> 29907879 | AF51: =SUM(T51:AE51) -> 1.6630706e+08
C52: LS | D52: =D46*D49 -> 363.18008 | E52: =E46*E49 -> 216.61117 | F52: =F46*F49 -> 0 | G52: =G46*G49 -> 216.86958 | H52: =H46*H49 -> 281.85767 | I52: =I46*I49 -> 332.17275 | P52: =P46*P49 -> 96.031852 | T52: =T36/T51-1 -> -0.08624152 | U52: =U36/U51-1 -> 0.048473213 | V52: =V36/V51-1 -> 0.03577748 | W52: =W36/W51-1 -> 0.099716208 | X52: =X36/X51-1 -> -0.026158719 | AF52: =AF36/AF51-1 -> 0.18021772
C53: SS | D53: =D47*D50 -> 2030.7121 | E53: =E47*E50 -> 2467.4803 | F53: =F47*F50 -> 0 | G53: =G47*G50 -> 1940.3774 | H53: =H47*H50 -> 1606.8191 | I53: =I47*I50 -> 1582.3581 | P53: =P47*P50 -> 391.44322 | S53: GOP | T53: ='[275]result FY25'!T42 -> 24241888 | U53: ='[275]result FY25'!U42 -> 20170272 | V53: ='[275]result FY25'!V42 -> 18090458 | W53: ='[275]result FY25'!W42 -> 16113520 | X53: ='[275]result FY25'!X42 -> 16903865 | AF53: =SUM(T53:AE53) -> 95520003
C54: compset dif | D54: =D51/[275]Compset!B101 -> 1.0854715 | E54: =E51/[275]Compset!C101 -> 1.1660263 | F54: =F51/[275]Compset!D101 -> 1.0778691 | G54: =G51/[275]Compset!E101 -> 1.1424054 | H54: =H51/[275]Compset!F101 -> 1.015357 | I54: =I51/[275]Compset!G101 -> 1.1586829 | J54: =J51/[275]Compset!H101 -> #DIV/0! | K54: =K51/[275]Compset!I101 -> #DIV/0! | ... O54: =O51/[275]Compset!M101 -> #DIV/0! | T54: =T42/T53-1 -> -0.074780958 | U54: =U42/U53-1 -> 0.11562058 | V54: =V42/V53-1 -> 0.03272072 | W54: =W42/W53-1 -> 0.10311089 | X54: =X42/X53-1 -> -0.10338596 | AF54: =AF42/AF53-1 -> 0.17267241
B55: ADR BF | D55: ='[276]Pick Up Pace_SR9'!$AI$49 -> 2969.9605 | E55: ='[276]Pick Up Pace_SR9'!$AF$50 -> 3139.3684 | F55: ='[276]Pick Up Pace_SR9'!$AI$51 -> 2856.2136 | G55: ='[276]Pick Up Pace_SR9'!$AH$52 -> 2965.1404 | H55: ='[276]Pick Up Pace_SR9'!$AI$53 -> 2706.696 | I55: =(25457894.27+1791102.04)/I56 -> 2671.7322 | P55: =(D55*31+E55*28+F55*31+G55*30+H55*31+I55*30+J55*31+K55*31+L55*30+M55*31+N55*30+O55*31)/365 -> 1428.8424
E56: 393 | I56: =10260-21-40 -> 10199
B57: AES | D57: =$D$20 -> 2026 | P57: Avg | R57: AES | T57: =$T$20 -> 2026 | AF57: Total
D58: Jan | E58: Feb | F58: Mar | G58: Apr | H58: May | I58: Jun | J58: Jul | K58: Aug | L58: Sep | M58: Oct | N58: Nov | O58: Dec | T58: Jan | U58: Feb | V58: Mar | W58: Apr | X58: May | Y58: Jun | Z58: Jul | AA58: Aug | AB58: Sep | AC58: Oct | AD58: Nov | AE58: Dec
B59: Ascott BP | R59: Total Revenue | T59: 35431726 | U59: 38907552 | V59: 30984316 | W59: 26245239 | X59: 23379075 | Y59: 24286103 | AF59: =SUM(T59:AE59) -> 1.7923401e+08
B60: OCC | D60: 0.77 | E60: 0.81 | F60: 0.65 | G60: 0.7 | H60: 0.69 | I60: 0.69 | J60: 0.83 | K60: 0.84 | L60: 0.71 | M60: 0.73 | N60: 0.82 | O60: 0.81 | P60: =SUMPRODUCT(D60:O60,$D$19:$O$19)/$P$19 -> 0.7539726 | R60: Ascott BP OPEX | T60: -16899769 | U60: -16439844 | V60: -15555594 | W60: -15955151 | X60: -16104512 | Y60: -15895821 | Z60: -17782792 | AA60: -17865198 | AB60: -16069331 | AC60: -16575079 | AD60: -17366340 | AE60: -17553672 | AF60: =SUM(T60:AE60) -> -2.000631e+08
B61: ADR | D61: 3857.0946 | E61: 3903.4948 | F61: 3536.0115 | G61: 3726.9314 | H61: 3356.8241 | I61: 3441 | J61: 3686.6351 | K61: 3751.6056 | L61: 3531.9724 | M61: 3680.5822 | N61: 3887.8818 | O61: 3924.8842 | P61: =SUMPRODUCT(D61:O61,$D$19:$O$19)/$P$19 -> 3689.1348 | R61: MF Projection OPEX | T61: -17286424 | U61: -16839998 | V61: -15955749 | W61: -16356188 | X61: -16505549 | Y61: -16296858 | Z61: -18183828 | AA61: -18266235 | AB61: -16470367 | AC61: -16976116 | AD61: -17767377 | AE61: -17954708 | AF61: =SUM(T61:AE61) -> -2.048594e+08
B62: RevPar | D62: =D60*D61 -> 2969.9629 | E62: =E60*E61 -> 3161.8308 | F62: =F60*F61 -> 2298.4075 | G62: =G60*G61 -> 2608.852 | H62: =H60*H61 -> 2316.2086 | I62: =I60*I61 -> 2374.29 | J62: =J60*J61 -> 3059.9071 | K62: =K60*K61 -> 3151.3487 | ... O62: =O60*O61 -> 3179.1562 | P62: =SUMPRODUCT(D62:O62,$D$19:$O$19)/$P$19 -> 2790.1773 | R62: OPEX | T62: -15339359 | U62: -15397642 | V62: -13864449 | W62: -13116715 | X62: -12592589 | Y62: -13325554 | AF62: =SUM(T62:AE62) -> -83636307
B63: MF Projection | R63: Ascott BP GOP | T63: 22379947 | U63: 21400220 | V63: 15365336 | W63: 17719654 | X63: 15068864 | Y63: 15232832 | Z63: 23048572 | AA63: 24046050 | AB63: 16447304 | AC63: 19166150 | AD63: 23645681 | AE63: 24788995 | AF63: =SUM(T63:AE63) -> 2.3830961e+08
B64: OCC | D64: 0.76614955 | E64: 0.80870593 | F64: 0.6500041 | G64: 0.7 | H64: 0.68874661 | I64: 0.69007634 | J64: 0.83000903 | K64: 0.84002298 | L64: 0.71000848 | M64: 0.72601166 | N64: 0.82001696 | O64: 0.8100632 | P64: =SUMPRODUCT(D64:O64,$D$19:$O$19)/$P$19 -> 0.75311792 | R64: MF Projection GOP | T64: 21993292 | U64: 21000065 | V64: 14965182 | W64: 17318618 | X64: 14667827 | Y64: 14831796 | Z64: 22647535 | AA64: 23645013 | AB64: 16046267 | AC64: 18765113 | AD64: 23244645 | AE64: 24387959 | AF64: =SUM(T64:AE64) -> 2.3351331e+08
B65: ADR | D65: 3857.0946 | E65: 3903.4948 | F65: 3536.0115 | G65: 3726.9314 | H65: 3356.8241 | I65: 3441 | J65: 3686.6351 | K65: 3751.6056 | L65: 3531.9724 | M65: 3680.5822 | N65: 3887.8818 | O65: 3924.8842 | P65: =SUMPRODUCT(D65:O65,$D$19:$O$19)/$P$19 -> 3689.1348 | R65: GOP | T65: =T59+T62 -> 20092368 | U65: =U59+U62 -> 23509910 | V65: =V59+V62 -> 17119867 | W65: =W59+W62 -> 13128524 | X65: =X59+X62 -> 10786486 | Y65: =Y59+Y62 -> 10960549 | AF65: =SUM(T65:AE65) -> 95597704
B66: RevPar | D66: =D64*D65 -> 2955.1113 | E66: =E64*E65 -> 3156.7794 | F66: =F64*F65 -> 2298.422 | G66: =G64*G65 -> 2608.852 | H66: =H64*H65 -> 2312.0012 | I66: =I64*I65 -> 2374.5527 | J66: =J64*J65 -> 3059.9404 | K66: =K64*K65 -> 3151.435 | ... O66: =O64*O65 -> 3179.4043 | P66: =SUMPRODUCT(D66:O66,$D$19:$O$19)/$P$19 -> 2786.9863 | R66: Ascott BP % GOP | T66: 0.56975837 | U66: 0.56554397 | V66: 0.49692348 | W66: 0.52619916 | X66: 0.48338891 | Y66: 0.48935083 | Z66: 0.56448205 | AA66: 0.57373738 | AB66: 0.505812 | AC66: 0.53624764 | AD66: 0.57655489 | AE66: 0.58543774 | AF66: =AVERAGE(T66:AE66) -> 0.53945303
B67: Actual Result | R67: MF Projection % GOP | T67: 0.56 | U67: 0.56 | V67: 0.49 | W67: 0.52 | X67: 0.47 | Y67: 0.48 | Z67: 0.56 | AA67: 0.57 | AB67: 0.5 | AC67: 0.53 | AD67: 0.57 | AE67: 0.58 | AF67: =AVERAGE(T67:AE67) -> 0.5325
B68: OCC | D68: 0.75285234 | E68: ='[275]LSSS FY26'!D9 -> 0.92366412 | F68: ='[275]LSSS FY26'!E9 -> 0.74538291 | G68: ='[275]LSSS FY26'!F9 -> 0.64020356 | H68: ='[275]LSSS FY26'!G9 -> 0.58163014 | I68: ='[275]LSSS FY26'!H9 -> 0.59864292 | P68: =(D68*31+E68*28+F68*31+G68*30+H68*31+I68*30+J68*31+K68*31+L68*30+M68*31+N68*30+O68*31)/365 -> 0.34932553 | R68: % GOP Margin | T68: =T65/T59 -> 0.56707278 | U68: =U65/U59 -> 0.60425056 | V68: =V65/V59 -> 0.55253333 | W68: =W65/W59 -> 0.50022498 | X68: =X65/X59 -> 0.46137351 | Y68: =Y65/Y59 -> 0.45130951 | AF68: =AF65/AF59 -> 0.5333681
C69: LS | D69: ='[275]LSSS FY26'!C30 -> 0.19601083 | E69: ='[275]LSSS FY26'!D30 -> 0.22082879 | F69: ='[275]LSSS FY26'!E30 -> 0.20151089 | G69: ='[275]LSSS FY26'!F30 -> 0.14274809 | H69: ='[275]LSSS FY26'!G30 -> 0.1703193 | I69: ='[275]LSSS FY26'!H30 -> 0.15640373 | P69: =(D69*31+E69*28+F69*31+G69*30+H69*31+I69*30+J69*31+K69*31+L69*30+M69*31+N69*30+O69*31)/365 -> 0.089755705 | R69: Ascott BP EBIT | T69: 13203341 | U69: 12295195 | V69: 6657387.3 | W69: 8854688.2 | X69: 6366211.8 | Y69: 6524627.6 | Z69: 13809426 | AA69: 14742708 | AB69: 7659290.6 | AC69: 10196829 | AD69: 14378587 | AE69: 15446229 | AF69: =SUM(T69:AE69) -> 1.3013452e+08
C70: SS | D70: ='[275]LSSS FY26'!C31 -> 0.55799064 | E70: ='[275]LSSS FY26'!D31 -> 0.70283533 | F70: ='[275]LSSS FY26'!E31 -> 0.54387203 | G70: ='[275]LSSS FY26'!F31 -> 0.49745547 | H70: ='[275]LSSS FY26'!G31 -> 0.41131084 | I70: ='[275]LSSS FY26'!H31 -> 0.44223919 | P70: =(D70*31+E70*28+F70*31+G70*30+H70*31+I70*30+J70*31+K70*31+L70*30+M70*31+N70*30+O70*31)/365 -> 0.25966742 | R70: MF Projection EBIT | T70: 10033841 | U70: 9113903.7 | V70: 3541197.4 | W70: 5710432.2 | X70: 3263497.6 | Y70: 3423265.4 | Z70: 10630223 | AA70: 11548476 | AB70: 4530011.2 | AC70: 7039563.1 | AD70: 11191056 | AE70: 12252772 | AF70: =SUM(T70:AE70) -> 92278238
B71: ADR | D71: 3594.5582 | E71: ='[275]LSSS FY26'!D10 -> 3565.9648 | F71: ='[275]LSSS FY26'!E10 -> 3139.8449 | G71: ='[275]LSSS FY26'!F10 -> 3273.2802 | H71: ='[275]LSSS FY26'!G10 -> 3066.0889 | I71: ='[275]LSSS FY26'!H10 -> 3198.9923 | P71: =(D71*31+E71*28+F71*31+G71*30+H71*31+I71*30+J71*31+K71*31+L71*30+M71*31+N71*30+O71*31)/365 -> 1637.8916 | R71: EBIT | T71: 9260675.5 | U71: 11130612 | V71: 6621672.5 | W71: 2921229.6 | X71: 221666.09 | Y71: 3359223.7 | AF71: =SUM(T71:AE71) -> 33515079
C72: LS | D72: 2449.5834 | E72: 2540.2146 | G72: 2553.7654 | H72: 2445.7517 | I72: 2628.8273 | P72: =(D72*31+E72*28+F72*31+G72*30+H72*31+I72*30+J72*31+K72*31+L72*30+M72*31+N72*30+O72*31)/365 -> 1036.6005 | R72: NPAT | T72: 1110168.3 | U72: 5407584.6 | V72: 329697.63 | W72: -2419790.4 | X72: -4755075.3 | Y72: -1956091.8 | AF72: =SUM(T72:AE72) -> -2283507
C73: SS | D73: 3974.9541 | E73: 3888.2525 | G73: 3479.7496 | H73: 3322.9638 | I73: 3400.6387 | P73: =(D73*31+E73*28+F73*31+G73*30+H73*31+I73*30+J73*31+K73*31+L73*30+M73*31+N73*30+O73*31)/365 -> 1483.6114
B74: RevPar | D74: =D71*D68 -> 2706.1715 | E74: =E71*E68 -> 3293.7538 | F74: =F71*F68 -> 2340.3867 | G74: =G71*G68 -> 2095.5656 | H74: =H71*H68 -> 1783.3297 | I74: =I71*I68 -> 1915.0541 | P74: =P68*P71 -> 572.15735 | R74: 2025 | S74: Revenue | T74: ='[275]result FY25'!T80 -> 42691295 | U74: ='[275]result FY25'!U80 -> 34251573 | V74: ='[275]result FY25'!V80 -> 25843470 | W74: ='[275]result FY25'!W80 -> 29043751 | X74: ='[275]result FY25'!X80 -> 27716957 | AF74: =SUM(T74:AE74) -> 1.5954705e+08
C75: LS | D75: =D69*D72 -> 480.14488 | E75: =E69*E72 -> 560.95252 | F75: =F69*F72 -> 0 | G75: =G69*G72 -> 364.54514 | H75: =H69*H72 -> 416.55871 | I75: =I69*I72 -> 411.15841 | P75: =P69*P72 -> 93.040808 | T75: =T59/T74-1 -> -0.17004798 | U75: =U59/U74-1 -> 0.13593475 | V75: =V59/V74-1 -> 0.19892241 | W75: =W59/W74-1 -> -0.09635506 | X75: =X59/X74-1 -> -0.15650643 | AF75: =AF59/AF74-1 -> 0.12339285
C76: SS | D76: =D70*D73 -> 2217.9872 | E76: =E70*E73 -> 2732.8012 | F76: =F70*F73 -> 0 | G76: =G70*G73 -> 1731.0205 | H76: =H70*H73 -> 1366.771 | I76: =I70*I73 -> 1503.8957 | P76: =P70*P73 -> 385.24555 | S76: GOP | T76: ='[275]result FY25'!T86 -> 25382957 | U76: ='[275]result FY25'!U86 -> 18945296 | V76: ='[275]result FY25'!V86 -> 12671300 | W76: ='[275]result FY25'!W86 -> 14031513 | X76: ='[275]result FY25'!X86 -> 13081294 | AF76: =SUM(T76:AE76) -> 84112360
C77: compset dif | D77: =D74/[275]Compset!B167 -> 0.99409859 | E77: =E74/[275]Compset!C155 -> 0.89430301 | F77: =F74/[275]Compset!D167 -> 1.0404213 | G77: =G74/[275]Compset!E167 -> 1.0779001 | H77: =H74/[275]Compset!F167 -> 1.0835924 | I77: =I74/[275]Compset!G167 -> 1.2850034 | J77: =J74/[275]Compset!H167 -> #DIV/0! | K77: =K74/[275]Compset!I167 -> #DIV/0! | L77: =L74/[275]Compset!J167 -> #DIV/0! | M77: =M74/[275]Compset!K167 -> #DIV/0! | ... O77: =O74/[275]Compset!M167 -> #DIV/0! | T77: =T65/T76-1 -> -0.20843077 | U77: =U65/U76-1 -> 0.24093654 | V77: =V65/V76-1 -> 0.35107423 | W77: =W65/W76-1 -> -0.064354338 | X77: =X65/X76-1 -> -0.17542671 | AF77: =AF65/AF76-1 -> 0.13654763
B78: =B55 -> ADR BF | D78: ='[276]Pick Up Pace_RB'!$AI$49 -> 3781.0576 | E78: ='[276]Pick Up Pace_RB'!$AF$50 -> 3755.0035 | F78: ='[276]Pick Up Pace_RB'!$AI$51 -> 3282.8766 | G78: ='[276]Pick Up Pace_RB'!$AH$52 -> 3407.7299 | H78: ='[276]Pick Up Pace_RB'!$AI$53 -> 3200.3146 | I78: =(22533209.23+936298.17)/I79 -> 3330.898 | P78: =(D78*31+E78*28+F78*31+G78*30+H78*31+I78*30+J78*31+K78*31+L78*30+M78*31+N78*30+O78*31)/365 -> 1713.673
E79: 196 | I79: =7111-18-47 -> 7046
B80: Lyf | D80: =$D$20 -> 2026 | P80: Avg | R80: Lyf | T80: =$T$20 -> 2026 | AF80: Total
D81: Jan | E81: Feb | F81: Mar | G81: Apr | H81: May | I81: Jun | J81: Jul | K81: Aug | L81: Sep | M81: Oct | N81: Nov | O81: Dec | T81: Jan | U81: Feb | V81: Mar | W81: Apr | X81: May | Y81: Jun | Z81: Jul | AA81: Aug | AB81: Sep | AC81: Oct | AD81: Nov | AE81: Dec
B82: Ascott BP | R82: Total Revenue | T82: 9283927.7 | U82: 8589919.7 | V82: 7238468.9 | W82: 4493751.3 | X82: 5625446.3 | Y82: 4727539.1 | AF82: =SUM(T82:AE82) -> 39959053
B83: OCC | D83: 0.8805135 | E83: 0.93276239 | F83: 0.77485188 | G83: 0.82619048 | H83: 0.78159974 | I83: 0.77108844 | J83: 0.80513496 | K83: 0.83179724 | L83: 0.74642857 | M83: 0.75115207 | N83: 0.88469388 | O83: 0.87146149 | P83: =SUMPRODUCT(D83:O83,$D$19:$O$19)/$P$19 -> 0.82071568 | R83: Ascott BP OPEX | T83: -4036430.3 | U83: -3974883.4 | V83: -3804439.2 | W83: -3922299.4 | X83: -3876063.1 | Y83: -3790993.8 | Z83: -3950350.2 | AA83: -4002836.2 | AB83: -3736767.7 | AC83: -3822027.5 | AD83: -4076593.9 | AE83: -4085675.1 | AF83: =SUM(T83:AE83) -> -47079360
B84: ADR | D84: 1760.0154 | E84: 1774.2702 | F84: 1445.7773 | G84: 1415.3661 | H84: 1330.2948 | I84: 1284.1787 | J84: 1435.9459 | K84: 1495.0452 | L84: 1371.1964 | M84: 1430.6654 | N84: 1813.8997 | O84: 1890.7825 | P84: =SUMPRODUCT(D84:O84,$D$19:$O$19)/$P$19 -> 1536.0633 | R84: MF Projection OPEX | T84: -3986763.7 | U84: -3836360 | V84: -3665271.9 | W84: -3811065.3 | X84: -3726894 | Y84: -3608841.3 | Z84: -3829446.1 | AA84: -3862666.4 | AB84: -3634136.8 | AC84: -3661214.1 | AD84: -3976261 | AE84: -3938878.3 | AF84: =SUM(T84:AE84) -> -45537799
B85: RevPar | D85: =D83*D84 -> 1549.7173 | E85: =E83*E84 -> 1654.9725 | F85: =F83*F84 -> 1120.2633 | G85: =G83*G84 -> 1169.362 | H85: =H83*H84 -> 1039.7581 | I85: =I83*I84 -> 990.21531 | J85: =J83*J84 -> 1156.1302 | K85: =K83*K84 -> 1243.5745 | ... O85: =O83*O84 -> 1647.7441 | P85: =SUMPRODUCT(D85:O85,$D$19:$O$19)/$P$19 -> 1270.5776 | R85: OPEX | T85: -4351370.5 | U85: -4017939.2 | V85: -3759122.7 | W85: -3002633 | X85: -3377435.2 | Y85: -3116495.1 | AF85: =SUM(T85:AE85) -> -21624996
B86: MF Projection | R86: Ascott BP GOP | T86: 5631034 | U86: 5349441.6 | V86: 3227131.6 | W86: 3184599.1 | X86: 2666470.7 | Y86: 2288520.9 | Z86: 3306752 | AA86: 3792272 | AB86: 2491499.9 | AC86: 2924847.9 | AD86: 5604578.4 | AE86: 6216097.1 | AF86: =SUM(T86:AE86) -> 46683245
B87: OCC | D87: 0.8805135 | E87: 0.93276239 | F87: 0.77485188 | G87: 0.82619048 | H87: 0.78159974 | I87: 0.77108844 | J87: 0.80513496 | K87: 0.83179724 | L87: 0.74642857 | M87: 0.75115207 | N87: 0.88469388 | O87: 0.87146149 | P87: =SUMPRODUCT(D87:O87,$D$19:$O$19)/$P$19 -> 0.82071568 | R87: MF Projection GOP | T87: 5284779.7 | U87: 5085407.5 | V87: 2998858.8 | W87: 2994408.5 | X87: 2484596 | Y87: 2119478.2 | Z87: 3133183.2 | AA87: 3565538.2 | AB87: 2323464.5 | AC87: 2761968.5 | AD87: 5270857.5 | AE87: 5908317.5 | AF87: =SUM(T87:AE87) -> 43930858
B88: ADR | D88: 1734.0053 | E88: 1748.0495 | F88: 1424.4111 | G88: 1394.4494 | H88: 1310.6353 | I88: 1265.2006 | J88: 1414.725 | K88: 1472.951 | L88: 1350.9324 | M88: 1409.5225 | N88: 1787.0933 | O88: 1862.8399 | P88: =SUMPRODUCT(D88:O88,$D$19:$O$19)/$P$19 -> 1513.3629 | R88: GOP | T88: =T82+T85 -> 4932557.3 | U88: =U82+U85 -> 4571980.5 | V88: =V82+V85 -> 3479346.2 | W88: =W82+W85 -> 1491118.3 | X88: =X82+X85 -> 2248011.1 | Y88: =Y82+Y85 -> 1611044 | Z88: =Z82+Z85 -> 0 | AA88: =AA82+AA85 -> 0 | ... AD88: =AD82+AD85 -> 0 | AF88: =SUM(T88:AE88) -> 18334057
B89: RevPar | D89: =D87*D88 -> 1526.8151 | E89: =E87*E88 -> 1630.5148 | F89: =F87*F88 -> 1103.7076 | G89: =G87*G88 -> 1152.0808 | H89: =H87*H88 -> 1024.3922 | I89: =I87*I88 -> 975.58158 | J89: =J87*J88 -> 1139.0445 | K89: =K87*K88 -> 1225.1965 | ... O89: =O87*O88 -> 1623.3932 | P89: =SUMPRODUCT(D89:O89,$D$19:$O$19)/$P$19 -> 1251.8006 | R89: Ascott BP % GOP | T89: 0.58 | U89: 0.57 | V89: 0.45 | W89: 0.44 | X89: 0.4 | Y89: 0.37 | Z89: 0.45 | AA89: 0.48 | AB89: 0.4 | AC89: 0.43 | AD89: 0.57 | AE89: 0.6 | AF89: =AVERAGE(T89:AE89) -> 0.47833333
B90: Actual Result | R90: MF Projection % GOP | T90: 0.57205397 | U90: 0.51360655 | V90: 0.53263319 | W90: 0.43785799 | X90: 0.41348948 | Y90: 0.39659269 | Z90: 0.46132688 | AA90: 0.46132688 | AB90: 0.46132688 | AC90: 0.46132688 | AD90: 0.46132688 | AE90: 0.46132688 | AF90: =AVERAGE(T90:AE90) -> 0.46951626
B91: OCC | D91: 0.92593812 | E91: ='[275]LSSS FY26'!D13 -> 0.94606414 | F91: ='[275]LSSS FY26'!E13 -> 0.87820935 | G91: ='[275]LSSS FY26'!F13 -> 0.5042517 | H91: ='[275]LSSS FY26'!G13 -> 0.73963134 | I91: ='[275]LSSS FY26'!H13 -> 0.6952381 | P91: =(D91*31+E91*28+F91*31+G91*30+H91*31+I91*30+J91*31+K91*31+L91*30+M91*31+N91*30+O91*31)/365 -> 0.38720995 | R91: % GOP Margin | T91: =T88/T82 -> 0.5313007 | U91: =U88/U82 -> 0.5322495 | V91: =V88/V82 -> 0.48067433 | W91: =W88/W82 -> 0.33182039 | X91: =X88/X82 -> 0.39961472 | Y91: =Y88/Y82 -> 0.34077857 | Z91: =Z88/Z82 -> #DIV/0! | AA91: =AA88/AA82 -> #DIV/0! | ... AD91: =AD88/AD82 -> #DIV/0! | AF91: =AF88/AF82 -> 0.45882112
C92: LS | D92: ='[275]LSSS FY26'!C35 -> 0.0051020408 | E92: ='[275]LSSS FY26'!D35 -> 0.0053929122 | F92: ='[275]LSSS FY26'!E35 -> 0.0051020408 | G92: ='[275]LSSS FY26'!F35 -> 0.0051020408 | H92: ='[275]LSSS FY26'!G35 -> 0.0051020408 | I92: ='[275]LSSS FY26'!H35 -> 0.0051020408 | J92: ='[275]LSSS FY26'!I35 -> 0 | K92: ='[275]LSSS FY26'!J35 -> 0 | L92: ='[275]LSSS FY26'!K35 -> 0 | P92: =(D92*31+E92*28+F92*31+G92*30+H92*31+I92*30+J92*31+K92*31+L92*30+M92*31+N92*30+O92*31)/365 -> 0.0025523665 | R92: Ascott BP EBIT | T92: 3971003.5 | U92: 3712675.9 | V92: 1763969.1 | W92: 1721612.9 | X92: 1239472.2 | Y92: 888969.56 | Z92: 1834894.5 | AA92: 2286466.2 | AB92: 1079533.9 | AC92: 1481711 | AD92: 3947043 | AE92: 4514068 | AF92: =SUM(T92:AE92) -> 28441420
C93: SS | D93: ='[275]LSSS FY26'!C36 -> 0.92297564 | E93: ='[275]LSSS FY26'!D36 -> 0.94067123 | F93: ='[275]LSSS FY26'!E36 -> 0.87310731 | G93: ='[275]LSSS FY26'!F36 -> 0.49914966 | H93: ='[275]LSSS FY26'!G36 -> 0.7345293 | I93: ='[275]LSSS FY26'!H36 -> 0.69013605 | J93: ='[275]LSSS FY26'!I36 -> 0 | K93: ='[275]LSSS FY26'!J36 -> 0 | L93: ='[275]LSSS FY26'!K36 -> 0 | P93: =(D93*31+E93*28+F93*31+G93*30+H93*31+I93*30+J93*31+K93*31+L93*30+M93*31+N93*30+O93*31)/365 -> 0.3848393 | R93: MF Projection EBIT | T93: 2815036 | U93: 2634244 | V93: 710581.51 | W93: 703190.03 | X93: 234129.3 | Y93: -100502.99 | Z93: 830973.8 | AA93: 1229627.3 | AB93: 87366.311 | AC93: 491838.32 | AD93: 2802411.3 | AE93: 3392125.1 | AF93: =SUM(T93:AE93) -> 15831020
B94: ADR | D94: 1578.1099 | E94: ='[275]LSSS FY26'!D14 -> 1585.5922 | F94: ='[275]LSSS FY26'!E14 -> 1289.0616 | G94: ='[275]LSSS FY26'!F14 -> 1449.7044 | H94: ='[275]LSSS FY26'!G14 -> 1188.3935 | I94: ='[275]LSSS FY26'!H14 -> 1086.8126 | P94: =(D94*31+E94*28+F94*31+G94*30+H94*31+I94*30+J94*31+K94*31+L94*30+M94*31+N94*30+O94*31)/365 -> 674.56057 | R94: EBIT | T94: 2558241.1 | U94: 2277395.2 | V94: 1323699.9 | W94: -533525.45 | X94: 91462.91 | Y94: -1171425.4 | AF94: =SUM(T94:AE94) -> 4545848.3
C95: LS | D95: 934.57935 | E95: 934.57964 | G95: 934.57833 | H95: 958.69581 | I95: 940.812 | P95: =(D95*31+E95*28+F95*31+G95*30+H95*31+I95*30+J95*31+K95*31+L95*30+M95*31+N95*30+O95*31)/365 -> 386.63416 | R95: NPAT | T95: -129000.32 | U95: -153979.94 | V95: -1360983 | W95: -2698657.2 | X95: -976667.71 | Y95: -3736400.1 | AF95: =SUM(T95:AE95) -> -9055688.2
C96: SS | D96: 1584.297 | E96: 1589.1221 | G96: 1454.9698 | H96: 1189.9889 | I96: 1087.892 | P96: =(D96*31+E96*28+F96*31+G96*30+H96*31+I96*30+J96*31+K96*31+L96*30+M96*31+N96*30+O96*31)/365 -> 566.53188
B97: RevPar | D97: =D94*D91 -> 1461.2321 | E97: =E94*E91 -> 1500.0719 | F97: =F94*F91 -> 1132.066 | G97: =G94*G91 -> 731.01592 | H97: =H94*H91 -> 878.97304 | I97: =I94*I91 -> 755.59355 | P97: =P91*P94 -> 261.19657 | R97: 2025 | S97: Revenue | T97: ='[275]result FY25'!T102 -> 10057547 | U97: ='[275]result FY25'!U102 -> 8360412.3 | V97: ='[275]result FY25'!V102 -> 6748527.7 | W97: ='[275]result FY25'!W102 -> 6301518.4 | X97: ='[275]result FY25'!X102 -> 5674281.4 | AF97: =SUM(T97:AE97) -> 37142287
C98: LS | D98: =D92*D95 -> 4.768262 | E98: =E92*E95 -> 5.0401059 | F98: =F92*F95 -> 0 | G98: =G92*G95 -> 4.7682568 | H98: =H92*H95 -> 4.8913051 | I98: =I92*I95 -> 4.8000612 | J98: =J92*J95 -> 0 | K98: =K92*K95 -> 0 | L98: =L92*L95 -> 0 | P98: =P92*P95 -> 0.9868321 | T98: =T82/T97-1 -> -0.076919287 | U98: =U82/U97-1 -> 0.027451678 | V98: =V82/V97-1 -> 0.072599715 | W98: =W82/W97-1 -> -0.28687802 | X98: =X82/X97-1 -> -0.0086063867 | AF98: =AF82/AF97-1 -> 0.075837174
C99: SS | D99: =D93*D96 -> 1462.2676 | E99: =E93*E96 -> 1494.8414 | F99: =F93*F96 -> 0 | G99: =G93*G96 -> 726.24766 | H99: =H93*H96 -> 874.08173 | I99: =I93*I96 -> 750.79348 | J99: =J93*J96 -> 0 | K99: =K93*K96 -> 0 | L99: =L93*L96 -> 0 | P99: =P93*P96 -> 218.02373 | S99: GOP | T99: ='[275]result FY25'!T108 -> 5753459.7 | U99: ='[275]result FY25'!U108 -> 4293962.6 | V99: ='[275]result FY25'!V108 -> 3594489.8 | W99: ='[275]result FY25'!W108 -> 2759170.2 | X99: ='[275]result FY25'!X108 -> 2346255.6 | AF99: =SUM(T99:AE99) -> 18747338
C100: compset dif | D100: =D97/[275]Compset!B277 -> 0.77753621 | E100: =E97/[275]Compset!C277 -> 0.80613509 | F100: =F97/[275]Compset!D277 -> 0.77022177 | G100: =G97/[275]Compset!E277 -> 0.60817379 | H100: =H97/[275]Compset!F277 -> 0.92185837 | I100: =I97/[275]Compset!G277 -> 0.78772337 | J100: =J97/[275]Compset!H277 -> #DIV/0! | K100: =K97/[275]Compset!I277 -> #DIV/0! | ... O100: =O97/[275]Compset!M277 -> #DIV/0! | T100: =T88/T99-1 -> -0.14267979 | U100: =U88/U99-1 -> 0.064746235 | V100: =V88/V99-1 -> -0.032033366 | W100: =W88/W99-1 -> -0.45957726 | X100: =X88/X99-1 -> -0.041872888 | AF100: =AF88/AF99-1 -> -0.022044755
E102: 324
B103: SP | D103: =$D$20 -> 2026 | P103: Avg | R103: SP | T103: =$T$20 -> 2026 | AF103: Total
D104: Jan | E104: Feb | F104: Mar | G104: Apr | H104: May | I104: Jun | J104: Jul | K104: Aug | L104: Sep | M104: Oct | N104: Nov | O104: Dec | T104: Jan | U104: Feb | V104: Mar | W104: Apr | X104: May | Y104: Jun | Z104: Jul | AA104: Aug | AB104: Sep | AC104: Oct | AD104: Nov | AE104: Dec
B105: Ascott BP | R105: Total Revenue | T105: 36745343 | U105: 32403886 | V105: 28025999 | W105: 25796931 | X105: 22402015 | Y105: 21058803 | AF105: =SUM(T105:AE105) -> 1.6643298e+08
B106: OCC | D106: 0.84 | E106: 0.87 | F106: 0.68 | G106: 0.78 | H106: 0.68 | I106: 0.65 | J106: 0.77 | K106: 0.76 | L106: 0.68 | M106: 0.78 | N106: 0.81 | O106: 0.84 | P106: =SUMPRODUCT(D106:O106,$D$19:$O$19)/$P$19 -> 0.76112329 | R106: Ascott BP OPEX | T106: -14814448 | U106: -14380098 | V106: -13565474 | W106: -14042863 | X106: -13130384 | Y106: -12622487 | Z106: -14249649 | AA106: -14086664 | AB106: -13229680 | AC106: -14533029 | AD106: -14393883 | AE106: -14798446 | AF106: =SUM(T106:AE106) -> -1.678471e+08
B107: ADR | D107: 4103.95 | E107: 4369.13 | F107: 3850.36 | G107: 3857.51 | H107: 3596.56 | I107: 3417.09 | J107: 3779.04 | K107: 3836.14 | L107: 3587.62 | M107: 3825.63 | N107: 4030.4 | O107: 4450.08 | P107: =SUMPRODUCT(D107:O107,$D$19:$O$19)/$P$19 -> 3889.8871 | R107: MF Projection OPEX | T107: -14958602 | U107: -14496831 | V107: -13633649 | W107: -13896149 | X107: -12981321 | Y107: -12466099 | Z107: -14105713 | AA107: -13953613 | AB107: -13065718 | AC107: -14650211 | AD107: -14512610 | AE107: -14946538 | AF107: =SUM(T107:AE107) -> -1.6766705e+08
...

Sheet Summary-arrival
E2: COVID-19 | J2: Earthquake
C3: 2018 | D3: 2019 | E3: 2020 | F3: 2021 | G3: 2022 | H3: 2023 | I3: 2024 | J3: 2025 | K3: 2026
B4: Foreign Arrival* | C4: 38277300 | D4: 39916251 | E4: 6702396 | F4: 427869 | G4: 11153026 | H4: 28099323 | I4: 35545714 | J4: 32974321
B5: Incl. land
B7: MOTS | C7: Jan | D7: Feb | E7: Mar | F7: Apr | G7: May | H7: Jun | I7: H1
B8: 2018 | C8: 3544528 | D8: 3566898 | E8: 3497260 | F8: 3092725 | G8: 2755059 | H8: 3025279
B9: =B8+1 -> 2019 | C9: 3713172 | D9: 3600922 | E9: 3478687 | F9: 3216929 | G9: 2736598 | H9: 3056697
B10: =B9+1 -> 2020 | C10: 3810155 | D10: 2061990 | E10: 819429 | F10: 0 | G10: 0 | H10: 0
B11: =B10+1 -> 2021 | C11: 7694 | D11: 5741 | E11: 6737 | F11: 8529 | G11: 6052 | H11: 5694
B12: =B11+1 -> 2022 | C12: 133903 | D12: 152954 | E12: 210836 | F12: 293350 | G12: 521410 | H12: 767497
B13: =B12+1 -> 2023 | C13: 2144948 | D13: 2113550 | E13: 2219040 | F13: 2182100 | G13: 2013852 | H13: 2241201
B14: =B13+1 -> 2024 | C14: 3035296 | D14: 3352302 | E14: 2982721 | F14: 2757128 | G14: 2633464 | H14: 2740372 | I14: =SUM(C14:H14) -> 17501283
B15: =B14+1 -> 2025 | C15: 3709102 | D15: 3119445 | E15: 2720457 | F15: 2547116 | G15: 2266574 | H15: 2322775 | I15: =SUM(C15:H15) -> 16685469
B16: =B15+1 -> 2026 | C16: 3277908 | D16: 3263802 | E16: 2775199 | F16: 2368895 | G16: 2346845 | H16: 1841551 | I16: =SUM(C16:H16) -> 15874200
C17: =(C16-C15)/C15 -> -0.11625294 | D17: =(D16-D15)/D15 -> 0.046276501 | E17: =(E16-E15)/E15 -> 0.020122354 | F17: =(F16-F15)/F15 -> -0.069969723 | G17: =(G16-G15)/G15 -> 0.035415124 | H17: =(H16-H15)/H15 -> -0.20717633 | I17: =(I16-I15)/I15 -> -0.048621288
B18: https://www.mots.go.th/more_news_new.php?cid=411 | H18: ***Data lost 4 days
B20: Number of Chinese Tourists
C21: Jan | D21: Feb | E21: Mar | F21: Apr | G21: May | H21: Jun | I21: H1 (Jan-Jun)
B22: 2019 | C22: 1069787 | D22: 1064806 | E22: 985232 | F22: 898994 | G22: 794913 | H22: 894105
B23: 2024 | C23: =Arrival!C101 -> 508563 | D23: =Arrival!D101 -> 674558 | E23: =Arrival!E101 -> 573216 | F23: =Arrival!F101 -> 595572 | G23: =Arrival!G101 -> 559461 | H23: =Arrival!H101 -> 528112 | I23: =SUM(C23:H23) -> 3439482
B24: 2025 | C24: 662779 | D24: 371542 | E24: 297113 | F24: 317213 | G24: 310292 | H24: 306617 | I24: =SUM(C24:H24) -> 2265556
B25: 2026 | C25: 400321 | D25: 677768 | E25: 410624 | F25: 418291 | G25: 411308 | H25: 283297 | I25: =SUM(C25:H25) -> 2601609
B26: 25 vs 26 % | C26: =(C25-C24)/C24 -> -0.39599625 | D26: =(D25-D24)/D24 -> 0.82420292 | E26: =(E25-E24)/E24 -> 0.38204656 | F26: =(F25-F24)/F24 -> 0.31864394 | G26: =(G25-G24)/G24 -> 0.32555142 | H26: =(H25-H24)/H24 -> -0.076055796 | I26: =(I25-I24)/I24 -> 0.14833136
E27: >> Seems Chinese coming back when compare to last year | H27: ***Data lost 4 days
B29: Number of India | H29: Month of indian season | K29: Number of Middle East
C30: Jan | D30: Feb | E30: Mar | F30: Apr | G30: May | H30: Jun | I30: H1 (Jan-Jun) | L30: Jan | M30: Feb | N30: Mar | O30: Apr | P30: May | Q30: Jun | R30: H1 (Jan-Jun)
B31: 2024 | C31: 162831 | D31: 148992 | E31: 161129 | F31: 170635 | G31: 198993 | H31: 197489 | I31: =SUM(C31:H31) -> 1040069 | K31: 2024 | L31: 44223 | M31: 35346 | N31: 8455 | O31: 45071 | P31: 44106 | Q31: 97083 | R31: =SUM(L31:Q31) -> 274284
B33: 2025 | C33: 185809 | D33: 169988 | E33: 187973 | F33: 206286 | G33: 228544 | H33: 205299 | I33: =SUM(C33:H33) -> 1183899 | K33: 2025 | L33: 49839 | M33: 32831 | N33: 18708 | O33: 50561 | P33: 48650 | Q33: 82462 | R33: =SUM(L33:Q33) -> 283051
B34: 2026 | C34: 231184 | D34: 185930 | E34: 208484 | F34: 206641 | G34: 224490 | H34: 163378 | I34: =SUM(C34:H34) -> 1220107 | K34: 2026 | L34: 52261 | M34: 15814 | N34: 12201 | O34: 21707 | P34: 47726 | Q34: 52702 | R34: =SUM(L34:Q34) -> 202411
B35: 25 vs 26 % | C35: =(C34-C33)/C33 -> 0.24420238 | D35: =(D34-D33)/D33 -> 0.093783091 | E35: =(E34-E33)/E33 -> 0.10911673 | F35: =(F34-F33)/F33 -> 0.0017209117 | G35: =(G34-G33)/G33 -> -0.017738379 | H35: =H34/H33 -> 0.79580514 | I35: =(I34-I33)/I33 -> 0.03058369 | K35: 25 vs 26 % | L35: =(L34-L33)/L33 -> 0.048596481 | M35: =(M34-M33)/M33 -> -0.5183211 | N35: =(N34-N33)/N33 -> -0.34781911 | O35: =(O34-O33)/O33 -> -0.570677 | P35: =(P34-P33)/P33 -> -0.018992806 | Q35: =(Q34-Q33)/Q33 -> -0.3608935 | R35: =(R34-R33)/R33 -> -0.28489565
G36: >> mid month Cancel free visa 60 Days | H36: ***Data lost 4 days | M36: >> War effected | Q36: >> ME come but not reach to LY
Q37: ***Data lost 4 days
B38: Number of Long hual USA
C39: Jan | D39: Feb | E39: Mar | F39: Apr | G39: May | H39: Jun | I39: H1 (Jan-Jun)
B40: 2019 | I40: =SUM(C40:H40) -> 0
B41: 2024 | C41: 146288 | D41: 138484 | E41: 135962 | F41: 108172 | G41: 97076 | H41: 107002 | I41: =SUM(C41:H41) -> 732984
B42: 2025 | C42: 177614 | D42: 155136 | E42: 151520 | F42: 119491 | G42: 98871 | H42: 106358 | I42: =SUM(C42:H42) -> 808990
B43: 2026 | C43: 181692 | D43: 154938 | E43: 148421 | F43: 117349 | G43: 102389 | H43: 90980 | I43: =SUM(C43:H43) -> 795769
B44: 25 vs 26 % | C44: =(C43-C42)/C42 -> 0.022959902 | D44: =(D43-D42)/D42 -> -0.0012762995 | E44: =(E43-E42)/E42 -> -0.020452746 | F44: =(F43-F42)/F42 -> -0.017926036 | G44: =(G43-G42)/G42 -> 0.035581718 | H44: =(H43-H42)/H42 -> -0.14458715 | I44: =(I43-I42)/I42 -> -0.0163426
H45: ***Data lost 4 days
B46: Number of Long hual EU
C47: Jan | D47: Feb | E47: Mar | F47: Apr | G47: May | H47: Jun | I47: H1 (Jan-Jun)
B48: 2019 | I48: =SUM(C48:H48) -> 0
B49: 2024 | C49: 879741 | D49: 849024 | E49: 765683 | F49: 523160 | G49: 343907 | H49: 325497 | I49: =SUM(C49:H49) -> 3687012
B50: 2025 | C50: 1080094 | D50: 1001220 | E50: 854963 | F50: 652062 | G50: 366631 | H50: 345417 | I50: =SUM(C50:H50) -> 4300387
B51: 2026 | C51: 1184479 | D51: 1047216 | E51: 819016 | F51: 549123 | G51: 365345 | H51: 289156 | I51: =SUM(C51:H51) -> 4254335
B52: 25 vs 26 % | C52: =(C51-C50)/C50 -> 0.096644366 | D52: =(D51-D50)/D50 -> 0.045939953 | E52: =(E51-E50)/E50 -> -0.042045094 | F52: =(F51-F50)/F50 -> -0.15786689 | G52: =(G51-G50)/G50 -> -0.0035076139 | H52: =(H51-H50)/H50 -> -0.16287849 | I52: =(I51-I50)/I50 -> -0.010708804
H53: ***Data lost 4 days
B54: Number of Long hual (EU+USA)
C55: Jan | D55: Feb | E55: Mar | F55: Apr | G55: May | H55: Jun | I55: H1 (Jan-Jun)
B56: 2024 | C56: =C49+C41 -> 1026029 | D56: =D49+D41 -> 987508 | E56: =E49+E41 -> 901645 | F56: =F49+F41 -> 631332 | G56: =G49+G41 -> 440983 | H56: =H49+H41 -> 432499 | I56: =SUM(C56:H56) -> 4419996
B57: 2025 | C57: =C50+C42 -> 1257708 | D57: =D50+D42 -> 1156356 | E57: =E50+E42 -> 1006483 | F57: =F50+F42 -> 771553 | G57: =G50+G42 -> 465502 | H57: =H50+H42 -> 451775 | I57: =SUM(C57:H57) -> 5109377
B58: 2026 | C58: =C51+C43 -> 1366171 | D58: =D51+D43 -> 1202154 | E58: =E51+E43 -> 967437 | F58: =F51+F43 -> 666472 | G58: =G51+G43 -> 467734 | H58: =H51+H43 -> 380136 | I58: =SUM(C58:H58) -> 5050104
B59: 25 vs 26 % | C59: =(C58-C57)/C57 -> 0.086238618 | D59: =(D58-D57)/D57 -> 0.03960545 | E59: =(E58-E57)/E57 -> -0.038794495 | F59: =(F58-F57)/F57 -> -0.13619414 | G59: =(G58-G57)/G57 -> 0.0047948237 | H59: =(H58-H57)/H57 -> -0.1585723 | I59: =(I58-I57)/I57 -> -0.011600827
H60: ***Data lost 4 days
C63: YTD total tourist numbers are 2% lower than last year.
C64: YTD Chinese tourist numbers are 18% higher than last year, with the improvement clear from the start of the year.
C65: YTD India: although arrivals began to drop in May after the free-visa scheme started, the year-to-date total is still higher than last year, with growth of 8%.
C66: YTD long-haul remains at a similar level to last year.
C67: YTD Middle East is affected by the war, with H1 numbers 25% lower than last year. In May the gap narrowed to a 2% decline (versus a normal year-over-year change of 30–60%).
B72: SR9
I74: SR9 | K74: 2026 | L74: 2025 | M74: 2026 | N74: 2025 | O74: 2026 | P74: 2025 | Q74: 2026 | R74: 2025 | S74: 2026 | T74: 2025 | U74: 2026 | V74: 2025 | W74: 2026 | X74: 2025
I75: Top 10 Nationality | K75: Jan | M75: Feb | O75: Mar | Q75: Apr | S75: May | U75: Jun | W75: YTD | Y75: Chg
I76: 1 | J76: ='SR9'!$AF38 -> China | K76: =INDEX('SR9'!AG$38:AG$47,MATCH($J76,'SR9'!$AF$38:$AF$47,0)) -> 5852 | L76: =INDEX('SR9'!AG$85:AG$94,MATCH($J76,'SR9'!$AF$85:$AF$94,0)) -> 5997 | M76: =INDEX('SR9'!AH$38:AH$47,MATCH($J76,'SR9'!$AF$38:$AF$47,0)) -> 5730 | N76: =INDEX('SR9'!AH$85:AH$94,MATCH($J76,'SR9'!$AF$85:$AF$94,0)) -> 4841 | O76: =INDEX('SR9'!AI$38:AI$47,MATCH($J76,'SR9'!$AF$38:$AF$47,0)) -> 5609 | P76: =INDEX('SR9'!AI$85:AI$94,MATCH($J76,'SR9'!$AF$85:$AF$94,0)) -> 4995 | Q76: =INDEX('SR9'!AJ$38:AJ$47,MATCH($J76,'SR9'!$AF$38:$AF$47,0)) -> 5440 | R76: =INDEX('SR9'!AJ$85:AJ$94,MATCH($J76,'SR9'!$AF$85:$AF$94,0)) -> 4774 | S76: =INDEX('SR9'!AK$38:AK$47,MATCH($J76,'SR9'!$AF$38:$AF$47,0)) -> 5045 | T76: =INDEX('SR9'!AK$85:AK$94,MATCH($J76,'SR9'!$AF$85:$AF$94,0)) -> 5137 | U76: =INDEX('SR9'!AL$38:AL$47,MATCH($J76,'SR9'!$AF$38:$AF$47,0)) -> 4727 | V76: =INDEX('SR9'!AL$85:AL$94,MATCH($J76,'SR9'!$AF$85:$AF$94,0)) -> 4867 | W76: =SUM(K76,M76,O76,Q76,S76,U76) -> 32403 | X76: =SUM(L76,N76,P76,R76,T76,V76) -> 30611 | Y76: =(W76-X76)/X76 -> 0.058541047
I77: 2 | J77: ='SR9'!$AF39 -> Taiwan | K77: =INDEX('SR9'!AG$38:AG$47,MATCH($J77,'SR9'!$AF$38:$AF$47,0)) -> 1397 | L77: =INDEX('SR9'!AG$85:AG$94,MATCH($J77,'SR9'!$AF$85:$AF$94,0)) -> 1519 | M77: =INDEX('SR9'!AH$38:AH$47,MATCH($J77,'SR9'!$AF$38:$AF$47,0)) -> 1121 | N77: =INDEX('SR9'!AH$85:AH$94,MATCH($J77,'SR9'!$AF$85:$AF$94,0)) -> 1274 | O77: =INDEX('SR9'!AI$38:AI$47,MATCH($J77,'SR9'!$AF$38:$AF$47,0)) -> 835 | P77: =INDEX('SR9'!AI$85:AI$94,MATCH($J77,'SR9'!$AF$85:$AF$94,0)) -> 1247 | Q77: =INDEX('SR9'!AJ$38:AJ$47,MATCH($J77,'SR9'!$AF$38:$AF$47,0)) -> 764 | R77: =INDEX('SR9'!AJ$85:AJ$94,MATCH($J77,'SR9'!$AF$85:$AF$94,0)) -> 749 | S77: =INDEX('SR9'!AK$38:AK$47,MATCH($J77,'SR9'!$AF$38:$AF$47,0)) -> 879 | T77: =INDEX('SR9'!AK$85:AK$94,MATCH($J77,'SR9'!$AF$85:$AF$94,0)) -> 992 | U77: =INDEX('SR9'!AL$38:AL$47,MATCH($J77,'SR9'!$AF$38:$AF$47,0)) -> 886 | V77: =INDEX('SR9'!AL$85:AL$94,MATCH($J77,'SR9'!$AF$85:$AF$94,0)) -> 755 | W77: =SUM(K77,M77,O77,Q77,S77,U77) -> 5882 | X77: =SUM(L77,N77,P77,R77,T77,V77) -> 6536 | Y77: =(W77-X77)/X77 -> -0.1000612
I78: 3 | J78: ='SR9'!$AF40 -> Thailand | K78: =INDEX('SR9'!AG$38:AG$47,MATCH($J78,'SR9'!$AF$38:$AF$47,0)) -> 645 | L78: =INDEX('SR9'!AG$85:AG$94,MATCH($J78,'SR9'!$AF$85:$AF$94,0)) -> 419 | M78: =INDEX('SR9'!AH$38:AH$47,MATCH($J78,'SR9'!$AF$38:$AF$47,0)) -> 556 | N78: =INDEX('SR9'!AH$85:AH$94,MATCH($J78,'SR9'!$AF$85:$AF$94,0)) -> 421 | O78: =INDEX('SR9'!AI$38:AI$47,MATCH($J78,'SR9'!$AF$38:$AF$47,0)) -> 707 | P78: =INDEX('SR9'!AI$85:AI$94,MATCH($J78,'SR9'!$AF$85:$AF$94,0)) -> 512 | Q78: =INDEX('SR9'!AJ$38:AJ$47,MATCH($J78,'SR9'!$AF$38:$AF$47,0)) -> 686 | R78: =INDEX('SR9'!AJ$85:AJ$94,MATCH($J78,'SR9'!$AF$85:$AF$94,0)) -> 513 | S78: =INDEX('SR9'!AK$38:AK$47,MATCH($J78,'SR9'!$AF$38:$AF$47,0)) -> 644 | T78: =INDEX('SR9'!AK$85:AK$94,MATCH($J78,'SR9'!$AF$85:$AF$94,0)) -> 589 | U78: =INDEX('SR9'!AL$38:AL$47,MATCH($J78,'SR9'!$AF$38:$AF$47,0)) -> 568 | V78: =INDEX('SR9'!AL$85:AL$94,MATCH($J78,'SR9'!$AF$85:$AF$94,0)) -> 590 | W78: =SUM(K78,M78,O78,Q78,S78,U78) -> 3806 | X78: =SUM(L78,N78,P78,R78,T78,V78) -> 3044 | Y78: =(W78-X78)/X78 -> 0.25032852
I79: 4 | J79: ='SR9'!$AF41 -> India | K79: =INDEX('SR9'!AG$38:AG$47,MATCH($J79,'SR9'!$AF$38:$AF$47,0)) -> 294 | L79: =INDEX('SR9'!AG$85:AG$94,MATCH($J79,'SR9'!$AF$85:$AF$94,0)) -> 139 | M79: =INDEX('SR9'!AH$38:AH$47,MATCH($J79,'SR9'!$AF$38:$AF$47,0)) -> 356 | N79: =INDEX('SR9'!AH$85:AH$94,MATCH($J79,'SR9'!$AF$85:$AF$94,0)) -> 344 | O79: =INDEX('SR9'!AI$38:AI$47,MATCH($J79,'SR9'!$AF$38:$AF$47,0)) -> 393 | P79: =INDEX('SR9'!AI$85:AI$94,MATCH($J79,'SR9'!$AF$85:$AF$94,0)) -> 282 | Q79: =INDEX('SR9'!AJ$38:AJ$47,MATCH($J79,'SR9'!$AF$38:$AF$47,0)) -> 451 | R79: =INDEX('SR9'!AJ$85:AJ$94,MATCH($J79,'SR9'!$AF$85:$AF$94,0)) -> 151 | S79: =INDEX('SR9'!AK$38:AK$47,MATCH($J79,'SR9'!$AF$38:$AF$47,0)) -> 754 | T79: =INDEX('SR9'!AK$85:AK$94,MATCH($J79,'SR9'!$AF$85:$AF$94,0)) -> 235 | U79: =INDEX('SR9'!AL$38:AL$47,MATCH($J79,'SR9'!$AF$38:$AF$47,0)) -> 426 | V79: =INDEX('SR9'!AL$85:AL$94,MATCH($J79,'SR9'!$AF$85:$AF$94,0)) -> 304 | W79: =SUM(K79,M79,O79,Q79,S79,U79) -> 2674 | X79: =SUM(L79,N79,P79,R79,T79,V79) -> 1455 | Y79: =(W79-X79)/X79 -> 0.83780069
I80: 5 | J80: ='SR9'!$AF42 -> Japan | K80: =INDEX('SR9'!AG$38:AG$47,MATCH($J80,'SR9'!$AF$38:$AF$47,0)) -> 427 | L80: =INDEX('SR9'!AG$85:AG$94,MATCH($J80,'SR9'!$AF$85:$AF$94,0)) -> 382 | M80: =INDEX('SR9'!AH$38:AH$47,MATCH($J80,'SR9'!$AF$38:$AF$47,0)) -> 408 | N80: =INDEX('SR9'!AH$85:AH$94,MATCH($J80,'SR9'!$AF$85:$AF$94,0)) -> 357 | O80: =INDEX('SR9'!AI$38:AI$47,MATCH($J80,'SR9'!$AF$38:$AF$47,0)) -> 366 | P80: =INDEX('SR9'!AI$85:AI$94,MATCH($J80,'SR9'!$AF$85:$AF$94,0)) -> 437 | Q80: =INDEX('SR9'!AJ$38:AJ$47,MATCH($J80,'SR9'!$AF$38:$AF$47,0)) -> 489 | R80: =INDEX('SR9'!AJ$85:AJ$94,MATCH($J80,'SR9'!$AF$85:$AF$94,0)) -> 387 | S80: =INDEX('SR9'!AK$38:AK$47,MATCH($J80,'SR9'!$AF$38:$AF$47,0)) -> 485 | T80: =INDEX('SR9'!AK$85:AK$94,MATCH($J80,'SR9'!$AF$85:$AF$94,0)) -> 728 | U80: =INDEX('SR9'!AL$38:AL$47,MATCH($J80,'SR9'!$AF$38:$AF$47,0)) -> 460 | V80: =INDEX('SR9'!AL$85:AL$94,MATCH($J80,'SR9'!$AF$85:$AF$94,0)) -> 388 | W80: =SUM(K80,M80,O80,Q80,S80,U80) -> 2635 | X80: =SUM(L80,N80,P80,R80,T80,V80) -> 2679 | Y80: =(W80-X80)/X80 -> -0.016424039
I81: 6 | J81: ='SR9'!$AF43 -> Malaysia | K81: =INDEX('SR9'!AG$38:AG$47,MATCH($J81,'SR9'!$AF$38:$AF$47,0)) -> 428 | L81: =INDEX('SR9'!AG$85:AG$94,MATCH($J81,'SR9'!$AF$85:$AF$94,0)) -> 385 | M81: =INDEX('SR9'!AH$38:AH$47,MATCH($J81,'SR9'!$AF$38:$AF$47,0)) -> 342 | N81: =INDEX('SR9'!AH$85:AH$94,MATCH($J81,'SR9'!$AF$85:$AF$94,0)) -> 405 | O81: =INDEX('SR9'!AI$38:AI$47,MATCH($J81,'SR9'!$AF$38:$AF$47,0)) -> 367 | P81: =INDEX('SR9'!AI$85:AI$94,MATCH($J81,'SR9'!$AF$85:$AF$94,0)) -> 492 | Q81: =INDEX('SR9'!AJ$38:AJ$47,MATCH($J81,'SR9'!$AF$38:$AF$47,0)) -> 307 | R81: =INDEX('SR9'!AJ$85:AJ$94,MATCH($J81,'SR9'!$AF$85:$AF$94,0)) -> 309 | S81: =INDEX('SR9'!AK$38:AK$47,MATCH($J81,'SR9'!$AF$38:$AF$47,0)) -> 405 | T81: =INDEX('SR9'!AK$85:AK$94,MATCH($J81,'SR9'!$AF$85:$AF$94,0)) -> 459 | U81: =INDEX('SR9'!AL$38:AL$47,MATCH($J81,'SR9'!$AF$38:$AF$47,0)) -> 398 | V81: =INDEX('SR9'!AL$85:AL$94,MATCH($J81,'SR9'!$AF$85:$AF$94,0)) -> 436 | W81: =SUM(K81,M81,O81,Q81,S81,U81) -> 2247 | X81: =SUM(L81,N81,P81,R81,T81,V81) -> 2486 | Y81: =(W81-X81)/X81 -> -0.096138375
I82: 7 | J82: ='SR9'!$AF44 -> Singapore | K82: =INDEX('SR9'!AG$38:AG$47,MATCH($J82,'SR9'!$AF$38:$AF$47,0)) -> 510 | L82: =INDEX('SR9'!AG$85:AG$94,MATCH($J82,'SR9'!$AF$85:$AF$94,0)) -> 347 | M82: =INDEX('SR9'!AH$38:AH$47,MATCH($J82,'SR9'!$AF$38:$AF$47,0)) -> 289 | N82: =INDEX('SR9'!AH$85:AH$94,MATCH($J82,'SR9'!$AF$85:$AF$94,0)) -> 286 | O82: =INDEX('SR9'!AI$38:AI$47,MATCH($J82,'SR9'!$AF$38:$AF$47,0)) -> 364 | P82: =INDEX('SR9'!AI$85:AI$94,MATCH($J82,'SR9'!$AF$85:$AF$94,0)) -> 366 | Q82: =INDEX('SR9'!AJ$38:AJ$47,MATCH($J82,'SR9'!$AF$38:$AF$47,0)) -> 302 | R82: =INDEX('SR9'!AJ$85:AJ$94,MATCH($J82,'SR9'!$AF$85:$AF$94,0)) -> 367 | S82: =INDEX('SR9'!AK$38:AK$47,MATCH($J82,'SR9'!$AF$38:$AF$47,0)) -> 266 | T82: =INDEX('SR9'!AK$85:AK$94,MATCH($J82,'SR9'!$AF$85:$AF$94,0)) -> 259 | U82: =INDEX('SR9'!AL$38:AL$47,MATCH($J82,'SR9'!$AF$38:$AF$47,0)) -> 438 | V82: =INDEX('SR9'!AL$85:AL$94,MATCH($J82,'SR9'!$AF$85:$AF$94,0)) -> 392 | W82: =SUM(K82,M82,O82,Q82,S82,U82) -> 2169 | X82: =SUM(L82,N82,P82,R82,T82,V82) -> 2017 | Y82: =(W82-X82)/X82 -> 0.075359445
I83: 8 | J83: ='SR9'!$AF45 -> Korea | K83: =INDEX('SR9'!AG$38:AG$47,MATCH($J83,'SR9'!$AF$38:$AF$47,0)) -> 583 | L83: =INDEX('SR9'!AG$85:AG$94,MATCH($J83,'SR9'!$AF$85:$AF$94,0)) -> 838 | M83: =INDEX('SR9'!AH$38:AH$47,MATCH($J83,'SR9'!$AF$38:$AF$47,0)) -> 481 | N83: =INDEX('SR9'!AH$85:AH$94,MATCH($J83,'SR9'!$AF$85:$AF$94,0)) -> 915 | O83: =INDEX('SR9'!AI$38:AI$47,MATCH($J83,'SR9'!$AF$38:$AF$47,0)) -> 297 | P83: =INDEX('SR9'!AI$85:AI$94,MATCH($J83,'SR9'!$AF$85:$AF$94,0)) -> 357 | Q83: =INDEX('SR9'!AJ$38:AJ$47,MATCH($J83,'SR9'!$AF$38:$AF$47,0)) -> 174 | R83: =INDEX('SR9'!AJ$85:AJ$94,MATCH($J83,'SR9'!$AF$85:$AF$94,0)) -> 176 | S83: =INDEX('SR9'!AK$38:AK$47,MATCH($J83,'SR9'!$AF$38:$AF$47,0)) -> 305 | T83: =INDEX('SR9'!AK$85:AK$94,MATCH($J83,'SR9'!$AF$85:$AF$94,0)) -> 205 | U83: =INDEX('SR9'!AL$38:AL$47,MATCH($J83,'SR9'!$AF$38:$AF$47,0)) -> 266 | V83: =INDEX('SR9'!AL$85:AL$94,MATCH($J83,'SR9'!$AF$85:$AF$94,0)) -> 372 | W83: =SUM(K83,M83,O83,Q83,S83,U83) -> 2106 | X83: =SUM(L83,N83,P83,R83,T83,V83) -> 2863 | Y83: =(W83-X83)/X83 -> -0.26440796
I84: 9 | J84: ='SR9'!$AF46 -> Indonesia | K84: =INDEX('SR9'!AG$38:AG$47,MATCH($J84,'SR9'!$AF$38:$AF$47,0)) -> 206 | L84: =INDEX('SR9'!AG$85:AG$94,MATCH($J84,'SR9'!$AF$85:$AF$94,0)) -> 176 | M84: =INDEX('SR9'!AH$38:AH$47,MATCH($J84,'SR9'!$AF$38:$AF$47,0)) -> 226 | N84: =INDEX('SR9'!AH$85:AH$94,MATCH($J84,'SR9'!$AF$85:$AF$94,0)) -> 252 | O84: =INDEX('SR9'!AI$38:AI$47,MATCH($J84,'SR9'!$AF$38:$AF$47,0)) -> 223 | P84: =INDEX('SR9'!AI$85:AI$94,MATCH($J84,'SR9'!$AF$85:$AF$94,0)) -> 176 | Q84: =INDEX('SR9'!AJ$38:AJ$47,MATCH($J84,'SR9'!$AF$38:$AF$47,0)) -> 155 | R84: =INDEX('SR9'!AJ$85:AJ$94,MATCH($J84,'SR9'!$AF$85:$AF$94,0)) -> 90 | S84: =INDEX('SR9'!AK$38:AK$47,MATCH($J84,'SR9'!$AF$38:$AF$47,0)) -> 153 | T84: =INDEX('SR9'!AK$85:AK$94,MATCH($J84,'SR9'!$AF$85:$AF$94,0)) -> 212 | U84: =INDEX('SR9'!AL$38:AL$47,MATCH($J84,'SR9'!$AF$38:$AF$47,0)) -> 310 | V84: =INDEX('SR9'!AL$85:AL$94,MATCH($J84,'SR9'!$AF$85:$AF$94,0)) -> 214 | W84: =SUM(K84,M84,O84,Q84,S84,U84) -> 1273 | X84: =SUM(L84,N84,P84,R84,T84,V84) -> 1120 | Y84: =(W84-X84)/X84 -> 0.13660714
I85: 10 | J85: ='SR9'!$AF47 -> USA | K85: =INDEX('SR9'!AG$38:AG$47,MATCH($J85,'SR9'!$AF$38:$AF$47,0)) -> 242 | L85: =INDEX('SR9'!AG$85:AG$94,MATCH($J85,'SR9'!$AF$85:$AF$94,0)) -> 241 | M85: =INDEX('SR9'!AH$38:AH$47,MATCH($J85,'SR9'!$AF$38:$AF$47,0)) -> 187 | N85: =INDEX('SR9'!AH$85:AH$94,MATCH($J85,'SR9'!$AF$85:$AF$94,0)) -> 224 | O85: =INDEX('SR9'!AI$38:AI$47,MATCH($J85,'SR9'!$AF$38:$AF$47,0)) -> 200 | P85: =INDEX('SR9'!AI$85:AI$94,MATCH($J85,'SR9'!$AF$85:$AF$94,0)) -> 119 | Q85: =INDEX('SR9'!AJ$38:AJ$47,MATCH($J85,'SR9'!$AF$38:$AF$47,0)) -> 215 | R85: =INDEX('SR9'!AJ$85:AJ$94,MATCH($J85,'SR9'!$AF$85:$AF$94,0)) -> 159 | S85: =INDEX('SR9'!AK$38:AK$47,MATCH($J85,'SR9'!$AF$38:$AF$47,0)) -> 84 | T85: =INDEX('SR9'!AK$85:AK$94,MATCH($J85,'SR9'!$AF$85:$AF$94,0)) -> 176 | U85: =INDEX('SR9'!AL$38:AL$47,MATCH($J85,'SR9'!$AF$38:$AF$47,0)) -> 104 | V85: =INDEX('SR9'!AL$85:AL$94,MATCH($J85,'SR9'!$AF$85:$AF$94,0)) -> 115 | W85: =SUM(K85,M85,O85,Q85,S85,U85) -> 1032 | X85: =SUM(L85,N85,P85,R85,T85,V85) -> 1034 | Y85: =(W85-X85)/X85 -> -0.001934236
I87: Chinese room nights increased 6%.
I88: Thailand also increased.
I89: India increased 84%.
I90: However, SR9's mix is about 60% China and Taiwan in 2025, and this level is maintained going into 2026.
B93: AES | I93: AES | K93: 2026 | L93: 2025 | M93: 2026 | N93: 2025 | O93: 2026 | P93: 2025 | Q93: 2026 | R93: 2025 | S93: 2026 | T93: 2025 | U93: 2026 | V93: 2025 | W93: 2026 | X93: 2025
I94: Top 10 Nationality | K94: Jan | M94: Feb | O94: Mar | Q94: Apr | S94: May | U94: Jun | W94: YTD | Y94: Chg
I95: 1 | J95: =AES!$AF34 -> China | K95: =INDEX(AES!AG$34:AG$43,MATCH($J95,AES!$AF$34:$AF$43,0)) -> 2704 | L95: =IFERROR(INDEX(AES!AG$79:AG$88,MATCH($J95,AES!$AF$79:$AF$88,0)),"") -> 3652 | M95: =INDEX(AES!AH$34:AH$43,MATCH($J95,AES!$AF$34:$AF$43,0)) -> 4314 | N95: =IFERROR(INDEX(AES!AH$79:AH$88,MATCH($J95,AES!$AF$79:$AF$88,0)),"") -> 2735 | O95: =INDEX(AES!AI$34:AI$43,MATCH($J95,AES!$AF$34:$AF$43,0)) -> 2522 | P95: =IFERROR(INDEX(AES!AI$79:AI$88,MATCH($J95,AES!$AF$79:$AF$88,0)),"") -> 2039 | Q95: =INDEX(AES!AJ$34:AJ$43,MATCH($J95,AES!$AF$34:$AF$43,0)) -> 3353 | R95: =IFERROR(INDEX(AES!AJ$79:AJ$88,MATCH($J95,AES!$AF$79:$AF$88,0)),"") -> 2950 | S95: =INDEX(AES!AK$34:AK$43,MATCH($J95,AES!$AF$34:$AF$43,0)) -> 2790 | T95: =IFERROR(INDEX(AES!AK$79:AK$88,MATCH($J95,AES!$AF$79:$AF$88,0)),"") -> 3177 | U95: =INDEX(AES!AL$34:AL$43,MATCH($J95,AES!$AF$34:$AF$43,0)) -> 2930 | V95: =IFERROR(INDEX(AES!AL$79:AL$88,MATCH($J95,AES!$AF$79:$AF$88,0)),"") -> 2368 | W95: =SUM(K95,M95,O95,Q95,S95,U95) -> 18613 | X95: =SUM(L95,N95,P95,R95,T95,V95) -> 16921 | Y95: =(W95-X95)/X95 -> 0.09999409
I96: 2 | J96: =AES!$AF35 -> Japan | K96: =INDEX(AES!AG$34:AG$43,MATCH($J96,AES!$AF$34:$AF$43,0)) -> 777 | L96: =IFERROR(INDEX(AES!AG$79:AG$88,MATCH($J96,AES!$AF$79:$AF$88,0)),"") -> 468 | M96: =INDEX(AES!AH$34:AH$43,MATCH($J96,AES!$AF$34:$AF$43,0)) -> 737 | N96: =IFERROR(INDEX(AES!AH$79:AH$88,MATCH($J96,AES!$AF$79:$AF$88,0)),"") -> 560 | O96: =INDEX(AES!AI$34:AI$43,MATCH($J96,AES!$AF$34:$AF$43,0)) -> 609 | P96: =IFERROR(INDEX(AES!AI$79:AI$88,MATCH($J96,AES!$AF$79:$AF$88,0)),"") -> 423 | Q96: =INDEX(AES!AJ$34:AJ$43,MATCH($J96,AES!$AF$34:$AF$43,0)) -> 453 | R96: =IFERROR(INDEX(AES!AJ$79:AJ$88,MATCH($J96,AES!$AF$79:$AF$88,0)),"") -> 436 | S96: =INDEX(AES!AK$34:AK$43,MATCH($J96,AES!$AF$34:$AF$43,0)) -> 472 | T96: =IFERROR(INDEX(AES!AK$79:AK$88,MATCH($J96,AES!$AF$79:$AF$88,0)),"") -> 411 | U96: =INDEX(AES!AL$34:AL$43,MATCH($J96,AES!$AF$34:$AF$43,0)) -> 552 | V96: =IFERROR(INDEX(AES!AL$79:AL$88,MATCH($J96,AES!$AF$79:$AF$88,0)),"") -> 425 | W96: =SUM(K96,M96,O96,Q96,S96,U96) -> 3600 | X96: =SUM(L96,N96,P96,R96,T96,V96) -> 2723 | Y96: =(W96-X96)/X96 -> 0.32207124
I97: 3 | J97: =AES!$AF36 -> Finland | K97: =INDEX(AES!AG$34:AG$43,MATCH($J97,AES!$AF$34:$AF$43,0)) -> 649 | L97: 17 | M97: =INDEX(AES!AH$34:AH$43,MATCH($J97,AES!$AF$34:$AF$43,0)) -> 1102 | N97: 13 | O97: =INDEX(AES!AI$34:AI$43,MATCH($J97,AES!$AF$34:$AF$43,0)) -> 1158 | P97: 15 | Q97: =INDEX(AES!AJ$34:AJ$43,MATCH($J97,AES!$AF$34:$AF$43,0)) -> 10 | R97: 6 | S97: =INDEX(AES!AK$34:AK$43,MATCH($J97,AES!$AF$34:$AF$43,0)) -> 0 | T97: 4 | U97: =INDEX(AES!AL$34:AL$43,MATCH($J97,AES!$AF$34:$AF$43,0)) -> 3 | V97: 0 | W97: =SUM(K97,M97,O97,Q97,S97,U97) -> 2922 | X97: =SUM(L97,N97,P97,R97,T97,V97) -> 55 | Y97: =(W97-X97)/X97 -> 52.127273
I98: 4 | J98: =AES!$AF37 -> Singapore | K98: =INDEX(AES!AG$34:AG$43,MATCH($J98,AES!$AF$34:$AF$43,0)) -> 362 | L98: =IFERROR(INDEX(AES!AG$79:AG$88,MATCH($J98,AES!$AF$79:$AF$88,0)),"") -> 375 | M98: =INDEX(AES!AH$34:AH$43,MATCH($J98,AES!$AF$34:$AF$43,0)) -> 288 | N98: =IFERROR(INDEX(AES!AH$79:AH$88,MATCH($J98,AES!$AF$79:$AF$88,0)),"") -> 297 | O98: =INDEX(AES!AI$34:AI$43,MATCH($J98,AES!$AF$34:$AF$43,0)) -> 346 | P98: =IFERROR(INDEX(AES!AI$79:AI$88,MATCH($J98,AES!$AF$79:$AF$88,0)),"") -> 354 | Q98: =INDEX(AES!AJ$34:AJ$43,MATCH($J98,AES!$AF$34:$AF$43,0)) -> 226 | R98: =IFERROR(INDEX(AES!AJ$79:AJ$88,MATCH($J98,AES!$AF$79:$AF$88,0)),"") -> 474 | S98: =INDEX(AES!AK$34:AK$43,MATCH($J98,AES!$AF$34:$AF$43,0)) -> 360 | T98: =IFERROR(INDEX(AES!AK$79:AK$88,MATCH($J98,AES!$AF$79:$AF$88,0)),"") -> 335 | U98: =INDEX(AES!AL$34:AL$43,MATCH($J98,AES!$AF$34:$AF$43,0)) -> 352 | V98: =IFERROR(INDEX(AES!AL$79:AL$88,MATCH($J98,AES!$AF$79:$AF$88,0)),"") -> 428 | W98: =SUM(K98,M98,O98,Q98,S98,U98) -> 1934 | X98: =SUM(L98,N98,P98,R98,T98,V98) -> 2263 | Y98: =(W98-X98)/X98 -> -0.14538224
I99: 5 | J99: =AES!$AF38 -> USA | K99: =INDEX(AES!AG$34:AG$43,MATCH($J99,AES!$AF$34:$AF$43,0)) -> 280 | L99: =IFERROR(INDEX(AES!AG$79:AG$88,MATCH($J99,AES!$AF$79:$AF$88,0)),"") -> 368 | M99: =INDEX(AES!AH$34:AH$43,MATCH($J99,AES!$AF$34:$AF$43,0)) -> 307 | N99: =IFERROR(INDEX(AES!AH$79:AH$88,MATCH($J99,AES!$AF$79:$AF$88,0)),"") -> 295 | O99: =INDEX(AES!AI$34:AI$43,MATCH($J99,AES!$AF$34:$AF$43,0)) -> 360 | P99: =IFERROR(INDEX(AES!AI$79:AI$88,MATCH($J99,AES!$AF$79:$AF$88,0)),"") -> 403 | Q99: =INDEX(AES!AJ$34:AJ$43,MATCH($J99,AES!$AF$34:$AF$43,0)) -> 290 | R99: =IFERROR(INDEX(AES!AJ$79:AJ$88,MATCH($J99,AES!$AF$79:$AF$88,0)),"") -> 261 | S99: =INDEX(AES!AK$34:AK$43,MATCH($J99,AES!$AF$34:$AF$43,0)) -> 233 | T99: =IFERROR(INDEX(AES!AK$79:AK$88,MATCH($J99,AES!$AF$79:$AF$88,0)),"") -> 363 | U99: =INDEX(AES!AL$34:AL$43,MATCH($J99,AES!$AF$34:$AF$43,0)) -> 348 | V99: =IFERROR(INDEX(AES!AL$79:AL$88,MATCH($J99,AES!$AF$79:$AF$88,0)),"") -> 388 | W99: =SUM(K99,M99,O99,Q99,S99,U99) -> 1818 | X99: =SUM(L99,N99,P99,R99,T99,V99) -> 2078 | Y99: =(W99-X99)/X99 -> -0.12512031
I100: 6 | J100: =AES!$AF39 -> Thailand | K100: =INDEX(AES!AG$34:AG$43,MATCH($J100,AES!$AF$34:$AF$43,0)) -> 328 | L100: =IFERROR(INDEX(AES!AG$79:AG$88,MATCH($J100,AES!$AF$79:$AF$88,0)),"") -> 189 | M100: =INDEX(AES!AH$34:AH$43,MATCH($J100,AES!$AF$34:$AF$43,0)) -> 235 | N100: =IFERROR(INDEX(AES!AH$79:AH$88,MATCH($J100,AES!$AF$79:$AF$88,0)),"") -> 250 | O100: =INDEX(AES!AI$34:AI$43,MATCH($J100,AES!$AF$34:$AF$43,0)) -> 271 | P100: =IFERROR(INDEX(AES!AI$79:AI$88,MATCH($J100,AES!$AF$79:$AF$88,0)),"") -> 275 | Q100: =INDEX(AES!AJ$34:AJ$43,MATCH($J100,AES!$AF$34:$AF$43,0)) -> 297 | R100: =IFERROR(INDEX(AES!AJ$79:AJ$88,MATCH($J100,AES!$AF$79:$AF$88,0)),"") -> 212 | S100: =INDEX(AES!AK$34:AK$43,MATCH($J100,AES!$AF$34:$AF$43,0)) -> 276 | T100: =IFERROR(INDEX(AES!AK$79:AK$88,MATCH($J100,AES!$AF$79:$AF$88,0)),"") -> 356 | U100: =INDEX(AES!AL$34:AL$43,MATCH($J100,AES!$AF$34:$AF$43,0)) -> 218 | V100: =IFERROR(INDEX(AES!AL$79:AL$88,MATCH($J100,AES!$AF$79:$AF$88,0)),"") -> 242 | W100: =SUM(K100,M100,O100,Q100,S100,U100) -> 1625 | X100: =SUM(L100,N100,P100,R100,T100,V100) -> 1524 | Y100: =(W100-X100)/X100 -> 0.066272966
I101: 7 | J101: =AES!$AF40 -> Germany | K101: =INDEX(AES!AG$34:AG$43,MATCH($J101,AES!$AF$34:$AF$43,0)) -> 383 | L101: =IFERROR(INDEX(AES!AG$79:AG$88,MATCH($J101,AES!$AF$79:$AF$88,0)),"") -> 276 | M101: =INDEX(AES!AH$34:AH$43,MATCH($J101,AES!$AF$34:$AF$43,0)) -> 350 | N101: =IFERROR(INDEX(AES!AH$79:AH$88,MATCH($J101,AES!$AF$79:$AF$88,0)),"") -> 311 | O101: =INDEX(AES!AI$34:AI$43,MATCH($J101,AES!$AF$34:$AF$43,0)) -> 385 | P101: =IFERROR(INDEX(AES!AI$79:AI$88,MATCH($J101,AES!$AF$79:$AF$88,0)),"") -> 322 | Q101: =INDEX(AES!AJ$34:AJ$43,MATCH($J101,AES!$AF$34:$AF$43,0)) -> 170 | R101: =IFERROR(INDEX(AES!AJ$79:AJ$88,MATCH($J101,AES!$AF$79:$AF$88,0)),"") -> 149 | S101: =INDEX(AES!AK$34:AK$43,MATCH($J101,AES!$AF$34:$AF$43,0)) -> 125 | T101: =IFERROR(INDEX(AES!AK$79:AK$88,MATCH($J101,AES!$AF$79:$AF$88,0)),"") -> 256 | U101: =INDEX(AES!AL$34:AL$43,MATCH($J101,AES!$AF$34:$AF$43,0)) -> 113 | V101: =IFERROR(INDEX(AES!AL$79:AL$88,MATCH($J101,AES!$AF$79:$AF$88,0)),"") -> 222 | W101: =SUM(K101,M101,O101,Q101,S101,U101) -> 1526 | X101: =SUM(L101,N101,P101,R101,T101,V101) -> 1536 | Y101: =(W101-X101)/X101 -> -0.0065104167
I102: 8 | J102: =AES!$AF41 -> UK | K102: =INDEX(AES!AG$34:AG$43,MATCH($J102,AES!$AF$34:$AF$43,0)) -> 272 | L102: 313 | M102: =INDEX(AES!AH$34:AH$43,MATCH($J102,AES!$AF$34:$AF$43,0)) -> 197 | N102: 308 | O102: =INDEX(AES!AI$34:AI$43,MATCH($J102,AES!$AF$34:$AF$43,0)) -> 324 | P102: 223 | Q102: =INDEX(AES!AJ$34:AJ$43,MATCH($J102,AES!$AF$34:$AF$43,0)) -> 295 | R102: 153 | S102: =INDEX(AES!AK$34:AK$43,MATCH($J102,AES!$AF$34:$AF$43,0)) -> 168 | T102: 94 | U102: =INDEX(AES!AL$34:AL$43,MATCH($J102,AES!$AF$34:$AF$43,0)) -> 129 | V102: 62 | W102: =SUM(K102,M102,O102,Q102,S102,U102) -> 1385 | X102: =SUM(L102,N102,P102,R102,T102,V102) -> 1153 | Y102: =(W102-X102)/X102 -> 0.20121422
I103: 9 | J103: =AES!$AF42 -> Korea | K103: =INDEX(AES!AG$34:AG$43,MATCH($J103,AES!$AF$34:$AF$43,0)) -> 285 | L103: =IFERROR(INDEX(AES!AG$79:AG$88,MATCH($J103,AES!$AF$79:$AF$88,0)),"") -> 609 | M103: =INDEX(AES!AH$34:AH$43,MATCH($J103,AES!$AF$34:$AF$43,0)) -> 281 | N103: =IFERROR(INDEX(AES!AH$79:AH$88,MATCH($J103,AES!$AF$79:$AF$88,0)),"") -> 429 | O103: =INDEX(AES!AI$34:AI$43,MATCH($J103,AES!$AF$34:$AF$43,0)) -> 191 | P103: =IFERROR(INDEX(AES!AI$79:AI$88,MATCH($J103,AES!$AF$79:$AF$88,0)),"") -> 247 | Q103: =INDEX(AES!AJ$34:AJ$43,MATCH($J103,AES!$AF$34:$AF$43,0)) -> 176 | R103: =IFERROR(INDEX(AES!AJ$79:AJ$88,MATCH($J103,AES!$AF$79:$AF$88,0)),"") -> 253 | S103: =INDEX(AES!AK$34:AK$43,MATCH($J103,AES!$AF$34:$AF$43,0)) -> 256 | T103: =IFERROR(INDEX(AES!AK$79:AK$88,MATCH($J103,AES!$AF$79:$AF$88,0)),"") -> 388 | U103: =INDEX(AES!AL$34:AL$43,MATCH($J103,AES!$AF$34:$AF$43,0)) -> 115 | V103: =IFERROR(INDEX(AES!AL$79:AL$88,MATCH($J103,AES!$AF$79:$AF$88,0)),"") -> 288 | W103: =SUM(K103,M103,O103,Q103,S103,U103) -> 1304 | X103: =SUM(L103,N103,P103,R103,T103,V103) -> 2214 | Y103: =(W103-X103)/X103 -> -0.41102078
I104: 10 | J104: =AES!$AF43 -> Taiwan | K104: =INDEX(AES!AG$34:AG$43,MATCH($J104,AES!$AF$34:$AF$43,0)) -> 155 | L104: 477 | M104: =INDEX(AES!AH$34:AH$43,MATCH($J104,AES!$AF$34:$AF$43,0)) -> 329 | N104: 249 | O104: =INDEX(AES!AI$34:AI$43,MATCH($J104,AES!$AF$34:$AF$43,0)) -> 186 | P104: 167 | Q104: =INDEX(AES!AJ$34:AJ$43,MATCH($J104,AES!$AF$34:$AF$43,0)) -> 226 | R104: 169 | S104: =INDEX(AES!AK$34:AK$43,MATCH($J104,AES!$AF$34:$AF$43,0)) -> 155 | T104: 216 | U104: =INDEX(AES!AL$34:AL$43,MATCH($J104,AES!$AF$34:$AF$43,0)) -> 165 | V104: 148 | W104: =SUM(K104,M104,O104,Q104,S104,U104) -> 1216 | X104: =SUM(L104,N104,P104,R104,T104,V104) -> 1426 | Y104: =(W104-X104)/X104 -> -0.14726508
B106: L8 | I106: LYF | K106: 2026 | L106: 2025 | M106: 2026 | N106: 2025 | O106: 2026 | P106: 2025 | Q106: 2026 | R106: 2025 | S106: 2026 | T106: 2025 | U106: 2026 | V106: 2025 | W106: 2026 | X106: 2025
I107: Top 10 Nationality | K107: Jan | M107: Feb | O107: Mar | Q107: Apr | S107: May | U107: Jun | W107: YTD | Y107: Chg
I108: 1 | J108: =LYF!$AF34 -> China | K108: =INDEX(LYF!AG$34:AG$43,MATCH($J108,LYF!$AF$34:$AF$43,0)) -> 808 | L108: =IFERROR(INDEX(LYF!AG$78:AG$87,MATCH($J108,LYF!$AF$78:$AF$87,0)),"") -> 973 | M108: =INDEX(LYF!AH$34:AH$43,MATCH($J108,LYF!$AF$34:$AF$43,0)) -> 1267 | N108: =IFERROR(INDEX(LYF!AH$78:AH$87,MATCH($J108,LYF!$AF$78:$AF$87,0)),"") -> 803 | O108: =INDEX(LYF!AI$34:AI$43,MATCH($J108,LYF!$AF$34:$AF$43,0)) -> 1117 | P108: =IFERROR(INDEX(LYF!AI$78:AI$87,MATCH($J108,LYF!$AF$78:$AF$87,0)),"") -> 754 | Q108: =INDEX(LYF!AJ$34:AJ$43,MATCH($J108,LYF!$AF$34:$AF$43,0)) -> 654 | R108: =IFERROR(INDEX(LYF!AJ$78:AJ$87,MATCH($J108,LYF!$AF$78:$AF$87,0)),"") -> 667 | S108: =INDEX(LYF!AK$34:AK$43,MATCH($J108,LYF!$AF$34:$AF$43,0)) -> 1010 | T108: =IFERROR(INDEX(LYF!AK$78:AK$87,MATCH($J108,LYF!$AF$78:$AF$87,0)),"") -> 743 | U108: =INDEX(LYF!AL$34:AL$43,MATCH($J108,LYF!$AF$34:$AF$43,0)) -> 1098 | V108: =IFERROR(INDEX(LYF!AL$78:AL$87,MATCH($J108,LYF!$AF$78:$AF$87,0)),"") -> 702 | W108: =SUM(K108,M108,O108,Q108,S108,U108) -> 5954 | X108: =SUM(L108,N108,P108,R108,T108,V108) -> 4642 | Y108: =(W108-X108)/X108 -> 0.28263679
I109: 2 | J109: =LYF!$AF35 -> Indonesia | K109: =INDEX(LYF!AG$34:AG$43,MATCH($J109,LYF!$AF$34:$AF$43,0)) -> 439 | L109: =IFERROR(INDEX(LYF!AG$78:AG$87,MATCH($J109,LYF!$AF$78:$AF$87,0)),"") -> 163 | M109: =INDEX(LYF!AH$34:AH$43,MATCH($J109,LYF!$AF$34:$AF$43,0)) -> 315 | N109: =IFERROR(INDEX(LYF!AH$78:AH$87,MATCH($J109,LYF!$AF$78:$AF$87,0)),"") -> 150 | O109: =INDEX(LYF!AI$34:AI$43,MATCH($J109,LYF!$AF$34:$AF$43,0)) -> 446 | P109: =IFERROR(INDEX(LYF!AI$78:AI$87,MATCH($J109,LYF!$AF$78:$AF$87,0)),"") -> 124 | Q109: =INDEX(LYF!AJ$34:AJ$43,MATCH($J109,LYF!$AF$34:$AF$43,0)) -> 368 | R109: =IFERROR(INDEX(LYF!AJ$78:AJ$87,MATCH($J109,LYF!$AF$78:$AF$87,0)),"") -> 162 | S109: =INDEX(LYF!AK$34:AK$43,MATCH($J109,LYF!$AF$34:$AF$43,0)) -> 898 | T109: =IFERROR(INDEX(LYF!AK$78:AK$87,MATCH($J109,LYF!$AF$78:$AF$87,0)),"") -> 211 | U109: =INDEX(LYF!AL$34:AL$43,MATCH($J109,LYF!$AF$34:$AF$43,0)) -> 568 | V109: =IFERROR(INDEX(LYF!AL$78:AL$87,MATCH($J109,LYF!$AF$78:$AF$87,0)),"") -> 207 | W109: =SUM(K109,M109,O109,Q109,S109,U109) -> 3034 | X109: =SUM(L109,N109,P109,R109,T109,V109) -> 1017 | Y109: =(W109-X109)/X109 -> 1.9832842
I110: 3 | J110: =LYF!$AF36 -> Singapore | K110: =INDEX(LYF!AG$34:AG$43,MATCH($J110,LYF!$AF$34:$AF$43,0)) -> 521 | L110: =IFERROR(INDEX(LYF!AG$78:AG$87,MATCH($J110,LYF!$AF$78:$AF$87,0)),"") -> 493 | M110: =INDEX(LYF!AH$34:AH$43,MATCH($J110,LYF!$AF$34:$AF$43,0)) -> 427 | N110: =IFERROR(INDEX(LYF!AH$78:AH$87,MATCH($J110,LYF!$AF$78:$AF$87,0)),"") -> 439 | O110: =INDEX(LYF!AI$34:AI$43,MATCH($J110,LYF!$AF$34:$AF$43,0)) -> 524 | P110: =IFERROR(INDEX(LYF!AI$78:AI$87,MATCH($J110,LYF!$AF$78:$AF$87,0)),"") -> 561 | Q110: =INDEX(LYF!AJ$34:AJ$43,MATCH($J110,LYF!$AF$34:$AF$43,0)) -> 221 | R110: =IFERROR(INDEX(LYF!AJ$78:AJ$87,MATCH($J110,LYF!$AF$78:$AF$87,0)),"") -> 391 | S110: =INDEX(LYF!AK$34:AK$43,MATCH($J110,LYF!$AF$34:$AF$43,0)) -> 381 | T110: =IFERROR(INDEX(LYF!AK$78:AK$87,MATCH($J110,LYF!$AF$78:$AF$87,0)),"") -> 419 | U110: =INDEX(LYF!AL$34:AL$43,MATCH($J110,LYF!$AF$34:$AF$43,0)) -> 262 | V110: =IFERROR(INDEX(LYF!AL$78:AL$87,MATCH($J110,LYF!$AF$78:$AF$87,0)),"") -> 459 | W110: =SUM(K110,M110,O110,Q110,S110,U110) -> 2336 | X110: =SUM(L110,N110,P110,R110,T110,V110) -> 2762 | Y110: =(W110-X110)/X110 -> -0.15423606
I111: 4 | J111: =LYF!$AF37 -> Malaysia | K111: =INDEX(LYF!AG$34:AG$43,MATCH($J111,LYF!$AF$34:$AF$43,0)) -> 432 | L111: =IFERROR(INDEX(LYF!AG$78:AG$87,MATCH($J111,LYF!$AF$78:$AF$87,0)),"") -> 328 | M111: =INDEX(LYF!AH$34:AH$43,MATCH($J111,LYF!$AF$34:$AF$43,0)) -> 322 | N111: =IFERROR(INDEX(LYF!AH$78:AH$87,MATCH($J111,LYF!$AF$78:$AF$87,0)),"") -> 387 | O111: =INDEX(LYF!AI$34:AI$43,MATCH($J111,LYF!$AF$34:$AF$43,0)) -> 391 | P111: =IFERROR(INDEX(LYF!AI$78:AI$87,MATCH($J111,LYF!$AF$78:$AF$87,0)),"") -> 397 | Q111: =INDEX(LYF!AJ$34:AJ$43,MATCH($J111,LYF!$AF$34:$AF$43,0)) -> 265 | R111: =IFERROR(INDEX(LYF!AJ$78:AJ$87,MATCH($J111,LYF!$AF$78:$AF$87,0)),"") -> 391 | S111: =INDEX(LYF!AK$34:AK$43,MATCH($J111,LYF!$AF$34:$AF$43,0)) -> 402 | T111: =IFERROR(INDEX(LYF!AK$78:AK$87,MATCH($J111,LYF!$AF$78:$AF$87,0)),"") -> 358 | U111: =INDEX(LYF!AL$34:AL$43,MATCH($J111,LYF!$AF$34:$AF$43,0)) -> 308 | V111: =IFERROR(INDEX(LYF!AL$78:AL$87,MATCH($J111,LYF!$AF$78:$AF$87,0)),"") -> 277 | W111: =SUM(K111,M111,O111,Q111,S111,U111) -> 2120 | X111: =SUM(L111,N111,P111,R111,T111,V111) -> 2138 | Y111: =(W111-X111)/X111 -> -0.0084190833
I112: 5 | J112: =LYF!$AF38 -> Taiwan | K112: =INDEX(LYF!AG$34:AG$43,MATCH($J112,LYF!$AF$34:$AF$43,0)) -> 258 | L112: =IFERROR(INDEX(LYF!AG$78:AG$87,MATCH($J112,LYF!$AF$78:$AF$87,0)),"") -> 246 | M112: =INDEX(LYF!AH$34:AH$43,MATCH($J112,LYF!$AF$34:$AF$43,0)) -> 316 | N112: =IFERROR(INDEX(LYF!AH$78:AH$87,MATCH($J112,LYF!$AF$78:$AF$87,0)),"") -> 183 | O112: =INDEX(LYF!AI$34:AI$43,MATCH($J112,LYF!$AF$34:$AF$43,0)) -> 364 | P112: =IFERROR(INDEX(LYF!AI$78:AI$87,MATCH($J112,LYF!$AF$78:$AF$87,0)),"") -> 182 | Q112: =INDEX(LYF!AJ$34:AJ$43,MATCH($J112,LYF!$AF$34:$AF$43,0)) -> 179 | R112: =IFERROR(INDEX(LYF!AJ$78:AJ$87,MATCH($J112,LYF!$AF$78:$AF$87,0)),"") -> 172 | S112: =INDEX(LYF!AK$34:AK$43,MATCH($J112,LYF!$AF$34:$AF$43,0)) -> 186 | T112: =IFERROR(INDEX(LYF!AK$78:AK$87,MATCH($J112,LYF!$AF$78:$AF$87,0)),"") -> 210 | U112: =INDEX(LYF!AL$34:AL$43,MATCH($J112,LYF!$AF$34:$AF$43,0)) -> 221 | V112: =IFERROR(INDEX(LYF!AL$78:AL$87,MATCH($J112,LYF!$AF$78:$AF$87,0)),"") -> 207 | W112: =SUM(K112,M112,O112,Q112,S112,U112) -> 1524 | X112: =SUM(L112,N112,P112,R112,T112,V112) -> 1200 | Y112: =(W112-X112)/X112 -> 0.27
I113: 6 | J113: =LYF!$AF39 -> Thailand | K113: =INDEX(LYF!AG$34:AG$43,MATCH($J113,LYF!$AF$34:$AF$43,0)) -> 214 | L113: =IFERROR(INDEX(LYF!AG$78:AG$87,MATCH($J113,LYF!$AF$78:$AF$87,0)),"") -> 218 | M113: =INDEX(LYF!AH$34:AH$43,MATCH($J113,LYF!$AF$34:$AF$43,0)) -> 227 | N113: =IFERROR(INDEX(LYF!AH$78:AH$87,MATCH($J113,LYF!$AF$78:$AF$87,0)),"") -> 251 | O113: =INDEX(LYF!AI$34:AI$43,MATCH($J113,LYF!$AF$34:$AF$43,0)) -> 279 | P113: =IFERROR(INDEX(LYF!AI$78:AI$87,MATCH($J113,LYF!$AF$78:$AF$87,0)),"") -> 305 | Q113: =INDEX(LYF!AJ$34:AJ$43,MATCH($J113,LYF!$AF$34:$AF$43,0)) -> 162 | R113: =IFERROR(INDEX(LYF!AJ$78:AJ$87,MATCH($J113,LYF!$AF$78:$AF$87,0)),"") -> 301 | S113: =INDEX(LYF!AK$34:AK$43,MATCH($J113,LYF!$AF$34:$AF$43,0)) -> 262 | T113: =IFERROR(INDEX(LYF!AK$78:AK$87,MATCH($J113,LYF!$AF$78:$AF$87,0)),"") -> 364 | U113: =INDEX(LYF!AL$34:AL$43,MATCH($J113,LYF!$AF$34:$AF$43,0)) -> 319 | V113: =IFERROR(INDEX(LYF!AL$78:AL$87,MATCH($J113,LYF!$AF$78:$AF$87,0)),"") -> 434 | W113: =SUM(K113,M113,O113,Q113,S113,U113) -> 1463 | X113: =SUM(L113,N113,P113,R113,T113,V113) -> 1873 | Y113: =(W113-X113)/X113 -> -0.21890016
I114: 7 | J114: =LYF!$AF40 -> USA | K114: =INDEX(LYF!AG$34:AG$43,MATCH($J114,LYF!$AF$34:$AF$43,0)) -> 518 | L114: =IFERROR(INDEX(LYF!AG$78:AG$87,MATCH($J114,LYF!$AF$78:$AF$87,0)),"") -> 608 | M114: =INDEX(LYF!AH$34:AH$43,MATCH($J114,LYF!$AF$34:$AF$43,0)) -> 320 | N114: =IFERROR(INDEX(LYF!AH$78:AH$87,MATCH($J114,LYF!$AF$78:$AF$87,0)),"") -> 356 | O114: =INDEX(LYF!AI$34:AI$43,MATCH($J114,LYF!$AF$34:$AF$43,0)) -> 192 | P114: =IFERROR(INDEX(LYF!AI$78:AI$87,MATCH($J114,LYF!$AF$78:$AF$87,0)),"") -> 346 | Q114: =INDEX(LYF!AJ$34:AJ$43,MATCH($J114,LYF!$AF$34:$AF$43,0)) -> 102 | R114: =IFERROR(INDEX(LYF!AJ$78:AJ$87,MATCH($J114,LYF!$AF$78:$AF$87,0)),"") -> 301 | S114: =INDEX(LYF!AK$34:AK$43,MATCH($J114,LYF!$AF$34:$AF$43,0)) -> 135 | T114: =IFERROR(INDEX(LYF!AK$78:AK$87,MATCH($J114,LYF!$AF$78:$AF$87,0)),"") -> 183 | U114: =INDEX(LYF!AL$34:AL$43,MATCH($J114,LYF!$AF$34:$AF$43,0)) -> 173 | V114: =IFERROR(INDEX(LYF!AL$78:AL$87,MATCH($J114,LYF!$AF$78:$AF$87,0)),"") -> 205 | W114: =SUM(K114,M114,O114,Q114,S114,U114) -> 1440 | X114: =SUM(L114,N114,P114,R114,T114,V114) -> 1999 | Y114: =(W114-X114)/X114 -> -0.27963982
I115: 8 | J115: =LYF!$AF41 -> Japan | K115: =INDEX(LYF!AG$34:AG$43,MATCH($J115,LYF!$AF$34:$AF$43,0)) -> 191 | L115: =IFERROR(INDEX(LYF!AG$78:AG$87,MATCH($J115,LYF!$AF$78:$AF$87,0)),"") -> 125 | M115: =INDEX(LYF!AH$34:AH$43,MATCH($J115,LYF!$AF$34:$AF$43,0)) -> 233 | N115: =IFERROR(INDEX(LYF!AH$78:AH$87,MATCH($J115,LYF!$AF$78:$AF$87,0)),"") -> 223 | O115: =INDEX(LYF!AI$34:AI$43,MATCH($J115,LYF!$AF$34:$AF$43,0)) -> 233 | P115: =IFERROR(INDEX(LYF!AI$78:AI$87,MATCH($J115,LYF!$AF$78:$AF$87,0)),"") -> 154 | Q115: =INDEX(LYF!AJ$34:AJ$43,MATCH($J115,LYF!$AF$34:$AF$43,0)) -> 140 | R115: =IFERROR(INDEX(LYF!AJ$78:AJ$87,MATCH($J115,LYF!$AF$78:$AF$87,0)),"") -> 125 | S115: =INDEX(LYF!AK$34:AK$43,MATCH($J115,LYF!$AF$34:$AF$43,0)) -> 144 | T115: =IFERROR(INDEX(LYF!AK$78:AK$87,MATCH($J115,LYF!$AF$78:$AF$87,0)),"") -> 164 | U115: =INDEX(LYF!AL$34:AL$43,MATCH($J115,LYF!$AF$34:$AF$43,0)) -> 97 | V115: =IFERROR(INDEX(LYF!AL$78:AL$87,MATCH($J115,LYF!$AF$78:$AF$87,0)),"") -> 135 | W115: =SUM(K115,M115,O115,Q115,S115,U115) -> 1038 | X115: =SUM(L115,N115,P115,R115,T115,V115) -> 926 | Y115: =(W115-X115)/X115 -> 0.12095032
I116: 9 | J116: =LYF!$AF42 -> UK | K116: =INDEX(LYF!AG$34:AG$43,MATCH($J116,LYF!$AF$34:$AF$43,0)) -> 250 | L116: =IFERROR(INDEX(LYF!AG$78:AG$87,MATCH($J116,LYF!$AF$78:$AF$87,0)),"") -> 253 | M116: =INDEX(LYF!AH$34:AH$43,MATCH($J116,LYF!$AF$34:$AF$43,0)) -> 150 | N116: =IFERROR(INDEX(LYF!AH$78:AH$87,MATCH($J116,LYF!$AF$78:$AF$87,0)),"") -> 243 | O116: =INDEX(LYF!AI$34:AI$43,MATCH($J116,LYF!$AF$34:$AF$43,0)) -> 152 | P116: =IFERROR(INDEX(LYF!AI$78:AI$87,MATCH($J116,LYF!$AF$78:$AF$87,0)),"") -> 211 | Q116: =INDEX(LYF!AJ$34:AJ$43,MATCH($J116,LYF!$AF$34:$AF$43,0)) -> 82 | R116: =IFERROR(INDEX(LYF!AJ$78:AJ$87,MATCH($J116,LYF!$AF$78:$AF$87,0)),"") -> 221 | S116: =INDEX(LYF!AK$34:AK$43,MATCH($J116,LYF!$AF$34:$AF$43,0)) -> 91 | T116: =IFERROR(INDEX(LYF!AK$78:AK$87,MATCH($J116,LYF!$AF$78:$AF$87,0)),"") -> 168 | U116: =INDEX(LYF!AL$34:AL$43,MATCH($J116,LYF!$AF$34:$AF$43,0)) -> 84 | V116: =IFERROR(INDEX(LYF!AL$78:AL$87,MATCH($J116,LYF!$AF$78:$AF$87,0)),"") -> 105 | W116: =SUM(K116,M116,O116,Q116,S116,U116) -> 809 | X116: =SUM(L116,N116,P116,R116,T116,V116) -> 1201 | Y116: =(W116-X116)/X116 -> -0.32639467
...

Sheet Province arrival
A2: Bangkok Arrivals | B2: Jan | C2: Feb | D2: Mar | E2: Apr | F2: May | G2: Jun | H2: Jul | I2: Aug | J2: Sep | K2: Oct | L2: Nov | M2: Dec | N2: Total
A3: 2019 | B3: =SUM(B4:B5) -> 0 | C3: =SUM(C4:C5) -> 0 | D3: =SUM(D4:D5) -> 0 | E3: =SUM(E4:E5) -> 0 | F3: =SUM(F4:F5) -> 0 | G3: =SUM(G4:G5) -> 0 | H3: =SUM(H4:H5) -> 0 | I3: =SUM(I4:I5) -> 0 | ... M3: =SUM(M4:M5) -> 0 | N3: =SUM(B3:M3) -> 0
A4: - Domestics | N4: =SUM(B4:M4) -> 0
A5: - International | N5: =SUM(B5:M5) -> 0
A6: % Domestic | B6: =B4/B3 -> #DIV/0! | C6: =C4/C3 -> #DIV/0! | D6: =D4/D3 -> #DIV/0! | E6: =E4/E3 -> #DIV/0! | F6: =F4/F3 -> #DIV/0! | G6: =G4/G3 -> #DIV/0!
A7: 2023 | B7: =SUM(B8:B9) -> 4440412 | C7: =SUM(C8:C9) -> 4240162 | D7: =SUM(D8:D9) -> 4874409 | E7: =SUM(E8:E9) -> 4679594 | F7: =SUM(F8:F9) -> 4576767 | G7: =SUM(G8:G9) -> 4421785 | N7: =SUM(B7:M7) -> 27233129
A8: - Domestics | B8: 2487365 | C8: 2281696 | D8: 2808837 | E8: 2789539 | F8: 2802826 | G8: 2447327 | N8: =SUM(B8:M8) -> 15617590
A9: - International | B9: 1953047 | C9: 1958466 | D9: 2065572 | E9: 1890055 | F9: 1773941 | G9: 1974458 | N9: =SUM(B9:M9) -> 11615539
A10: % Domestic | B10: =B8/B7 -> 0.56016536 | C10: =C8/C7 -> 0.53811529 | D10: =D8/D7 -> 0.57624155 | E10: =E8/E7 -> 0.59610706 | F10: =F8/F7 -> 0.61240303 | G10: =G8/G7 -> 0.55347037 | N10: =N8/N7 -> 0.57347762
A11: 2024 | B11: =SUM(B12:B13) -> 5097274 | C11: =SUM(C12:C13) -> 4740224 | D11: =SUM(D12:D13) -> 4585853 | E11: =SUM(E12:E13) -> 4772088 | F11: =SUM(F12:F13) -> 4657051 | G11: =SUM(G12:G13) -> 4468565 | N11: =SUM(B11:M11) -> 28321055
A12: - Domestics | B12: 2665097 | C12: 2206042 | D12: 2342580 | E12: 2649470 | F12: 2639221 | G12: 2325320 | N12: =SUM(B12:M12) -> 14827730
A13: - International | B13: 2432177 | C13: 2534182 | D13: 2243273 | E13: 2122618 | F13: 2017830 | G13: 2143245 | N13: =SUM(B13:M13) -> 13493325
A14: % Domestic | B14: =B12/B11 -> 0.52284751 | C14: =C12/C11 -> 0.46538771 | D14: =D12/D11 -> 0.51082754 | E14: =E12/E11 -> 0.55520141 | F14: =F12/F11 -> 0.56671507 | G14: =G12/G11 -> 0.52037287 | N14: =N12/N11 -> 0.52355853
A15: 2025 | B15: =SUM(B16:B17) -> 4788549 | C15: =SUM(C16:C17) -> 4660225 | D15: =SUM(D16:D17) -> 4645416 | E15: =SUM(E16:E17) -> 4300436 | F15: =SUM(F16:F17) -> 4406680 | G15: =SUM(G16:G17) -> 4177945 | H15: =SUM(H16:H17) -> 0 | I15: =SUM(I16:I17) -> 0 | ... M15: =SUM(M16:M17) -> 0 | N15: =SUM(B15:M15) -> 26979251
A16: - Domestics | B16: 2157546 | C16: 2379572 | D16: 2650644 | E16: 2343256 | F16: 2645108 | G16: 2370875 | N16: =SUM(B16:M16) -> 14547001
A17: - International | B17: 2631003 | C17: 2280653 | D17: 1994772 | E17: 1957180 | F17: 1761572 | G17: 1807070 | N17: =SUM(B17:M17) -> 12432250
A18: % Domestic | B18: =B16/B15 -> 0.45056363 | C18: =C16/C15 -> 0.51061311 | D18: =D16/D15 -> 0.57059346 | E18: =E16/E15 -> 0.54488801 | F18: =F16/F15 -> 0.60024962 | G18: =G16/G15 -> 0.56747396 | N18: =N16/N15 -> 0.53919217
A19: 2026 | B19: =SUM(B20:B21) -> 4804054 | C19: =SUM(C20:C21) -> 4979158 | D19: =SUM(D20:D21) -> 5003513 | E19: =SUM(E20:E21) -> 4294250 | F19: =SUM(F20:F21) -> 4536642 | G19: =SUM(G20:G21) -> 4246420 | H19: =SUM(H20:H21) -> 0 | I19: =SUM(I20:I21) -> 0 | ... M19: =SUM(M20:M21) -> 0 | N19: =SUM(B19:M19) -> 27864037
A20: - Domestics | B20: 2334187 | C20: 2499572 | D20: 2907661 | E20: 2472364 | F20: 2718774 | G20: 2512532 | N20: =SUM(B20:M20) -> 15445090
A21: - International | B21: 2469867 | C21: 2479586 | D21: 2095852 | E21: 1821886 | F21: 1817868 | G21: 1733888 | N21: =SUM(B21:M21) -> 12418947
A22: % Domestic | B22: =B20/B19 -> 0.48587859 | C22: =C20/C19 -> 0.50200697 | D22: =D20/D19 -> 0.5811239 | E22: =E20/E19 -> 0.57573825 | F22: =F20/F19 -> 0.59929216 | G22: =G20/G19 -> 0.59168241 | N22: =N20/N19 -> 0.55430195
A23: Total
A24: 26 Vs 25 | B24: =(B19-B15)/B15 -> 0.0032379328 | C24: =(C19-C15)/C15 -> 0.068437254 | D24: =(D19-D15)/D15 -> 0.0770861 | E24: =(E19-E15)/E15 -> -0.0014384588 | F24: =(F19-F15)/F15 -> 0.029492044 | G24: =(G19-G15)/G15 -> 0.016389637 | N24: =(N19-N15)/N15 -> 0.032795054
A25: 26 Vs 24 | B25: =(B19-B11)/B11 -> -0.057524865 | C25: =(C19-C11)/C11 -> 0.050405635 | D25: =(D19-D11)/D11 -> 0.09107575 | E25: =(E19-E11)/E11 -> -0.10013185 | F25: =(F19-F11)/F11 -> -0.025855203 | G25: =(G19-G11)/G11 -> -0.049712827 | N25: =(N19-N11)/N11 -> -0.01613704
A26: FR
A27: 26 Vs 25 | B27: =(B21-B17)/B17 -> -0.061245084 | C27: =(C21-C17)/C17 -> 0.087226334 | D27: =(D21-D17)/D17 -> 0.050672458 | E27: =(E21-E17)/E17 -> -0.069127009 | F27: =(F21-F17)/F17 -> 0.031957819 | G27: =(G21-G17)/G17 -> -0.040497601 | N27: =(N21-N17)/N17 -> -0.0010700396
A28: 26 Vs 24 | B28: =(B22-B18)/B18 -> 0.078379535 | C28: =(C22-C18)/C18 -> -0.016854538 | D28: =(D22-D18)/D18 -> 0.018455241 | E28: =(E22-E18)/E18 -> 0.056617594 | F28: =(F22-F18)/F18 -> -0.0015950986 | G28: =(G22-G18)/G18 -> 0.042660008 | N28: =(N21-N13)/N13 -> -0.079622925
A29: Phuket Arrivals | B29: Jan | C29: Feb | D29: Mar | E29: Apr | F29: May | G29: Jun | H29: Jul | I29: Aug | J29: Sep | K29: Oct | L29: Nov | M29: Dec | N29: Total
A30: 2019 | B30: =SUM(B31:B32) -> 0 | C30: =SUM(C31:C32) -> 0 | D30: =SUM(D31:D32) -> 0 | E30: =SUM(E31:E32) -> 0 | F30: =SUM(F31:F32) -> 0 | G30: =SUM(G31:G32) -> 0 | H30: =SUM(H31:H32) -> 0 | I30: =SUM(I31:I32) -> 0 | ... M30: =SUM(M31:M32) -> 0 | N30: =SUM(B30:M30) -> 0
A31: - Domestics | N31: =SUM(B31:M31) -> 0
A32: - International | N32: =SUM(B32:M32) -> 0
A33: % Domestic | B33: =B31/B30 -> #DIV/0! | C33: =C31/C30 -> #DIV/0! | D33: =D31/D30 -> #DIV/0! | E33: =E31/E30 -> #DIV/0! | F33: =F31/F30 -> #DIV/0! | G33: =G31/G30 -> #DIV/0!
A34: 2023 | B34: =SUM(B35:B36) -> 985536 | C34: =SUM(C35:C36) -> 1037736 | D34: =SUM(D35:D36) -> 1065712 | E34: =SUM(E35:E36) -> 1057691 | F34: =SUM(F35:F36) -> 1053550 | G34: =SUM(G35:G36) -> 1021758 | N34: =SUM(B34:M34) -> 6221983
A35: - Domestics | B35: 313221 | C35: 315450 | D35: 332029 | E35: 258774 | F35: 310898 | G35: 277694 | N35: =SUM(B35:M35) -> 1808066
A36: - International | B36: 672315 | C36: 722286 | D36: 733683 | E36: 798917 | F36: 742652 | G36: 744064 | N36: =SUM(B36:M36) -> 4413917
A37: % Domestic | B37: =B35/B34 -> 0.31781792 | C37: =C35/C34 -> 0.30397905 | D37: =D35/D34 -> 0.31155603 | E37: =E35/E34 -> 0.24465936 | F37: =F35/F34 -> 0.29509563 | G37: =G35/G34 -> 0.2717806 | H37: =H35/H34 -> #DIV/0! | I37: =I35/I34 -> #DIV/0! | ... N37: =N35/N34 -> 0.29059321
A38: 2024 | B38: =SUM(B39:B40) -> 1213907 | C38: =SUM(C39:C40) -> 1245852 | D38: =SUM(D39:D40) -> 1178697 | E38: =SUM(E39:E40) -> 1216157 | F38: =SUM(F39:F40) -> 1143864 | G38: =SUM(G39:G40) -> 1207119 | N38: =SUM(B38:M38) -> 7205596
A39: - Domestics | B39: 287306 | C39: 340760 | D39: 350780 | E39: 295050 | F39: 278343 | G39: 327396 | N39: =SUM(B39:M39) -> 1879635
A40: - International | B40: 926601 | C40: 905092 | D40: 827917 | E40: 921107 | F40: 865521 | G40: 879723 | N40: =SUM(B40:M40) -> 5325961
A41: % Domestic | B41: =B39/B38 -> 0.23667876 | C41: =C39/C38 -> 0.27351563 | D41: =D39/D38 -> 0.29759981 | E41: =E39/E38 -> 0.24260848 | F41: =F39/F38 -> 0.24333575 | G41: =G39/G38 -> 0.27122098 | H41: =H39/H38 -> #DIV/0! | I41: =I39/I38 -> #DIV/0! | ... N41: =N39/N38 -> 0.26085767
A42: 2025 | B42: =SUM(B43:B44) -> 1330782 | C42: =SUM(C43:C44) -> 1263436 | D42: =SUM(D43:D44) -> 1150397 | E42: =SUM(E43:E44) -> 1174215 | F42: =SUM(F43:F44) -> 1118618 | G42: =SUM(G43:G44) -> 1046614 | H42: =SUM(H43:H44) -> 0 | I42: =SUM(I43:I44) -> 0 | ... M42: =SUM(M43:M44) -> 0 | N42: =SUM(B42:M42) -> 7084062
A43: - Domestics | B43: 264110 | C43: 329335 | D43: 355294 | E43: 307492 | F43: 301130 | G43: 320771 | N43: =SUM(B43:M43) -> 1878132
A44: - International | B44: 1066672 | C44: 934101 | D44: 795103 | E44: 866723 | F44: 817488 | G44: 725843 | N44: =SUM(B44:M44) -> 5205930
A45: % Domestic | B45: =B43/B42 -> 0.19846226 | C45: =C43/C42 -> 0.26066615 | D45: =D43/D42 -> 0.30884469 | E45: =E43/E42 -> 0.26187027 | F45: =F43/F42 -> 0.26919824 | G45: =G43/G42 -> 0.30648453 | H45: =H43/H42 -> #DIV/0! | I45: =I43/I42 -> #DIV/0! | ... N45: =N43/N42 -> 0.26512077
A46: 2026 | B46: =SUM(B47:B48) -> 1318929 | C46: =SUM(C47:C48) -> 1320701 | D46: =SUM(D47:D48) -> 1127519 | E46: =SUM(E47:E48) -> 1127817 | F46: =SUM(F47:F48) -> 1088322 | G46: =SUM(G47:G48) -> 979389 | H46: =SUM(H47:H48) -> 0 | I46: =SUM(I47:I48) -> 0 | ... M46: =SUM(M47:M48) -> 0 | N46: =SUM(B46:M46) -> 6962677
A47: - Domestics | B47: 276027 | C47: 384121 | D47: 344081 | E47: 300106 | F47: 292548 | G47: 306229 | N47: =SUM(B47:M47) -> 1903112
A48: - International | B48: 1042902 | C48: 936580 | D48: 783438 | E48: 827711 | F48: 795774 | G48: 673160 | N48: =SUM(B48:M48) -> 5059565
A49: % Domestic | B49: =B47/B46 -> 0.20928117 | C49: =C47/C46 -> 0.2908463 | D49: =D47/D46 -> 0.30516648 | E49: =E47/E46 -> 0.26609459 | F49: =F47/F46 -> 0.26880647 | G49: =G47/G46 -> 0.31267351 | H49: =H47/H46 -> #DIV/0! | I49: =I47/I46 -> #DIV/0! | ... N49: =N47/N46 -> 0.2733305
A50: 26 Vs 25 | B50: =(B46-B42)/B42 -> -0.0089067931 | C50: =(C46-C42)/C42 -> 0.045324813 | D50: =(D46-D42)/D42 -> -0.019887048 | E50: =(E46-E42)/E42 -> -0.039514058 | F50: =(F46-F42)/F42 -> -0.027083419 | G50: =(G46-G42)/G42 -> -0.064230939 | H50: =(H46-H42)/H42 -> #DIV/0! | I50: =(I46-I42)/I42 -> #DIV/0! | ... N50: =(N46-N42)/N42 -> -0.017134943
A51: 26 Vs 24 | B51: =(B46-B38)/B38 -> 0.086515689 | C51: =(C46-C38)/C38 -> 0.060078565 | D51: =(D46-D38)/D38 -> -0.043419131 | E51: =(E46-E38)/E38 -> -0.072638648 | F51: =(F46-F38)/F38 -> -0.048556472 | G51: =(G46-G38)/G38 -> -0.1886558 | H51: =(H46-H38)/H38 -> #DIV/0! | I51: =(I46-I38)/I38 -> #DIV/0! | ... N51: =(N46-N38)/N38 -> -0.033712548
A52: Pattaya (Chonburi) Arrival | B52: Jan | C52: Feb | D52: Mar | E52: Apr | F52: May | G52: Jun | H52: Jul | I52: Aug | J52: Sep | K52: Oct | L52: Nov | M52: Dec | N52: Total
A53: 2019 | B53: =SUM(B54:B55) -> 0 | C53: =SUM(C54:C55) -> 0 | D53: =SUM(D54:D55) -> 0 | E53: =SUM(E54:E55) -> 0 | F53: =SUM(F54:F55) -> 0 | G53: =SUM(G54:G55) -> 0 | H53: =SUM(H54:H55) -> 0 | I53: =SUM(I54:I55) -> 0 | ... M53: =SUM(M54:M55) -> 0 | N53: =SUM(B53:M53) -> 0
A54: - Domestics | N54: =SUM(B54:M54) -> 0
A55: - International | N55: =SUM(B55:M55) -> 0
A56: % Domestic | B56: =B54/B53 -> #DIV/0! | C56: =C54/C53 -> #DIV/0! | D56: =D54/D53 -> #DIV/0! | E56: =E54/E53 -> #DIV/0! | F56: =F54/F53 -> #DIV/0! | G56: =G54/G53 -> #DIV/0!
A57: 2023 | B57: =SUM(B58:B59) -> 2135864 | C57: =SUM(C58:C59) -> 1845288 | D57: =SUM(D58:D59) -> 1961835 | E57: =SUM(E58:E59) -> 1964973 | F57: =SUM(F58:F59) -> 1945847 | G57: =SUM(G58:G59) -> 1965559 | N57: =SUM(B57:M57) -> 11819366
A58: - Domestics | B58: 1388394 | C58: 1095770 | D58: 1129687 | E58: 1152479 | F58: 1184150 | G58: 1170560 | N58: =SUM(B58:M58) -> 7121040
A59: - International | B59: 747470 | C59: 749518 | D59: 832148 | E59: 812494 | F59: 761697 | G59: 794999 | N59: =SUM(B59:M59) -> 4698326
A60: % Domestic | B60: =B58/B57 -> 0.65003858 | C60: =C58/C57 -> 0.59382059 | D60: =D58/D57 -> 0.57583181 | E60: =E58/E57 -> 0.58651137 | F60: =F58/F57 -> 0.60855247 | G60: =G58/G57 -> 0.59553542 | H60: =H58/H57 -> #DIV/0! | I60: =I58/I57 -> #DIV/0! | ... N60: =N58/N57 -> 0.60248917
A61: 2024 | B61: =SUM(B62:B63) -> 2163066 | C61: =SUM(C62:C63) -> 2135992 | D61: =SUM(D62:D63) -> 2275036 | E61: =SUM(E62:E63) -> 2428315 | F61: =SUM(F62:F63) -> 2294207 | G61: =SUM(G62:G63) -> 2050297 | N61: =SUM(B61:M61) -> 13346913
A62: - Domestics | B62: 1143640 | C62: 1038036 | D62: 1230795 | E62: 1419211 | F62: 1437662 | G62: 1297317 | N62: =SUM(B62:M62) -> 7566661
A63: - International | B63: 1019426 | C63: 1097956 | D63: 1044241 | E63: 1009104 | F63: 856545 | G63: 752980 | N63: =SUM(B63:M63) -> 5780252
A64: % Domestic | B64: =B62/B61 -> 0.52871248 | C64: =C62/C61 -> 0.48597373 | D64: =D62/D61 -> 0.54100023 | E64: =E62/E61 -> 0.58444271 | F64: =F62/F61 -> 0.62664877 | G64: =G62/G61 -> 0.63274589 | H64: =H62/H61 -> #DIV/0! | I64: =I62/I61 -> #DIV/0! | ... N64: =N62/N61 -> 0.56692218
A65: 2025 | B65: =SUM(B66:B67) -> 2262654 | C65: =SUM(C66:C67) -> 2213324 | D65: =SUM(D66:D67) -> 2406473 | E65: =SUM(E66:E67) -> 2615454 | F65: =SUM(F66:F67) -> 2394099 | G65: =SUM(G66:G67) -> 1982886 | H65: =SUM(H66:H67) -> 0 | I65: =SUM(I66:I67) -> 0 | ... M65: =SUM(M66:M67) -> 0 | N65: =SUM(B65:M65) -> 13874890
A66: - Domestics | B66: 1185508 | C66: 1182365 | D66: 1376266 | E66: 1764642 | F66: 1651588 | G66: 1292830 | N66: =SUM(B66:M66) -> 8453199
A67: - International | B67: 1077146 | C67: 1030959 | D67: 1030207 | E67: 850812 | F67: 742511 | G67: 690056 | N67: =SUM(B67:M67) -> 5421691
A68: % Domestic | B68: =B66/B65 -> 0.52394577 | C68: =C66/C65 -> 0.53420331 | D68: =D66/D65 -> 0.5719017 | E68: =E66/E65 -> 0.67469816 | F68: =F66/F65 -> 0.68985785 | G68: =G66/G65 -> 0.65199411 | H68: =H66/H65 -> #DIV/0! | I68: =I66/I65 -> #DIV/0! | ... N68: =N66/N65 -> 0.6092444
A69: 2026 | B69: =SUM(B70:B71) -> 2128326 | C69: =SUM(C70:C71) -> 2212684 | D69: =SUM(D70:D71) -> 2264574 | E69: =SUM(E70:E71) -> 2570359 | F69: =SUM(F70:F71) -> 2355099 | G69: =SUM(G70:G71) -> 1975570 | H69: =SUM(H70:H71) -> 0 | I69: =SUM(I70:I71) -> 0 | ... M69: =SUM(M70:M71) -> 0 | N69: =SUM(B69:M69) -> 13506612
A70: - Domestics | B70: 1187042 | C70: 1131059 | D70: 1289860 | E70: 1829691 | F70: 1607296 | G70: 1331330 | N70: =SUM(B70:M70) -> 8376278
A71: - International | B71: 941284 | C71: 1081625 | D71: 974714 | E71: 740668 | F71: 747803 | G71: 644240 | N71: =SUM(B71:M71) -> 5130334
A72: % Domestic | B72: =B70/B69 -> 0.55773505 | C72: =C70/C69 -> 0.5111706 | D72: =D70/D69 -> 0.56958174 | E72: =E70/E69 -> 0.71184259 | F72: =F70/F69 -> 0.68247492 | G72: =G70/G69 -> 0.67389665 | H72: =H70/H69 -> #DIV/0! | I72: =I70/I69 -> #DIV/0! | ... N72: =N70/N69 -> 0.6201613
A73: 26 Vs 25 | B73: =(B69-B65)/B65 -> -0.059367451 | C73: =(C69-C65)/C65 -> -0.00028915785 | D73: =(D69-D65)/D65 -> -0.058965548 | E73: =(E69-E65)/E65 -> -0.017241748 | F73: =(F69-F65)/F65 -> -0.016290053 | G73: =(G69-G65)/G65 -> -0.0036895717 | H73: =(H69-H65)/H65 -> #DIV/0! | I73: =(I69-I65)/I65 -> #DIV/0! | ... N73: =(N69-N65)/N65 -> -0.026542769
A74: 26 Vs 24 | B74: =(B69-B61)/B61 -> -0.016060536 | C74: =(C69-C61)/C61 -> 0.035904629 | D74: =(D69-D61)/D61 -> -0.0045986085 | E74: =(E69-E61)/E61 -> 0.058494882 | F74: =(F69-F61)/F61 -> 0.026541633 | G74: =(G69-G61)/G61 -> -0.036446915 | H74: =(H69-H61)/H61 -> #DIV/0! | I74: =(I69-I61)/I61 -> #DIV/0! | ... N74: =(N69-N61)/N61 -> 0.011965239
E75: Thai school break | K75: Thai school break
A76: Source: MOTS provincial visitor statistics (ผู้เยี่ยมเยือน) — 2025+2026 Jan-Jun filled; Jan-Mar 2026 final (R), Apr-Jun preliminary (p). 2019/2024 await those year editions. Chonburi province = Pattaya per Mae.

Sheet Revenue from tourists
A1: Revenue from tourists (รายได้จากผู้เยี่ยมเยือน) — Unit: Million THB
A2: Sources: MOTS provincial files (2567 full year R; 2569 Jan-Jun, Apr-Jun preliminary; 2023/2025 from comparison columns). Domestics = คนไทย, International = ชาวต่างชาติ.
A4: Bangkok — Revenue (M THB) | B4: Jan | C4: Feb | D4: Mar | E4: Apr | F4: May | G4: Jun | H4: Jul | I4: Aug | J4: Sep | K4: Oct | L4: Nov | M4: Dec | N4: Total H1
A5: 2023 | B5: =SUM(B6:B7) -> 62268.22 | C5: =SUM(C6:C7) -> 61093.21 | D5: =SUM(D6:D7) -> 66985.44 | E5: =SUM(E6:E7) -> 71888.85 | F5: =SUM(F6:F7) -> 69251.24 | G5: =SUM(G6:G7) -> 70602.65 | H5: =SUM(H6:H7) -> 74164.51 | I5: =SUM(I6:I7) -> 77688.97 | ... M5: =SUM(M6:M7) -> 83453.61 | N5: =SUM(B5:G5) -> 402089.61
A6: - Domestics | B6: 15770.84 | C6: 14466.82 | D6: 17809.1 | E6: 26871.5 | F6: 26999.5 | G6: 23575 | H6: 19847.97 | I6: 23941.35 | J6: 24644.66 | K6: 20052.22 | L6: 23663.02 | M6: 23040.8 | N6: =SUM(B6:G6) -> 125492.76
A7: - International | B7: 46497.38 | C7: 46626.39 | D7: 49176.34 | E7: 45017.35 | F7: 42251.74 | G7: 47027.65 | H7: 54316.54 | I7: 53747.62 | J7: 47174.66 | K7: 49288.24 | L7: 54084.57 | M7: 60412.81 | N7: =SUM(B7:G7) -> 276596.85
A9: 2024 | B9: =SUM(B10:B11) -> 76337.8 | C9: =SUM(C10:C11) -> 75690.27 | D9: =SUM(D10:D11) -> 69629.78 | E9: =SUM(E10:E11) -> 78091.58 | F9: =SUM(F10:F11) -> 75436.91 | G9: =SUM(G10:G11) -> 75365.84 | H9: =SUM(H10:H11) -> 76227.34 | I9: =SUM(I10:I11) -> 79553.68 | ... M9: =SUM(M10:M11) -> 94961.52 | N9: =SUM(B9:G9) -> 450552.18
A10: - Domestics | B10: 17970.96 | C10: 14875.52 | D10: 15796.22 | E10: 26385.77 | F10: 26283.7 | G10: 23157.58 | H10: 21284.7 | I10: 25665.4 | J10: 25871.12 | K10: 26334.91 | L10: 22288.42 | M10: 26376.43 | N10: =SUM(B10:G10) -> 124469.75
A11: - International | B11: 58366.84 | C11: 60814.75 | D11: 53833.56 | E11: 51705.81 | F11: 49153.21 | G11: 52208.26 | H11: 54942.64 | I11: 53888.28 | J11: 47296.28 | K11: 56541.99 | L11: 62565.7 | M11: 68585.09 | N11: =SUM(B11:G11) -> 326082.43
A13: 2025 | B13: =SUM(B14:B15) -> 80528.28 | C13: =SUM(C14:C15) -> 73295.42 | D13: =SUM(D14:D15) -> 68009.64 | E13: =SUM(E14:E15) -> 69817.72 | F13: =SUM(F14:F15) -> 68165.71 | G13: =SUM(G14:G15) -> 66522.91 | H13: =SUM(H14:H15) -> 0 | I13: =SUM(I14:I15) -> 0 | ... M13: =SUM(M14:M15) -> 0 | N13: =SUM(B13:M13) -> 426339.68
A14: - Domestics | B14: 14785.79 | C14: 16307.35 | D14: 18165.02 | E14: 23281.21 | F14: 26280.24 | G14: 23555.64 | N14: =SUM(B14:M14) -> 122375.25
A15: - International | B15: 65742.49 | C15: 56988.07 | D15: 49844.62 | E15: 46536.51 | F15: 41885.47 | G15: 42967.27 | N15: =SUM(B15:M15) -> 303964.43
A17: 2026 | B17: =SUM(B18:B19) -> 81187.82 | C17: =SUM(C18:C19) -> 82589.18 | D17: =SUM(D18:D19) -> 75954.22 | E17: =SUM(E18:E19) -> 67596.95 | F17: =SUM(F18:F19) -> 71100.04 | G17: =SUM(G18:G19) -> 66406.77 | H17: =SUM(H18:H19) -> 0 | I17: =SUM(I18:I19) -> 0 | ... M17: =SUM(M18:M19) -> 0 | N17: =SUM(B17:M17) -> 444834.98
A18: - Domestics | B18: 17051.47 | C18: 18200.47 | D18: 21530.13 | E18: 24277.37 | F18: 27127.32 | G18: 25179.56 | N18: =SUM(B18:M18) -> 133366.32
A19: - International | B19: 64136.35 | C19: 64388.71 | D19: 54424.09 | E19: 43319.58 | F19: 43972.72 | G19: 41227.21 | N19: =SUM(B19:M19) -> 311468.66
A20: Total | N20: =SUM(B20:M20) -> 0
A21: 26 Vs 25 | B21: =(B17-B13)/B13 -> 0.0081901662 | C21: =(C17-C13)/C13 -> 0.12679865 | D21: =(D17-D13)/D13 -> 0.1168155 | E21: =(E17-E13)/E13 -> -0.031808114 | F21: =(F17-F13)/F13 -> 0.04304701 | G21: =(G17-G13)/G13 -> -0.0017458647 | H21: =(H17-H13)/H13 -> #DIV/0! | I21: =(I17-I13)/I13 -> #DIV/0! | ... N21: =(N17-N13)/N13 -> 0.043381606
A22: 26 Vs 24 | B22: =(B17-B9)/B9 -> 0.063533662 | C22: =(C17-C9)/C9 -> 0.09114659 | D22: =(D17-D9)/D9 -> 0.090829527 | E22: =(E17-E9)/E9 -> -0.13438875 | F22: =(F17-F9)/F9 -> -0.057490027 | G22: =(G17-G9)/G9 -> -0.11887441 | H22: =(H17-H9)/H9 -> -1 | I22: =(I17-I9)/I9 -> -1 | ... N22: =(N17-N9)/N9 -> -0.012689318
A23: FR
A24: 26 Vs 25 | B24: =(B19-B15)/B15 -> -0.024430775 | C24: =(C19-C15)/C15 -> 0.12986297 | D24: =(D19-D15)/D15 -> 0.09187491 | E24: =(E19-E15)/E15 -> -0.069127014 | F24: =(F19-F15)/F15 -> 0.049832317 | G24: =(G19-G15)/G15 -> -0.040497337 | H24: =(H19-H15)/H15 -> #DIV/0! | I24: =(I19-I15)/I15 -> #DIV/0! | ... N24: =(N19-N15)/N15 -> 0.024687856
A25: 26 Vs 24 | B25: =(B19-B11)/B11 -> 0.098849107 | C25: =(C19-C11)/C11 -> 0.05876798 | D25: =(D19-D11)/D11 -> 0.010969551 | E25: =(E19-E11)/E11 -> -0.16219125 | F25: =(F19-F11)/F11 -> -0.10539474 | G25: =(G19-G11)/G11 -> -0.21033166 | H25: =(H19-H11)/H11 -> -1 | I25: =(I19-I11)/I11 -> -1 | ... N25: =(N19-N11)/N11 -> -0.044816183
A27: Phuket — Revenue (M THB) | B27: Jan | C27: Feb | D27: Mar | E27: Apr | F27: May | G27: Jun | H27: Jul | I27: Aug | J27: Sep | K27: Oct | L27: Nov | M27: Dec | N27: Total H1
A28: 2023 | B28: =SUM(B29:B30) -> 35079.46 | C28: =SUM(C29:C30) -> 37473.77 | D28: =SUM(D29:D30) -> 38182.51 | E28: =SUM(E29:E30) -> 40097.87 | F28: =SUM(F29:F30) -> 37997.65 | G28: =SUM(G29:G30) -> 37722.24 | H28: =SUM(H29:H30) -> 34992.61 | I28: =SUM(I29:I30) -> 35473.95 | ... M28: =SUM(M29:M30) -> 42943.55 | N28: =SUM(B28:G28) -> 226553.5
A29: - Domestics | B29: 3170.01 | C29: 3192.57 | D29: 3360.38 | E29: 2662.25 | F29: 3198.5 | G29: 2856.93 | H29: 4158.41 | I29: 3303.29 | J29: 3316.68 | K29: 2772.87 | L29: 2375.54 | M29: 2680.09 | N29: =SUM(B29:G29) -> 18440.64
A30: - International | B30: 31909.45 | C30: 34281.2 | D30: 34822.13 | E30: 37435.62 | F30: 34799.15 | G30: 34865.31 | H30: 30834.2 | I30: 32170.66 | J30: 31032.38 | K30: 31263.75 | L30: 35973.35 | M30: 40263.46 | N30: =SUM(B30:G30) -> 208112.86
A32: 2024 | B32: =SUM(B33:B34) -> 47181.35 | C32: =SUM(C33:C34) -> 46675.69 | D32: =SUM(D33:D34) -> 43079 | E32: =SUM(E33:E34) -> 47407.14 | F32: =SUM(F33:F34) -> 44558.89 | G32: =SUM(G33:G34) -> 45801.04 | H32: =SUM(H33:H34) -> 49662.21 | I32: =SUM(I33:I34) -> 50112.01 | ... M32: =SUM(M33:M34) -> 54163.01 | N32: =SUM(B32:G32) -> 274703.11
A33: - Domestics | B33: 2817.32 | C33: 3341.5 | D33: 3439.77 | E33: 3389.21 | F33: 3197.3 | G33: 3760.78 | H33: 2729.67 | I33: 3492.08 | J33: 3289.08 | K33: 2946.59 | L33: 2925.56 | M33: 3304 | N33: =SUM(B33:G33) -> 19945.88
A34: - International | B34: 44364.03 | C34: 43334.19 | D34: 39639.23 | E34: 44017.93 | F34: 41361.59 | G34: 42040.26 | H34: 46932.54 | I34: 46619.93 | J34: 44392.01 | K34: 40421.6 | L34: 48934.82 | M34: 50859.01 | N34: =SUM(B34:G34) -> 254757.23
A36: 2025 | B36: =SUM(B37:B38) -> 52118.13 | C36: =SUM(C37:C38) -> 46590.59 | D36: =SUM(D37:D38) -> 40383.97 | E36: =SUM(E37:E38) -> 44919.2 | F36: =SUM(F37:F38) -> 42495.6 | G36: =SUM(G37:G38) -> 38347.38 | H36: =SUM(H37:H38) -> 0 | I36: =SUM(I37:I38) -> 0 | ... M36: =SUM(M37:M38) -> 0 | N36: =SUM(B36:M36) -> 264854.87
A37: - Domestics | B37: 2558.73 | C37: 3190.64 | D37: 3442.14 | E37: 3546.28 | F37: 3472.9 | G37: 3699.41 | N37: =SUM(B37:M37) -> 19910.1
A38: - International | B38: 49559.4 | C38: 43399.95 | D38: 36941.83 | E38: 41372.92 | F38: 39022.7 | G38: 34647.97 | N38: =SUM(B38:M38) -> 244944.77
A40: 2026 | B40: =SUM(B41:B42) -> 52806.72 | C40: =SUM(C41:C42) -> 48806.02 | D40: =SUM(D41:D42) -> 41056.8 | E40: =SUM(E41:E42) -> 43280.8 | F40: =SUM(F41:F42) -> 41391.37 | G40: =SUM(G41:G42) -> 35664.93 | H40: =SUM(H41:H42) -> 0 | I40: =SUM(I41:I42) -> 0 | ... M40: =SUM(M41:M42) -> 0 | N40: =SUM(B40:M40) -> 263006.64
A41: - Domestics | B41: 2801.91 | C41: 3899.15 | D41: 3492.74 | E41: 3442.17 | F41: 3397.06 | G41: 3531.71 | N41: =SUM(B41:M41) -> 20564.74
A42: - International | B42: 50004.81 | C42: 44906.87 | D42: 37564.06 | E42: 39838.63 | F42: 37994.31 | G42: 32133.22 | N42: =SUM(B42:M42) -> 242441.9
A44: 26 Vs 25 | B44: =(B40-B36)/B36 -> 0.013212101 | C44: =(C40-C36)/C36 -> 0.047551018 | D44: =(D40-D36)/D36 -> 0.016660819 | E44: =(E40-E36)/E36 -> -0.036474381 | F44: =(F40-F36)/F36 -> -0.025984573 | G44: =(G40-G36)/G36 -> -0.069951324 | H44: =(H40-H36)/H36 -> #DIV/0! | I44: =(I40-I36)/I36 -> #DIV/0! | ... N44: =(N40-N36)/N36 -> -0.0069782746
A45: 26 Vs 24 | B45: =(B40-B32)/B32 -> 0.11922868 | C45: =(C40-C32)/C32 -> 0.045641104 | D45: =(D40-D32)/D32 -> -0.046941665 | E45: =(E40-E32)/E32 -> -0.087040475 | F45: =(F40-F32)/F32 -> -0.071086151 | G45: =(G40-G32)/G32 -> -0.22130742 | H45: =(H40-H32)/H32 -> -1 | I45: =(I40-I32)/I32 -> -1 | ... N45: =(N40-N32)/N32 -> -0.042578586
A47: Pattaya (Chonburi) — Revenue (M THB) | B47: Jan | C47: Feb | D47: Mar | E47: Apr | F47: May | G47: Jun | H47: Jul | I47: Aug | J47: Sep | K47: Oct | L47: Nov | M47: Dec | N47: Total H1
A48: 2023 | B48: =SUM(B49:B50) -> 23573.74 | C48: =SUM(C49:C50) -> 21957.42 | D48: =SUM(D49:D50) -> 23829.65 | E48: =SUM(E49:E50) -> 26601.37 | F48: =SUM(F49:F50) -> 25593.29 | G48: =SUM(G49:G50) -> 26346.06 | H48: =SUM(H49:H50) -> 24220.4 | I48: =SUM(I49:I50) -> 25372.71 | ... M48: =SUM(M49:M50) -> 28670.04 | N48: =SUM(B48:G48) -> 147901.53
A49: - Domestics | B49: 7872.94 | C49: 6213.61 | D49: 6405.91 | E49: 7278.19 | F49: 7478.2 | G49: 7392.38 | H49: 5235.32 | I49: 7579.15 | J49: 5667.97 | K49: 7974.47 | L49: 9197.75 | M49: 10307.82 | N49: =SUM(B49:G49) -> 42641.23
A50: - International | B50: 15700.8 | C50: 15743.81 | D50: 17423.74 | E50: 19323.18 | F50: 18115.09 | G50: 18953.68 | H50: 18985.08 | I50: 17793.56 | J50: 17243.37 | K50: 15304.05 | L50: 16418.89 | M50: 18362.22 | N50: =SUM(B50:G50) -> 105260.3
A52: 2024 | B52: =SUM(B53:B54) -> 28931.9 | C52: =SUM(C53:C54) -> 29971.71 | D52: =SUM(D53:D54) -> 30065.13 | E52: =SUM(E53:E54) -> 31887.37 | F52: =SUM(F53:F54) -> 28596.67 | G52: =SUM(G53:G54) -> 25389.26 | H52: =SUM(H53:H54) -> 27711.95 | I52: =SUM(I53:I54) -> 26622.25 | ... M52: =SUM(M53:M54) -> 31014 | N52: =SUM(B52:G52) -> 174842.04
A53: - Domestics | B53: 7019.43 | C53: 6371.26 | D53: 7554.39 | E53: 9319.56 | F53: 9440.73 | G53: 8519.12 | H53: 7727.16 | I53: 9040.52 | J53: 8759.33 | K53: 9175.89 | L53: 9982.35 | M53: 10983.61 | N53: =SUM(B53:G53) -> 48224.49
A54: - International | B54: 21912.47 | C54: 23600.45 | D54: 22510.74 | E54: 22567.81 | F54: 19155.94 | G54: 16870.14 | H54: 19984.79 | I54: 17581.73 | J54: 18200.77 | K54: 18212.67 | L54: 18781.89 | M54: 20030.39 | N54: =SUM(B54:G54) -> 126617.55
A56: 2025 | B56: =SUM(B57:B58) -> 30954.8 | C56: =SUM(C57:C58) -> 29944.71 | D56: =SUM(D57:D58) -> 31249.08 | E56: =SUM(E57:E58) -> 31231.8 | F56: =SUM(F57:F58) -> 28022.49 | G56: =SUM(G57:G58) -> 24380.34 | H56: =SUM(H57:H58) -> 0 | I56: =SUM(I57:I58) -> 0 | ... M56: =SUM(M57:M58) -> 0 | N56: =SUM(B56:M56) -> 175783.22
A57: - Domestics | B57: 7885.24 | C57: 7864.34 | D57: 9154.08 | E57: 12119.08 | F57: 11342.65 | G57: 8878.83 | N57: =SUM(B57:M57) -> 57244.22
A58: - International | B58: 23069.56 | C58: 22080.37 | D58: 22095 | E58: 19112.72 | F58: 16679.84 | G58: 15501.51 | N58: =SUM(B58:M58) -> 118539
A60: 2026 | B60: =SUM(B61:B62) -> 28627.09 | C60: =SUM(C61:C62) -> 31340.47 | D60: =SUM(D61:D62) -> 30100.95 | E60: =SUM(E61:E62) -> 28521.54 | F60: =SUM(F61:F62) -> 28016.04 | G60: =SUM(G61:G62) -> 23555.35 | H60: =SUM(H61:H62) -> 0 | I60: =SUM(I61:I62) -> 0 | ... M60: =SUM(M61:M62) -> 0 | N60: =SUM(B60:M60) -> 170161.44
A61: - Domestics | B61: 7922.19 | C61: 7548.57 | D61: 8608.43 | E61: 12581.91 | F61: 11105.26 | G61: 9072.81 | N61: =SUM(B61:M61) -> 56839.17
A62: - International | B62: 20704.9 | C62: 23791.9 | D62: 21492.52 | E62: 15939.63 | F62: 16910.78 | G62: 14482.54 | N62: =SUM(B62:M62) -> 113322.27
A64: 26 Vs 25 | B64: =(B60-B56)/B56 -> -0.075197062 | C64: =(C60-C56)/C56 -> 0.046611238 | D64: =(D60-D56)/D56 -> -0.036741242 | E64: =(E60-E56)/E56 -> -0.08677886 | F64: =(F60-F56)/F56 -> -0.00023017227 | G64: =(G60-G56)/G56 -> -0.03383833 | H64: =(H60-H56)/H56 -> #DIV/0! | I64: =(I60-I56)/I56 -> #DIV/0! | ... N64: =(N60-N56)/N56 -> -0.031981323
A65: 26 Vs 24 | B65: =(B60-B52)/B52 -> -0.01053543 | C65: =(C60-C52)/C52 -> 0.045668399 | D65: =(D60-D52)/D52 -> 0.0011914134 | E65: =(E60-E52)/E52 -> -0.1055537 | F65: =(F60-F52)/F52 -> -0.020304112 | G65: =(G60-G52)/G52 -> -0.072231723 | H65: =(H60-H52)/H52 -> -1 | I65: =(I60-I52)/I52 -> -1 | ... N65: =(N60-N52)/N52 -> -0.026770449

Sheet Arrival
B2: AOT Data | C2: Jan | D2: Feb | E2: Mar | F2: Apr | G2: May | H2: Jun | I2: Jul | J2: Aug | K2: Sep | L2: Oct | M2: Nov | N2: Dec | O2: Total
B3: 2019 | C3: 3212983 | D3: 2926838 | E3: 3068856 | F3: 2992203 | G3: 2557618 | H3: 2684801 | I3: 2994417 | J3: 2996390 | K3: 2614898 | L3: 2933784 | M3: 3029088 | N3: 3350162 | O3: =SUM(C3:N3) -> 35362038
B4: 2020 | C4: 3255085 | D4: 1852474 | E4: 657642 | F4: 5087 | G4: 10685 | H4: 14554 | I4: 16412 | J4: 20088 | K4: 21125 | L4: 27851 | M4: 26572 | N4: 32311 | O4: =SUM(C4:N4) -> 5939886
B5: 2021 | C5: 30109 | D5: 24173 | E5: 30565 | F5: 29724 | G5: 23817 | H5: 23615 | I5: 22203 | J5: 18553 | K5: 24136 | L5: 31981 | M5: 102542 | N5: 217200 | O5: =SUM(C5:N5) -> 578618
B6: 2022 | C6: 107583 | D6: 129306 | E6: 219933 | F6: 361849 | G6: 567679 | H6: 767075 | I6: 1044613 | J6: 1114039 | K6: 1123351 | L6: 1375723 | M6: 1552954 | N6: 1877245 | O6: =SUM(C6:N6) -> 10241350 | Q6: No | R6: 2019 | V6: No | W6: 2022 | AA6: No | AB6: 2023 | AF6: No | AG6: 2024 | AK6: No | AL6: 2025 | AP6: No | AQ6: 2026 (Jan-May) | AU6: No | AV6: 44652 | AY6: 44682 | BB6: 44713 | BE6: 44743 | BH6: 44774 | BK6: 44805 | BN6: 44835 | BQ6: 44866 | BT6: 44896
B7: 19 vs 22 % | C7: =C6/C3 -> 0.033483837 | D7: =D6/D3 -> 0.044179418 | E7: =E6/E3 -> 0.071666119 | F7: =F6/F3 -> 0.12093063 | G7: =G6/G3 -> 0.22195613 | H7: =H6/H3 -> 0.28571019 | I7: =I6/I3 -> 0.34885355 | J7: =J6/J3 -> 0.37179373 | ... O7: =O6/O3 -> 0.28961425 | R7: Nationality | S7: Number | T7: % | W7: Nationality | X7: Number | Y7: % | AB7: Nationality | AC7: Number | AD7: % | AG7: Nationality | AH7: Number | AI7: % | AL7: Nationality | AM7: Number | AN7: % | AQ7: Nationality | AR7: Number | AS7: % | AV7: Nationality | AW7: Number | AX7: % | AY7: Nationality | AZ7: Number | BA7: % | BB7: Nationality | BC7: Number | BD7: % | BE7: Nationality | BF7: Number | BG7: % | BH7: Nationality | BI7: Number | BJ7: % | BK7: Nationality | BL7: Number | BM7: % | BN7: Nationality | BO7: Number | BP7: % | BQ7: Nationality | BR7: Number | BS7: % | BT7: Nationality | BU7: Number | BV7: %
B8: 2023 | C8: 1852179 | D8: 1760744 | E8: 1951234 | F8: 1993717 | G8: 1902761 | H8: 1985941 | I8: 2223052 | J8: 2156970 | K8: 1946206 | L8: 2200260 | M8: 2315423 | N8: 2678220 | O8: =SUM(C8:N8) -> 24966707 | Q8: 1 | R8: China | S8: 10997338 | T8: =S8/$S$56 -> 0.27551029 | V8: 1 | W8: Malaysia | X8: 1949530 | Y8: =X8/$X$56 -> 0.17618529 | AA8: 1 | AB8: Malaysia | AC8: 4626422 | AD8: =AC8/$AC$56 -> 0.16434882 | AF8: 1 | AG8: China | AH8: 6733162 | AI8: =AH8/$AH$56 -> 0.18942261 | AK8: 1 | AL8: Malaysia | AM8: 4520856 | AN8: =AM8/AM$56 -> 0.13710232 | AP8: 1 | AQ8: China | AR8: 2318312 | AS8: =AR8/AR$56 -> 0.16520844 | AU8: 1 | AV8: UK | AW8: 29647 | AX8: =AW8/$AW$20 -> 0.10106358 | AY8: India | AZ8: 78286 | BA8: 0.15014288 | BB8: Malaysia | BC8: 124211 | BD8: =BC8/$BC$20 -> 0.16183907 | BE8: Malaysia | BF8: 220554 | BG8: =BF8/$BF$20 -> 0.1961828 | BH8: Malaysia | BI8: 221166 | BJ8: =BI8/$BI$20 -> 0.18826756 | BK8: Malaysia | BL8: 332493 | BM8: =BL8/$BL$20 -> 0.25398303 | BN8: Malaysia | BO8: 316537 | BP8: =BO8/$BO$20 -> 0.21453881 | BQ8: Malaysia | BR8: 258873 | BS8: =BR8/$BR$20 -> 0.14806568 | BT8: Malaysia | BU8: 398295 | BV8: =BU8/$BU$20 -> 0.17771546
B9: 19 vs 23 % | C9: =C8/C3 -> 0.5764671 | D9: =D8/D3 -> 0.60158574 | E9: =E8/E3 -> 0.63581804 | F9: =F8/F3 -> 0.66630406 | G9: =G8/G3 -> 0.74395825 | H9: =H8/H3 -> 0.73969765 | I9: =I8/I3 -> 0.74239894 | J9: =J8/J3 -> 0.71985623 | ... O9: =O8/O3 -> 0.70603134 | Q9: 2 | R9: Malaysia | S9: 4265574 | T9: =S9/$S$56 -> 0.10686309 | V9: 2 | W9: India | X9: 980281 | Y9: =X9/$X$56 -> 0.088591141 | AA9: 2 | AB9: China | AC9: 3521095 | AD9: =AC9/$AC$56 -> 0.12508323 | AF9: 2 | AG9: Malaysia | AH9: 4952078 | AI9: =AH9/$AH$56 -> 0.13931576 | AK9: 2 | AL9: China | AM9: 4473992 | AN9: =AM9/AM$56 -> 0.1356811 | AP9: 2 | AQ9: Malaysia | AR9: 1737938 | AS9: =AR9/AR$56 -> 0.1238496 | AU9: 2 | AV9: India | AW9: 27309 | AX9: =AW9/$AW$20 -> 0.093093574 | AY9: Malaysia | AZ9: 57869 | BA9: 0.1109856 | BB9: India | BC9: 113394 | BD9: =BC9/$BC$20 -> 0.1477452 | BE9: India | BF9: 106139 | BG9: =BF9/$BF$20 -> 0.094410648 | BH9: India | BI9: 113769 | BJ9: =BI9/$BI$20 -> 0.096845863 | BK9: India | BL9: 116386 | BM9: =BL9/$BL$20 -> 0.088904336 | BN9: India | BO9: 126606 | BP9: =BO9/$BO$20 -> 0.085809561 | BQ9: India | BR9: 145628 | BS9: =BR9/$BR$20 -> 0.083293773 | BT9: Russia | BU9: 178324 | BV9: =BU9/$BU$20 -> 0.079566481
B10: 2024 | C10: 2647669 | D10: 2625441 | E10: 2682018 | F10: 2607071 | G10: 2404729 | H10: 2411407 | I10: 2707169 | J10: 2558599 | K10: 2240979 | L10: 2633579 | M10: 2865879 | N10: 3242340 | O10: =SUM(C10:N10) -> 31626880 | Q10: 3 | R10: India | S10: 1996842 | T10: =S10/$S$56 -> 0.05002579 | V10: 3 | W10: Singapore | X10: 610169 | Y10: =X10/$X$56 -> 0.055142932 | AA10: 3 | AB10: Korea | AC10: 1660042 | AD10: =AC10/$AC$56 -> 0.058971263 | AF10: 3 | AG10: India | AH10: 2129149 | AI10: =AH10/$AH$56 -> 0.059898895 | AK10: 3 | AL10: India | AM10: 2487319 | AN10: =AM10/AM$56 -> 0.075432001 | AP10: 3 | AQ10: India | AR10: 1056729 | AS10: =AR10/AR$56 -> 0.075305026 | AU10: 3 | AV10: Germany | AW10: 19769 | AX10: =AW10/$AW$20 -> 0.067390489 | AY10: Singapore | AZ10: 38032 | BA10: 0.07294068 | BB10: Singapore | BC10: 60165 | BD10: =BC10/$BC$20 -> 0.078391186 | BE10: Vietnam | BF10: 60981 | BG10: =BF10/$BF$20 -> 0.054242604 | BH10: Vietnam | BI10: 73897 | BJ10: =BI10/$BI$20 -> 0.062904823 | BK10: Laos | BL10: 83891 | BM10: =BL10/$BL$20 -> 0.064082223 | BN10: Laos | BO10: 86591 | BP10: =BO10/$BO$20 -> 0.058688653 | BQ10: Russia | BR10: 108985 | BS10: =BR10/$BR$20 -> 0.062335346 | BT10: India | BU10: 153528 | BV10: =BU10/$BU$20 -> 0.068502741
B11: 19 vs 24 % | C11: =C10/C3 -> 0.82405322 | D11: =D10/D3 -> 0.897023 | E11: =E10/E3 -> 0.87394716 | F11: =F10/F3 -> 0.87128814 | G11: =G10/G3 -> 0.94022211 | H11: =H10/H3 -> 0.89816973 | I11: =I10/I3 -> 0.90407214 | J11: =J10/J3 -> 0.85389385 | ... O11: =O10/O3 -> 0.89437379 | Q11: 4 | R11: Korea | S11: 1890973 | T11: =S11/$S$56 -> 0.047373512 | V11: 4 | W11: Korea | X11: 531685 | Y11: =X11/$X$56 -> 0.04805008 | AA11: 4 | AB11: India | AC11: 1628542 | AD11: =AC11/$AC$56 -> 0.057852258 | AF11: 4 | AG11: Korea | AH11: 1868945 | AI11: =AH11/$AH$56 -> 0.052578632 | AK11: 4 | AL11: Russian Federation | AM11: 1898837 | AN11: =AM11/AM$56 -> 0.057585325 | AP11: 4 | AQ11: Russian Federation | AR11: 946732 | AS11: =AR11/AR$56 -> 0.067466378 | AU11: 4 | AV11: Singapore | AW11: 17943 | AX11: =AW11/$AW$20 -> 0.061165843 | AY11: Cambodia | AZ11: 25255 | BA11: 0.048435972 | BB11: Vietnam | BC11: 40832 | BD11: =BC11/$BC$20 -> 0.053201511 | BE11: Korea | BF11: 59226 | BG11: =BF11/$BF$20 -> 0.052681531 | BH11: Laos | BI11: 72419 | BJ11: =BI11/$BI$20 -> 0.061646675 | BK11: Singapore | BL11: 69957 | BM11: =BL11/$BL$20 -> 0.053438392 | BN11: Korea | BO11: 73225 | BP11: =BO11/$BO$20 -> 0.0496296 | BQ11: Singapore | BR11: 101203 | BS11: =BR11/$BR$20 -> 0.057884333 | BT11: Singapore | BU11: 131484 | BV11: =BU11/$BU$20 -> 0.058666917
B12: 2025 | C12: 3153058 | D12: 2644682 | E12: 2577224 | F12: 2606253 | G12: 2271028 | H12: 2215178 | I12: 2512117 | J12: 2424308 | K12: 2217271 | L12: 2687230 | M12: 2811736 | N12: 3205968 | O12: =SUM(C12:N12) -> 31326053 | Q12: 5 | R12: Laos | S12: 1854792 | T12: =S12/$S$56 -> 0.046467089 | V12: 5 | W12: Laos | X12: 487215 | Y12: =X12/$X$56 -> 0.044031184 | AA12: 5 | AB12: Russia | AC12: 1482611 | AD12: =AC12/$AC$56 -> 0.052668212 | AF12: 5 | AG12: Russia | AH12: 1745327 | AI12: =AH12/$AH$56 -> 0.049100913 | AK12: 5 | AL12: Korea (Republic of) | AM12: 1555227 | AN12: =AM12/AM$56 -> 0.047164792 | AP12: 5 | AQ12: Korea (Republic of) | AR12: 539848 | AS12: =AR12/AR$56 -> 0.038470855 | AU12: 5 | AV12: Australia | AW12: 17182 | AX12: =AW12/$AW$20 -> 0.058571672 | AY12: USA | AZ12: 24333 | BA12: 0.04666769 | BB12: USA | BC12: 34430 | BD12: =BC12/$BC$20 -> 0.04486011 | BE12: Singapore | BF12: 56673 | BG12: =BF12/$BF$20 -> 0.050410638 | BH12: Korea | BI12: 66573 | BJ12: =BI12/$BI$20 -> 0.056670267 | BK12: Vietnam | BL12: 64559 | BM12: =BL12/$BL$20 -> 0.049314995 | BN12: Vietnam | BO12: 71228 | BP12: =BO12/$BO$20 -> 0.048276096 | BQ12: Korea | BR12: 92009 | BS12: =BR12/$BR$20 -> 0.052625709 | BT12: Korea | BU12: 130517 | BV12: =BU12/$BU$20 -> 0.05823545
B13: 19 vs 25 % | C13: =C12/C3 -> 0.98134911 | D13: =D12/D3 -> 0.90359699 | E13: =E12/E3 -> 0.83979959 | F13: =F12/F3 -> 0.87101477 | G13: =G12/G3 -> 0.88794652 | H13: =H12/H3 -> 0.82508089 | I13: =I12/I3 -> 0.83893359 | J13: =J12/J3 -> 0.80907626 | ... O13: =O12/O3 -> 0.88586673 | Q13: 6 | R13: Japan | S13: 1806438 | T13: =S13/$S$56 -> 0.045255703 | V13: 6 | W13: Cambodia | X13: 464141 | Y13: =X13/$X$56 -> 0.041945912 | AA13: 6 | AB13: Vietnam | AC13: 1033688 | AD13: =AC13/$AC$56 -> 0.03672069 | AF13: 6 | AG13: Laos | AH13: 1124202 | AI13: =AH13/$AH$56 -> 0.031626935 | AK13: 6 | AL13: Japan | AM13: 1091227 | AN13: =AM13/AM$56 -> 0.033093236 | AP13: 6 | AQ13: United Kingdom | AR13: 497589 | AS13: =AR13/AR$56 -> 0.035459378 | AU13: 6 | AV13: USA | AW13: 17116 | AX13: =AW13/$AW$20 -> 0.058346685 | AY13: UK | AZ13: 23739 | BA13: 0.045528471 | BB13: Laos | BC13: 31304 | BD13: =BC13/$BC$20 -> 0.04078713 | BE13: Cambodia | BF13: 51841 | BG13: =BF13/$BF$20 -> 0.046112573 | BH13: Singapore | BI13: 58930 | BJ13: =BI13/$BI$20 -> 0.050164164 | BK13: Korea | BL13: 58552 | BM13: =BL13/$BL$20 -> 0.044726399 | BN13: Singapore | BO13: 68148 | BP13: =BO13/$BO$20 -> 0.046188569 | BQ13: USA | BR13: 79624 | BS13: =BR13/$BR$20 -> 0.045541952 | BT13: USA | BU13: 90843 | BV13: =BU13/$BU$20 -> 0.040533287
B14: 2026 | C14: 3099420 | D14: 2830997 | E14: 2850123 | F14: 2632415 | G14: 2103393 | O14: =SUM(C14:N14) -> 13516348 | Q14: 7 | R14: Russia | S14: 1483337 | T14: =S14/$S$56 -> 0.03716123 | V14: 7 | W14: Vietnam | X14: 458789 | Y14: =X14/$X$56 -> 0.041462235 | AA14: 7 | AB14: Singapore | AC14: 1027424 | AD14: =AC14/$AC$56 -> 0.036498168 | AF14: 7 | AG14: Taiwan | AH14: 1089910 | AI14: =AH14/$AH$56 -> 0.030662206 | AK14: 7 | AL14: United Kingdom | AM14: 1083162 | AN14: =AM14/AM$56 -> 0.032848652 | AP14: 7 | AQ14: United States of America | AR14: 471254 | AS14: =AR14/AR$56 -> 0.033582683 | AU14: 5 | AV14: Australia | AW14: 17182 | AX14: =AW14/$AW$20 -> 0.058571672 | AY14: USA | AZ14: 24333 | BA14: 0.04666769 | BB14: USA | BC14: 34430 | BD14: =BC14/$BC$20 -> 0.04486011 | BE14: Singapore | BF14: 56673 | BG14: =BF14/$BF$20 -> 0.050410638 | BH14: Korea | BI14: 66573 | BJ14: =BI14/$BI$20 -> 0.056670267 | BK14: Vietnam | BL14: 64559 | BM14: =BL14/$BL$20 -> 0.049314995 | BN14: Vietnam | BO14: 71228 | BP14: =BO14/$BO$20 -> 0.048276096 | BQ14: Korea | BR14: 92009 | BS14: =BR14/$BR$20 -> 0.052625709 | BT14: Korea | BU14: 130517 | BV14: =BU14/$BU$20 -> 0.05823545
B15: 19 vs 26 % | C15: =C14/C3 -> 0.96465496 | D15: =D14/D3 -> 0.96725442 | E15: =E14/E3 -> 0.92872491 | F15: =F14/F3 -> 0.87975816 | G15: =G14/G3 -> 0.82240311 | H15: =H14/H3 -> 0 | I15: =I14/I3 -> 0 | J15: =J14/J3 -> 0 | ... O15: =O14/O3 -> 0.38222763 | Q15: 8 | R15: USA | S15: 1165950 | T15: =S15/$S$56 -> 0.029209908 | V15: 8 | W15: USA | X15: 437409 | Y15: =X15/$X$56 -> 0.039530056 | AA15: 8 | AB15: USA | AC15: 930206 | AD15: =AC15/$AC$56 -> 0.033044599 | AF15: 8 | AG15: Japan | AH15: 1050904 | AI15: =AH15/$AH$56 -> 0.029564858 | AK15: 8 | AL15: The United States of America | AM15: 1081929 | AN15: =AM15/AM$56 -> 0.032811259 | AP15: 8 | AQ15: Germany | AR15: 449076 | AS15: =AR15/AR$56 -> 0.032002226 | AU15: 6 | AV15: USA | AW15: 17116 | AX15: =AW15/$AW$20 -> 0.058346685 | AY15: UK | AZ15: 23739 | BA15: 0.045528471 | BB15: Laos | BC15: 31304 | BD15: =BC15/$BC$20 -> 0.04078713 | BE15: Cambodia | BF15: 51841 | BG15: =BF15/$BF$20 -> 0.046112573 | BH15: Singapore | BI15: 58930 | BJ15: =BI15/$BI$20 -> 0.050164164 | BK15: Korea | BL15: 58552 | BM15: =BL15/$BL$20 -> 0.044726399 | BN15: Singapore | BO15: 68148 | BP15: =BO15/$BO$20 -> 0.046188569 | BQ15: USA | BR15: 79624 | BS15: =BR15/$BR$20 -> 0.045541952 | BT15: USA | BU15: 90843 | BV15: =BU15/$BU$20 -> 0.040533287
B16: https://investor.airportthai.co.th/transport.html | Q16: 9 | R16: Singapore | S16: 1059484 | T16: =S16/$S$56 -> 0.026542673 | V16: 9 | W16: United Kingdom | X16: 434333 | Y16: =X16/$X$56 -> 0.039252068 | AA16: 9 | AB16: Laos | AC16: 919401 | AD16: =AC16/$AC$56 -> 0.032660763 | AF16: 9 | AG16: USA | AH16: 1030733 | AI16: =AH16/$AH$56 -> 0.028997392 | AK16: 9 | AL16: Taiwan | AM16: 987633 | AN16: =AM16/AM$56 -> 0.02995158 | AP16: 9 | AQ16: Taiwan | AR16: 443997 | AS16: =AR16/AR$56 -> 0.031640284 | AU16: 7 | AV16: France | AW16: 14132 | AX16: =AW16/$AW$20 -> 0.048174536 | AY16: Australia | AZ16: 18962 | BA16: 0.036366775 | BB16: UK | BC16: 27901 | BD16: =BC16/$BC$20 -> 0.036353237 | BE16: Laos | BF16: 49299 | BG16: =BF16/$BF$20 -> 0.043851464 | BH16: UK | BI16: 41130 | BJ16: =BI16/$BI$20 -> 0.035011913 | BK16: Cambodia | BL16: 54379 | BM16: =BL16/$BL$20 -> 0.041538749 | BN16: USA | BO16: 57302 | BP16: =BO16/$BO$20 -> 0.038837491 | BQ16: Laos | BR16: 78606 | BS16: =BR16/$BR$20 -> 0.044959694 | BT16: UK | BU16: 87376 | BV16: =BU16/$BU$20 -> 0.038986344
Q17: 10 | R17: Vietnam | S17: 1048181 | T17: =S17/$S$56 -> 0.026259505 | V17: 10 | W17: Russia | X17: 429359 | Y17: =X17/$X$56 -> 0.038802551 | AA17: 10 | AB17: United Kingdom | AC17: 817220 | AD17: =AC17/$AC$56 -> 0.029030889 | AF17: 10 | AG17: Singapore | AH17: 1009640 | AI17: =AH17/$AH$56 -> 0.028403987 | AK17: 10 | AL17: Singapore | AM17: 967341 | AN17: =AM17/AM$56 -> 0.029336192 | AP17: 10 | AQ17: Japan | AR17: 434980 | AS17: =AR17/AR$56 -> 0.030997711 | AU17: 8 | AV17: Japan | AW17: 11164 | AX17: =AW17/$AW$20 -> 0.038056929 | AY17: Vietnam | AZ17: 18905 | BA17: 0.036257456 | BB17: Cambodia | BC17: 27564 | BD17: =BC17/$BC$20 -> 0.035914147 | BE17: USA | BF17: 43923 | BG17: =BF17/$BF$20 -> 0.039069512 | BH17: Japan | BI17: 39297 | BJ17: =BI17/$BI$20 -> 0.033451572 | BK17: USA | BL17: 38704 | BM17: =BL17/$BL$20 -> 0.029565011 | BN17: UK | BO17: 51992 | BP17: =BO17/$BO$20 -> 0.035238541 | BQ17: Vietnam | BR17: 67925 | BS17: =BR17/$BR$20 -> 0.038850561 | BT17: Laos | BU17: 77809 | BV17: =BU17/$BU$20 -> 0.034717639
Q18: 11 | R18: Hong Kong | S18: 1045361 | T18: =S18/$S$56 -> 0.026188857 | V18: 11 | W18: Germany | X18: 356889 | Y18: =X18/$X$56 -> 0.032253205 | AA18: 11 | AB18: Japan | AC18: 805768 | AD18: =AC18/$AC$56 -> 0.028624069 | AF18: 11 | AG18: Vietnam | AH18: 984248 | AI18: =AH18/$AH$56 -> 0.027689639 | AK18: 11 | AL18: Germany | AM18: 965898 | AN18: =AM18/AM$56 -> 0.02929243 | AP18: 11 | AQ18: France | AR18: 417343 | AS18: =AR18/AR$56 -> 0.029740856 | AU18: 9 | AV18: Malaysia | AW18: 10793 | AX18: =AW18/$AW$20 -> 0.036792228 | AY18: Laos | AZ18: 18645 | BA18: 0.035758808 | BB18: Australia | BC18: 26795 | BD18: =BC18/$BC$20 -> 0.034912189 | BE18: UK | BF18: 40596 | BG18: =BF18/$BF$20 -> 0.036110145 | BH18: Cambodia | BI18: 38302 | BJ18: =BI18/$BI$20 -> 0.032604578 | BK18: Australia | BL18: 38041 | BM18: =BL18/$BL$20 -> 0.029058562 | BN18: Germany | BO18: 45707 | BP18: =BO18/$BO$20 -> 0.030978766 | BQ18: UK | BR18: 65303 | BS18: =BR18/$BR$20 -> 0.037350875 | BT18: Cambodia | BU18: 71896 | BV18: =BU18/$BU$20 -> 0.032079315
Q19: 12 | R19: United Kingdom | S19: 992574 | T19: =S19/$S$56 -> 0.024866413 | V19: 12 | W19: Australia | X19: 330597 | Y19: =X19/$X$56 -> 0.029877112 | AA19: 12 | AB19: Hong Kong | AC19: 802368 | AD19: =AC19/$AC$56 -> 0.028503288 | AF19: 12 | AG19: UK | AH19: 965862 | AI19: =AH19/$AH$56 -> 0.02717239 | AK19: 12 | AL19: Laos | AM19: 868368 | AN19: =AM19/AM$56 -> 0.026334674 | AP19: 12 | AQ19: Singapore | AR19: 348136 | AS19: =AR19/AR$56 -> 0.024809001 | AU19: 10 | AV19: Israel | AW19: 9850 | AX19: =AW19/$AW$20 -> 0.033577638 | AY19: Korea | AZ19: 16184 | BA19: 0.031038914 | BB19: Korea | BC19: 25702 | BD19: =BC19/$BC$20 -> 0.033488079 | BE19: Australia | BF19: 36525 | BG19: =BF19/$BF$20 -> 0.03248899 | BH19: USA | BI19: 37659 | BJ19: =BI19/$BI$20 -> 0.032057224 | BK19: Japan | BL19: 36535 | BM19: =BL19/$BL$20 -> 0.027908167 | BN19: Cambodia | BO19: 44540 | BP19: =BO19/$BO$20 -> 0.03018781 | BQ19: Germany | BR19: 62108 | BS19: =BR19/$BR$20 -> 0.035523454 | BT19: Germany | BU19: 67326 | BV19: =BU19/$BU$20 -> 0.030040224
Q20: 13 | R20: Cambodia | S20: 910696 | T20: =S20/$S$56 -> 0.022815169 | V20: 13 | W20: Japan | X20: 288342 | Y20: =X20/$X$56 -> 0.026058392 | AA20: 13 | AB20: Indonesia | AC20: 762118 | AD20: =AC20/$AC$56 -> 0.027073448 | AF20: 13 | AG20: Indonesia | AH20: 876610 | AI20: =AH20/$AH$56 -> 0.024661482 | AK20: 13 | AL20: France | AM20: 816935 | AN20: =AM20/AM$56 -> 0.024774885 | AP20: 13 | AQ20: Australia | AR20: 323789 | AS20: =AR20/AR$56 -> 0.023073976 | AV20: Total | AW20: 293350 | AZ20: 521410 | BC20: 767497 | BF20: 1124227 | BI20: 1174743 | BL20: 1309115 | BO20: 1475430 | BR20: 1748366 | BU20: 2241195
Q21: 14 | R21: Germany | S21: 852481 | T21: =S21/$S$56 -> 0.02135674 | V21: 14 | W21: France | X21: 260223 | Y21: =X21/$X$56 -> 0.023517188 | AA21: 14 | AB21: Germany | AC21: 729163 | AD21: =AC21/$AC$56 -> 0.025902756 | AF21: 14 | AG21: Hong Kong | AH21: 876076 | AI21: =AH21/$AH$56 -> 0.024646459 | AK21: 14 | AL21: Australia | AM21: 808682 | AN21: =AM21/AM$56 -> 0.024524599 | AP21: 14 | AQ21: Myanmar | AR21: 317634 | AS21: =AR21/AR$56 -> 0.022635356
Q22: 15 | R22: Taiwan | S22: 790039 | T22: =S22/$S$56 -> 0.019792415 | V22: 15 | W22: China | X22: 258586 | Y22: =X22/$X$56 -> 0.023369247 | AA22: 15 | AB22: Taiwan | AC22: 724594 | AD22: =AC22/$AC$56 -> 0.025740447 | AF22: 15 | AG22: Germany | AH22: 873364 | AI22: =AH22/$AH$56 -> 0.024570163 | AK22: 15 | AL22: Indonesia | AM22: 787524 | AN22: =AM22/AM$56 -> 0.023882948 | AP22: 15 | AQ22: Laos | AR22: 305785 | AS22: =AR22/AR$56 -> 0.021790968
Q23: 16 | R23: Australia | S23: 767291 | T23: =S23/$S$56 -> 0.019222522 | V23: 16 | W23: Indonesia | X23: 231747 | Y23: =X23/$X$56 -> 0.02094372 | AA23: 16 | AB23: Australia | AC23: 687745 | AD23: =AC23/$AC$56 -> 0.024431425 | AF23: 16 | AG23: Australia | AH23: 775010 | AI23: =AH23/$AH$56 -> 0.021803191 | AK23: 16 | AL23: Philippines | AM23: 704575 | AN23: =AM23/AM$56 -> 0.021367385 | AP23: 16 | AQ23: Indonesia | AR23: 288026 | AS23: =AR23/AR$56 -> 0.020525419 | AU23: No | AV23: 44927 | AY23: 44958 | BB23: 44986 | BE23: 45017 | BH23: 45047 | BK23: 45078 | BN23: 45108 | BQ23: 45139 | BT23: 45170 | BW23: 45200 | BZ23: 45231 | CC23: 45261
Q24: 17 | R24: France | S24: 745346 | T24: =S24/$S$56 -> 0.018672746 | V24: 17 | W24: Myanmar | X24: 211925 | Y24: =X24/$X$56 -> 0.019152343 | AA24: 17 | AB24: Cambodia | AC24: 583708 | AD24: =AC24/$AC$56 -> 0.020735619 | AF24: 17 | AG24: France | AH24: 720806 | AI24: =AH24/$AH$56 -> 0.020278282 | AK24: 17 | AL24: Myanmar | AM24: 688678 | AN24: =AM24/AM$56 -> 0.020885282 | AP24: 17 | AQ24: Philippines | AR24: 270344 | AS24: =AR24/AR$56 -> 0.019265358 | AV24: Nationality | AW24: Number | AX24: % | AY24: Nationality | AZ24: Number | BA24: % | BB24: Nationality | BC24: Number | BD24: % | BE24: Nationality | BF24: Number | BG24: % | BH24: Nationality | BI24: Number | BJ24: % | BK24: Nationality | BL24: Number | BM24: % | BN24: Nationality | BO24: Number | BP24: % | BQ24: Nationality | BR24: Number | BS24: % | BT24: Nationality | BU24: Number | BV24: % | BW24: Nationality | BX24: Number | BY24: % | BZ24: Nationality | CA24: Number | CB24: % | CC24: Nationality | CD24: Number | CE24: %
Q25: 18 | R25: Indonesia | S25: 710494 | T25: =S25/$S$56 -> 0.017799618 | V25: 18 | W25: Philippines | X25: 168970 | Y25: =X25/$X$56 -> 0.015270361 | AA25: 18 | AB25: France | AC25: 545003 | AD25: =AC25/$AC$56 -> 0.019360664 | AF25: 18 | AG25: Philippines | AH25: 598124 | AI25: =AH25/$AH$56 -> 0.016826895 | AK25: 18 | AL25: Vietnam | AM25: 660386 | AN25: =AM25/AM$56 -> 0.020027281 | AP25: 18 | AQ25: Hong Kong (China) | AR25: 245903 | AS25: =AR25/AR$56 -> 0.017523634 | AU25: 1 | AV25: Malaysia | AW25: 288745 | AX25: =AW25/$AW$35 -> 0.13461632 | AY25: Malaysia | AZ25: 305367 | BA25: =AZ25/$AZ$35 -> 0.14448061 | BB25: Malaysia | BC25: 326930 | BD25: =BC25/$BC$35 -> 0.14732948 | BE25: Malaysia | BF25: 401394 | BG25: =BF25/$BF$35 -> 0.18394849 | BH25: Malaysia | BI25: 373922 | BJ25: =BI25/$BI$35 -> 0.18567501 | BK25: Malaysia | BL25: 408356 | BM25: =BL25/$BL$35 -> 0.1822041 | BN25: China | BO25: 410311 | BP25: =BO25/$BO$35 -> 0.16474099 | BQ25: Malaysia | BR25: 438556 | BS25: =BR25/$BR$35 -> 0.1776939 | BT25: Malaysia | BU25: 388197 | BV25: =BU25/$BU$35 -> 0.18220113 | BW25: Malaysia | BX25: 348403 | BY25: =BX25/$BX$35 -> 0.15858002 | BZ25: Malaysia | CA25: 392969 | CB25: =CA25/$CA$35 -> 0.14901688 | CC25: Malaysia | CD25: 547243 | CE25: =CD25/$CD$35 -> 0.16780125
